{
  "type": "Feature",
  "properties": {
    "gn:admin1_code":"17.0",
    "gn:admin2_code":"171.0",
    "gn:admin3_code":"72.0",
    "gn:asciiname":"Kittilaennurkka",
    "gn:country_code":"FI",
    "gn:dem":12,
    "gn:feature_class":"P",
    "gn:feature_code":"PPL",
    "gn:name":"Kittil\u00e4nnurkka",
    "gn:population":0,
    "gn:timezone":"Europe/Helsinki",
    "iso:country":"FI",
    "wof:name":"Kittilaennurkka",
    "wof:placetype":"locality"
},
  "geometry": {"coordinates":[24.68879,65.02055],"type":"Point"}
}