{
  "type": "Feature",
  "properties": {
    "gn:admin1_code":"12.0",
    "gn:admin2_code":"124.0",
    "gn:admin3_code":"707.0",
    "gn:asciiname":"Tuunala",
    "gn:country_code":"FI",
    "gn:dem":67,
    "gn:feature_class":"P",
    "gn:feature_code":"PPL",
    "gn:name":"Tuunala",
    "gn:population":0,
    "gn:timezone":"Europe/Helsinki",
    "iso:country":"FI",
    "wof:name":"Tuunala",
    "wof:placetype":"locality"
},
  "geometry": {"coordinates":[29.95,62.35],"type":"Point"}
}