{
  "type": "Feature",
  "properties": {
    "gn:admin1_code":"5.0",
    "gn:admin2_code":"51.0",
    "gn:admin3_code":"109.0",
    "gn:asciiname":"Vaehae-Evo",
    "gn:country_code":"FI",
    "gn:dem":90,
    "gn:feature_class":"P",
    "gn:feature_code":"PPL",
    "gn:name":"V\u00e4h\u00e4-Evo",
    "gn:population":0,
    "gn:timezone":"Europe/Helsinki",
    "iso:country":"FI",
    "name:swe_x_preferred":[
        "Lill Evois"
    ],
    "wof:name":"Vaehae-Evo",
    "wof:placetype":"locality"
},
  "geometry": {"coordinates":[24.94541,61.18688],"type":"Point"}
}