{
  "type": "Feature",
  "properties": {
    "gn:admin1_code":"2.0",
    "gn:admin2_code":"25.0",
    "gn:admin3_code":"561.0",
    "gn:asciiname":"Myllykylae",
    "gn:country_code":"FI",
    "gn:dem":70,
    "gn:feature_class":"P",
    "gn:feature_code":"PPL",
    "gn:name":"Myllykyl\u00e4",
    "gn:population":0,
    "gn:timezone":"Europe/Helsinki",
    "iso:country":"FI",
    "wof:name":"Myllykylae",
    "wof:placetype":"locality"
},
  "geometry": {"coordinates":[22.71089,60.90084],"type":"Point"}
}