{
  "type": "Feature",
  "properties": {
    "gn:admin1_code":"6.0",
    "gn:admin2_code":"69.0",
    "gn:admin3_code":"936.0",
    "gn:asciiname":"Kangasniemi",
    "gn:country_code":"FI",
    "gn:dem":123,
    "gn:feature_class":"P",
    "gn:feature_code":"PPL",
    "gn:name":"Kangasniemi",
    "gn:population":0,
    "gn:timezone":"Europe/Helsinki",
    "iso:country":"FI",
    "name:ceb_x_preferred":[
        "Kangasniemi"
    ],
    "name:deu_x_preferred":[
        "Kangasniemi"
    ],
    "name:est_x_preferred":[
        "Kangasniemi vald"
    ],
    "name:eus_x_preferred":[
        "Kangasniemi"
    ],
    "name:fin_x_preferred":[
        "Kangasniemi"
    ],
    "name:fra_x_preferred":[
        "Kangasniemi"
    ],
    "name:glg_x_preferred":[
        "Kangasniemi"
    ],
    "name:ita_x_preferred":[
        "Kangasniemi"
    ],
    "name:nld_x_preferred":[
        "Kangasniemi"
    ],
    "name:nor_x_preferred":[
        "Kangasniemi"
    ],
    "name:pol_x_preferred":[
        "Kangasniemi"
    ],
    "name:ron_x_preferred":[
        "Kangasniemi"
    ],
    "name:rus_x_preferred":[
        "\u041a\u0430\u043d\u0433\u0430\u0441\u043d\u0438\u0435\u043c\u0438"
    ],
    "name:sme_x_preferred":[
        "Kangasniemi"
    ],
    "name:spa_x_preferred":[
        "Kangasniemi"
    ],
    "name:sqi_x_preferred":[
        "Kangasniemi"
    ],
    "name:swe_x_preferred":[
        "Kangasniemi"
    ],
    "name:tur_x_preferred":[
        "Kangasniemi"
    ],
    "name:zho_x_preferred":[
        "\u5eb7\u963f\u65af\u6d85\u7c73"
    ],
    "wof:name":"Kangasniemi",
    "wof:placetype":"locality"
},
  "geometry": {"coordinates":[23.98333,62.28333000000001],"type":"Point"}
}