{
  "type": "Feature",
  "properties": {
    "gn:admin1_code":"6.0",
    "gn:admin2_code":"69.0",
    "gn:admin3_code":"936.0",
    "gn:asciiname":"Kangasniemi",
    "gn:country_code":"FI",
    "gn:dem":123,
    "gn:feature_class":"P",
    "gn:feature_code":"PPL",
    "gn:name":"Kangasniemi",
    "gn:population":0,
    "gn:timezone":"Europe/Helsinki",
    "iso:country":"FI",
    "wof:name":"Kangasniemi",
    "wof:placetype":"locality"
},
  "geometry": {"coordinates":[23.98333,62.28333000000001],"type":"Point"}
}