{
  "type": "Feature",
  "properties": {
    "gn:admin1_code":"18.0",
    "gn:admin2_code":"181.0",
    "gn:admin3_code":"777.0",
    "gn:asciiname":"Ketrae",
    "gn:country_code":"FI",
    "gn:dem":246,
    "gn:feature_class":"P",
    "gn:feature_code":"PPL",
    "gn:name":"Ketr\u00e4",
    "gn:population":0,
    "gn:timezone":"Europe/Helsinki",
    "iso:country":"FI",
    "wof:name":"Ketrae",
    "wof:placetype":"locality"
},
  "geometry": {"coordinates":[29.23333,65.18333],"type":"Point"}
}