{
  "type": "Feature",
  "properties": {
    "gn:admin1_code":"17.0",
    "gn:admin2_code":"176.0",
    "gn:admin3_code":"317.0",
    "gn:asciiname":"Miiluranta",
    "gn:country_code":"FI",
    "gn:dem":99,
    "gn:feature_class":"P",
    "gn:feature_code":"PPL",
    "gn:name":"Miiluranta",
    "gn:population":0,
    "gn:timezone":"Europe/Helsinki",
    "iso:country":"FI",
    "name:fin_x_preferred":[
        "Miiluranta"
    ],
    "wof:name":"Miiluranta",
    "wof:placetype":"locality"
},
  "geometry": {"coordinates":[26.0297,63.95983],"type":"Point"}
}