{
  "type": "Feature",
  "properties": {
    "gn:admin1_code":"7.0",
    "gn:admin2_code":"71.0",
    "gn:admin3_code":"98.0",
    "gn:asciiname":"Etola",
    "gn:country_code":"FI",
    "gn:dem":151,
    "gn:feature_class":"P",
    "gn:feature_code":"PPL",
    "gn:name":"Etola",
    "gn:population":0,
    "gn:timezone":"Europe/Helsinki",
    "iso:country":"FI",
    "wof:name":"Etola",
    "wof:placetype":"locality"
},
  "geometry": {"coordinates":[25.17702,61.04791],"type":"Point"}
}