{
  "type": "Feature",
  "properties": {
    "gn:admin1_code":"1.0",
    "gn:admin2_code":"14.0",
    "gn:admin3_code":"710.0",
    "gn:asciiname":"Billnaes",
    "gn:country_code":"FI",
    "gn:dem":32,
    "gn:feature_class":"P",
    "gn:feature_code":"PPL",
    "gn:name":"Billn\u00e4s",
    "gn:population":0,
    "gn:timezone":"Europe/Helsinki",
    "iso:country":"FI",
    "name:eng_x_preferred":[
        "Billn\u00e4s"
    ],
    "name:fin_x_preferred":[
        "Pinjainen"
    ],
    "name:nno_x_preferred":[
        "Billn\u00e4s"
    ],
    "name:nob_x_preferred":[
        "Billn\u00e4s"
    ],
    "name:swe_x_preferred":[
        "Billn\u00e4s"
    ],
    "wof:name":"Billnaes",
    "wof:placetype":"locality"
},
  "geometry": {"coordinates":[23.63971,60.08237],"type":"Point"}
}