{
  "type": "Feature",
  "properties": {
    "gn:admin1_code":"1.0",
    "gn:admin2_code":"11.0",
    "gn:admin3_code":"444.0",
    "gn:asciiname":"Voerloe",
    "gn:country_code":"FI",
    "gn:dem":43,
    "gn:feature_class":"P",
    "gn:feature_code":"PPL",
    "gn:name":"V\u00f6rl\u00f6",
    "gn:population":0,
    "gn:timezone":"Europe/Helsinki",
    "iso:country":"FI",
    "wof:name":"Voerloe",
    "wof:placetype":"locality"
},
  "geometry": {"coordinates":[24.07626,60.41636999999999],"type":"Point"}
}