{
  "type": "Feature",
  "properties": {
    "gn:admin1_code":"14.0",
    "gn:admin2_code":"142.0",
    "gn:admin3_code":"301.0",
    "gn:asciiname":"Murtoinen",
    "gn:country_code":"FI",
    "gn:dem":30,
    "gn:feature_class":"P",
    "gn:feature_code":"PPL",
    "gn:name":"Murtoinen",
    "gn:population":0,
    "gn:timezone":"Europe/Helsinki",
    "iso:country":"FI",
    "wof:name":"Murtoinen",
    "wof:placetype":"locality"
},
  "geometry": {"coordinates":[21.74012,62.81241],"type":"Point"}
}