{
  "type": "Feature",
  "properties": {
    "gn:admin1_code":"14.0",
    "gn:admin2_code":"141.0",
    "gn:admin3_code":"232.0",
    "gn:asciiname":"Talvitie",
    "gn:country_code":"FI",
    "gn:dem":134,
    "gn:feature_class":"P",
    "gn:feature_code":"PPL",
    "gn:name":"Talvitie",
    "gn:population":0,
    "gn:timezone":"Europe/Helsinki",
    "iso:country":"FI",
    "name:fin_x_preferred":[
        "Talvitie"
    ],
    "wof:name":"Talvitie",
    "wof:placetype":"locality"
},
  "geometry": {"coordinates":[22.05416,62.25162],"type":"Point"}
}