{
  "type": "Feature",
  "properties": {
    "gn:admin1_code":"6.0",
    "gn:admin2_code":"64.0",
    "gn:admin3_code":"108.0",
    "gn:asciiname":"Turkkila",
    "gn:country_code":"FI",
    "gn:dem":88,
    "gn:feature_class":"P",
    "gn:feature_code":"PPL",
    "gn:name":"Turkkila",
    "gn:population":0,
    "gn:timezone":"Europe/Helsinki",
    "iso:country":"FI",
    "wof:name":"Turkkila",
    "wof:placetype":"locality"
},
  "geometry": {"coordinates":[23.26002,61.65273000000001],"type":"Point"}
}