{
  "type": "Feature",
  "properties": {
    "gn:admin1_code":"4.0",
    "gn:admin2_code":"43.0",
    "gn:admin3_code":"609.0",
    "gn:asciiname":"Toejoki",
    "gn:country_code":"FI",
    "gn:dem":8,
    "gn:feature_class":"P",
    "gn:feature_code":"PPL",
    "gn:name":"Toejoki",
    "gn:population":0,
    "gn:timezone":"Europe/Helsinki",
    "iso:country":"FI",
    "wof:name":"Toejoki",
    "wof:placetype":"locality"
},
  "geometry": {"coordinates":[21.8131,61.50493],"type":"Point"}
}