{
  "type": "Feature",
  "properties": {
    "gn:admin1_code":"6.0",
    "gn:admin2_code":"64.0",
    "gn:admin3_code":"418.0",
    "gn:asciiname":"Lempaeaelae",
    "gn:country_code":"FI",
    "gn:dem":85,
    "gn:feature_class":"P",
    "gn:feature_code":"PPLA3",
    "gn:name":"Lemp\u00e4\u00e4l\u00e4",
    "gn:population":18096,
    "gn:timezone":"Europe/Helsinki",
    "iso:country":"FI",
    "name:ara_x_preferred":[
        "\u0644\u0645\u0628\u0627\u0644\u0627"
    ],
    "name:deu_x_preferred":[
        "Lemp\u00e4\u00e4l\u00e4"
    ],
    "name:eng_x_preferred":[
        "Lemp\u00e4\u00e4l\u00e4"
    ],
    "name:est_x_preferred":[
        "Lemp\u00e4\u00e4l\u00e4 vald"
    ],
    "name:fin_x_preferred":[
        "Lemp\u00e4\u00e4l\u00e4"
    ],
    "name:fra_x_preferred":[
        "Lemp\u00e4\u00e4l\u00e4"
    ],
    "name:nld_x_preferred":[
        "Lemp\u00e4\u00e4l\u00e4"
    ],
    "name:nor_x_preferred":[
        "Lemp\u00e4\u00e4l\u00e4"
    ],
    "name:ron_x_preferred":[
        "Lemp\u00e4\u00e4l\u00e4"
    ],
    "name:rus_x_preferred":[
        "\u041b\u0435\u043c\u043f\u044f\u0430\u043b\u044f"
    ],
    "name:swe_x_historical":[
        "Lembois"
    ],
    "name:swe_x_preferred":[
        "Lembois"
    ],
    "name:zho_x_preferred":[
        "\u502b\u6d3e\u840a"
    ],
    "wof:name":"Lempaeaelae",
    "wof:placetype":"locality",
    "wof:population":18096
},
  "geometry": {"coordinates":[23.75,61.31667],"type":"Point"}
}