{
  "type": "Feature",
  "properties": {
    "gn:admin1_code":"19.0",
    "gn:admin2_code":"193.0",
    "gn:admin3_code":"854.0",
    "gn:asciiname":"Orajaervi",
    "gn:country_code":"FI",
    "gn:dem":131,
    "gn:feature_class":"P",
    "gn:feature_code":"PPL",
    "gn:name":"Oraj\u00e4rvi",
    "gn:population":0,
    "gn:timezone":"Europe/Helsinki",
    "iso:country":"FI",
    "name:fin_x_preferred":[
        "Oraj\u00e4rvi"
    ],
    "wof:name":"Orajaervi",
    "wof:placetype":"locality"
},
  "geometry": {"coordinates":[24.09059,66.90408000000001],"type":"Point"}
}