{
  "type": "Feature",
  "properties": {
    "gn:admin1_code":"19.0",
    "gn:admin2_code":"194.0",
    "gn:admin3_code":"614.0",
    "gn:asciiname":"Vuoska",
    "gn:cc2":"FI",
    "gn:country_code":"FI",
    "gn:dem":229,
    "gn:feature_class":"P",
    "gn:feature_code":"PPL",
    "gn:name":"Vuoska",
    "gn:population":0,
    "gn:timezone":"Europe/Helsinki",
    "iso:country":"FI",
    "name:und_x_variant":[
        "Vuosko",
        "Vuoska"
    ],
    "wof:name":"Vuoska",
    "wof:placetype":"locality"
},
  "geometry": {"coordinates":[28.45,65.84999999999999],"type":"Point"}
}