{
  "type": "Feature",
  "properties": {
    "gn:admin1_code":"11.0",
    "gn:admin2_code":"111.0",
    "gn:admin3_code":"595.0",
    "gn:asciiname":"Tommonmaeki",
    "gn:country_code":"FI",
    "gn:dem":155,
    "gn:feature_class":"P",
    "gn:feature_code":"PPL",
    "gn:name":"Tommonm\u00e4ki",
    "gn:population":0,
    "gn:timezone":"Europe/Helsinki",
    "iso:country":"FI",
    "wof:name":"Tommonmaeki",
    "wof:placetype":"locality"
},
  "geometry": {"coordinates":[26.62211,63.39059],"type":"Point"}
}