{
  "type": "Feature",
  "properties": {
    "gn:admin1_code":"11.0",
    "gn:admin2_code":"111.0",
    "gn:admin3_code":"140.0",
    "gn:asciiname":"Riuttaanmaeki",
    "gn:country_code":"FI",
    "gn:dem":194,
    "gn:feature_class":"P",
    "gn:feature_code":"PPL",
    "gn:name":"Riuttaanm\u00e4ki",
    "gn:population":0,
    "gn:timezone":"Europe/Helsinki",
    "iso:country":"FI",
    "name:eng_x_preferred":[
        "Riuttaanm\u00e4ki"
    ],
    "name:rus_x_preferred":[
        "\u0420\u0443\u043e\u0442\u0430\u043d\u043c\u044f\u043a\u0438"
    ],
    "name:und_x_variant":[
        "Ruottanm\u00e4ki",
        "Riuttaanm\u00e4ki"
    ],
    "wof:name":"Riuttaanmaeki",
    "wof:placetype":"locality"
},
  "geometry": {"coordinates":[26.95,63.46666999999999],"type":"Point"}
}