{
  "type": "Feature",
  "properties": {
    "gn:admin1_code":"1.0",
    "gn:admin2_code":"11.0",
    "gn:admin3_code":"927.0",
    "gn:asciiname":"Salmi",
    "gn:country_code":"FI",
    "gn:dem":69,
    "gn:feature_class":"P",
    "gn:feature_code":"PPL",
    "gn:name":"Salmi",
    "gn:population":0,
    "gn:timezone":"Europe/Helsinki",
    "iso:country":"FI",
    "wof:name":"Salmi",
    "wof:placetype":"locality"
},
  "geometry": {"coordinates":[24.50569,60.37476],"type":"Point"}
}