{
  "type": "Feature",
  "properties": {
    "gn:admin1_code":"12.0",
    "gn:admin2_code":"125.0",
    "gn:admin3_code":"422.0",
    "gn:asciiname":"Lehmivaara",
    "gn:country_code":"FI",
    "gn:dem":200,
    "gn:feature_class":"P",
    "gn:feature_code":"PPL",
    "gn:name":"Lehmivaara",
    "gn:population":0,
    "gn:timezone":"Europe/Helsinki",
    "iso:country":"FI",
    "name:eng_x_preferred":[
        "Lehmivaara"
    ],
    "name:rus_x_preferred":[
        "\u041b\u0435\u0445\u043c\u0438\u0432\u0430\u0440\u0430"
    ],
    "wof:name":"Lehmivaara",
    "wof:placetype":"locality"
},
  "geometry": {"coordinates":[30.61644,63.28072],"type":"Point"}
}