{
  "type": "Feature",
  "properties": {
    "gn:admin1_code":"12.0",
    "gn:admin2_code":"125.0",
    "gn:admin3_code":"911.0",
    "gn:asciiname":"Puukari",
    "gn:cc2":"FI",
    "gn:country_code":"FI",
    "gn:dem":156,
    "gn:feature_class":"P",
    "gn:feature_code":"PPL",
    "gn:name":"Puukari",
    "gn:population":0,
    "gn:timezone":"Europe/Helsinki",
    "iso:country":"FI",
    "name:und_x_variant":[
        "Puukarila",
        "Puukari"
    ],
    "wof:name":"Puukari",
    "wof:placetype":"locality"
},
  "geometry": {"coordinates":[28.67858,63.75052],"type":"Point"}
}