{
  "type": "Feature",
  "properties": {
    "gn:admin1_code":"1.0",
    "gn:admin2_code":"11.0",
    "gn:admin3_code":"49.0",
    "gn:asciiname":"Nissinmaeki",
    "gn:country_code":"FI",
    "gn:dem":47,
    "gn:feature_class":"P",
    "gn:feature_code":"PPL",
    "gn:name":"Nissinm\u00e4ki",
    "gn:population":0,
    "gn:timezone":"Europe/Helsinki",
    "iso:country":"FI",
    "name:fin_x_preferred":[
        "Nissinm\u00e4ki"
    ],
    "name:swe_x_preferred":[
        "Nissbacken"
    ],
    "wof:name":"Nissinmaeki",
    "wof:placetype":"locality"
},
  "geometry": {"coordinates":[24.62313,60.18055],"type":"Point"}
}