{
  "type": "Feature",
  "properties": {
    "gn:country":"FI",
    "gn:fcode":"PPL",
    "gn:population":8853,
    "iso:country":"FI",
    "name:ceb_x_preferred":[
        "Karis"
    ],
    "name:deu_x_preferred":[
        "Karis"
    ],
    "name:eng_x_preferred":[
        "Karis"
    ],
    "name:est_x_preferred":[
        "Karis"
    ],
    "name:fin_x_preferred":[
        "Karjaa"
    ],
    "name:fra_x_preferred":[
        "Karis"
    ],
    "name:glg_x_preferred":[
        "Karis - Karjaa"
    ],
    "name:ita_x_preferred":[
        "Karis"
    ],
    "name:jpn_x_preferred":[
        "\u30ab\u30ea\u30b9"
    ],
    "name:kor_x_preferred":[
        "\uce74\ub9ac\uc2a4"
    ],
    "name:mrj_x_preferred":[
        "\u041a\u0430\u0440\u044c\u044f\u0430"
    ],
    "name:nld_x_preferred":[
        "Karis"
    ],
    "name:nob_x_preferred":[
        "Karis"
    ],
    "name:nor_x_preferred":[
        "Karis"
    ],
    "name:pol_x_preferred":[
        "Karjaa"
    ],
    "name:ron_x_preferred":[
        "Karis"
    ],
    "name:rus_x_preferred":[
        "\u041a\u0430\u0440\u044c\u044f\u0430"
    ],
    "name:rus_x_variant":[
        "\u041a\u0430\u0440\u0438\u0441"
    ],
    "name:sme_x_preferred":[
        "Karjaa"
    ],
    "name:swe_x_preferred":[
        "Karis"
    ],
    "name:tur_x_preferred":[
        "Karis"
    ],
    "name:ukr_x_preferred":[
        "\u041a\u0430\u0440\u0439\u0430\u0430"
    ],
    "name:und_x_variant":[
        "Karja"
    ],
    "name:urd_x_preferred":[
        "\u06a9\u0627\u0631\u06cc\u0633"
    ],
    "name:vie_x_preferred":[
        "Karis"
    ],
    "name:zho_x_preferred":[
        "\u5361\u91cc\u65af"
    ],
    "qs_pg:aaroncc":"FI",
    "qs_pg:gn_country":"FI",
    "qs_pg:gn_fcode":"PPL",
    "qs_pg:gn_pop":8853,
    "qs_pg:name":"Karis",
    "qs_pg:photos_9r":0,
    "qs_pg:photos_sr":0,
    "qs_pg:pop_sr":5,
    "qs_pg:qs_pg_placetype":"locality",
    "wof:name":"Karis",
    "wof:placetype":"locality",
    "wof:population":8853
},
  "geometry": {"coordinates":[23.66163,60.07178],"type":"Point"}
}