{
  "type": "Feature",
  "properties": {
    "gn:admin1_code":"19.0",
    "gn:admin2_code":"194.0",
    "gn:admin3_code":"742.0",
    "gn:asciiname":"Mukkavaara",
    "gn:country_code":"FI",
    "gn:dem":200,
    "gn:feature_class":"P",
    "gn:feature_code":"PPL",
    "gn:name":"Mukkavaara",
    "gn:population":0,
    "gn:timezone":"Europe/Helsinki",
    "iso:country":"FI",
    "name:eng_x_preferred":[
        "Mukkavaara"
    ],
    "name:rus_x_preferred":[
        "\u041c\u0443\u043a\u043a\u0430\u0432\u0430\u0440\u0430"
    ],
    "wof:name":"Mukkavaara",
    "wof:placetype":"locality"
},
  "geometry": {"coordinates":[28.11833,67.26861],"type":"Point"}
}