{
  "type": "Feature",
  "properties": {
    "gn:admin1_code":"13.0",
    "gn:admin2_code":"138.0",
    "gn:admin3_code":"265.0",
    "gn:asciiname":"Toeyriniemi",
    "gn:country_code":"FI",
    "gn:dem":160,
    "gn:feature_class":"P",
    "gn:feature_code":"PPL",
    "gn:name":"T\u00f6yriniemi",
    "gn:population":0,
    "gn:timezone":"Europe/Helsinki",
    "iso:country":"FI",
    "wof:name":"Toeyriniemi",
    "wof:placetype":"locality"
},
  "geometry": {"coordinates":[25.08333,63.05],"type":"Point"}
}