{
  "type": "Feature",
  "properties": {
    "gn:gn_country":"FI",
    "gn:gn_fcode":"PPL",
    "gn:gn_pop":0,
    "iso:country":"FI",
    "name:swe_x_preferred":[
        "Oitbacka"
    ],
    "qs_pg:aaroncc":"FI",
    "qs_pg:gn_country":"FI",
    "qs_pg:gn_fcode":"PPL",
    "qs_pg:gn_pop":0,
    "qs_pg:name":"Oitm\u00e4ki",
    "qs_pg:name_adm0":"Suomi",
    "qs_pg:name_adm1":"Uudenmaan maakunta",
    "qs_pg:photos":85,
    "qs_pg:photos_1k":17,
    "qs_pg:photos_9k":1,
    "qs_pg:photos_9r":3,
    "qs_pg:photos_all":85,
    "qs_pg:photos_sr":3,
    "qs_pg:pop_sr":0,
    "qs_pg:qs_pg_placetype":"locality",
    "qs_pg:qs_pg_placetype_gp":"Town",
    "qs_pg:woe_adm0":23424812,
    "woe:adm0_id":23424812,
    "woe:name_adm0":"Suomi",
    "woe:name_adm1":"Uudenmaan maakunta",
    "woe:placetype":"Town",
    "wof:name":"Oitm\u00e4ki",
    "wof:placetype":"locality"
},
  "geometry": {"coordinates":[24.50149,60.20422],"type":"Point"}
}