{
  "type": "Feature",
  "properties": {
    "gn:admin1_code":"12.0",
    "gn:admin2_code":"125.0",
    "gn:admin3_code":"422.0",
    "gn:asciiname":"Tiensuu",
    "gn:country_code":"FI",
    "gn:dem":126,
    "gn:feature_class":"P",
    "gn:feature_code":"PPL",
    "gn:name":"Tiensuu",
    "gn:population":0,
    "gn:timezone":"Europe/Helsinki",
    "iso:country":"FI",
    "name:eng_x_preferred":[
        "Tiensuu"
    ],
    "name:rus_x_preferred":[
        "\u0422\u0438\u0435\u043d\u0441\u0443"
    ],
    "wof:name":"Tiensuu",
    "wof:placetype":"locality"
},
  "geometry": {"coordinates":[30.09755,63.25995],"type":"Point"}
}