{
  "type": "Feature",
  "properties": {
    "gn:admin1_code":"13.0",
    "gn:admin2_code":"138.0",
    "gn:admin3_code":"931.0",
    "gn:asciiname":"Pirttikylae",
    "gn:country_code":"FI",
    "gn:dem":177,
    "gn:feature_class":"P",
    "gn:feature_code":"PPL",
    "gn:name":"Pirttikyl\u00e4",
    "gn:population":0,
    "gn:timezone":"Europe/Helsinki",
    "iso:country":"FI",
    "name:und_x_variant":[
        "Pirttim\u00e4ki",
        "Pirttikyl\u00e4"
    ],
    "wof:name":"Pirttikylae",
    "wof:placetype":"locality"
},
  "geometry": {"coordinates":[26.14026,63.21918],"type":"Point"}
}