{
  "type": "Feature",
  "properties": {
    "gn:admin1_code":"2.0",
    "gn:admin2_code":"25.0",
    "gn:admin3_code":"636.0",
    "gn:asciiname":"Poeytyae",
    "gn:country_code":"FI",
    "gn:dem":91,
    "gn:feature_class":"P",
    "gn:feature_code":"PPLA3",
    "gn:name":"P\u00f6yty\u00e4",
    "gn:population":3650,
    "gn:timezone":"Europe/Helsinki",
    "iso:country":"FI",
    "wof:name":"Poeytyae",
    "wof:placetype":"locality",
    "wof:population":3650
},
  "geometry": {"coordinates":[22.66667,60.76667],"type":"Point"}
}