{
  "type": "Feature",
  "properties": {
    "gn:admin1_code":"16.0",
    "gn:admin2_code":"162.0",
    "gn:admin3_code":"272.0",
    "gn:asciiname":"Jokikylae",
    "gn:country_code":"FI",
    "gn:dem":21,
    "gn:feature_class":"P",
    "gn:feature_code":"PPL",
    "gn:name":"Jokikyl\u00e4",
    "gn:population":0,
    "gn:timezone":"Europe/Helsinki",
    "iso:country":"FI",
    "wof:name":"Jokikylae",
    "wof:placetype":"locality"
},
  "geometry": {"coordinates":[23.52676,64.00688000000001],"type":"Point"}
}