{
  "type": "Feature",
  "properties": {
    "gn:admin1_code":"4.0",
    "gn:admin2_code":"43.0",
    "gn:admin3_code":"102.0",
    "gn:asciiname":"Matkusjoki",
    "gn:country_code":"FI",
    "gn:dem":67,
    "gn:feature_class":"P",
    "gn:feature_code":"PPL",
    "gn:name":"Matkusjoki",
    "gn:population":0,
    "gn:timezone":"Europe/Helsinki",
    "iso:country":"FI",
    "wof:name":"Matkusjoki",
    "wof:placetype":"locality"
},
  "geometry": {"coordinates":[22.64271,61.03901],"type":"Point"}
}