{
  "type": "Feature",
  "properties": {
    "gn:admin1_code":"6.0",
    "gn:admin2_code":"64.0",
    "gn:admin3_code":"562.0",
    "gn:asciiname":"Vihasjaervi",
    "gn:country_code":"FI",
    "gn:dem":94,
    "gn:feature_class":"P",
    "gn:feature_code":"PPL",
    "gn:name":"Vihasj\u00e4rvi",
    "gn:population":0,
    "gn:timezone":"Europe/Helsinki",
    "iso:country":"FI",
    "wof:name":"Vihasjaervi",
    "wof:placetype":"locality"
},
  "geometry": {"coordinates":[24.61038,61.55071],"type":"Point"}
}