{
  "type": "Feature",
  "properties": {
    "gn:admin1_code":"1.0",
    "gn:admin2_code":"16.0",
    "gn:admin3_code":"407.0",
    "gn:asciiname":"Pockar",
    "gn:cc2":"FI",
    "gn:country_code":"FI",
    "gn:dem":24,
    "gn:feature_class":"P",
    "gn:feature_code":"PPL",
    "gn:name":"Pockar",
    "gn:population":0,
    "gn:timezone":"Europe/Helsinki",
    "iso:country":"FI",
    "name:fin_x_preferred":[
        "Pukaro"
    ],
    "name:swe_x_preferred":[
        "Pockar"
    ],
    "wof:name":"Pockar",
    "wof:placetype":"locality"
},
  "geometry": {"coordinates":[26.24024,60.67194],"type":"Point"}
}