{
  "type": "Feature",
  "properties": {
    "gn:admin1_code":"12.0",
    "gn:admin2_code":"122.0",
    "gn:admin3_code":"426.0",
    "gn:asciiname":"Paavola",
    "gn:country_code":"FI",
    "gn:dem":61,
    "gn:feature_class":"P",
    "gn:feature_code":"PPL",
    "gn:name":"Paavola",
    "gn:population":0,
    "gn:timezone":"Europe/Helsinki",
    "iso:country":"FI",
    "name:ara_x_preferred":[
        "\u0628\u0627\u0641\u0648\u0644\u0627"
    ],
    "name:fin_x_preferred":[
        "Paavola"
    ],
    "name:nor_x_preferred":[
        "Paavola"
    ],
    "name:sme_x_preferred":[
        "Paavola"
    ],
    "name:swe_x_preferred":[
        "Paavola"
    ],
    "wof:name":"Paavola",
    "wof:placetype":"locality"
},
  "geometry": {"coordinates":[29.31667,62.45],"type":"Point"}
}