{
  "type": "Feature",
  "properties": {
    "gn:admin1_code":"11.0",
    "gn:admin2_code":"113.0",
    "gn:admin3_code":"204.0",
    "gn:asciiname":"Petkellahti",
    "gn:country_code":"FI",
    "gn:dem":138,
    "gn:feature_class":"P",
    "gn:feature_code":"PPL",
    "gn:name":"Petkellahti",
    "gn:population":0,
    "gn:timezone":"Europe/Helsinki",
    "iso:country":"FI",
    "wof:name":"Petkellahti",
    "wof:placetype":"locality"
},
  "geometry": {"coordinates":[28.69275,62.94021],"type":"Point"}
}