{
  "type": "Feature",
  "properties": {
    "gn:admin1_code":"14.0",
    "gn:admin2_code":"141.0",
    "gn:admin3_code":"232.0",
    "gn:asciiname":"Kulmalankylae",
    "gn:country_code":"FI",
    "gn:dem":159,
    "gn:feature_class":"P",
    "gn:feature_code":"PPL",
    "gn:name":"Kulmalankyl\u00e4",
    "gn:population":0,
    "gn:timezone":"Europe/Helsinki",
    "iso:country":"FI",
    "name:fin_x_preferred":[
        "Kulmalankyl\u00e4"
    ],
    "wof:name":"Kulmalankylae",
    "wof:placetype":"locality"
},
  "geometry": {"coordinates":[22.48345,62.28021999999999],"type":"Point"}
}