{
  "type": "Feature",
  "properties": {
    "gn:admin1_code":"6.0",
    "gn:admin2_code":"69.0",
    "gn:admin3_code":"936.0",
    "gn:asciiname":"Raski",
    "gn:country_code":"FI",
    "gn:dem":98,
    "gn:feature_class":"P",
    "gn:feature_code":"PPL",
    "gn:name":"Raski",
    "gn:population":0,
    "gn:timezone":"Europe/Helsinki",
    "iso:country":"FI",
    "name:pol_x_preferred":[
        "Raski"
    ],
    "wof:name":"Raski",
    "wof:placetype":"locality"
},
  "geometry": {"coordinates":[23.93333,62.16667],"type":"Point"}
}