{
  "type": "Feature",
  "properties": {
    "gn:admin1_code":"18.0",
    "gn:admin2_code":"182.0",
    "gn:admin3_code":"765.0",
    "gn:asciiname":"Halola",
    "gn:country_code":"FI",
    "gn:dem":161,
    "gn:feature_class":"P",
    "gn:feature_code":"PPL",
    "gn:name":"Halola",
    "gn:population":0,
    "gn:timezone":"Europe/Helsinki",
    "iso:country":"FI",
    "wof:name":"Halola",
    "wof:placetype":"locality"
},
  "geometry": {"coordinates":[28.25,64.16667],"type":"Point"}
}