{
  "type": "Feature",
  "properties": {
    "gn:gn_country":"FI",
    "gn:gn_fcode":"PPL",
    "gn:gn_pop":0,
    "iso:country":"FI",
    "qs_pg:aaroncc":"FI",
    "qs_pg:gn_country":"FI",
    "qs_pg:gn_fcode":"PPL",
    "qs_pg:gn_pop":0,
    "qs_pg:name":"Pitk\u00e4niemi",
    "qs_pg:name_adm0":"Suomi",
    "qs_pg:name_adm1":"Pirkanmaan maakunta",
    "qs_pg:photos":198,
    "qs_pg:photos_1k":40,
    "qs_pg:photos_9k":1,
    "qs_pg:photos_9r":4,
    "qs_pg:photos_all":198,
    "qs_pg:photos_sr":4,
    "qs_pg:pop_sr":0,
    "qs_pg:qs_pg_placetype":"locality",
    "qs_pg:qs_pg_placetype_gp":"Town",
    "qs_pg:woe_adm0":23424812,
    "woe:adm0_id":23424812,
    "woe:name_adm0":"Suomi",
    "woe:name_adm1":"Pirkanmaan maakunta",
    "woe:placetype":"Town",
    "wof:name":"Pitk\u00e4niemi",
    "wof:placetype":"locality"
},
  "geometry": {"coordinates":[23.58333,61.48333],"type":"Point"}
}