{
  "type": "Feature",
  "properties": {
    "gn:admin1_code":"2.0",
    "gn:admin2_code":"23.0",
    "gn:admin3_code":"481.0",
    "gn:asciiname":"Hievuinen",
    "gn:country_code":"FI",
    "gn:dem":22,
    "gn:feature_class":"P",
    "gn:feature_code":"PPL",
    "gn:name":"Hievuinen",
    "gn:population":0,
    "gn:timezone":"Europe/Helsinki",
    "iso:country":"FI",
    "wof:name":"Hievuinen",
    "wof:placetype":"locality"
},
  "geometry": {"coordinates":[21.91873,60.56695],"type":"Point"}
}