{
  "type": "Feature",
  "properties": {
    "gn:admin1_code":"2.0",
    "gn:admin2_code":"21.0",
    "gn:admin3_code":"322.0",
    "gn:asciiname":"Kyrksundet",
    "gn:country_code":"FI",
    "gn:dem":24,
    "gn:feature_class":"P",
    "gn:feature_code":"PPL",
    "gn:name":"Kyrksundet",
    "gn:population":0,
    "gn:timezone":"Europe/Helsinki",
    "iso:country":"FI",
    "wof:name":"Kyrksundet",
    "wof:placetype":"locality"
},
  "geometry": {"coordinates":[22.49086,59.87674000000001],"type":"Point"}
}