{
  "type": "Feature",
  "properties": {
    "gn:admin1_code":"11.0",
    "gn:admin2_code":"112.0",
    "gn:admin3_code":"297.0",
    "gn:asciiname":"Leinolanlahti",
    "gn:country_code":"FI",
    "gn:dem":140,
    "gn:feature_class":"P",
    "gn:feature_code":"PPL",
    "gn:name":"Leinolanlahti",
    "gn:population":0,
    "gn:timezone":"Europe/Helsinki",
    "iso:country":"FI",
    "wof:name":"Leinolanlahti",
    "wof:placetype":"locality"
},
  "geometry": {"coordinates":[27.25,63.03333000000001],"type":"Point"}
}