{
  "type": "Feature",
  "properties": {
    "gn:admin1_code":"1.0",
    "gn:admin2_code":"16.0",
    "gn:admin3_code":"407.0",
    "gn:asciiname":"Kimonkylae",
    "gn:cc2":"FI",
    "gn:country_code":"FI",
    "gn:dem":33,
    "gn:feature_class":"P",
    "gn:feature_code":"PPL",
    "gn:name":"Kimonkyl\u00e4",
    "gn:population":0,
    "gn:timezone":"Europe/Helsinki",
    "iso:country":"FI",
    "name:eng_x_preferred":[
        "Kimonkyla"
    ],
    "name:rus_x_preferred":[
        "\u041a\u0438\u043c\u043e\u043d\u043a\u044e\u043b\u044f"
    ],
    "name:und_x_variant":[
        "Kimob\u00f6le",
        "Kimonkyla"
    ],
    "wof:name":"Kimonkylae",
    "wof:placetype":"locality"
},
  "geometry": {"coordinates":[26.30438,60.70663],"type":"Point"}
}