{
  "type": "Feature",
  "properties": {
    "gn:admin1_code":"1.0",
    "gn:admin2_code":"15.0",
    "gn:admin3_code":"638.0",
    "gn:asciiname":"Ali-Vekkoski",
    "gn:country_code":"FI",
    "gn:dem":29,
    "gn:feature_class":"P",
    "gn:feature_code":"PPL",
    "gn:name":"Ali-Vekkoski",
    "gn:population":0,
    "gn:timezone":"Europe/Helsinki",
    "iso:country":"FI",
    "name:fin_x_preferred":[
        "Ali-Vekkoski"
    ],
    "name:swe_x_preferred":[
        "S\u00f6derveckoski"
    ],
    "wof:name":"Ali-Vekkoski",
    "wof:placetype":"locality"
},
  "geometry": {"coordinates":[25.43581,60.37091],"type":"Point"}
}