{
  "type": "Feature",
  "properties": {
    "gn:admin1_code":"1.0",
    "gn:admin2_code":"11.0",
    "gn:admin3_code":"92.0",
    "gn:asciiname":"Simonkallio",
    "gn:country_code":"FI",
    "gn:dem":26,
    "gn:feature_class":"P",
    "gn:feature_code":"PPL",
    "gn:name":"Simonkallio",
    "gn:population":0,
    "gn:timezone":"Europe/Helsinki",
    "iso:country":"FI",
    "name:fin_x_preferred":[
        "Simonkallio"
    ],
    "name:swe_x_preferred":[
        "Simonsberg"
    ],
    "wof:name":"Simonkallio",
    "wof:placetype":"locality"
},
  "geometry": {"coordinates":[25.01913,60.30541],"type":"Point"}
}