{
  "type": "Feature",
  "properties": {
    "gn:admin1_code":"12.0",
    "gn:admin2_code":"122.0",
    "gn:admin3_code":"146.0",
    "gn:asciiname":"Lylykoski",
    "gn:country_code":"FI",
    "gn:dem":148,
    "gn:feature_class":"P",
    "gn:feature_code":"PPL",
    "gn:name":"Lylykoski",
    "gn:population":0,
    "gn:timezone":"Europe/Helsinki",
    "iso:country":"FI",
    "wof:name":"Lylykoski",
    "wof:placetype":"locality"
},
  "geometry": {"coordinates":[30.68333,62.76667],"type":"Point"}
}