{
  "type": "Feature",
  "properties": {
    "gn:admin1_code":"19.0",
    "gn:admin2_code":"193.0",
    "gn:admin3_code":"854.0",
    "gn:asciiname":"Mikontorma",
    "gn:country_code":"FI",
    "gn:dem":61,
    "gn:feature_class":"P",
    "gn:feature_code":"PPL",
    "gn:name":"Mikont\u00f6rm\u00e4",
    "gn:population":0,
    "gn:timezone":"Europe/Helsinki",
    "iso:country":"FI",
    "name:fin_x_preferred":[
        "Mikont\u00f6rm\u00e4"
    ],
    "name:und_x_variant":[
        "M\u00e4kituoma"
    ],
    "wof:name":"Mikontorma",
    "wof:placetype":"locality"
},
  "geometry": {"coordinates":[23.97683,66.78023],"type":"Point"}
}