{
  "type": "Feature",
  "properties": {
    "iso:country":"FI",
    "name:deu_x_preferred":[
        "Vanaja"
    ],
    "name:eng_x_preferred":[
        "Vanaja"
    ],
    "name:fin_x_preferred":[
        "Vanaja"
    ],
    "name:fra_x_preferred":[
        "Vanaja"
    ],
    "name:nob_x_preferred":[
        "V\u00e5n\u00e5"
    ],
    "name:rus_x_preferred":[
        "\u0412\u0430\u043d\u0430\u044f"
    ],
    "name:swe_x_preferred":[
        "V\u00e5n\u00e5"
    ],
    "qs:a0":"Suomi#Finland",
    "qs:a1":"*Kanta-H\u00e4me#Egentliga Tavastland",
    "qs:a1r":"0Etel\u00e4-Suomen AVI#S\u00f6dra Finlands RFV",
    "qs:adm0":"Suomi#Finland",
    "qs:la_lc":"*",
    "qs:level":"locality",
    "qs:loc":"Vanaja",
    "qs:loc_alt":"Vanaja",
    "qs:pop":0,
    "qs:type":"buffered point",
    "wd:wordcount":60,
    "wof:name":"Vanaja",
    "wof:placetype":"locality"
},
  "geometry": {"coordinates":[24.523534,60.964291],"type":"Point"}
}