{
  "type": "Feature",
  "properties": {
    "iso:country":"FI",
    "name:ara_x_preferred":[
        "\u0641\u0627\u0646\u0627\u064a\u0627"
    ],
    "name:cat_x_preferred":[
        "Vanaja"
    ],
    "name:deu_x_preferred":[
        "Vanaja"
    ],
    "name:eng_x_preferred":[
        "Vanaja"
    ],
    "name:est_x_preferred":[
        "Vanaja vald"
    ],
    "name:fin_x_preferred":[
        "Vanaja"
    ],
    "name:fra_x_preferred":[
        "Vanaja"
    ],
    "name:gle_x_preferred":[
        "Vanaja"
    ],
    "name:jpn_x_preferred":[
        "\u30f4\u30a1\u30ca\u30cf"
    ],
    "name:nob_x_preferred":[
        "V\u00e5n\u00e5"
    ],
    "name:rus_x_preferred":[
        "\u0412\u0430\u043d\u0430\u044f"
    ],
    "name:sju_x_preferred":[
        "Vanaja"
    ],
    "name:sme_x_preferred":[
        "Vanaja"
    ],
    "name:smn_x_preferred":[
        "Vanaja"
    ],
    "name:sms_x_preferred":[
        "Vanaja"
    ],
    "name:spa_x_preferred":[
        "Vanaja"
    ],
    "name:swe_x_preferred":[
        "V\u00e5n\u00e5"
    ],
    "name:zho_x_preferred":[
        "\u74e6\u7eb3\u4e9a"
    ],
    "qs:a0":"Suomi#Finland",
    "qs:a1":"*Kanta-H\u00e4me#Egentliga Tavastland",
    "qs:a1r":"0Etel\u00e4-Suomen AVI#S\u00f6dra Finlands RFV",
    "qs:adm0":"Suomi#Finland",
    "qs:la_lc":"*",
    "qs:level":"locality",
    "qs:loc":"Vanaja",
    "qs:loc_alt":"Vanaja",
    "qs:pop":0,
    "qs:type":"buffered point",
    "wd:wordcount":60,
    "wof:name":"Vanaja",
    "wof:placetype":"locality"
},
  "geometry": {"coordinates":[24.523534,60.964291],"type":"Point"}
}