{
  "type": "Feature",
  "properties": {
    "gn:admin1_code":"7.0",
    "gn:admin2_code":"71.0",
    "gn:admin3_code":"111.0",
    "gn:asciiname":"Paistjaervi",
    "gn:country_code":"FI",
    "gn:dem":92,
    "gn:feature_class":"P",
    "gn:feature_code":"PPL",
    "gn:name":"Paistj\u00e4rvi",
    "gn:population":0,
    "gn:timezone":"Europe/Helsinki",
    "iso:country":"FI",
    "wof:name":"Paistjaervi",
    "wof:placetype":"locality"
},
  "geometry": {"coordinates":[26.3645,61.26893000000001],"type":"Point"}
}