{
  "type": "Feature",
  "properties": {
    "gn:admin1_code":"17.0",
    "gn:admin2_code":"176.0",
    "gn:admin3_code":"626.0",
    "gn:asciiname":"Honkaperae",
    "gn:country_code":"FI",
    "gn:dem":152,
    "gn:feature_class":"P",
    "gn:feature_code":"PPL",
    "gn:name":"Honkaper\u00e4",
    "gn:population":0,
    "gn:timezone":"Europe/Helsinki",
    "iso:country":"FI",
    "name:und_x_variant":[
        "Honkam\u00e4ki",
        "Honkaper\u00e4"
    ],
    "wof:name":"Honkaperae",
    "wof:placetype":"locality"
},
  "geometry": {"coordinates":[26.25779,63.69692],"type":"Point"}
}