{
  "type": "Feature",
  "properties": {
    "gn:admin1_code":"6.0",
    "gn:admin2_code":"64.0",
    "gn:admin3_code":"980.0",
    "gn:asciiname":"Heinaelammi",
    "gn:country_code":"FI",
    "gn:dem":151,
    "gn:feature_class":"P",
    "gn:feature_code":"PPL",
    "gn:name":"Hein\u00e4lammi",
    "gn:population":0,
    "gn:timezone":"Europe/Helsinki",
    "iso:country":"FI",
    "wof:name":"Heinaelammi",
    "wof:placetype":"locality"
},
  "geometry": {"coordinates":[23.50277,61.77794],"type":"Point"}
}