{
  "type": "Feature",
  "properties": {
    "gn:admin1_code":"12.0",
    "gn:admin2_code":"122.0",
    "gn:admin3_code":"276.0",
    "gn:asciiname":"Kontiolahti",
    "gn:country_code":"FI",
    "gn:dem":138,
    "gn:feature_class":"P",
    "gn:feature_code":"PPLA3",
    "gn:name":"Kontiolahti",
    "gn:population":12411,
    "gn:timezone":"Europe/Helsinki",
    "iso:country":"FI",
    "name:bel_x_preferred":[
        "\u041a\u043e\u043d\u0442\u044b\u044f\u043b\u0430\u0445\u0442\u044b"
    ],
    "name:ceb_x_preferred":[
        "Kontiolahti"
    ],
    "name:ces_x_preferred":[
        "Kontiolahti"
    ],
    "name:deu_x_preferred":[
        "Kontiolahti"
    ],
    "name:eng_x_preferred":[
        "Kontiolahti"
    ],
    "name:epo_x_preferred":[
        "Kontiolahti"
    ],
    "name:est_x_preferred":[
        "Kontiolahti vald"
    ],
    "name:eus_x_preferred":[
        "Kontiolahti"
    ],
    "name:fin_x_preferred":[
        "Kontiolahti"
    ],
    "name:fra_x_preferred":[
        "Kontiolahti"
    ],
    "name:glg_x_preferred":[
        "Kontiolahti"
    ],
    "name:ile_x_preferred":[
        "Kontiolahti"
    ],
    "name:ita_x_preferred":[
        "Kontiolahti"
    ],
    "name:lav_x_preferred":[
        "Kontiolahti"
    ],
    "name:nds_x_preferred":[
        "Kontiolahti"
    ],
    "name:nld_x_preferred":[
        "Kontiolahti"
    ],
    "name:nno_x_preferred":[
        "Kontiolax"
    ],
    "name:nor_x_preferred":[
        "Kontiolahti"
    ],
    "name:pol_x_preferred":[
        "Kontiolahti"
    ],
    "name:ron_x_preferred":[
        "Kontiolahti"
    ],
    "name:rus_x_preferred":[
        "\u041a\u043e\u043d\u0442\u0438\u043e\u043b\u0430\u0445\u0442\u0438"
    ],
    "name:slk_x_preferred":[
        "Kontiolahti"
    ],
    "name:sme_x_preferred":[
        "Kontiolahti"
    ],
    "name:spa_x_preferred":[
        "Kontiolahti"
    ],
    "name:sqi_x_preferred":[
        "Kontiolahti"
    ],
    "name:swe_x_preferred":[
        "Kontiolax"
    ],
    "name:tur_x_preferred":[
        "Kontiolahti"
    ],
    "name:ukr_x_preferred":[
        "\u041a\u043e\u043d\u0442\u0456\u043e\u043b\u0430\u0433\u0442\u0456"
    ],
    "name:ukr_x_variant":[
        "\u041a\u043e\u043d\u0442\u0456\u043e\u043b\u0430\u0445\u0442\u0456"
    ],
    "name:zho_x_preferred":[
        "\u5b54\u8482\u5967\u62c9\u8d6b\u8482"
    ],
    "wof:name":"Kontiolahti",
    "wof:placetype":"locality",
    "wof:population":12411
},
  "geometry": {"coordinates":[29.84711,62.76023000000001],"type":"Point"}
}