{
  "type": "Feature",
  "properties": {
    "gn:admin1_code":"15.0",
    "gn:admin2_code":"153.0",
    "gn:admin3_code":"287.0",
    "gn:asciiname":"Korsbaeck",
    "gn:country_code":"FI",
    "gn:dem":72,
    "gn:feature_class":"P",
    "gn:feature_code":"PPL",
    "gn:name":"Korsb\u00e4ck",
    "gn:population":0,
    "gn:timezone":"Europe/Helsinki",
    "iso:country":"FI",
    "wof:name":"Korsbaeck",
    "wof:placetype":"locality"
},
  "geometry": {"coordinates":[21.65958,62.18833000000001],"type":"Point"}
}