{
  "type": "Feature",
  "properties": {
    "gn:admin1_code":"7.0",
    "gn:admin2_code":"71.0",
    "gn:admin3_code":"560.0",
    "gn:asciiname":"Niemenkylae",
    "gn:country_code":"FI",
    "gn:dem":82,
    "gn:feature_class":"P",
    "gn:feature_code":"PPL",
    "gn:name":"Niemenkyl\u00e4",
    "gn:population":0,
    "gn:timezone":"Europe/Helsinki",
    "iso:country":"FI",
    "name:und_x_variant":[
        "Niemist\u00f6",
        "Niemi",
        "Niemenkyl\u00e4"
    ],
    "wof:name":"Niemenkylae",
    "wof:placetype":"locality"
},
  "geometry": {"coordinates":[25.67977,60.81028000000001],"type":"Point"}
}