{
  "type": "Feature",
  "properties": {
    "gn:admin1_code":"15.0",
    "gn:admin2_code":"154.0",
    "gn:admin3_code":"599.0",
    "gn:asciiname":"OEverpurmo",
    "gn:country_code":"FI",
    "gn:dem":41,
    "gn:feature_class":"P",
    "gn:feature_code":"PPL",
    "gn:name":"\u00d6verpurmo",
    "gn:population":0,
    "gn:timezone":"Europe/Helsinki",
    "iso:country":"FI",
    "wof:name":"OEverpurmo",
    "wof:placetype":"locality"
},
  "geometry": {"coordinates":[23.03333,63.48333],"type":"Point"}
}