{
  "type": "Feature",
  "properties": {
    "gn:admin1_code":"14.0",
    "gn:admin2_code":"146.0",
    "gn:admin3_code":"403.0",
    "gn:asciiname":"Myllykangas",
    "gn:country_code":"FI",
    "gn:dem":72,
    "gn:feature_class":"P",
    "gn:feature_code":"PPL",
    "gn:name":"Myllykangas",
    "gn:population":0,
    "gn:timezone":"Europe/Helsinki",
    "iso:country":"FI",
    "wof:name":"Myllykangas",
    "wof:placetype":"locality"
},
  "geometry": {"coordinates":[23.61667000000001,63.03333000000001],"type":"Point"}
}