{
  "type": "Feature",
  "properties": {
    "iso:country":"FI",
    "name:eng_x_preferred":[
        "T\u00f6rm\u00e4"
    ],
    "name:eus_x_preferred":[
        "T\u00f6rm\u00e4"
    ],
    "name:fas_x_preferred":[
        "\u062a\u0631\u0645\u0627"
    ],
    "name:fin_x_preferred":[
        "T\u00f6rm\u00e4"
    ],
    "name:nld_x_preferred":[
        "T\u00f6rm\u00e4"
    ],
    "qs_pg:aaroncc":"FI",
    "qs_pg:name":"T\u00f6rm\u00e4",
    "qs_pg:name_adm0":"Suomi",
    "qs_pg:name_adm1":"Lapin maakunta",
    "qs_pg:photos":4,
    "qs_pg:photos_1k":1,
    "qs_pg:photos_9k":1,
    "qs_pg:photos_9r":1,
    "qs_pg:photos_all":4,
    "qs_pg:photos_sr":1,
    "qs_pg:pop_sr":0,
    "qs_pg:qs_pg_placetype":"locality",
    "qs_pg:qs_pg_placetype_gp":"Town",
    "qs_pg:woe_adm0":23424812,
    "woe:adm0_id":23424812,
    "woe:name_adm0":"Suomi",
    "woe:name_adm1":"Lapin maakunta",
    "woe:placetype":"Town",
    "wof:name":"T\u00f6rm\u00e4",
    "wof:placetype":"locality"
},
  "geometry": {"coordinates":[24.590836,65.91022599999999],"type":"Point"}
}