{
  "type": "Feature",
  "properties": {
    "gn:admin1_code":"1.0",
    "gn:admin2_code":"11.0",
    "gn:admin3_code":"49.0",
    "gn:asciiname":"Tillinmaeki",
    "gn:cc2":"FI",
    "gn:country_code":"FI",
    "gn:dem":30,
    "gn:feature_class":"P",
    "gn:feature_code":"PPL",
    "gn:name":"Tillinm\u00e4ki",
    "gn:population":0,
    "gn:timezone":"Europe/Helsinki",
    "iso:country":"FI",
    "name:fin_x_preferred":[
        "Tillinm\u00e4ki"
    ],
    "wof:name":"Tillinmaeki",
    "wof:placetype":"locality"
},
  "geometry": {"coordinates":[24.63049,60.16995],"type":"Point"}
}