{
  "type": "Feature",
  "properties": {
    "gn:admin1_code":"7.0",
    "gn:admin2_code":"71.0",
    "gn:admin3_code":"398.0",
    "gn:asciiname":"Uusikylae",
    "gn:country_code":"FI",
    "gn:dem":108,
    "gn:feature_class":"P",
    "gn:feature_code":"PPL",
    "gn:name":"Uusikyl\u00e4",
    "gn:population":0,
    "gn:timezone":"Europe/Helsinki",
    "iso:country":"FI",
    "wof:name":"Uusikylae",
    "wof:placetype":"locality"
},
  "geometry": {"coordinates":[26.02386,60.92718000000001],"type":"Point"}
}