{
  "type": "Feature",
  "properties": {
    "gn:admin1_code":"1.0",
    "gn:admin2_code":"11.0",
    "gn:admin3_code":"49.0",
    "gn:asciiname":"Kilonkallio",
    "gn:country_code":"FI",
    "gn:dem":24,
    "gn:feature_class":"P",
    "gn:feature_code":"PPLL",
    "gn:name":"Kilonkallio",
    "gn:population":0,
    "gn:timezone":"Europe/Helsinki",
    "iso:country":"FI",
    "name:dan_x_preferred":[
        "Kiloberget"
    ],
    "name:isl_x_preferred":[
        "Kiloberget"
    ],
    "name:nor_x_preferred":[
        "Kiloberget"
    ],
    "name:swe_x_preferred":[
        "Kiloberget"
    ],
    "wof:name":"Kilonkallio",
    "wof:placetype":"locality"
},
  "geometry": {"coordinates":[24.78016,60.22012],"type":"Point"}
}