{
  "type": "Feature",
  "properties": {
    "gn:admin1_code":"14.0",
    "gn:admin2_code":"142.0",
    "gn:admin3_code":"145.0",
    "gn:asciiname":"Haapaloukko",
    "gn:country_code":"FI",
    "gn:dem":108,
    "gn:feature_class":"P",
    "gn:feature_code":"PPL",
    "gn:name":"Haapaloukko",
    "gn:population":0,
    "gn:timezone":"Europe/Helsinki",
    "iso:country":"FI",
    "name:fin_x_preferred":[
        "Haapaloukko"
    ],
    "wof:name":"Haapaloukko",
    "wof:placetype":"locality"
},
  "geometry": {"coordinates":[22.31744,62.7034],"type":"Point"}
}