{
  "type": "Feature",
  "properties": {
    "gn:admin1_code":"18.0",
    "gn:admin2_code":"181.0",
    "gn:admin3_code":"620.0",
    "gn:asciiname":"Ulkola",
    "gn:country_code":"FI",
    "gn:dem":208,
    "gn:feature_class":"P",
    "gn:feature_code":"PPL",
    "gn:name":"Ulkola",
    "gn:population":0,
    "gn:timezone":"Europe/Helsinki",
    "iso:country":"FI",
    "wof:name":"Ulkola",
    "wof:placetype":"locality"
},
  "geometry": {"coordinates":[27.95,65.06667],"type":"Point"}
}