{
  "type": "Feature",
  "properties": {
    "gn:admin1_code":"13.0",
    "gn:admin2_code":"134.0",
    "gn:admin3_code":"182.0",
    "gn:asciiname":"Kaeaepaelae",
    "gn:country_code":"FI",
    "gn:dem":79,
    "gn:feature_class":"P",
    "gn:feature_code":"PPL",
    "gn:name":"K\u00e4\u00e4p\u00e4l\u00e4",
    "gn:population":0,
    "gn:timezone":"Europe/Helsinki",
    "iso:country":"FI",
    "wof:name":"Kaeaepaelae",
    "wof:placetype":"locality"
},
  "geometry": {"coordinates":[25.14277,61.85814],"type":"Point"}
}