{
  "type": "Feature",
  "properties": {
    "gn:admin1_code":"1.0",
    "gn:admin2_code":"11.0",
    "gn:admin3_code":"92.0",
    "gn:asciiname":"Simonmetsae",
    "gn:country_code":"FI",
    "gn:dem":26,
    "gn:feature_class":"P",
    "gn:feature_code":"PPL",
    "gn:name":"Simonmets\u00e4",
    "gn:population":0,
    "gn:timezone":"Europe/Helsinki",
    "iso:country":"FI",
    "name:fin_x_preferred":[
        "Simonmets\u00e4"
    ],
    "name:swe_x_preferred":[
        "Simonsskog"
    ],
    "wof:name":"Simonmetsae",
    "wof:placetype":"locality"
},
  "geometry": {"coordinates":[25.02493,60.30597],"type":"Point"}
}