{
  "type": "Feature",
  "properties": {
    "iso:country":"FI",
    "name:eng_x_preferred":[
        "Lauritsala"
    ],
    "name:est_x_preferred":[
        "Lauritsala vald"
    ],
    "name:fin_x_preferred":[
        "Lauritsala"
    ],
    "name:fre_x_preferred":[
        "Lauritsala"
    ],
    "name:ger_x_preferred":[
        "Lauritsala"
    ],
    "name:nob_x_preferred":[
        "Lauritsala"
    ],
    "name:rus_x_preferred":[
        "\u041b\u0430\u0443\u0440\u0438\u0442\u0441\u0430\u043b\u0430"
    ],
    "name:swe_x_preferred":[
        "Lauritsala"
    ],
    "qs_pg:aaroncc":"FI",
    "qs_pg:name":"Lauritsala",
    "qs_pg:name_adm0":"Suomi",
    "qs_pg:name_adm1":"Etel\u00e4-Karjalan maakunta",
    "qs_pg:photos":107,
    "qs_pg:photos_1k":22,
    "qs_pg:photos_9k":1,
    "qs_pg:photos_9r":3,
    "qs_pg:photos_all":107,
    "qs_pg:photos_sr":3,
    "qs_pg:pop_sr":0,
    "qs_pg:qs_pg_placetype":"locality",
    "qs_pg:qs_pg_placetype_gp":"Town",
    "qs_pg:woe_adm0":23424812,
    "woe:adm0_id":23424812,
    "woe:name_adm0":"Suomi",
    "woe:name_adm1":"Etel\u00e4-Karjalan maakunta",
    "woe:placetype":"Town",
    "wof:name":"Lauritsala",
    "wof:placetype":"locality"
},
  "geometry": {"coordinates":[28.266155,61.074297],"type":"Point"}
}