{
  "type": "Feature",
  "properties": {
    "gn:admin1_code":"1.0",
    "gn:admin2_code":"14.0",
    "gn:admin3_code":"710.0",
    "gn:asciiname":"Persboele",
    "gn:country_code":"FI",
    "gn:dem":24,
    "gn:feature_class":"P",
    "gn:feature_code":"PPL",
    "gn:name":"Persb\u00f6le",
    "gn:population":0,
    "gn:timezone":"Europe/Helsinki",
    "iso:country":"FI",
    "wof:name":"Persboele",
    "wof:placetype":"locality"
},
  "geometry": {"coordinates":[23.41404,60.08646],"type":"Point"}
}