{
  "type": "Feature",
  "properties": {
    "gn:admin1_code":"9.0",
    "gn:admin2_code":"91.0",
    "gn:admin3_code":"441.0",
    "gn:asciiname":"Hietamies",
    "gn:country_code":"FI",
    "gn:dem":80,
    "gn:feature_class":"P",
    "gn:feature_code":"PPL",
    "gn:name":"Hietamies",
    "gn:population":0,
    "gn:timezone":"Europe/Helsinki",
    "iso:country":"FI",
    "wof:name":"Hietamies",
    "wof:placetype":"locality"
},
  "geometry": {"coordinates":[27.34184,60.92664],"type":"Point"}
}