{
  "type": "Feature",
  "properties": {
    "gn:admin1_code":"11.0",
    "gn:admin2_code":"112.0",
    "gn:admin3_code":"297.0",
    "gn:asciiname":"Patajaervi",
    "gn:country_code":"FI",
    "gn:dem":82,
    "gn:feature_class":"P",
    "gn:feature_code":"PPL",
    "gn:name":"Pataj\u00e4rvi",
    "gn:population":0,
    "gn:timezone":"Europe/Helsinki",
    "iso:country":"FI",
    "wof:name":"Patajaervi",
    "wof:placetype":"locality"
},
  "geometry": {"coordinates":[27.16667,63.23333],"type":"Point"}
}