{
  "type": "Feature",
  "properties": {
    "gn:admin1_code":"10.0",
    "gn:admin2_code":"101.0",
    "gn:admin3_code":"507.0",
    "gn:asciiname":"Metsaekylae",
    "gn:country_code":"FI",
    "gn:dem":120,
    "gn:feature_class":"P",
    "gn:feature_code":"PPL",
    "gn:name":"Mets\u00e4kyl\u00e4",
    "gn:population":0,
    "gn:timezone":"Europe/Helsinki",
    "iso:country":"FI",
    "wof:name":"Metsaekylae",
    "wof:placetype":"locality"
},
  "geometry": {"coordinates":[26.74501,61.27071],"type":"Point"}
}