{
  "type": "Feature",
  "properties": {
    "gn:admin1_code":"2.0",
    "gn:admin2_code":"23.0",
    "gn:admin3_code":"738.0",
    "gn:asciiname":"Laempinen",
    "gn:country_code":"FI",
    "gn:dem":16,
    "gn:feature_class":"P",
    "gn:feature_code":"PPL",
    "gn:name":"L\u00e4mpinen",
    "gn:population":0,
    "gn:timezone":"Europe/Helsinki",
    "iso:country":"FI",
    "name:swe_x_preferred":[
        "L\u00e4mmis"
    ],
    "name:und_x_variant":[
        "Lemminen",
        "L\u00e4mpinen"
    ],
    "wof:name":"Laempinen",
    "wof:placetype":"locality"
},
  "geometry": {"coordinates":[22.65,60.26667],"type":"Point"}
}