{
  "type": "Feature",
  "properties": {
    "gn:admin1_code":"19.0",
    "gn:admin2_code":"197.0",
    "gn:admin3_code":"758.0",
    "gn:asciiname":"Metsola",
    "gn:country_code":"FI",
    "gn:dem":274,
    "gn:feature_class":"P",
    "gn:feature_code":"PPL",
    "gn:name":"Metsola",
    "gn:population":0,
    "gn:timezone":"Europe/Helsinki",
    "iso:country":"FI",
    "wof:name":"Metsola",
    "wof:placetype":"locality"
},
  "geometry": {"coordinates":[26.21667,67.26666999999999],"type":"Point"}
}