{
  "type": "Feature",
  "properties": {
    "gn:admin1_code":"7.0",
    "gn:admin2_code":"71.0",
    "gn:admin3_code":"111.0",
    "gn:asciiname":"Hirvisalo",
    "gn:country_code":"FI",
    "gn:dem":94,
    "gn:feature_class":"P",
    "gn:feature_code":"PPL",
    "gn:name":"Hirvisalo",
    "gn:population":0,
    "gn:timezone":"Europe/Helsinki",
    "iso:country":"FI",
    "name:eng_x_preferred":[
        "Hirvisalo"
    ],
    "name:rus_x_preferred":[
        "\u0425\u0438\u0440\u0432\u0438\u0441\u0430\u043b\u043e"
    ],
    "wof:name":"Hirvisalo",
    "wof:placetype":"locality"
},
  "geometry": {"coordinates":[26.28021,61.25555],"type":"Point"}
}