{
  "type": "Feature",
  "properties": {
    "gn:admin1_code":"4.0",
    "gn:admin2_code":"41.0",
    "gn:admin3_code":"50.0",
    "gn:asciiname":"Liesjaervenkulma",
    "gn:country_code":"FI",
    "gn:dem":70,
    "gn:feature_class":"P",
    "gn:feature_code":"PPL",
    "gn:name":"Liesj\u00e4rvenkulma",
    "gn:population":0,
    "gn:timezone":"Europe/Helsinki",
    "iso:country":"FI",
    "name:fin_x_preferred":[
        "Liesj\u00e4rvenkulma"
    ],
    "wof:name":"Liesjaervenkulma",
    "wof:placetype":"locality"
},
  "geometry": {"coordinates":[21.97416,60.92719],"type":"Point"}
}