{
  "type": "Feature",
  "properties": {
    "gn:admin1_code":"17.0",
    "gn:admin2_code":"173.0",
    "gn:admin3_code":"615.0",
    "gn:asciiname":"Puhos",
    "gn:country_code":"FI",
    "gn:dem":174,
    "gn:feature_class":"P",
    "gn:feature_code":"PPL",
    "gn:name":"Puhos",
    "gn:population":224,
    "gn:timezone":"Europe/Helsinki",
    "iso:country":"FI",
    "name:eng_x_preferred":[
        "Puhos"
    ],
    "name:rus_x_preferred":[
        "\u041f\u0443\u0445\u043e\u0441"
    ],
    "name:und_x_variant":[
        "Puhoskyl\u00e4"
    ],
    "wof:name":"Puhos",
    "wof:placetype":"locality",
    "wof:population":224
},
  "geometry": {"coordinates":[27.8524,65.27743000000001],"type":"Point"}
}