{
  "type": "Feature",
  "properties": {
    "gn:admin1_code":"17.0",
    "gn:admin2_code":"174.0",
    "gn:admin3_code":"748.0",
    "gn:asciiname":"Rankinen",
    "gn:cc2":"FI",
    "gn:country_code":"FI",
    "gn:dem":76,
    "gn:feature_class":"P",
    "gn:feature_code":"PPL",
    "gn:name":"Rankinen",
    "gn:population":0,
    "gn:timezone":"Europe/Helsinki",
    "iso:country":"FI",
    "name:und_x_variant":[
        "Iso Rankinen",
        "Rankinen"
    ],
    "wof:name":"Rankinen",
    "wof:placetype":"locality"
},
  "geometry": {"coordinates":[25.29756,64.48869000000001],"type":"Point"}
}