{
  "type": "Feature",
  "properties": {
    "gn:country":"FI",
    "gn:fcode":"PPL",
    "gn:population":0,
    "iso:country":"FI",
    "name:eng_x_preferred":[
        "Kotala"
    ],
    "name:rus_x_preferred":[
        "\u041a\u043e\u0442\u0430\u043b\u0430"
    ],
    "qs_pg:aaroncc":"FI",
    "qs_pg:gn_country":"FI",
    "qs_pg:gn_fcode":"PPL",
    "qs_pg:gn_pop":0,
    "qs_pg:name":"Kotala",
    "qs_pg:name_adm0":"Suomi",
    "qs_pg:name_adm1":"Pirkanmaan maakunta",
    "qs_pg:photos_9r":0,
    "qs_pg:photos_sr":0,
    "qs_pg:pop_sr":0,
    "qs_pg:qs_pg_placetype":"locality",
    "qs_pg:qs_pg_placetype_gp":"Town",
    "qs_pg:woe_adm0":23424812,
    "woe:adm0_id":23424812,
    "woe:name_adm0":"Suomi",
    "woe:name_adm1":"Pirkanmaan maakunta",
    "woe:placetype":"Town",
    "wof:name":"Kotala",
    "wof:placetype":"locality"
},
  "geometry": {"coordinates":[24.03333,62.26667],"type":"Point"}
}