{
  "type": "Feature",
  "properties": {
    "gn:admin1_code":"12.0",
    "gn:admin2_code":"122.0",
    "gn:admin3_code":"167.0",
    "gn:asciiname":"Kuusjaervi",
    "gn:country_code":"FI",
    "gn:dem":179,
    "gn:feature_class":"P",
    "gn:feature_code":"PPL",
    "gn:name":"Kuusj\u00e4rvi",
    "gn:population":0,
    "gn:timezone":"Europe/Helsinki",
    "iso:country":"FI",
    "wof:name":"Kuusjaervi",
    "wof:placetype":"locality"
},
  "geometry": {"coordinates":[30.03709000000001,62.8751],"type":"Point"}
}