{
  "type": "Feature",
  "properties": {
    "gn:admin1_code":"4.0",
    "gn:admin2_code":"43.0",
    "gn:admin3_code":"531.0",
    "gn:asciiname":"Viikkala",
    "gn:country_code":"FI",
    "gn:dem":25,
    "gn:feature_class":"P",
    "gn:feature_code":"PPL",
    "gn:name":"Viikkala",
    "gn:population":0,
    "gn:timezone":"Europe/Helsinki",
    "iso:country":"FI",
    "wof:name":"Viikkala",
    "wof:placetype":"locality"
},
  "geometry": {"coordinates":[22.04669,61.3736],"type":"Point"}
}