{
  "type": "Feature",
  "properties": {
    "gn:admin1_code":"11.0",
    "gn:admin2_code":"113.0",
    "gn:admin3_code":"204.0",
    "gn:asciiname":"Luikonlahti",
    "gn:country_code":"FI",
    "gn:dem":155,
    "gn:feature_class":"P",
    "gn:feature_code":"PPL",
    "gn:name":"Luikonlahti",
    "gn:population":0,
    "gn:timezone":"Europe/Helsinki",
    "iso:country":"FI",
    "name:eng_x_preferred":[
        "Luikonlahti"
    ],
    "name:rus_x_preferred":[
        "\u041b\u0443\u0439\u043a\u043e\u043d\u043b\u0430\u0445\u0442\u0438"
    ],
    "wof:name":"Luikonlahti",
    "wof:placetype":"locality"
},
  "geometry": {"coordinates":[28.67913,62.92709],"type":"Point"}
}