{
  "type": "Feature",
  "properties": {
    "gn:admin1_code":"15.0",
    "gn:admin2_code":"154.0",
    "gn:admin3_code":"893.0",
    "gn:asciiname":"Levaelae",
    "gn:country_code":"FI",
    "gn:dem":20,
    "gn:feature_class":"P",
    "gn:feature_code":"PPL",
    "gn:name":"Lev\u00e4l\u00e4",
    "gn:population":0,
    "gn:timezone":"Europe/Helsinki",
    "iso:country":"FI",
    "name:fin_x_preferred":[
        "Lev\u00e4l\u00e4"
    ],
    "name:swe_x_preferred":[
        "L\u00f6vas"
    ],
    "name:und_x_variant":[
        "Levil\u00e4"
    ],
    "wof:name":"Levaelae",
    "wof:placetype":"locality"
},
  "geometry": {"coordinates":[22.54944,63.46036],"type":"Point"}
}