{
  "type": "Feature",
  "properties": {
    "gn:admin1_code":"15.0",
    "gn:admin2_code":"153.0",
    "gn:admin3_code":"545.0",
    "gn:asciiname":"Svartbaecken",
    "gn:country_code":"FI",
    "gn:dem":34,
    "gn:feature_class":"P",
    "gn:feature_code":"PPL",
    "gn:name":"Svartb\u00e4cken",
    "gn:population":0,
    "gn:timezone":"Europe/Helsinki",
    "iso:country":"FI",
    "name:und_x_variant":[
        "Svartb\u00e4ck",
        "Svartb\u00e4cken"
    ],
    "wof:name":"Svartbaecken",
    "wof:placetype":"locality"
},
  "geometry": {"coordinates":[21.4808,62.49177],"type":"Point"}
}