{
  "type": "Feature",
  "properties": {
    "gn:admin1_code":"10.0",
    "gn:admin2_code":"101.0",
    "gn:admin3_code":"213.0",
    "gn:asciiname":"Kutemajaervi",
    "gn:country_code":"FI",
    "gn:dem":135,
    "gn:feature_class":"P",
    "gn:feature_code":"PPL",
    "gn:name":"Kutemaj\u00e4rvi",
    "gn:population":0,
    "gn:timezone":"Europe/Helsinki",
    "iso:country":"FI",
    "name:eng_x_preferred":[
        "Kutemaj\u00e4rvi"
    ],
    "name:rus_x_preferred":[
        "\u041a\u0443\u0442\u0435\u043c\u0430\u044f\u0440\u0432\u0438"
    ],
    "wof:name":"Kutemajaervi",
    "wof:placetype":"locality"
},
  "geometry": {"coordinates":[26.75352,62.10187],"type":"Point"}
}