{
  "type": "Feature",
  "properties": {
    "gn:admin1_code":"17.0",
    "gn:admin2_code":"178.0",
    "gn:admin3_code":"305.0",
    "gn:asciiname":"Paeivaeniemi",
    "gn:country_code":"FI",
    "gn:dem":297,
    "gn:feature_class":"P",
    "gn:feature_code":"PPL",
    "gn:name":"P\u00e4iv\u00e4niemi",
    "gn:population":0,
    "gn:timezone":"Europe/Helsinki",
    "iso:country":"FI",
    "wof:name":"Paeivaeniemi",
    "wof:placetype":"locality"
},
  "geometry": {"coordinates":[29.05,66.13333],"type":"Point"}
}