{
  "type": "Feature",
  "properties": {
    "gn:admin1_code":"5.0",
    "gn:admin2_code":"52.0",
    "gn:admin3_code":"86.0",
    "gn:asciiname":"Monni",
    "gn:country_code":"FI",
    "gn:dem":120,
    "gn:feature_class":"P",
    "gn:feature_code":"PPL",
    "gn:name":"Monni",
    "gn:population":0,
    "gn:timezone":"Europe/Helsinki",
    "iso:country":"FI",
    "wof:name":"Monni",
    "wof:placetype":"locality"
},
  "geometry": {"coordinates":[24.85485,60.67839],"type":"Point"}
}