{
  "type": "Feature",
  "properties": {
    "gn:admin1_code":"14.0",
    "gn:admin2_code":"142.0",
    "gn:admin3_code":"301.0",
    "gn:asciiname":"Aho",
    "gn:country_code":"FI",
    "gn:dem":88,
    "gn:feature_class":"P",
    "gn:feature_code":"PPL",
    "gn:name":"Aho",
    "gn:population":0,
    "gn:timezone":"Europe/Helsinki",
    "iso:country":"FI",
    "name:ceb_x_preferred":[
        "Aho"
    ],
    "name:ces_x_preferred":[
        "Aho"
    ],
    "name:deu_x_preferred":[
        "Aho"
    ],
    "name:fin_x_preferred":[
        "Aho"
    ],
    "name:kaz_x_preferred":[
        "\u0410\u0445\u043e"
    ],
    "name:rus_x_preferred":[
        "\u0410\u0445\u043e"
    ],
    "name:slv_x_preferred":[
        "Aho"
    ],
    "name:swe_x_preferred":[
        "Aho"
    ],
    "name:ukr_x_preferred":[
        "\u0410\u0445\u043e"
    ],
    "wof:name":"Aho",
    "wof:placetype":"locality"
},
  "geometry": {"coordinates":[22.61667000000001,62.55],"type":"Point"}
}