{
  "type": "Feature",
  "properties": {
    "gn:admin1_code":"2.0",
    "gn:admin2_code":"25.0",
    "gn:admin3_code":"636.0",
    "gn:asciiname":"Rannankulma",
    "gn:country_code":"FI",
    "gn:dem":57,
    "gn:feature_class":"P",
    "gn:feature_code":"PPL",
    "gn:name":"Rannankulma",
    "gn:population":0,
    "gn:timezone":"Europe/Helsinki",
    "iso:country":"FI",
    "name:fin_x_preferred":[
        "Rannankulma"
    ],
    "wof:name":"Rannankulma",
    "wof:placetype":"locality"
},
  "geometry": {"coordinates":[22.42115,60.93646999999999],"type":"Point"}
}