{
  "type": "Feature",
  "properties": {
    "gn:admin1_code":"6.0",
    "gn:admin2_code":"64.0",
    "gn:admin3_code":"837.0",
    "gn:asciiname":"Taulakylae",
    "gn:country_code":"FI",
    "gn:dem":107,
    "gn:feature_class":"P",
    "gn:feature_code":"PPL",
    "gn:name":"Taulakyl\u00e4",
    "gn:population":0,
    "gn:timezone":"Europe/Helsinki",
    "iso:country":"FI",
    "wof:name":"Taulakylae",
    "wof:placetype":"locality"
},
  "geometry": {"coordinates":[23.78881,61.65726],"type":"Point"}
}