{
  "type": "Feature",
  "properties": {
    "gn:admin1_code":"10.0",
    "gn:admin2_code":"105.0",
    "gn:admin3_code":"178.0",
    "gn:asciiname":"Jaervenpaeae",
    "gn:country_code":"FI",
    "gn:dem":120,
    "gn:feature_class":"P",
    "gn:feature_code":"PPL",
    "gn:name":"J\u00e4rvenp\u00e4\u00e4",
    "gn:population":0,
    "gn:timezone":"Europe/Helsinki",
    "iso:country":"FI",
    "name:eng_x_preferred":[
        "J\u00e4rvenp\u00e4\u00e4"
    ],
    "name:rus_x_preferred":[
        "\u042f\u0440\u0432\u0435\u043d\u043f\u044f"
    ],
    "name:und_x_variant":[
        "J\u00e4rvenp\u00e4\u00e4"
    ],
    "wof:name":"Jaervenpaeae",
    "wof:placetype":"locality"
},
  "geometry": {"coordinates":[27.96348,61.83193000000001],"type":"Point"}
}