{
  "type": "Feature",
  "properties": {
    "gn:admin1_code":"1.0",
    "gn:admin2_code":"11.0",
    "gn:admin3_code":"49.0",
    "gn:asciiname":"Punametsae",
    "gn:country_code":"FI",
    "gn:dem":57,
    "gn:feature_class":"P",
    "gn:feature_code":"PPL",
    "gn:name":"Punamets\u00e4",
    "gn:population":0,
    "gn:timezone":"Europe/Helsinki",
    "iso:country":"FI",
    "name:dan_x_preferred":[
        "Brunskog"
    ],
    "name:fin_x_preferred":[
        "Punamets\u00e4"
    ],
    "name:isl_x_preferred":[
        "Brunskog"
    ],
    "name:nor_x_preferred":[
        "Brunskog"
    ],
    "name:swe_x_preferred":[
        "Brunsko"
    ],
    "name:swe_x_variant":[
        "Brunskog"
    ],
    "wof:name":"Punametsae",
    "wof:placetype":"locality"
},
  "geometry": {"coordinates":[24.71005,60.28498],"type":"Point"}
}