{
  "type": "Feature",
  "properties": {
    "gn:admin1_code":"15.0",
    "gn:admin2_code":"154.0",
    "gn:admin3_code":"893.0",
    "gn:asciiname":"Grisseloeren",
    "gn:country_code":"FI",
    "gn:dem":-9999,
    "gn:feature_class":"P",
    "gn:feature_code":"PPL",
    "gn:name":"Grissel\u00f6ren",
    "gn:population":0,
    "gn:timezone":"Europe/Helsinki",
    "iso:country":"FI",
    "name:und_x_variant":[
        "Grissel\u00f6",
        "Grissel\u00f6n",
        "Grissel\u00f6ren"
    ],
    "wof:name":"Grisseloeren",
    "wof:placetype":"locality"
},
  "geometry": {"coordinates":[22.49346,63.61221],"type":"Point"}
}