{
  "type": "Feature",
  "properties": {
    "gn:admin1_code":"8.0",
    "gn:admin2_code":"82.0",
    "gn:admin3_code":"75.0",
    "gn:asciiname":"Maentlahti",
    "gn:country_code":"FI",
    "gn:dem":6,
    "gn:feature_class":"P",
    "gn:feature_code":"PPL",
    "gn:name":"M\u00e4ntlahti",
    "gn:population":0,
    "gn:timezone":"Europe/Helsinki",
    "iso:country":"FI",
    "name:swe_x_preferred":[
        "M\u00e4ntlax"
    ],
    "wof:name":"Maentlahti",
    "wof:placetype":"locality"
},
  "geometry": {"coordinates":[27.34452000000001,60.5135],"type":"Point"}
}