{
  "type": "Feature",
  "properties": {
    "gn:admin1_code":"12.0",
    "gn:admin2_code":"122.0",
    "gn:admin3_code":"309.0",
    "gn:asciiname":"Porola",
    "gn:cc2":"FI",
    "gn:country_code":"FI",
    "gn:dem":91,
    "gn:feature_class":"P",
    "gn:feature_code":"PPL",
    "gn:name":"Porola",
    "gn:population":0,
    "gn:timezone":"Europe/Helsinki",
    "iso:country":"FI",
    "name:und_x_variant":[
        "Porokkola",
        "Poroila"
    ],
    "wof:name":"Porola",
    "wof:placetype":"locality"
},
  "geometry": {"coordinates":[29.13444,62.75458],"type":"Point"}
}