{
  "type": "Feature",
  "properties": {
    "gn:admin1_code":"7.0",
    "gn:admin2_code":"71.0",
    "gn:admin3_code":"398.0",
    "gn:asciiname":"Seesta",
    "gn:cc2":"FI",
    "gn:country_code":"FI",
    "gn:dem":128,
    "gn:feature_class":"P",
    "gn:feature_code":"PPL",
    "gn:name":"Seesta",
    "gn:population":0,
    "gn:timezone":"Europe/Helsinki",
    "iso:country":"FI",
    "name:und_x_variant":[
        "Seestaa",
        "Sesta",
        "Seesta"
    ],
    "wof:name":"Seesta",
    "wof:placetype":"locality"
},
  "geometry": {"coordinates":[25.83369,61.03968],"type":"Point"}
}