{
  "type": "Feature",
  "properties": {
    "gn:admin1_code":"14.0",
    "gn:admin2_code":"144.0",
    "gn:admin3_code":"300.0",
    "gn:asciiname":"Heroja",
    "gn:country_code":"FI",
    "gn:dem":100,
    "gn:feature_class":"P",
    "gn:feature_code":"PPL",
    "gn:name":"Heroja",
    "gn:population":0,
    "gn:timezone":"Europe/Helsinki",
    "iso:country":"FI",
    "wof:name":"Heroja",
    "wof:placetype":"locality"
},
  "geometry": {"coordinates":[23.51113,62.85882],"type":"Point"}
}