{
  "type": "Feature",
  "properties": {
    "gn:admin1_code":"8.0",
    "gn:admin2_code":"81.0",
    "gn:admin3_code":"286.0",
    "gn:asciiname":"Tervaskangas",
    "gn:country_code":"FI",
    "gn:dem":68,
    "gn:feature_class":"P",
    "gn:feature_code":"PPL",
    "gn:name":"Tervaskangas",
    "gn:population":0,
    "gn:timezone":"Europe/Helsinki",
    "iso:country":"FI",
    "wof:name":"Tervaskangas",
    "wof:placetype":"locality"
},
  "geometry": {"coordinates":[26.64695,60.87672],"type":"Point"}
}