{
  "type": "Feature",
  "properties": {
    "gn:admin1_code":"11.0",
    "gn:admin2_code":"111.0",
    "gn:admin3_code":"263.0",
    "gn:asciiname":"Aittojaervi",
    "gn:country_code":"FI",
    "gn:dem":142,
    "gn:feature_class":"P",
    "gn:feature_code":"PPL",
    "gn:name":"Aittoj\u00e4rvi",
    "gn:population":0,
    "gn:timezone":"Europe/Helsinki",
    "iso:country":"FI",
    "name:eng_x_preferred":[
        "Aittoj\u00e4rvi"
    ],
    "name:rus_x_preferred":[
        "\u0410\u0439\u0442\u0442\u043e\u044f\u0440\u0432\u0438"
    ],
    "name:und_x_variant":[
        "Aittoj\u00e4rvi"
    ],
    "wof:name":"Aittojaervi",
    "wof:placetype":"locality"
},
  "geometry": {"coordinates":[26.39625,63.67021],"type":"Point"}
}