{
  "type": "Feature",
  "properties": {
    "gn:admin1_code":"1.0",
    "gn:admin2_code":"15.0",
    "gn:admin3_code":"638.0",
    "gn:asciiname":"Baggboele",
    "gn:country_code":"FI",
    "gn:dem":9,
    "gn:feature_class":"P",
    "gn:feature_code":"PPL",
    "gn:name":"Baggb\u00f6le",
    "gn:population":0,
    "gn:timezone":"Europe/Helsinki",
    "iso:country":"FI",
    "wof:name":"Baggboele",
    "wof:placetype":"locality"
},
  "geometry": {"coordinates":[25.71826,60.29509],"type":"Point"}
}