{
  "type": "Feature",
  "properties": {
    "gn:admin1_code":"17.0",
    "gn:admin2_code":"176.0",
    "gn:admin3_code":"626.0",
    "gn:asciiname":"Lammasmaeki",
    "gn:country_code":"FI",
    "gn:dem":161,
    "gn:feature_class":"P",
    "gn:feature_code":"PPL",
    "gn:name":"Lammasm\u00e4ki",
    "gn:population":0,
    "gn:timezone":"Europe/Helsinki",
    "iso:country":"FI",
    "wof:name":"Lammasmaeki",
    "wof:placetype":"locality"
},
  "geometry": {"coordinates":[25.94119,63.71005],"type":"Point"}
}