{
  "type": "Feature",
  "properties": {
    "gn:admin1_code":"1.0",
    "gn:admin2_code":"15.0",
    "gn:admin3_code":"638.0",
    "gn:asciiname":"Ebbo",
    "gn:cc2":"FI",
    "gn:country_code":"FI",
    "gn:dem":27,
    "gn:feature_class":"P",
    "gn:feature_code":"PPL",
    "gn:name":"Ebbo",
    "gn:population":0,
    "gn:timezone":"Europe/Helsinki",
    "iso:country":"FI",
    "name:eng_x_preferred":[
        "Ebbo"
    ],
    "name:fin_x_preferred":[
        "Epoo"
    ],
    "name:ita_x_preferred":[
        "Ebbone abate"
    ],
    "name:rus_x_preferred":[
        "\u042d\u0431\u0431\u043e"
    ],
    "name:rus_x_variant":[
        "\u042d\u0431\u0431\u043e\u043d \u0420\u0435\u0439\u043c\u0441\u0441\u043a\u0438\u0439"
    ],
    "name:spa_x_preferred":[
        "Ebbo"
    ],
    "name:swe_x_preferred":[
        "Ebbo"
    ],
    "wof:name":"Ebbo",
    "wof:placetype":"locality"
},
  "geometry": {"coordinates":[25.84609,60.34906],"type":"Point"}
}