{
  "type": "Feature",
  "properties": {
    "gn:admin1_code":"7.0",
    "gn:admin2_code":"71.0",
    "gn:admin3_code":"98.0",
    "gn:asciiname":"Untila",
    "gn:country_code":"FI",
    "gn:dem":105,
    "gn:feature_class":"P",
    "gn:feature_code":"PPL",
    "gn:name":"Untila",
    "gn:population":0,
    "gn:timezone":"Europe/Helsinki",
    "iso:country":"FI",
    "wof:name":"Untila",
    "wof:placetype":"locality"
},
  "geometry": {"coordinates":[25.43564,60.98239],"type":"Point"}
}