{
  "type": "Feature",
  "properties": {
    "gn:admin1_code":"17.0",
    "gn:admin2_code":"175.0",
    "gn:admin3_code":"71.0",
    "gn:asciiname":"Ala-Sydaenmaa",
    "gn:country_code":"FI",
    "gn:dem":121,
    "gn:feature_class":"P",
    "gn:feature_code":"PPL",
    "gn:name":"Ala-Syd\u00e4nmaa",
    "gn:population":0,
    "gn:timezone":"Europe/Helsinki",
    "iso:country":"FI",
    "name:eng_x_preferred":[
        "Alasyd\u00e4nmaa"
    ],
    "name:rus_x_preferred":[
        "\u0410\u043b\u0430\u0441\u044e\u0434\u044f\u043d\u043c\u0430"
    ],
    "wof:name":"Ala-Sydaenmaa",
    "wof:placetype":"locality"
},
  "geometry": {"coordinates":[25.10282,64.06350999999999],"type":"Point"}
}