{
  "type": "Feature",
  "properties": {
    "gn:admin1_code":"17.0",
    "gn:admin2_code":"173.0",
    "gn:admin3_code":"889.0",
    "gn:asciiname":"Pinoniemi",
    "gn:country_code":"FI",
    "gn:dem":134,
    "gn:feature_class":"P",
    "gn:feature_code":"PPL",
    "gn:name":"Pinoniemi",
    "gn:population":0,
    "gn:timezone":"Europe/Helsinki",
    "iso:country":"FI",
    "wof:name":"Pinoniemi",
    "wof:placetype":"locality"
},
  "geometry": {"coordinates":[27.15,64.91667],"type":"Point"}
}