{
  "type": "Feature",
  "properties": {
    "gn:admin1_code":"5.0",
    "gn:admin2_code":"52.0",
    "gn:admin3_code":"86.0",
    "gn:asciiname":"Puujaa",
    "gn:cc2":"FI",
    "gn:country_code":"FI",
    "gn:dem":94,
    "gn:feature_class":"P",
    "gn:feature_code":"PPL",
    "gn:name":"Puujaa",
    "gn:population":0,
    "gn:timezone":"Europe/Helsinki",
    "iso:country":"FI",
    "name:und_x_variant":[
        "Puujas",
        "Puujaa"
    ],
    "wof:name":"Puujaa",
    "wof:placetype":"locality"
},
  "geometry": {"coordinates":[24.93658,60.81741],"type":"Point"}
}