{
  "type": "Feature",
  "properties": {
    "gn:admin1_code":"17.0",
    "gn:admin2_code":"178.0",
    "gn:admin3_code":"305.0",
    "gn:asciiname":"Laemsaenkylae",
    "gn:country_code":"FI",
    "gn:dem":261,
    "gn:feature_class":"P",
    "gn:feature_code":"PPL",
    "gn:name":"L\u00e4ms\u00e4nkyl\u00e4",
    "gn:population":0,
    "gn:timezone":"Europe/Helsinki",
    "iso:country":"FI",
    "name:und_x_variant":[
        "L\u00e4ms\u00e4nkyl\u00e4",
        "L\u00e4ms\u00e4"
    ],
    "wof:name":"Laemsaenkylae",
    "wof:placetype":"locality"
},
  "geometry": {"coordinates":[29.9348,65.83548],"type":"Point"}
}