{
  "type": "Feature",
  "properties": {
    "iso:country":"FI",
    "qs_pg:aaroncc":"FI",
    "qs_pg:name":"P\u00f6yh\u00f6nen",
    "qs_pg:name_adm0":"Suomi",
    "qs_pg:name_adm1":"Etel\u00e4-Pohjanmaan maakunta",
    "qs_pg:photos":12,
    "qs_pg:photos_1k":2,
    "qs_pg:photos_9k":1,
    "qs_pg:photos_9r":1,
    "qs_pg:photos_all":12,
    "qs_pg:photos_sr":1,
    "qs_pg:pop_sr":0,
    "qs_pg:qs_pg_placetype":"locality",
    "qs_pg:qs_pg_placetype_gp":"Town",
    "qs_pg:woe_adm0":23424812,
    "woe:adm0_id":23424812,
    "woe:name_adm0":"Suomi",
    "woe:name_adm1":"Etel\u00e4-Pohjanmaan maakunta",
    "woe:placetype":"Town",
    "wof:name":"P\u00f6yh\u00f6nen",
    "wof:placetype":"locality"
},
  "geometry": {"coordinates":[22.8282,63.147833],"type":"Point"}
}