{
  "type": "Feature",
  "properties": {
    "gn:admin1_code":"12.0",
    "gn:admin2_code":"124.0",
    "gn:admin3_code":"848.0",
    "gn:asciiname":"Tikkala",
    "gn:cc2":"FI",
    "gn:country_code":"FI",
    "gn:dem":129,
    "gn:feature_class":"P",
    "gn:feature_code":"PPL",
    "gn:name":"Tikkala",
    "gn:population":0,
    "gn:timezone":"Europe/Helsinki",
    "iso:country":"FI",
    "name:eng_x_preferred":[
        "Tikkala"
    ],
    "name:rus_x_preferred":[
        "\u0422\u0438\u043a\u043a\u0430\u043b\u0430"
    ],
    "name:und_x_variant":[
        "Tikkalaout"
    ],
    "wof:name":"Tikkala",
    "wof:placetype":"locality"
},
  "geometry": {"coordinates":[30.11093,62.34806],"type":"Point"}
}