{
  "type": "Feature",
  "properties": {
    "gn:admin1_code":"13.0",
    "gn:admin2_code":"131.0",
    "gn:admin3_code":"179.0",
    "gn:asciiname":"Vellipohja",
    "gn:country_code":"FI",
    "gn:dem":200,
    "gn:feature_class":"P",
    "gn:feature_code":"PPL",
    "gn:name":"Vellipohja",
    "gn:population":0,
    "gn:timezone":"Europe/Helsinki",
    "iso:country":"FI",
    "name:fin_x_preferred":[
        "Vellipohja"
    ],
    "wof:name":"Vellipohja",
    "wof:placetype":"locality"
},
  "geometry": {"coordinates":[25.4698,62.06831],"type":"Point"}
}