{
  "type": "Feature",
  "properties": {
    "gn:admin1_code":"15.0",
    "gn:admin2_code":"153.0",
    "gn:admin3_code":"545.0",
    "gn:asciiname":"Braenngardarna",
    "gn:country_code":"FI",
    "gn:dem":31,
    "gn:feature_class":"P",
    "gn:feature_code":"PPL",
    "gn:name":"Br\u00e4nng\u00e5rdarna",
    "gn:population":0,
    "gn:timezone":"Europe/Helsinki",
    "iso:country":"FI",
    "wof:name":"Braenngardarna",
    "wof:placetype":"locality"
},
  "geometry": {"coordinates":[21.54333,62.67256999999999],"type":"Point"}
}