{
  "type": "Feature",
  "properties": {
    "gn:admin1_code":"18.0",
    "gn:admin2_code":"182.0",
    "gn:admin3_code":"205.0",
    "gn:asciiname":"Katajakangas",
    "gn:country_code":"FI",
    "gn:dem":164,
    "gn:feature_class":"P",
    "gn:feature_code":"PPL",
    "gn:name":"Katajakangas",
    "gn:population":0,
    "gn:timezone":"Europe/Helsinki",
    "iso:country":"FI",
    "wof:name":"Katajakangas",
    "wof:placetype":"locality"
},
  "geometry": {"coordinates":[27.56667,64.06667],"type":"Point"}
}