{
  "type": "Feature",
  "properties": {
    "gn:admin1_code":"14.0",
    "gn:admin2_code":"146.0",
    "gn:admin3_code":"5.0",
    "gn:asciiname":"Anttila",
    "gn:country_code":"FI",
    "gn:dem":75,
    "gn:feature_class":"P",
    "gn:feature_code":"PPL",
    "gn:name":"Anttila",
    "gn:population":0,
    "gn:timezone":"Europe/Helsinki",
    "iso:country":"FI",
    "name:deu_x_preferred":[
        "Anttila"
    ],
    "name:fin_x_preferred":[
        "Anttila"
    ],
    "name:fra_x_preferred":[
        "Anttila"
    ],
    "name:rus_x_preferred":[
        "\u0410\u043d\u0442\u0442\u0438\u043b\u0430"
    ],
    "wof:name":"Anttila",
    "wof:placetype":"locality"
},
  "geometry": {"coordinates":[23.65,63.01667],"type":"Point"}
}