{
  "type": "Feature",
  "properties": {
    "gn:admin1_code":"14.0",
    "gn:admin2_code":"141.0",
    "gn:admin3_code":"151.0",
    "gn:asciiname":"Villamo",
    "gn:country_code":"FI",
    "gn:dem":91,
    "gn:feature_class":"P",
    "gn:feature_code":"PPL",
    "gn:name":"Villamo",
    "gn:population":0,
    "gn:timezone":"Europe/Helsinki",
    "iso:country":"FI",
    "wof:name":"Villamo",
    "wof:placetype":"locality"
},
  "geometry": {"coordinates":[21.87935,62.16086],"type":"Point"}
}