{
  "type": "Feature",
  "properties": {
    "gn:admin1_code":"11.0",
    "gn:admin2_code":"113.0",
    "gn:admin3_code":"857.0",
    "gn:asciiname":"Tuusmaeki",
    "gn:country_code":"FI",
    "gn:dem":152,
    "gn:feature_class":"P",
    "gn:feature_code":"PPL",
    "gn:name":"Tuusm\u00e4ki",
    "gn:population":0,
    "gn:timezone":"Europe/Helsinki",
    "iso:country":"FI",
    "wof:name":"Tuusmaeki",
    "wof:placetype":"locality"
},
  "geometry": {"coordinates":[28.55,62.81667],"type":"Point"}
}