{
  "type": "Feature",
  "properties": {
    "iso:country":"FI",
    "qs_pg:aaroncc":"FI",
    "qs_pg:name":"Passk\u00e4ret",
    "qs_pg:name_adm0":"Suomi",
    "qs_pg:name_adm1":"Pohjanmaan maakunta",
    "qs_pg:photos":19,
    "qs_pg:photos_1k":4,
    "qs_pg:photos_9k":1,
    "qs_pg:photos_9r":1,
    "qs_pg:photos_all":19,
    "qs_pg:photos_sr":1,
    "qs_pg:pop_sr":0,
    "qs_pg:qs_pg_placetype":"locality",
    "qs_pg:qs_pg_placetype_gp":"Town",
    "qs_pg:woe_adm0":23424812,
    "woe:adm0_id":23424812,
    "woe:name_adm0":"Suomi",
    "woe:name_adm1":"Pohjanmaan maakunta",
    "woe:placetype":"Town",
    "wof:name":"Passk\u00e4ret",
    "wof:placetype":"locality"
},
  "geometry": {"coordinates":[21.57968,63.119003],"type":"Point"}
}