{
  "type": "Feature",
  "properties": {
    "gn:admin1_code":"1.0",
    "gn:admin2_code":"15.0",
    "gn:admin3_code":"638.0",
    "gn:asciiname":"Pirlax",
    "gn:country_code":"FI",
    "gn:dem":25,
    "gn:feature_class":"P",
    "gn:feature_code":"PPL",
    "gn:name":"Pirlax",
    "gn:population":0,
    "gn:timezone":"Europe/Helsinki",
    "iso:country":"FI",
    "name:fin_x_preferred":[
        "Piirlahti"
    ],
    "name:swe_x_preferred":[
        "Pirlax"
    ],
    "name:und_x_variant":[
        "Pirklaks",
        "Pirlaks"
    ],
    "wof:name":"Pirlax",
    "wof:placetype":"locality"
},
  "geometry": {"coordinates":[25.84813,60.33696],"type":"Point"}
}