{
  "type": "Feature",
  "properties": {
    "gn:admin1_code":"2.0",
    "gn:admin2_code":"23.0",
    "gn:admin3_code":"738.0",
    "gn:asciiname":"Inkiniemi",
    "gn:cc2":"FI",
    "gn:country_code":"FI",
    "gn:dem":-9999,
    "gn:feature_class":"P",
    "gn:feature_code":"PPL",
    "gn:name":"Inkiniemi",
    "gn:population":0,
    "gn:timezone":"Europe/Helsinki",
    "iso:country":"FI",
    "name:dan_x_preferred":[
        "Iggn\u00e4s"
    ],
    "name:isl_x_preferred":[
        "Iggn\u00e4s"
    ],
    "name:nno_x_preferred":[
        "Iggn\u00e4s"
    ],
    "name:swe_x_preferred":[
        "Iggnes"
    ],
    "name:und_x_variant":[
        "Ikknes",
        "Ingniemi",
        "Inkiniemi"
    ],
    "wof:name":"Inkiniemi",
    "wof:placetype":"locality"
},
  "geometry": {"coordinates":[22.86067,60.28993000000001],"type":"Point"}
}