{
  "type": "Feature",
  "properties": {
    "gn:admin1_code":"8.0",
    "gn:admin2_code":"81.0",
    "gn:admin3_code":"142.0",
    "gn:asciiname":"Peraemetsaekulma",
    "gn:country_code":"FI",
    "gn:dem":85,
    "gn:feature_class":"P",
    "gn:feature_code":"PPL",
    "gn:name":"Per\u00e4mets\u00e4kulma",
    "gn:population":0,
    "gn:timezone":"Europe/Helsinki",
    "iso:country":"FI",
    "wof:name":"Peraemetsaekulma",
    "wof:placetype":"locality"
},
  "geometry": {"coordinates":[26.11667000000001,60.88333000000001],"type":"Point"}
}