{
  "type": "Feature",
  "properties": {
    "gn:admin1_code":"15.0",
    "gn:admin2_code":"153.0",
    "gn:admin3_code":"545.0",
    "gn:asciiname":"Valsas",
    "gn:country_code":"FI",
    "gn:dem":64,
    "gn:feature_class":"P",
    "gn:feature_code":"PPL",
    "gn:name":"Vals\u00e5s",
    "gn:population":0,
    "gn:timezone":"Europe/Helsinki",
    "iso:country":"FI",
    "wof:name":"Valsas",
    "wof:placetype":"locality"
},
  "geometry": {"coordinates":[21.62281,62.64024000000001],"type":"Point"}
}