{
  "type": "Feature",
  "properties": {
    "gn:admin1_code":"15.0",
    "gn:admin2_code":"152.0",
    "gn:admin3_code":"905.0",
    "gn:asciiname":"Alnaeset",
    "gn:country_code":"FI",
    "gn:dem":10,
    "gn:feature_class":"P",
    "gn:feature_code":"PPL",
    "gn:name":"Aln\u00e4set",
    "gn:population":0,
    "gn:timezone":"Europe/Helsinki",
    "iso:country":"FI",
    "wof:name":"Alnaeset",
    "wof:placetype":"locality"
},
  "geometry": {"coordinates":[21.59056,63.04821999999999],"type":"Point"}
}