{
  "type": "Feature",
  "properties": {
    "gn:admin1_code":"13.0",
    "gn:admin2_code":"138.0",
    "gn:admin3_code":"216.0",
    "gn:asciiname":"Kannonsaha",
    "gn:country_code":"FI",
    "gn:dem":130,
    "gn:feature_class":"P",
    "gn:feature_code":"PPL",
    "gn:name":"Kannonsaha",
    "gn:population":0,
    "gn:timezone":"Europe/Helsinki",
    "iso:country":"FI",
    "wof:name":"Kannonsaha",
    "wof:placetype":"locality"
},
  "geometry": {"coordinates":[25.2211,62.94747],"type":"Point"}
}