{
  "type": "Feature",
  "properties": {
    "gn:admin1_code":"15.0",
    "gn:admin2_code":"152.0",
    "gn:admin3_code":"905.0",
    "gn:asciiname":"Sabelsbacken",
    "gn:country_code":"FI",
    "gn:dem":17,
    "gn:feature_class":"P",
    "gn:feature_code":"PPL",
    "gn:name":"Sabelsbacken",
    "gn:population":0,
    "gn:timezone":"Europe/Helsinki",
    "iso:country":"FI",
    "name:swe_x_preferred":[
        "Sabelsbacken"
    ],
    "wof:name":"Sabelsbacken",
    "wof:placetype":"locality"
},
  "geometry": {"coordinates":[21.77694,63.06988000000001],"type":"Point"}
}