{
  "type": "Feature",
  "properties": {
    "gn:admin1_code":"4.0",
    "gn:admin2_code":"41.0",
    "gn:admin3_code":"51.0",
    "gn:asciiname":"Peraenkylae",
    "gn:country_code":"FI",
    "gn:dem":14,
    "gn:feature_class":"P",
    "gn:feature_code":"PPL",
    "gn:name":"Per\u00e4nkyl\u00e4",
    "gn:population":0,
    "gn:timezone":"Europe/Helsinki",
    "iso:country":"FI",
    "name:swa_x_preferred":[
        "Per\u00e4by"
    ],
    "name:und_x_variant":[
        "Per\u00e4",
        "Per\u00e4kyl\u00e4",
        "Per\u00e4nkyl\u00e4"
    ],
    "wof:name":"Peraenkylae",
    "wof:placetype":"locality"
},
  "geometry": {"coordinates":[21.66566,61.32017],"type":"Point"}
}