{
  "type": "Feature",
  "properties": {
    "gn:admin1_code":"15.0",
    "gn:admin2_code":"152.0",
    "gn:admin3_code":"946.0",
    "gn:asciiname":"Palvis",
    "gn:country_code":"FI",
    "gn:dem":14,
    "gn:feature_class":"P",
    "gn:feature_code":"PPL",
    "gn:name":"Palvis",
    "gn:population":0,
    "gn:timezone":"Europe/Helsinki",
    "iso:country":"FI",
    "name:swe_x_preferred":[
        "Palvis"
    ],
    "wof:name":"Palvis",
    "wof:placetype":"locality"
},
  "geometry": {"coordinates":[22.17416,63.21276999999999],"type":"Point"}
}