{
  "type": "Feature",
  "properties": {
    "gn:admin1_code":"1.0",
    "gn:admin2_code":"11.0",
    "gn:admin3_code":"245.0",
    "gn:asciiname":"Kuusisaari",
    "gn:country_code":"FI",
    "gn:dem":52,
    "gn:feature_class":"P",
    "gn:feature_code":"PPL",
    "gn:name":"Kuusisaari",
    "gn:population":0,
    "gn:timezone":"Europe/Helsinki",
    "iso:country":"FI",
    "name:fin_x_preferred":[
        "Kuusisaari"
    ],
    "name:fra_x_preferred":[
        "Kuusisaari"
    ],
    "name:swe_x_preferred":[
        "Gran\u00f6"
    ],
    "wof:name":"Kuusisaari",
    "wof:placetype":"locality"
},
  "geometry": {"coordinates":[25.15127,60.41014000000001],"type":"Point"}
}