{
  "type": "Feature",
  "properties": {
    "gn:admin1_code":"19.0",
    "gn:admin2_code":"191.0",
    "gn:admin3_code":"698.0",
    "gn:asciiname":"Pahalampi",
    "gn:country_code":"FI",
    "gn:dem":194,
    "gn:feature_class":"P",
    "gn:feature_code":"PPL",
    "gn:name":"Pahalampi",
    "gn:population":0,
    "gn:timezone":"Europe/Helsinki",
    "iso:country":"FI",
    "wof:name":"Pahalampi",
    "wof:placetype":"locality"
},
  "geometry": {"coordinates":[27.11667000000001,66.28333000000001],"type":"Point"}
}