{
  "type": "Feature",
  "properties": {
    "gn:admin1_code":"1.0",
    "gn:admin2_code":"11.0",
    "gn:admin3_code":"753.0",
    "gn:asciiname":"Savijaervi",
    "gn:country_code":"FI",
    "gn:dem":49,
    "gn:feature_class":"P",
    "gn:feature_code":"PPL",
    "gn:name":"Savij\u00e4rvi",
    "gn:population":0,
    "gn:timezone":"Europe/Helsinki",
    "iso:country":"FI",
    "wof:name":"Savijaervi",
    "wof:placetype":"locality"
},
  "geometry": {"coordinates":[25.3303,60.36866],"type":"Point"}
}