{
  "type": "Feature",
  "properties": {
    "gn:admin1_code":"1.0",
    "gn:admin2_code":"11.0",
    "gn:admin3_code":"927.0",
    "gn:asciiname":"Viranoja",
    "gn:country_code":"FI",
    "gn:dem":102,
    "gn:feature_class":"P",
    "gn:feature_code":"PPLL",
    "gn:name":"Viranoja",
    "gn:population":0,
    "gn:timezone":"Europe/Helsinki",
    "iso:country":"FI",
    "wof:name":"Viranoja",
    "wof:placetype":"locality"
},
  "geometry": {"coordinates":[24.58333,60.51667],"type":"Point"}
}