{
  "type": "Feature",
  "properties": {
    "gn:admin1_code":"12.0",
    "gn:admin2_code":"125.0",
    "gn:admin3_code":"911.0",
    "gn:asciiname":"Rasimaeki",
    "gn:country_code":"FI",
    "gn:dem":135,
    "gn:feature_class":"P",
    "gn:feature_code":"PPL",
    "gn:name":"Rasim\u00e4ki",
    "gn:population":0,
    "gn:timezone":"Europe/Helsinki",
    "iso:country":"FI",
    "name:und_x_variant":[
        "Rasim\u00e4ki",
        "Rasinm\u00e4ki"
    ],
    "wof:name":"Rasimaeki",
    "wof:placetype":"locality"
},
  "geometry": {"coordinates":[28.58948,63.77881],"type":"Point"}
}