{
  "type": "Feature",
  "properties": {
    "gn:admin1_code":"13.0",
    "gn:admin2_code":"131.0",
    "gn:admin3_code":"410.0",
    "gn:asciiname":"Savio",
    "gn:country_code":"FI",
    "gn:dem":78,
    "gn:feature_class":"P",
    "gn:feature_code":"PPL",
    "gn:name":"Savio",
    "gn:population":0,
    "gn:timezone":"Europe/Helsinki",
    "iso:country":"FI",
    "wof:name":"Savio",
    "wof:placetype":"locality"
},
  "geometry": {"coordinates":[26.02371,62.28426999999999],"type":"Point"}
}