{
  "type": "Feature",
  "properties": {
    "gn:admin1_code":"13.0",
    "gn:admin2_code":"131.0",
    "gn:admin3_code":"410.0",
    "gn:asciiname":"Savio",
    "gn:country_code":"FI",
    "gn:dem":78,
    "gn:feature_class":"P",
    "gn:feature_code":"PPL",
    "gn:name":"Savio",
    "gn:population":0,
    "gn:timezone":"Europe/Helsinki",
    "iso:country":"FI",
    "name:ceb_x_preferred":[
        "Savio"
    ],
    "name:deu_x_preferred":[
        "Savio"
    ],
    "name:fas_x_preferred":[
        "\u0633\u0627\u0648\u06cc\u0648"
    ],
    "name:fin_x_preferred":[
        "Savio"
    ],
    "name:fra_x_preferred":[
        "Savio"
    ],
    "name:ita_x_preferred":[
        "Savio"
    ],
    "name:nld_x_preferred":[
        "Savio"
    ],
    "name:rus_x_preferred":[
        "\u0421\u0430\u0432\u0438\u043e"
    ],
    "name:spa_x_preferred":[
        "Savio"
    ],
    "name:srp_x_preferred":[
        "\u0421\u0430\u0432\u0438\u043e"
    ],
    "name:swe_x_preferred":[
        "Savio"
    ],
    "wof:name":"Savio",
    "wof:placetype":"locality"
},
  "geometry": {"coordinates":[26.02371,62.28426999999999],"type":"Point"}
}