{
  "type": "Feature",
  "properties": {
    "gn:admin1_code":"9.0",
    "gn:admin2_code":"93.0",
    "gn:admin3_code":"700.0",
    "gn:asciiname":"Lempiaelae",
    "gn:country_code":"FI",
    "gn:dem":91,
    "gn:feature_class":"P",
    "gn:feature_code":"PPL",
    "gn:name":"Lempi\u00e4l\u00e4",
    "gn:population":0,
    "gn:timezone":"Europe/Helsinki",
    "iso:country":"FI",
    "wof:name":"Lempiaelae",
    "wof:placetype":"locality"
},
  "geometry": {"coordinates":[28.66673,61.31978],"type":"Point"}
}