{
  "type": "Feature",
  "properties": {
    "gn:admin1_code":"17.0",
    "gn:admin2_code":"173.0",
    "gn:admin3_code":"615.0",
    "gn:asciiname":"Konttila",
    "gn:country_code":"FI",
    "gn:dem":129,
    "gn:feature_class":"P",
    "gn:feature_code":"PPL",
    "gn:name":"Konttila",
    "gn:population":0,
    "gn:timezone":"Europe/Helsinki",
    "iso:country":"FI",
    "wof:name":"Konttila",
    "wof:placetype":"locality"
},
  "geometry": {"coordinates":[26.68968,65.63554000000001],"type":"Point"}
}