{
  "type": "Feature",
  "properties": {
    "gn:admin1_code":"2.0",
    "gn:admin2_code":"23.0",
    "gn:admin3_code":"202.0",
    "gn:asciiname":"Moskalanmaeki",
    "gn:country_code":"FI",
    "gn:dem":27,
    "gn:feature_class":"P",
    "gn:feature_code":"PPL",
    "gn:name":"Moskalanm\u00e4ki",
    "gn:population":0,
    "gn:timezone":"Europe/Helsinki",
    "iso:country":"FI",
    "wof:name":"Moskalanmaeki",
    "wof:placetype":"locality"
},
  "geometry": {"coordinates":[22.48782000000001,60.43223],"type":"Point"}
}