{
  "type": "Feature",
  "properties": {
    "gn:admin1_code":"18.0",
    "gn:admin2_code":"182.0",
    "gn:admin3_code":"205.0",
    "gn:asciiname":"Uimaniemi",
    "gn:country_code":"FI",
    "gn:dem":119,
    "gn:feature_class":"P",
    "gn:feature_code":"PPL",
    "gn:name":"Uimaniemi",
    "gn:population":0,
    "gn:timezone":"Europe/Helsinki",
    "iso:country":"FI",
    "wof:name":"Uimaniemi",
    "wof:placetype":"locality"
},
  "geometry": {"coordinates":[27.2303,64.18288000000001],"type":"Point"}
}