{
  "type": "Feature",
  "properties": {
    "gn:admin1_code":"2.0",
    "gn:admin2_code":"21.0",
    "gn:admin3_code":"322.0",
    "gn:asciiname":"Stusnaes",
    "gn:country_code":"FI",
    "gn:dem":33,
    "gn:feature_class":"P",
    "gn:feature_code":"PPL",
    "gn:name":"Stusn\u00e4s",
    "gn:population":0,
    "gn:timezone":"Europe/Helsinki",
    "iso:country":"FI",
    "wof:name":"Stusnaes",
    "wof:placetype":"locality"
},
  "geometry": {"coordinates":[22.48731,60.09153000000001],"type":"Point"}
}