{
  "type": "Feature",
  "properties": {
    "gn:admin1_code":"10.0",
    "gn:admin2_code":"105.0",
    "gn:admin3_code":"593.0",
    "gn:asciiname":"Suontaus",
    "gn:country_code":"FI",
    "gn:dem":122,
    "gn:feature_class":"P",
    "gn:feature_code":"PPL",
    "gn:name":"Suontaus",
    "gn:population":0,
    "gn:timezone":"Europe/Helsinki",
    "iso:country":"FI",
    "wof:name":"Suontaus",
    "wof:placetype":"locality"
},
  "geometry": {"coordinates":[27.43333,62.06667],"type":"Point"}
}