{
  "type": "Feature",
  "properties": {
    "gn:admin1_code":"4.0",
    "gn:admin2_code":"41.0",
    "gn:admin3_code":"684.0",
    "gn:asciiname":"Maeentaka",
    "gn:country_code":"FI",
    "gn:dem":28,
    "gn:feature_class":"P",
    "gn:feature_code":"PPL",
    "gn:name":"M\u00e4entaka",
    "gn:population":0,
    "gn:timezone":"Europe/Helsinki",
    "iso:country":"FI",
    "wof:name":"Maeentaka",
    "wof:placetype":"locality"
},
  "geometry": {"coordinates":[21.97784,61.04873000000001],"type":"Point"}
}