{
  "type": "Feature",
  "properties": {
    "gn:admin1_code":"16.0",
    "gn:admin2_code":"162.0",
    "gn:admin3_code":"272.0",
    "gn:asciiname":"Korplax",
    "gn:country_code":"FI",
    "gn:dem":14,
    "gn:feature_class":"P",
    "gn:feature_code":"PPL",
    "gn:name":"Korplax",
    "gn:population":0,
    "gn:timezone":"Europe/Helsinki",
    "iso:country":"FI",
    "name:fin_x_preferred":[
        "Korpilahti"
    ],
    "name:swe_x_preferred":[
        "Korplax"
    ],
    "wof:name":"Korplax",
    "wof:placetype":"locality"
},
  "geometry": {"coordinates":[23.23254,63.85685],"type":"Point"}
}