{
  "type": "Feature",
  "properties": {
    "gn:admin1_code":"15.0",
    "gn:admin2_code":"153.0",
    "gn:admin3_code":"287.0",
    "gn:asciiname":"Sarbacken",
    "gn:country_code":"FI",
    "gn:dem":29,
    "gn:feature_class":"P",
    "gn:feature_code":"PPL",
    "gn:name":"S\u00e5rbacken",
    "gn:population":0,
    "gn:timezone":"Europe/Helsinki",
    "iso:country":"FI",
    "wof:name":"Sarbacken",
    "wof:placetype":"locality"
},
  "geometry": {"coordinates":[21.4353,62.28885],"type":"Point"}
}