{
  "type": "Feature",
  "properties": {
    "gn:admin1_code":"1.0",
    "gn:admin2_code":"16.0",
    "gn:admin3_code":"434.0",
    "gn:asciiname":"OEsterby",
    "gn:country_code":"FI",
    "gn:dem":2,
    "gn:feature_class":"P",
    "gn:feature_code":"PPL",
    "gn:name":"\u00d6sterby",
    "gn:population":0,
    "gn:timezone":"Europe/Helsinki",
    "iso:country":"FI",
    "wof:name":"OEsterby",
    "wof:placetype":"locality"
},
  "geometry": {"coordinates":[26.47214,60.36895],"type":"Point"}
}