{
  "type": "Feature",
  "properties": {
    "gn:admin1_code":"13.0",
    "gn:admin2_code":"134.0",
    "gn:admin3_code":"182.0",
    "gn:asciiname":"Markkulanmaeki",
    "gn:country_code":"FI",
    "gn:dem":163,
    "gn:feature_class":"P",
    "gn:feature_code":"PPL",
    "gn:name":"Markkulanm\u00e4ki",
    "gn:population":0,
    "gn:timezone":"Europe/Helsinki",
    "iso:country":"FI",
    "name:fin_x_preferred":[
        "Markkulanm\u00e4ki"
    ],
    "wof:name":"Markkulanmaeki",
    "wof:placetype":"locality"
},
  "geometry": {"coordinates":[24.84362,61.85925],"type":"Point"}
}