{
  "type": "Feature",
  "properties": {
    "gn:admin1_code":"13.0",
    "gn:admin2_code":"138.0",
    "gn:admin3_code":"312.0",
    "gn:asciiname":"Kumpula",
    "gn:cc2":"FI",
    "gn:country_code":"FI",
    "gn:dem":235,
    "gn:feature_class":"P",
    "gn:feature_code":"PPL",
    "gn:name":"Kumpula",
    "gn:population":0,
    "gn:timezone":"Europe/Helsinki",
    "iso:country":"FI",
    "name:eng_x_preferred":[
        "Kumpula"
    ],
    "name:rus_x_preferred":[
        "\u041a\u0443\u043c\u043f\u0443\u043b\u0430"
    ],
    "name:und_x_variant":[
        "Kumpul\u00e4inen",
        "Kumpula"
    ],
    "wof:name":"Kumpula",
    "wof:placetype":"locality"
},
  "geometry": {"coordinates":[24.75291,63.05484000000001],"type":"Point"}
}