{
  "type": "Feature",
  "properties": {
    "gn:admin1_code":"15.0",
    "gn:admin2_code":"152.0",
    "gn:admin3_code":"499.0",
    "gn:asciiname":"Riback",
    "gn:country_code":"FI",
    "gn:dem":17,
    "gn:feature_class":"P",
    "gn:feature_code":"PPL",
    "gn:name":"Riback",
    "gn:population":0,
    "gn:timezone":"Europe/Helsinki",
    "iso:country":"FI",
    "name:swe_x_preferred":[
        "Riback"
    ],
    "wof:name":"Riback",
    "wof:placetype":"locality"
},
  "geometry": {"coordinates":[21.65919,63.16248],"type":"Point"}
}