{
  "type": "Feature",
  "properties": {
    "gn:gn_country":"FI",
    "gn:gn_fcode":"PPL",
    "gn:gn_pop":0,
    "iso:country":"FI",
    "qs_pg:aaroncc":"FI",
    "qs_pg:gn_country":"FI",
    "qs_pg:gn_fcode":"PPL",
    "qs_pg:gn_pop":0,
    "qs_pg:name":"Lillm\u00e4l\u00f6",
    "qs_pg:name_adm0":"Suomi",
    "qs_pg:name_adm1":"Varsinais-Suomen maakunta",
    "qs_pg:photos":98,
    "qs_pg:photos_1k":20,
    "qs_pg:photos_9k":1,
    "qs_pg:photos_9r":3,
    "qs_pg:photos_all":98,
    "qs_pg:photos_sr":3,
    "qs_pg:pop_sr":0,
    "qs_pg:qs_pg_placetype":"locality",
    "qs_pg:qs_pg_placetype_gp":"Town",
    "qs_pg:woe_adm0":23424812,
    "woe:adm0_id":23424812,
    "woe:name_adm0":"Suomi",
    "woe:name_adm1":"Varsinais-Suomen maakunta",
    "woe:placetype":"Town",
    "wof:name":"Lillm\u00e4l\u00f6",
    "wof:placetype":"locality"
},
  "geometry": {"coordinates":[22.16667,60.25],"type":"Point"}
}