{
  "type": "Feature",
  "properties": {
    "gn:admin1_code":"9.0",
    "gn:admin2_code":"91.0",
    "gn:admin3_code":"405.0",
    "gn:asciiname":"Lahnajaervi",
    "gn:country_code":"FI",
    "gn:dem":55,
    "gn:feature_class":"P",
    "gn:feature_code":"PPL",
    "gn:name":"Lahnaj\u00e4rvi",
    "gn:population":0,
    "gn:timezone":"Europe/Helsinki",
    "iso:country":"FI",
    "wof:name":"Lahnajaervi",
    "wof:placetype":"locality"
},
  "geometry": {"coordinates":[28.04667,60.79215],"type":"Point"}
}