{
  "type": "Feature",
  "properties": {
    "gn:admin1_code":"15.0",
    "gn:admin2_code":"152.0",
    "gn:admin3_code":"905.0",
    "gn:asciiname":"Torkkola",
    "gn:country_code":"FI",
    "gn:dem":15,
    "gn:feature_class":"P",
    "gn:feature_code":"PPL",
    "gn:name":"Torkkola",
    "gn:population":0,
    "gn:timezone":"Europe/Helsinki",
    "iso:country":"FI",
    "name:fin_x_preferred":[
        "Torkkola"
    ],
    "wof:name":"Torkkola",
    "wof:placetype":"locality"
},
  "geometry": {"coordinates":[22.02436,63.06148],"type":"Point"}
}