{
  "type": "Feature",
  "properties": {
    "gn:admin1_code":"12.0",
    "gn:admin2_code":"122.0",
    "gn:admin3_code":"167.0",
    "gn:asciiname":"Noljakka",
    "gn:country_code":"FI",
    "gn:dem":84,
    "gn:feature_class":"P",
    "gn:feature_code":"PPL",
    "gn:name":"Noljakka",
    "gn:population":0,
    "gn:timezone":"Europe/Helsinki",
    "iso:country":"FI",
    "wof:name":"Noljakka",
    "wof:placetype":"locality"
},
  "geometry": {"coordinates":[29.69673,62.62398],"type":"Point"}
}