{
  "type": "Feature",
  "properties": {
    "gn:admin1_code":"13.0",
    "gn:admin2_code":"132.0",
    "gn:admin3_code":"172.0",
    "gn:asciiname":"Tolvasniemi",
    "gn:country_code":"FI",
    "gn:dem":107,
    "gn:feature_class":"P",
    "gn:feature_code":"PPL",
    "gn:name":"Tolvasniemi",
    "gn:population":0,
    "gn:timezone":"Europe/Helsinki",
    "iso:country":"FI",
    "wof:name":"Tolvasniemi",
    "wof:placetype":"locality"
},
  "geometry": {"coordinates":[26.31791,61.73701],"type":"Point"}
}