{
  "type": "Feature",
  "properties": {
    "gn:admin1_code":"14.0",
    "gn:admin2_code":"142.0",
    "gn:admin3_code":"301.0",
    "gn:asciiname":"Riitaluoma",
    "gn:country_code":"FI",
    "gn:dem":124,
    "gn:feature_class":"P",
    "gn:feature_code":"PPL",
    "gn:name":"Riitaluoma",
    "gn:population":0,
    "gn:timezone":"Europe/Helsinki",
    "iso:country":"FI",
    "name:fin_x_preferred":[
        "Riitaluoma"
    ],
    "wof:name":"Riitaluoma",
    "wof:placetype":"locality"
},
  "geometry": {"coordinates":[22.26869,62.66521],"type":"Point"}
}