{
  "type": "Feature",
  "properties": {
    "gn:admin1_code":"10.0",
    "gn:admin2_code":"101.0",
    "gn:admin3_code":"491.0",
    "gn:asciiname":"Suurlahti",
    "gn:country_code":"FI",
    "gn:dem":93,
    "gn:feature_class":"P",
    "gn:feature_code":"PPL",
    "gn:name":"Suurlahti",
    "gn:population":0,
    "gn:timezone":"Europe/Helsinki",
    "iso:country":"FI",
    "name:eng_x_preferred":[
        "Suurlahti"
    ],
    "name:rus_x_preferred":[
        "\u0421\u0443\u0440\u043b\u0430\u0445\u0442\u0438"
    ],
    "wof:name":"Suurlahti",
    "wof:placetype":"locality"
},
  "geometry": {"coordinates":[27.66239,61.45851999999999],"type":"Point"}
}