{
  "type": "Feature",
  "properties": {
    "gn:admin1_code":"10.0",
    "gn:admin2_code":"101.0",
    "gn:admin3_code":"623.0",
    "gn:asciiname":"Kurenautio",
    "gn:country_code":"FI",
    "gn:dem":118,
    "gn:feature_class":"P",
    "gn:feature_code":"PPL",
    "gn:name":"Kurenautio",
    "gn:population":0,
    "gn:timezone":"Europe/Helsinki",
    "iso:country":"FI",
    "wof:name":"Kurenautio",
    "wof:placetype":"locality"
},
  "geometry": {"coordinates":[28.65,61.53333000000001],"type":"Point"}
}