{
  "type": "Feature",
  "properties": {
    "gn:admin1_code":"13.0",
    "gn:admin2_code":"131.0",
    "gn:admin3_code":"179.0",
    "gn:asciiname":"Iloniemi",
    "gn:country_code":"FI",
    "gn:dem":120,
    "gn:feature_class":"P",
    "gn:feature_code":"PPL",
    "gn:name":"Iloniemi",
    "gn:population":0,
    "gn:timezone":"Europe/Helsinki",
    "iso:country":"FI",
    "wof:name":"Iloniemi",
    "wof:placetype":"locality"
},
  "geometry": {"coordinates":[25.61162,62.01708000000001],"type":"Point"}
}