{
  "type": "Feature",
  "properties": {
    "gn:admin1_code":"18.0",
    "gn:admin2_code":"182.0",
    "gn:admin3_code":"578.0",
    "gn:asciiname":"Tervola",
    "gn:country_code":"FI",
    "gn:dem":124,
    "gn:feature_class":"P",
    "gn:feature_code":"PPL",
    "gn:name":"Tervola",
    "gn:population":0,
    "gn:timezone":"Europe/Helsinki",
    "iso:country":"FI",
    "name:ceb_x_preferred":[
        "Tervola"
    ],
    "name:ces_x_preferred":[
        "Tervola"
    ],
    "name:deu_x_preferred":[
        "Tervola"
    ],
    "name:epo_x_preferred":[
        "Tervola"
    ],
    "name:est_x_preferred":[
        "Tervola vald"
    ],
    "name:eus_x_preferred":[
        "Tervola"
    ],
    "name:fin_x_preferred":[
        "Tervola"
    ],
    "name:fra_x_preferred":[
        "Tervola"
    ],
    "name:glg_x_preferred":[
        "Tervola"
    ],
    "name:ita_x_preferred":[
        "Tervola"
    ],
    "name:lat_x_preferred":[
        "Tervola"
    ],
    "name:nld_x_preferred":[
        "Tervola"
    ],
    "name:nor_x_preferred":[
        "Tervola"
    ],
    "name:pol_x_preferred":[
        "Tervola"
    ],
    "name:ron_x_preferred":[
        "Tervola"
    ],
    "name:rus_x_preferred":[
        "\u0422\u0435\u0440\u0432\u043e\u043b\u0430"
    ],
    "name:sme_x_preferred":[
        "Tervola"
    ],
    "name:spa_x_preferred":[
        "Tervola"
    ],
    "name:sqi_x_preferred":[
        "Tervola"
    ],
    "name:swe_x_preferred":[
        "Tervola"
    ],
    "name:tur_x_preferred":[
        "Tervola"
    ],
    "name:vie_x_preferred":[
        "Tervola"
    ],
    "name:zho_x_preferred":[
        "\u6cf0\u723e\u6c83\u62c9"
    ],
    "wof:name":"Tervola",
    "wof:placetype":"locality"
},
  "geometry": {"coordinates":[27.65,64.40000000000001],"type":"Point"}
}