{
  "type": "Feature",
  "properties": {
    "gn:admin1_code":"15.0",
    "gn:admin2_code":"153.0",
    "gn:admin3_code":"287.0",
    "gn:asciiname":"Peninkylae",
    "gn:country_code":"FI",
    "gn:dem":36,
    "gn:feature_class":"P",
    "gn:feature_code":"PPL",
    "gn:name":"Peninkyl\u00e4",
    "gn:population":0,
    "gn:timezone":"Europe/Helsinki",
    "iso:country":"FI",
    "name:eng_x_preferred":[
        "\u00c5back"
    ],
    "name:fin_x_preferred":[
        "Peninkyl\u00e4"
    ],
    "name:swe_x_preferred":[
        "\u00c5back"
    ],
    "wof:name":"Peninkylae",
    "wof:placetype":"locality"
},
  "geometry": {"coordinates":[21.59716,62.33549],"type":"Point"}
}