{
  "type": "Feature",
  "properties": {
    "gn:admin1_code":"15.0",
    "gn:admin2_code":"151.0",
    "gn:admin3_code":"152.0",
    "gn:asciiname":"Seljaenkangas",
    "gn:country_code":"FI",
    "gn:dem":37,
    "gn:feature_class":"P",
    "gn:feature_code":"PPL",
    "gn:name":"Selj\u00e4nkangas",
    "gn:population":0,
    "gn:timezone":"Europe/Helsinki",
    "iso:country":"FI",
    "wof:name":"Seljaenkangas",
    "wof:placetype":"locality"
},
  "geometry": {"coordinates":[22.33561,62.90899],"type":"Point"}
}