{
  "type": "Feature",
  "properties": {
    "gn:admin1_code":"12.0",
    "gn:admin2_code":"122.0",
    "gn:admin3_code":"309.0",
    "gn:asciiname":"Kykkoelae",
    "gn:country_code":"FI",
    "gn:dem":92,
    "gn:feature_class":"P",
    "gn:feature_code":"PPL",
    "gn:name":"Kykk\u00f6l\u00e4",
    "gn:population":0,
    "gn:timezone":"Europe/Helsinki",
    "iso:country":"FI",
    "wof:name":"Kykkoelae",
    "wof:placetype":"locality"
},
  "geometry": {"coordinates":[29.16667,62.78333000000001],"type":"Point"}
}