{
  "type": "Feature",
  "properties": {
    "gn:admin1_code":"12.0",
    "gn:admin2_code":"125.0",
    "gn:admin3_code":"911.0",
    "gn:asciiname":"Halmejaervi",
    "gn:country_code":"FI",
    "gn:dem":157,
    "gn:feature_class":"P",
    "gn:feature_code":"PPL",
    "gn:name":"Halmej\u00e4rvi",
    "gn:population":0,
    "gn:timezone":"Europe/Helsinki",
    "iso:country":"FI",
    "wof:name":"Halmejaervi",
    "wof:placetype":"locality"
},
  "geometry": {"coordinates":[28.76934,63.76145],"type":"Point"}
}