{
  "type": "Feature",
  "properties": {
    "gn:admin1_code":"18.0",
    "gn:admin2_code":"182.0",
    "gn:admin3_code":"697.0",
    "gn:asciiname":"Vaeyrylae",
    "gn:country_code":"FI",
    "gn:dem":154,
    "gn:feature_class":"P",
    "gn:feature_code":"PPL",
    "gn:name":"V\u00e4yryl\u00e4",
    "gn:population":0,
    "gn:timezone":"Europe/Helsinki",
    "iso:country":"FI",
    "wof:name":"Vaeyrylae",
    "wof:placetype":"locality"
},
  "geometry": {"coordinates":[28.31667,64.55],"type":"Point"}
}