{
  "type": "Feature",
  "properties": {
    "gn:admin1_code":"19.0",
    "gn:admin2_code":"194.0",
    "gn:admin3_code":"320.0",
    "gn:asciiname":"AEmmaelae",
    "gn:country_code":"FI",
    "gn:dem":190,
    "gn:feature_class":"P",
    "gn:feature_code":"PPL",
    "gn:name":"\u00c4mm\u00e4l\u00e4",
    "gn:population":0,
    "gn:timezone":"Europe/Helsinki",
    "iso:country":"FI",
    "wof:name":"AEmmaelae",
    "wof:placetype":"locality"
},
  "geometry": {"coordinates":[27.63351,66.60205000000001],"type":"Point"}
}