{
  "type": "Feature",
  "properties": {
    "gn:admin1_code":"16.0",
    "gn:admin2_code":"161.0",
    "gn:admin3_code":"236.0",
    "gn:asciiname":"Paasila",
    "gn:country_code":"FI",
    "gn:dem":118,
    "gn:feature_class":"P",
    "gn:feature_code":"PPL",
    "gn:name":"Paasila",
    "gn:population":0,
    "gn:timezone":"Europe/Helsinki",
    "iso:country":"FI",
    "wof:name":"Paasila",
    "wof:placetype":"locality"
},
  "geometry": {"coordinates":[23.98333,63.55],"type":"Point"}
}