{
  "type": "Feature",
  "properties": {
    "gn:admin1_code":"12.0",
    "gn:admin2_code":"122.0",
    "gn:admin3_code":"426.0",
    "gn:asciiname":"Toerpilae",
    "gn:country_code":"FI",
    "gn:dem":83,
    "gn:feature_class":"P",
    "gn:feature_code":"PPL",
    "gn:name":"T\u00f6rpil\u00e4",
    "gn:population":0,
    "gn:timezone":"Europe/Helsinki",
    "iso:country":"FI",
    "name:und_x_variant":[
        "T\u00f6rpala",
        "T\u00f6rpil\u00e4"
    ],
    "wof:name":"Toerpilae",
    "wof:placetype":"locality"
},
  "geometry": {"coordinates":[29.38333,62.63333000000001],"type":"Point"}
}