{
  "type": "Feature",
  "properties": {
    "gn:admin1_code":"19.0",
    "gn:admin2_code":"197.0",
    "gn:admin3_code":"758.0",
    "gn:asciiname":"Riipi",
    "gn:country_code":"FI",
    "gn:dem":230,
    "gn:feature_class":"P",
    "gn:feature_code":"PPL",
    "gn:name":"Riipi",
    "gn:population":0,
    "gn:timezone":"Europe/Helsinki",
    "iso:country":"FI",
    "name:eng_x_preferred":[
        "Riipi"
    ],
    "name:rus_x_preferred":[
        "\u0420\u0438\u043f\u0438"
    ],
    "wof:name":"Riipi",
    "wof:placetype":"locality"
},
  "geometry": {"coordinates":[26.03471,67.33934000000001],"type":"Point"}
}