{
  "type": "Feature",
  "properties": {
    "gn:admin1_code":"11.0",
    "gn:admin2_code":"115.0",
    "gn:admin3_code":"686.0",
    "gn:asciiname":"Nokisenkoski",
    "gn:country_code":"FI",
    "gn:dem":93,
    "gn:feature_class":"P",
    "gn:feature_code":"PPL",
    "gn:name":"Nokisenkoski",
    "gn:population":0,
    "gn:timezone":"Europe/Helsinki",
    "iso:country":"FI",
    "wof:name":"Nokisenkoski",
    "wof:placetype":"locality"
},
  "geometry": {"coordinates":[26.86667000000001,62.71666999999999],"type":"Point"}
}