{
  "type": "Feature",
  "properties": {
    "gn:admin1_code":"12.0",
    "gn:admin2_code":"122.0",
    "gn:admin3_code":"146.0",
    "gn:asciiname":"Kaarinala",
    "gn:cc2":"FI",
    "gn:country_code":"FI",
    "gn:dem":181,
    "gn:feature_class":"P",
    "gn:feature_code":"PPL",
    "gn:name":"Kaarinala",
    "gn:population":0,
    "gn:timezone":"Europe/Helsinki",
    "iso:country":"FI",
    "name:eng_x_preferred":[
        "Kaarinala"
    ],
    "name:rus_x_preferred":[
        "\u0410\u0435\u0432\u0430\u0440\u0430"
    ],
    "name:und_x_variant":[
        "Aijenvaara"
    ],
    "wof:name":"Kaarinala",
    "wof:placetype":"locality"
},
  "geometry": {"coordinates":[31.38333,62.73333],"type":"Point"}
}