{
  "type": "Feature",
  "properties": {
    "gn:admin1_code":"2.0",
    "gn:admin2_code":"23.0",
    "gn:admin3_code":"853.0",
    "gn:asciiname":"Kaerla",
    "gn:country_code":"FI",
    "gn:dem":24,
    "gn:feature_class":"P",
    "gn:feature_code":"PPL",
    "gn:name":"Kaerla",
    "gn:population":0,
    "gn:timezone":"Europe/Helsinki",
    "iso:country":"FI",
    "name:fin_x_preferred":[
        "Kaerla"
    ],
    "name:koi_x_preferred":[
        "\u041a\u0430\u044d\u0440\u043b\u0430"
    ],
    "name:rus_x_preferred":[
        "\u041a\u0430\u0435\u0440\u043b\u0430"
    ],
    "wof:name":"Kaerla",
    "wof:placetype":"locality"
},
  "geometry": {"coordinates":[22.26529,60.47922],"type":"Point"}
}