{
  "type": "Feature",
  "properties": {
    "gn:admin1_code":"11.0",
    "gn:admin2_code":"111.0",
    "gn:admin3_code":"402.0",
    "gn:asciiname":"Kaersaemaeki",
    "gn:country_code":"FI",
    "gn:dem":136,
    "gn:feature_class":"P",
    "gn:feature_code":"PPL",
    "gn:name":"K\u00e4rs\u00e4m\u00e4ki",
    "gn:population":0,
    "gn:timezone":"Europe/Helsinki",
    "iso:country":"FI",
    "wof:name":"Kaersaemaeki",
    "wof:placetype":"locality"
},
  "geometry": {"coordinates":[27.93446,63.39321],"type":"Point"}
}