{
  "type": "Feature",
  "properties": {
    "gn:admin1_code":"2.0",
    "gn:admin2_code":"25.0",
    "gn:admin3_code":"284.0",
    "gn:asciiname":"Koivukylae",
    "gn:country_code":"FI",
    "gn:dem":78,
    "gn:feature_class":"P",
    "gn:feature_code":"PPL",
    "gn:name":"Koivukyl\u00e4",
    "gn:population":0,
    "gn:timezone":"Europe/Helsinki",
    "iso:country":"FI",
    "wof:name":"Koivukylae",
    "wof:placetype":"locality"
},
  "geometry": {"coordinates":[23.02745,60.64259000000001],"type":"Point"}
}