{
  "type": "Feature",
  "properties": {
    "gn:admin1_code":"4.0",
    "gn:admin2_code":"44.0",
    "gn:admin3_code":"214.0",
    "gn:asciiname":"Veneskoski",
    "gn:country_code":"FI",
    "gn:dem":82,
    "gn:feature_class":"P",
    "gn:feature_code":"PPL",
    "gn:name":"Veneskoski",
    "gn:population":0,
    "gn:timezone":"Europe/Helsinki",
    "iso:country":"FI",
    "wof:name":"Veneskoski",
    "wof:placetype":"locality"
},
  "geometry": {"coordinates":[22.20316,61.77665],"type":"Point"}
}