{
  "type": "Feature",
  "properties": {
    "gn:admin1_code":"12.0",
    "gn:admin2_code":"124.0",
    "gn:admin3_code":"260.0",
    "gn:asciiname":"Rasti",
    "gn:cc2":"FI",
    "gn:country_code":"FI",
    "gn:dem":91,
    "gn:feature_class":"P",
    "gn:feature_code":"PPL",
    "gn:name":"Rasti",
    "gn:population":0,
    "gn:timezone":"Europe/Helsinki",
    "iso:country":"FI",
    "name:eng_x_preferred":[
        "Rastinniemi"
    ],
    "name:rus_x_preferred":[
        "\u0420\u0430\u0441\u0442\u0438"
    ],
    "name:und_x_variant":[
        "Rastinniemi"
    ],
    "wof:name":"Rasti",
    "wof:placetype":"locality"
},
  "geometry": {"coordinates":[29.73153,61.97668],"type":"Point"}
}