{
  "type": "Feature",
  "properties": {
    "gn:admin1_code":"2.0",
    "gn:admin2_code":"24.0",
    "gn:admin3_code":"918.0",
    "gn:asciiname":"Kuulila",
    "gn:country_code":"FI",
    "gn:dem":10,
    "gn:feature_class":"P",
    "gn:feature_code":"PPL",
    "gn:name":"Kuulila",
    "gn:population":0,
    "gn:timezone":"Europe/Helsinki",
    "iso:country":"FI",
    "wof:name":"Kuulila",
    "wof:placetype":"locality"
},
  "geometry": {"coordinates":[21.76083,60.67278],"type":"Point"}
}