{
  "type": "Feature",
  "properties": {
    "gn:admin1_code":"11.0",
    "gn:admin2_code":"111.0",
    "gn:admin3_code":"239.0",
    "gn:asciiname":"Jussila",
    "gn:country_code":"FI",
    "gn:dem":151,
    "gn:feature_class":"P",
    "gn:feature_code":"PPL",
    "gn:name":"Jussila",
    "gn:population":0,
    "gn:timezone":"Europe/Helsinki",
    "iso:country":"FI",
    "wof:name":"Jussila",
    "wof:placetype":"locality"
},
  "geometry": {"coordinates":[26.18333,63.26667],"type":"Point"}
}