{
  "type": "Feature",
  "properties": {
    "gn:admin1_code":"12.0",
    "gn:admin2_code":"125.0",
    "gn:admin3_code":"422.0",
    "gn:asciiname":"Kivisaerkkae",
    "gn:country_code":"FI",
    "gn:dem":126,
    "gn:feature_class":"P",
    "gn:feature_code":"PPL",
    "gn:name":"Kivis\u00e4rkk\u00e4",
    "gn:population":0,
    "gn:timezone":"Europe/Helsinki",
    "iso:country":"FI",
    "wof:name":"Kivisaerkkae",
    "wof:placetype":"locality"
},
  "geometry": {"coordinates":[29.53333,63.53333000000001],"type":"Point"}
}