{
  "type": "Feature",
  "properties": {
    "gn:admin1_code":"7.0",
    "gn:admin2_code":"71.0",
    "gn:admin3_code":"560.0",
    "gn:asciiname":"Kuivannon Metsaekulma",
    "gn:country_code":"FI",
    "gn:dem":83,
    "gn:feature_class":"P",
    "gn:feature_code":"PPL",
    "gn:name":"Kuivannon Mets\u00e4kulma",
    "gn:population":0,
    "gn:timezone":"Europe/Helsinki",
    "iso:country":"FI",
    "wof:name":"Kuivannon Metsaekulma",
    "wof:placetype":"locality"
},
  "geometry": {"coordinates":[26.09535,60.87563000000001],"type":"Point"}
}