{
  "type": "Feature",
  "properties": {
    "gn:admin1_code":"1.0",
    "gn:admin2_code":"15.0",
    "gn:admin3_code":"638.0",
    "gn:asciiname":"Haikkoo",
    "gn:country_code":"FI",
    "gn:dem":1,
    "gn:feature_class":"P",
    "gn:feature_code":"PPL",
    "gn:name":"Haikkoo",
    "gn:population":0,
    "gn:timezone":"Europe/Helsinki",
    "iso:country":"FI",
    "name:fin_x_preferred":[
        "Haikkoo"
    ],
    "name:swe_x_preferred":[
        "Haiko"
    ],
    "wof:name":"Haikkoo",
    "wof:placetype":"locality"
},
  "geometry": {"coordinates":[25.61954,60.3472],"type":"Point"}
}