{
  "type": "Feature",
  "properties": {
    "gn:admin1_code":"2.0",
    "gn:admin2_code":"21.0",
    "gn:admin3_code":"445.0",
    "gn:asciiname":"Strandby",
    "gn:cc2":"FI",
    "gn:country_code":"FI",
    "gn:dem":28,
    "gn:feature_class":"P",
    "gn:feature_code":"PPL",
    "gn:name":"Strandby",
    "gn:population":0,
    "gn:timezone":"Europe/Helsinki",
    "iso:country":"FI",
    "name:ceb_x_preferred":[
        "Strandby"
    ],
    "name:dan_x_preferred":[
        "Strandby"
    ],
    "name:deu_x_preferred":[
        "Strandby"
    ],
    "name:nld_x_preferred":[
        "Strandby"
    ],
    "name:spa_x_preferred":[
        "Strandby"
    ],
    "name:swe_x_preferred":[
        "Strandby"
    ],
    "name:und_x_variant":[
        "Stanby",
        "Stranby",
        "Strandby"
    ],
    "wof:name":"Strandby",
    "wof:placetype":"locality"
},
  "geometry": {"coordinates":[22.11667000000001,60.28333000000001],"type":"Point"}
}