{
  "type": "Feature",
  "properties": {
    "gn:admin1_code":"1.0",
    "gn:admin2_code":"14.0",
    "gn:admin3_code":"149.0",
    "gn:asciiname":"Hovgard",
    "gn:country_code":"FI",
    "gn:dem":24,
    "gn:feature_class":"P",
    "gn:feature_code":"PPL",
    "gn:name":"Hovg\u00e5rd",
    "gn:population":0,
    "gn:timezone":"Europe/Helsinki",
    "iso:country":"FI",
    "wof:name":"Hovgard",
    "wof:placetype":"locality"
},
  "geometry": {"coordinates":[24.05,60.05],"type":"Point"}
}