{
  "type": "Feature",
  "properties": {
    "gn:country":"FI",
    "gn:fcode":"PPL",
    "gn:population":0,
    "iso:country":"FI",
    "name:eng_x_preferred":[
        "Virkkala"
    ],
    "name:rus_x_preferred":[
        "\u0412\u0438\u0440\u043a\u043a\u0430\u043b\u0430"
    ],
    "name:swe_x_preferred":[
        "Virkby"
    ],
    "qs_pg:aaroncc":"FI",
    "qs_pg:gn_country":"FI",
    "qs_pg:gn_fcode":"PPL",
    "qs_pg:gn_pop":0,
    "qs_pg:name":"Virkkala",
    "qs_pg:name_adm0":"Suomi",
    "qs_pg:name_adm1":"Uudenmaan maakunta",
    "qs_pg:photos":1468,
    "qs_pg:photos_1k":297,
    "qs_pg:photos_9k":7,
    "qs_pg:photos_9r":7,
    "qs_pg:photos_all":1468,
    "qs_pg:photos_sr":12,
    "qs_pg:pop_sr":0,
    "qs_pg:qs_pg_placetype":"locality",
    "qs_pg:qs_pg_placetype_gp":"Town",
    "qs_pg:woe_adm0":23424812,
    "woe:adm0_id":23424812,
    "woe:name_adm0":"Suomi",
    "woe:name_adm1":"Uudenmaan maakunta",
    "woe:placetype":"Town",
    "wof:name":"Virkkala",
    "wof:placetype":"locality"
},
  "geometry": {"coordinates":[23.99929,60.19197],"type":"Point"}
}