{
  "type": "Feature",
  "properties": {
    "gn:admin1_code":"2.0",
    "gn:admin2_code":"21.0",
    "gn:admin3_code":"445.0",
    "gn:asciiname":"Sandoe",
    "gn:country_code":"FI",
    "gn:dem":-9999,
    "gn:feature_class":"P",
    "gn:feature_code":"PPL",
    "gn:name":"Sand\u00f6",
    "gn:population":0,
    "gn:timezone":"Europe/Helsinki",
    "iso:country":"FI",
    "wof:name":"Sandoe",
    "wof:placetype":"locality"
},
  "geometry": {"coordinates":[22.11667000000001,60.16667],"type":"Point"}
}