{
  "type": "Feature",
  "properties": {
    "iso:country":"FI",
    "qs_pg:aaroncc":"FI",
    "qs_pg:name":"Hiukkajoki",
    "qs_pg:name_adm0":"Suomi",
    "qs_pg:name_adm1":"Etel\u00e4-Savon maakunta",
    "qs_pg:photos":13,
    "qs_pg:photos_1k":3,
    "qs_pg:photos_9k":1,
    "qs_pg:photos_9r":1,
    "qs_pg:photos_all":13,
    "qs_pg:photos_sr":1,
    "qs_pg:pop_sr":0,
    "qs_pg:qs_pg_placetype":"locality",
    "qs_pg:qs_pg_placetype_gp":"Town",
    "qs_pg:woe_adm0":23424812,
    "woe:adm0_id":23424812,
    "woe:name_adm0":"Suomi",
    "woe:name_adm1":"Etel\u00e4-Savon maakunta",
    "woe:placetype":"Town",
    "wof:name":"Hiukkajoki",
    "wof:placetype":"locality"
},
  "geometry": {"coordinates":[29.52449,61.766505],"type":"Point"}
}