{
  "type": "Feature",
  "properties": {
    "gn:admin1_code":"7.0",
    "gn:admin2_code":"71.0",
    "gn:admin3_code":"111.0",
    "gn:asciiname":"Onali",
    "gn:country_code":"FI",
    "gn:dem":84,
    "gn:feature_class":"P",
    "gn:feature_code":"PPL",
    "gn:name":"Onali",
    "gn:population":0,
    "gn:timezone":"Europe/Helsinki",
    "iso:country":"FI",
    "wof:name":"Onali",
    "wof:placetype":"locality"
},
  "geometry": {"coordinates":[25.82829,61.28699],"type":"Point"}
}