{
  "type": "Feature",
  "properties": {
    "gn:admin1_code":"15.0",
    "gn:admin2_code":"152.0",
    "gn:admin3_code":"475.0",
    "gn:asciiname":"Vaestervaegen",
    "gn:country_code":"FI",
    "gn:dem":10,
    "gn:feature_class":"P",
    "gn:feature_code":"PPL",
    "gn:name":"V\u00e4sterv\u00e4gen",
    "gn:population":0,
    "gn:timezone":"Europe/Helsinki",
    "iso:country":"FI",
    "wof:name":"Vaestervaegen",
    "wof:placetype":"locality"
},
  "geometry": {"coordinates":[21.40853,62.84656],"type":"Point"}
}