{
  "type": "Feature",
  "properties": {
    "gn:admin1_code":"11.0",
    "gn:admin2_code":"114.0",
    "gn:admin3_code":"420.0",
    "gn:asciiname":"Mikkolanpelto",
    "gn:cc2":"FI",
    "gn:country_code":"FI",
    "gn:dem":146,
    "gn:feature_class":"P",
    "gn:feature_code":"PPL",
    "gn:name":"Mikkolanpelto",
    "gn:population":0,
    "gn:timezone":"Europe/Helsinki",
    "iso:country":"FI",
    "name:und_x_variant":[
        "Mikkola",
        "Mikkolanpelto"
    ],
    "wof:name":"Mikkolanpelto",
    "wof:placetype":"locality"
},
  "geometry": {"coordinates":[28.07463,62.57488000000001],"type":"Point"}
}