{
  "type": "Feature",
  "properties": {
    "gn:admin1_code":"19.0",
    "gn:admin2_code":"196.0",
    "gn:admin3_code":"273.0",
    "gn:asciiname":"Maennistoe",
    "gn:country_code":"FI",
    "gn:dem":155,
    "gn:feature_class":"P",
    "gn:feature_code":"PPL",
    "gn:name":"M\u00e4nnist\u00f6",
    "gn:population":0,
    "gn:timezone":"Europe/Helsinki",
    "iso:country":"FI",
    "name:fin_x_preferred":[
        "M\u00e4nnist\u00f6"
    ],
    "wof:name":"Maennistoe",
    "wof:placetype":"locality"
},
  "geometry": {"coordinates":[23.9947,67.12538000000001],"type":"Point"}
}