{
  "type": "Feature",
  "properties": {
    "gn:admin1_code":"11.0",
    "gn:admin2_code":"113.0",
    "gn:admin3_code":"687.0",
    "gn:asciiname":"Suojaervi",
    "gn:country_code":"FI",
    "gn:dem":221,
    "gn:feature_class":"P",
    "gn:feature_code":"PPL",
    "gn:name":"Suoj\u00e4rvi",
    "gn:population":0,
    "gn:timezone":"Europe/Helsinki",
    "iso:country":"FI",
    "wof:name":"Suojaervi",
    "wof:placetype":"locality"
},
  "geometry": {"coordinates":[28.21667,63.46666999999999],"type":"Point"}
}