{
  "type": "Feature",
  "properties": {
    "gn:admin1_code":"6.0",
    "gn:admin2_code":"68.0",
    "gn:admin3_code":"790.0",
    "gn:asciiname":"Uusikylae",
    "gn:country_code":"FI",
    "gn:dem":101,
    "gn:feature_class":"P",
    "gn:feature_code":"PPL",
    "gn:name":"Uusikyl\u00e4",
    "gn:population":0,
    "gn:timezone":"Europe/Helsinki",
    "iso:country":"FI",
    "wof:name":"Uusikylae",
    "wof:placetype":"locality"
},
  "geometry": {"coordinates":[23.11057000000001,61.31389],"type":"Point"}
}