{
  "type": "Feature",
  "properties": {
    "iso:country":"FI",
    "qs_pg:aaroncc":"FI",
    "qs_pg:name":"Nen\u00e4inniemi",
    "qs_pg:name_adm0":"Suomi",
    "qs_pg:name_adm1":"Keski-Suomen maakunta",
    "qs_pg:photos":32,
    "qs_pg:photos_1k":6,
    "qs_pg:photos_9k":1,
    "qs_pg:photos_9r":2,
    "qs_pg:photos_all":32,
    "qs_pg:photos_sr":2,
    "qs_pg:pop_sr":0,
    "qs_pg:qs_pg_placetype":"locality",
    "qs_pg:qs_pg_placetype_gp":"Town",
    "qs_pg:woe_adm0":23424812,
    "woe:adm0_id":23424812,
    "woe:name_adm0":"Suomi",
    "woe:name_adm1":"Keski-Suomen maakunta",
    "woe:placetype":"Town",
    "wof:name":"Nen\u00e4inniemi",
    "wof:placetype":"locality"
},
  "geometry": {"coordinates":[25.7809735,62.2026505],"type":"Point"}
}