{
  "type": "Feature",
  "properties": {
    "gn:admin1_code":"15.0",
    "gn:admin2_code":"154.0",
    "gn:admin3_code":"599.0",
    "gn:asciiname":"Emaus",
    "gn:country_code":"FI",
    "gn:dem":43,
    "gn:feature_class":"P",
    "gn:feature_code":"PPL",
    "gn:name":"Emaus",
    "gn:population":0,
    "gn:timezone":"Europe/Helsinki",
    "iso:country":"FI",
    "wof:name":"Emaus",
    "wof:placetype":"locality"
},
  "geometry": {"coordinates":[23.02343,63.45061],"type":"Point"}
}