{
  "type": "Feature",
  "properties": {
    "gn:admin1_code":"13.0",
    "gn:admin2_code":"131.0",
    "gn:admin3_code":"179.0",
    "gn:asciiname":"Tikka",
    "gn:country_code":"FI",
    "gn:dem":81,
    "gn:feature_class":"P",
    "gn:feature_code":"PPL",
    "gn:name":"Tikka",
    "gn:population":0,
    "gn:timezone":"Europe/Helsinki",
    "iso:country":"FI",
    "name:deu_x_preferred":[
        "Tikka"
    ],
    "name:fin_x_preferred":[
        "Tikka"
    ],
    "name:spa_x_preferred":[
        "Tikka"
    ],
    "name:swe_x_preferred":[
        "Tikka"
    ],
    "wof:name":"Tikka",
    "wof:placetype":"locality"
},
  "geometry": {"coordinates":[25.76139,62.2198],"type":"Point"}
}