{
  "type": "Feature",
  "properties": {
    "gn:admin1_code":"12.0",
    "gn:admin2_code":"125.0",
    "gn:admin3_code":"541.0",
    "gn:asciiname":"Kiies",
    "gn:country_code":"FI",
    "gn:dem":119,
    "gn:feature_class":"P",
    "gn:feature_code":"PPL",
    "gn:name":"Kiies",
    "gn:population":0,
    "gn:timezone":"Europe/Helsinki",
    "iso:country":"FI",
    "wof:name":"Kiies",
    "wof:placetype":"locality"
},
  "geometry": {"coordinates":[29.20338,63.54769],"type":"Point"}
}