{
  "type": "Feature",
  "properties": {
    "gn:admin1_code":"17.0",
    "gn:admin2_code":"176.0",
    "gn:admin3_code":"317.0",
    "gn:asciiname":"Kaersaemaeki",
    "gn:country_code":"FI",
    "gn:dem":112,
    "gn:feature_class":"P",
    "gn:feature_code":"PPLA3",
    "gn:name":"K\u00e4rs\u00e4m\u00e4ki",
    "gn:population":2966,
    "gn:timezone":"Europe/Helsinki",
    "iso:country":"FI",
    "name:eng_x_preferred":[
        "K\u00e4rs\u00e4m\u00e4ki"
    ],
    "name:rus_x_preferred":[
        "\u041a\u044f\u0440\u0441\u044f\u043c\u044f\u043a\u0438"
    ],
    "wof:name":"Kaersaemaeki",
    "wof:placetype":"locality",
    "wof:population":2966
},
  "geometry": {"coordinates":[25.76667,63.96666999999999],"type":"Point"}
}