{
  "type": "Feature",
  "properties": {
    "gn:admin1_code":"17.0",
    "gn:admin2_code":"176.0",
    "gn:admin3_code":"317.0",
    "gn:asciiname":"Kaersaemaeki",
    "gn:country_code":"FI",
    "gn:dem":112,
    "gn:feature_class":"P",
    "gn:feature_code":"PPLA3",
    "gn:name":"K\u00e4rs\u00e4m\u00e4ki",
    "gn:population":2966,
    "gn:timezone":"Europe/Helsinki",
    "iso:country":"FI",
    "name:ceb_x_preferred":[
        "K\u00e4rs\u00e4m\u00e4ki"
    ],
    "name:ces_x_preferred":[
        "K\u00e4rs\u00e4m\u00e4ki"
    ],
    "name:deu_x_preferred":[
        "K\u00e4rs\u00e4m\u00e4ki"
    ],
    "name:ell_x_preferred":[
        "\u039a\u03b1\u03c1\u03c3\u03b1\u03bc\u03ac\u03ba\u03b9"
    ],
    "name:eng_x_preferred":[
        "K\u00e4rs\u00e4m\u00e4ki"
    ],
    "name:est_x_preferred":[
        "K\u00e4rs\u00e4m\u00e4ki vald"
    ],
    "name:fin_x_preferred":[
        "K\u00e4rs\u00e4m\u00e4ki"
    ],
    "name:fra_x_preferred":[
        "K\u00e4rs\u00e4m\u00e4ki"
    ],
    "name:glg_x_preferred":[
        "K\u00e4rs\u00e4m\u00e4ki"
    ],
    "name:ita_x_preferred":[
        "K\u00e4rs\u00e4m\u00e4ki"
    ],
    "name:nld_x_preferred":[
        "K\u00e4rs\u00e4m\u00e4ki"
    ],
    "name:nor_x_preferred":[
        "K\u00e4rs\u00e4m\u00e4ki"
    ],
    "name:pol_x_preferred":[
        "K\u00e4rs\u00e4m\u00e4ki"
    ],
    "name:ron_x_preferred":[
        "K\u00e4rs\u00e4m\u00e4ki"
    ],
    "name:rus_x_preferred":[
        "\u041a\u044f\u0440\u0441\u044f\u043c\u044f\u043a\u0438"
    ],
    "name:sme_x_preferred":[
        "K\u00e4rs\u00e4m\u00e4ki"
    ],
    "name:spa_x_preferred":[
        "K\u00e4rs\u00e4m\u00e4ki"
    ],
    "name:sqi_x_preferred":[
        "K\u00e4rs\u00e4m\u00e4ki"
    ],
    "name:swe_x_preferred":[
        "K\u00e4rs\u00e4m\u00e4ki"
    ],
    "name:tur_x_preferred":[
        "K\u00e4rs\u00e4m\u00e4ki"
    ],
    "name:vie_x_preferred":[
        "K\u00e4rs\u00e4m\u00e4ki"
    ],
    "name:zho_x_preferred":[
        "\u51f1\u723e\u8cfd\u9081\u57fa"
    ],
    "wof:name":"Kaersaemaeki",
    "wof:placetype":"locality",
    "wof:population":2966
},
  "geometry": {"coordinates":[25.76667,63.96666999999999],"type":"Point"}
}