{
  "type": "Feature",
  "properties": {
    "gn:admin1_code":"19.0",
    "gn:admin2_code":"193.0",
    "gn:admin3_code":"976.0",
    "gn:asciiname":"Kuivakangas",
    "gn:country_code":"FI",
    "gn:dem":65,
    "gn:feature_class":"P",
    "gn:feature_code":"PPL",
    "gn:name":"Kuivakangas",
    "gn:population":0,
    "gn:timezone":"Europe/Helsinki",
    "iso:country":"FI",
    "wof:name":"Kuivakangas",
    "wof:placetype":"locality"
},
  "geometry": {"coordinates":[23.66049,66.42933000000001],"type":"Point"}
}