{
  "type": "Feature",
  "properties": {
    "gn:admin1_code":"6.0",
    "gn:admin2_code":"69.0",
    "gn:admin3_code":"702.0",
    "gn:asciiname":"Haukkamaa",
    "gn:cc2":"FI",
    "gn:country_code":"FI",
    "gn:dem":160,
    "gn:feature_class":"P",
    "gn:feature_code":"PPL",
    "gn:name":"Haukkamaa",
    "gn:population":0,
    "gn:timezone":"Europe/Helsinki",
    "iso:country":"FI",
    "name:und_x_variant":[
        "Haukka",
        "Haukkamaa"
    ],
    "wof:name":"Haukkamaa",
    "wof:placetype":"locality"
},
  "geometry": {"coordinates":[23.75,62.05],"type":"Point"}
}