{
  "type": "Feature",
  "properties": {
    "gn:admin1_code":"17.0",
    "gn:admin2_code":"178.0",
    "gn:admin3_code":"305.0",
    "gn:asciiname":"Kaivola",
    "gn:country_code":"FI",
    "gn:dem":289,
    "gn:feature_class":"P",
    "gn:feature_code":"PPL",
    "gn:name":"Kaivola",
    "gn:population":0,
    "gn:timezone":"Europe/Helsinki",
    "iso:country":"FI",
    "wof:name":"Kaivola",
    "wof:placetype":"locality"
},
  "geometry": {"coordinates":[28.66667,65.90000000000001],"type":"Point"}
}