{
  "type": "Feature",
  "properties": {
    "gn:admin1_code":"10.0",
    "gn:admin2_code":"101.0",
    "gn:admin3_code":"213.0",
    "gn:asciiname":"Ukonniemi",
    "gn:country_code":"FI",
    "gn:dem":94,
    "gn:feature_class":"P",
    "gn:feature_code":"PPL",
    "gn:name":"Ukonniemi",
    "gn:population":0,
    "gn:timezone":"Europe/Helsinki",
    "iso:country":"FI",
    "wof:name":"Ukonniemi",
    "wof:placetype":"locality"
},
  "geometry": {"coordinates":[26.82623,61.9018],"type":"Point"}
}