{
  "type": "Feature",
  "properties": {
    "gn:admin1_code":"2.0",
    "gn:admin2_code":"23.0",
    "gn:admin3_code":"853.0",
    "gn:asciiname":"Naula",
    "gn:country_code":"FI",
    "gn:dem":25,
    "gn:feature_class":"P",
    "gn:feature_code":"PPL",
    "gn:name":"Naula",
    "gn:population":0,
    "gn:timezone":"Europe/Helsinki",
    "iso:country":"FI",
    "name:sin_x_preferred":[
        "\u0db1\u0dcf\u0d8b\u0dbd"
    ],
    "wof:name":"Naula",
    "wof:placetype":"locality"
},
  "geometry": {"coordinates":[22.17492,60.35039],"type":"Point"}
}