{
  "type": "Feature",
  "properties": {
    "gn:admin1_code":"6.0",
    "gn:admin2_code":"64.0",
    "gn:admin3_code":"211.0",
    "gn:asciiname":"Keljo",
    "gn:country_code":"FI",
    "gn:dem":96,
    "gn:feature_class":"P",
    "gn:feature_code":"PPL",
    "gn:name":"Keljo",
    "gn:population":0,
    "gn:timezone":"Europe/Helsinki",
    "iso:country":"FI",
    "wof:name":"Keljo",
    "wof:placetype":"locality"
},
  "geometry": {"coordinates":[24.37908,61.4867],"type":"Point"}
}