{
  "type": "Feature",
  "properties": {
    "gn:admin1_code":"8.0",
    "gn:admin2_code":"82.0",
    "gn:admin3_code":"285.0",
    "gn:asciiname":"Kyminsuu",
    "gn:country_code":"FI",
    "gn:dem":-9999,
    "gn:feature_class":"P",
    "gn:feature_code":"PPL",
    "gn:name":"Kyminsuu",
    "gn:population":0,
    "gn:timezone":"Europe/Helsinki",
    "iso:country":"FI",
    "wof:name":"Kyminsuu",
    "wof:placetype":"locality"
},
  "geometry": {"coordinates":[26.92884,60.49861],"type":"Point"}
}