{
  "type": "Feature",
  "properties": {
    "gn:admin1_code":"16.0",
    "gn:admin2_code":"162.0",
    "gn:admin3_code":"217.0",
    "gn:asciiname":"Nilkkula",
    "gn:cc2":"FI",
    "gn:country_code":"FI",
    "gn:dem":52,
    "gn:feature_class":"P",
    "gn:feature_code":"PPL",
    "gn:name":"Nilkkula",
    "gn:population":0,
    "gn:timezone":"Europe/Helsinki",
    "iso:country":"FI",
    "name:und_x_variant":[
        "Nilkku",
        "Nilkkula"
    ],
    "wof:name":"Nilkkula",
    "wof:placetype":"locality"
},
  "geometry": {"coordinates":[23.93182,64.00315999999999],"type":"Point"}
}