{
  "type": "Feature",
  "properties": {
    "gn:admin1_code":"10.0",
    "gn:admin2_code":"101.0",
    "gn:admin3_code":"507.0",
    "gn:asciiname":"Valtola",
    "gn:country_code":"FI",
    "gn:dem":91,
    "gn:feature_class":"P",
    "gn:feature_code":"PPL",
    "gn:name":"Valtola",
    "gn:population":0,
    "gn:timezone":"Europe/Helsinki",
    "iso:country":"FI",
    "name:eng_x_preferred":[
        "Valtola"
    ],
    "name:rus_x_preferred":[
        "\u0412\u0430\u043b\u0442\u043e\u043b\u0430"
    ],
    "wof:name":"Valtola",
    "wof:placetype":"locality"
},
  "geometry": {"coordinates":[27.09297,61.22965],"type":"Point"}
}