{
  "type": "Feature",
  "properties": {
    "gn:admin1_code":"17.0",
    "gn:admin2_code":"174.0",
    "gn:admin3_code":"748.0",
    "gn:asciiname":"Pudas",
    "gn:country_code":"FI",
    "gn:dem":8,
    "gn:feature_class":"P",
    "gn:feature_code":"PPL",
    "gn:name":"Pudas",
    "gn:population":0,
    "gn:timezone":"Europe/Helsinki",
    "iso:country":"FI",
    "wof:name":"Pudas",
    "wof:placetype":"locality"
},
  "geometry": {"coordinates":[24.98333,64.90000000000001],"type":"Point"}
}