{
  "type": "Feature",
  "properties": {
    "gn:admin1_code":"15.0",
    "gn:admin2_code":"152.0",
    "gn:admin3_code":"946.0",
    "gn:asciiname":"Kvimo",
    "gn:country_code":"FI",
    "gn:dem":11,
    "gn:feature_class":"P",
    "gn:feature_code":"PPL",
    "gn:name":"Kvimo",
    "gn:population":0,
    "gn:timezone":"Europe/Helsinki",
    "iso:country":"FI",
    "wof:name":"Kvimo",
    "wof:placetype":"locality"
},
  "geometry": {"coordinates":[22.11693,63.27399000000001],"type":"Point"}
}