{
  "type": "Feature",
  "properties": {
    "gn:admin1_code":"4.0",
    "gn:admin2_code":"41.0",
    "gn:admin3_code":"51.0",
    "gn:asciiname":"Rydinnummi",
    "gn:country_code":"FI",
    "gn:dem":12,
    "gn:feature_class":"P",
    "gn:feature_code":"PPL",
    "gn:name":"Rydinnummi",
    "gn:population":0,
    "gn:timezone":"Europe/Helsinki",
    "iso:country":"FI",
    "wof:name":"Rydinnummi",
    "wof:placetype":"locality"
},
  "geometry": {"coordinates":[21.6742,61.32469],"type":"Point"}
}