{
  "type": "Feature",
  "properties": {
    "gn:admin1_code":"15.0",
    "gn:admin2_code":"154.0",
    "gn:admin3_code":"288.0",
    "gn:asciiname":"Haestbacka",
    "gn:country_code":"FI",
    "gn:dem":56,
    "gn:feature_class":"P",
    "gn:feature_code":"PPL",
    "gn:name":"H\u00e4stbacka",
    "gn:population":0,
    "gn:timezone":"Europe/Helsinki",
    "iso:country":"FI",
    "wof:name":"Haestbacka",
    "wof:placetype":"locality"
},
  "geometry": {"coordinates":[23.43251,63.55411],"type":"Point"}
}