{
  "type": "Feature",
  "properties": {
    "gn:admin1_code":"12.0",
    "gn:admin2_code":"124.0",
    "gn:admin3_code":"260.0",
    "gn:asciiname":"Lakovaara",
    "gn:country_code":"FI",
    "gn:dem":105,
    "gn:feature_class":"P",
    "gn:feature_code":"PPL",
    "gn:name":"Lakovaara",
    "gn:population":0,
    "gn:timezone":"Europe/Helsinki",
    "iso:country":"FI",
    "wof:name":"Lakovaara",
    "wof:placetype":"locality"
},
  "geometry": {"coordinates":[29.58455,62.1012],"type":"Point"}
}