{
  "type": "Feature",
  "properties": {
    "gn:admin1_code":"10.0",
    "gn:admin2_code":"103.0",
    "gn:admin3_code":"740.0",
    "gn:asciiname":"Laitaatsilta",
    "gn:country_code":"FI",
    "gn:dem":71,
    "gn:feature_class":"P",
    "gn:feature_code":"PPL",
    "gn:name":"Laitaatsilta",
    "gn:population":0,
    "gn:timezone":"Europe/Helsinki",
    "iso:country":"FI",
    "wof:name":"Laitaatsilta",
    "wof:placetype":"locality"
},
  "geometry": {"coordinates":[28.82771,61.87891],"type":"Point"}
}