{
  "type": "Feature",
  "properties": {
    "gn:admin1_code":"13.0",
    "gn:admin2_code":"131.0",
    "gn:admin3_code":"179.0",
    "gn:asciiname":"Kypaeraemaeki",
    "gn:country_code":"FI",
    "gn:dem":123,
    "gn:feature_class":"P",
    "gn:feature_code":"PPL",
    "gn:name":"Kyp\u00e4r\u00e4m\u00e4ki",
    "gn:population":0,
    "gn:timezone":"Europe/Helsinki",
    "iso:country":"FI",
    "wof:name":"Kypaeraemaeki",
    "wof:placetype":"locality"
},
  "geometry": {"coordinates":[25.69256,62.23795],"type":"Point"}
}