{
  "type": "Feature",
  "properties": {
    "gn:admin1_code":"16.0",
    "gn:admin2_code":"162.0",
    "gn:admin3_code":"272.0",
    "gn:asciiname":"Langoe",
    "gn:country_code":"FI",
    "gn:dem":18,
    "gn:feature_class":"P",
    "gn:feature_code":"PPL",
    "gn:name":"L\u00e5ng\u00f6",
    "gn:population":0,
    "gn:timezone":"Europe/Helsinki",
    "iso:country":"FI",
    "wof:name":"Langoe",
    "wof:placetype":"locality"
},
  "geometry": {"coordinates":[22.89892,63.8078],"type":"Point"}
}