{
  "type": "Feature",
  "properties": {
    "gn:admin1_code":"14.0",
    "gn:admin2_code":"142.0",
    "gn:admin3_code":"233.0",
    "gn:asciiname":"Luomanperae",
    "gn:country_code":"FI",
    "gn:dem":38,
    "gn:feature_class":"P",
    "gn:feature_code":"PPL",
    "gn:name":"Luomanper\u00e4",
    "gn:population":0,
    "gn:timezone":"Europe/Helsinki",
    "iso:country":"FI",
    "wof:name":"Luomanperae",
    "wof:placetype":"locality"
},
  "geometry": {"coordinates":[22.76667,63.06667],"type":"Point"}
}