{
  "type": "Feature",
  "properties": {
    "gn:admin1_code":"15.0",
    "gn:admin2_code":"152.0",
    "gn:admin3_code":"475.0",
    "gn:asciiname":"Kaerrmetholmen",
    "gn:country_code":"FI",
    "gn:dem":13,
    "gn:feature_class":"P",
    "gn:feature_code":"PPL",
    "gn:name":"K\u00e4rrmetholmen",
    "gn:population":0,
    "gn:timezone":"Europe/Helsinki",
    "iso:country":"FI",
    "wof:name":"Kaerrmetholmen",
    "wof:placetype":"locality"
},
  "geometry": {"coordinates":[21.63333,62.88333000000001],"type":"Point"}
}