{
  "type": "Feature",
  "properties": {
    "gn:admin1_code":"2.0",
    "gn:admin2_code":"23.0",
    "gn:admin3_code":"529.0",
    "gn:asciiname":"Lemsio",
    "gn:country_code":"FI",
    "gn:dem":1,
    "gn:feature_class":"P",
    "gn:feature_code":"PPL",
    "gn:name":"Lemsio",
    "gn:population":0,
    "gn:timezone":"Europe/Helsinki",
    "iso:country":"FI",
    "name:swe_x_preferred":[
        "Lemsj\u00f6holm"
    ],
    "name:und_x_variant":[
        "Maanp\u00e4\u00e4",
        "Lemsio",
        "Lemsj\u00f6holm"
    ],
    "wof:name":"Lemsio",
    "wof:placetype":"locality"
},
  "geometry": {"coordinates":[21.76667,60.48333],"type":"Point"}
}