{
  "type": "Feature",
  "properties": {
    "gn:admin1_code":"4.0",
    "gn:admin2_code":"43.0",
    "gn:admin3_code":"609.0",
    "gn:asciiname":"Lehtola",
    "gn:country_code":"FI",
    "gn:dem":41,
    "gn:feature_class":"P",
    "gn:feature_code":"PPL",
    "gn:name":"Lehtola",
    "gn:population":0,
    "gn:timezone":"Europe/Helsinki",
    "iso:country":"FI",
    "name:fin_x_preferred":[
        "Lehtola"
    ],
    "wof:name":"Lehtola",
    "wof:placetype":"locality"
},
  "geometry": {"coordinates":[21.82908,61.56333000000001],"type":"Point"}
}