{
  "type": "Feature",
  "properties": {
    "gn:admin1_code":"13.0",
    "gn:admin2_code":"133.0",
    "gn:admin3_code":"495.0",
    "gn:asciiname":"Valkola",
    "gn:country_code":"FI",
    "gn:dem":235,
    "gn:feature_class":"P",
    "gn:feature_code":"PPL",
    "gn:name":"Valkola",
    "gn:population":0,
    "gn:timezone":"Europe/Helsinki",
    "iso:country":"FI",
    "wof:name":"Valkola",
    "wof:placetype":"locality"
},
  "geometry": {"coordinates":[25.06667,62.45],"type":"Point"}
}