{
  "type": "Feature",
  "properties": {
    "gn:country":"FI",
    "gn:fcode":"PPL",
    "gn:population":0,
    "iso:country":"FI",
    "name:fin_x_preferred":[
        "Martinkyl\u00e4"
    ],
    "name:swe_x_preferred":[
        "M\u00e5rtensby"
    ],
    "qs_pg:aaroncc":"FI",
    "qs_pg:gn_country":"FI",
    "qs_pg:gn_fcode":"PPL",
    "qs_pg:gn_pop":0,
    "qs_pg:name":"Martinkyl\u00e4",
    "qs_pg:name_adm0":"Suomi",
    "qs_pg:name_adm1":"It\u00e4-Uudenmaan maakunta",
    "qs_pg:photos":26,
    "qs_pg:photos_1k":5,
    "qs_pg:photos_9k":1,
    "qs_pg:photos_9r":2,
    "qs_pg:photos_all":26,
    "qs_pg:photos_sr":2,
    "qs_pg:pop_sr":0,
    "qs_pg:qs_pg_placetype":"locality",
    "qs_pg:qs_pg_placetype_gp":"Town",
    "qs_pg:woe_adm0":23424812,
    "woe:adm0_id":23424812,
    "woe:name_adm0":"Suomi",
    "woe:name_adm1":"It\u00e4-Uudenmaan maakunta",
    "woe:placetype":"Town",
    "wof:name":"Martinkyl\u00e4",
    "wof:placetype":"locality"
},
  "geometry": {"coordinates":[25.23333,60.38333],"type":"Point"}
}