{
  "type": "Feature",
  "properties": {
    "gn:admin1_code":"4.0",
    "gn:admin2_code":"43.0",
    "gn:admin3_code":"609.0",
    "gn:asciiname":"Musa",
    "gn:country_code":"FI",
    "gn:dem":15,
    "gn:feature_class":"P",
    "gn:feature_code":"PPL",
    "gn:name":"Musa",
    "gn:population":0,
    "gn:timezone":"Europe/Helsinki",
    "iso:country":"FI",
    "name:aze_x_preferred":[
        "Musa"
    ],
    "name:cat_x_preferred":[
        "Musa"
    ],
    "name:ceb_x_preferred":[
        "Musa"
    ],
    "name:deu_x_preferred":[
        "Musa"
    ],
    "name:epo_x_preferred":[
        "Musa"
    ],
    "name:est_x_preferred":[
        "Musa"
    ],
    "name:eus_x_preferred":[
        "Musa"
    ],
    "name:fas_x_preferred":[
        "\u0645\u0648\u0633\u06cc"
    ],
    "name:fin_x_preferred":[
        "Musa"
    ],
    "name:fra_x_preferred":[
        "Musa"
    ],
    "name:heb_x_preferred":[
        "\u05de\u05d5\u05e1\u05d0"
    ],
    "name:ind_x_preferred":[
        "Musa"
    ],
    "name:ita_x_preferred":[
        "Musa"
    ],
    "name:jpn_x_preferred":[
        "\u30e0\u30b5"
    ],
    "name:kat_x_preferred":[
        "\u10db\u10e3\u10e1\u10d0"
    ],
    "name:kor_x_preferred":[
        "\ubb34\uc0ac"
    ],
    "name:lat_x_preferred":[
        "Musa"
    ],
    "name:lav_x_preferred":[
        "Musa"
    ],
    "name:msa_x_preferred":[
        "Musa"
    ],
    "name:nld_x_preferred":[
        "Musa"
    ],
    "name:nno_x_preferred":[
        "Musa"
    ],
    "name:nor_x_preferred":[
        "Musa"
    ],
    "name:pol_x_preferred":[
        "Musa"
    ],
    "name:por_x_preferred":[
        "Musa"
    ],
    "name:que_x_preferred":[
        "Musa"
    ],
    "name:rus_x_preferred":[
        "\u041c\u0443\u0441\u0430"
    ],
    "name:swa_x_preferred":[
        "Mto Musa"
    ],
    "name:swe_x_preferred":[
        "Musa"
    ],
    "name:tgl_x_preferred":[
        "Musa"
    ],
    "name:tha_x_preferred":[
        "Musa"
    ],
    "name:tur_x_preferred":[
        "Musa"
    ],
    "name:ukr_x_preferred":[
        "\u041c\u0443\u0441\u0430"
    ],
    "name:urd_x_preferred":[
        "\u0645\u0648\u0633\u06cc\u0670"
    ],
    "wof:name":"Musa",
    "wof:placetype":"locality"
},
  "geometry": {"coordinates":[21.74364,61.47952],"type":"Point"}
}