{
  "type": "Feature",
  "properties": {
    "gn:admin1_code":"13.0",
    "gn:admin2_code":"132.0",
    "gn:admin3_code":"435.0",
    "gn:asciiname":"Lempaeae",
    "gn:country_code":"FI",
    "gn:dem":175,
    "gn:feature_class":"P",
    "gn:feature_code":"PPL",
    "gn:name":"Lemp\u00e4\u00e4",
    "gn:population":0,
    "gn:timezone":"Europe/Helsinki",
    "iso:country":"FI",
    "name:eng_x_preferred":[
        "Lemp\u00e4\u00e4"
    ],
    "name:rus_x_preferred":[
        "\u041b\u0435\u043c\u043f\u044f"
    ],
    "wof:name":"Lempaeae",
    "wof:placetype":"locality"
},
  "geometry": {"coordinates":[25.79081,61.77513],"type":"Point"}
}