{
  "type": "Feature",
  "properties": {
    "gn:admin1_code":"1.0",
    "gn:admin2_code":"15.0",
    "gn:admin3_code":"638.0",
    "gn:asciiname":"Svartsa",
    "gn:country_code":"FI",
    "gn:dem":22,
    "gn:feature_class":"P",
    "gn:feature_code":"PPL",
    "gn:name":"Svarts\u00e5",
    "gn:population":0,
    "gn:timezone":"Europe/Helsinki",
    "iso:country":"FI",
    "wof:name":"Svartsa",
    "wof:placetype":"locality"
},
  "geometry": {"coordinates":[25.53333,60.35],"type":"Point"}
}