{
  "type": "Feature",
  "properties": {
    "gn:admin1_code":"8.0",
    "gn:admin2_code":"82.0",
    "gn:admin3_code":"285.0",
    "gn:asciiname":"Pihkoo",
    "gn:cc2":"FI",
    "gn:country_code":"FI",
    "gn:dem":5,
    "gn:feature_class":"P",
    "gn:feature_code":"PPL",
    "gn:name":"Pihkoo",
    "gn:population":0,
    "gn:timezone":"Europe/Helsinki",
    "iso:country":"FI",
    "name:und_x_variant":[
        "Pihko",
        "Pihkoo"
    ],
    "wof:name":"Pihkoo",
    "wof:placetype":"locality"
},
  "geometry": {"coordinates":[26.85585,60.51895],"type":"Point"}
}