{
  "type": "Feature",
  "properties": {
    "gn:admin1_code":"19.0",
    "gn:admin2_code":"197.0",
    "gn:admin3_code":"148.0",
    "gn:asciiname":"Petsikko",
    "gn:country_code":"FI",
    "gn:dem":260,
    "gn:feature_class":"P",
    "gn:feature_code":"PPL",
    "gn:name":"Petsikko",
    "gn:population":0,
    "gn:timezone":"Europe/Helsinki",
    "iso:country":"FI",
    "wof:name":"Petsikko",
    "wof:placetype":"locality"
},
  "geometry": {"coordinates":[27.25,69.43333],"type":"Point"}
}