{
  "type": "Feature",
  "properties": {
    "gn:country":"FI",
    "gn:fcode":"PPL",
    "gn:population":0,
    "iso:country":"FI",
    "name:fin_x_preferred":[
        "Harittu"
    ],
    "name:koi_x_preferred":[
        "\u0425\u0430\u0440\u0438\u0442\u0442\u0443"
    ],
    "name:rus_x_preferred":[
        "\u0425\u0430\u0440\u0438\u0442\u0442\u0443"
    ],
    "qs_pg:aaroncc":"FI",
    "qs_pg:gn_country":"FI",
    "qs_pg:gn_fcode":"PPL",
    "qs_pg:gn_pop":0,
    "qs_pg:name":"Harittu",
    "qs_pg:name_adm0":"Suomi",
    "qs_pg:name_adm1":"Varsinais-Suomen maakunta",
    "qs_pg:photos":115,
    "qs_pg:photos_1k":23,
    "qs_pg:photos_9k":1,
    "qs_pg:photos_9r":3,
    "qs_pg:photos_all":115,
    "qs_pg:photos_sr":3,
    "qs_pg:pop_sr":0,
    "qs_pg:qs_pg_placetype":"locality",
    "qs_pg:qs_pg_placetype_gp":"Town",
    "qs_pg:woe_adm0":23424812,
    "woe:adm0_id":23424812,
    "woe:name_adm0":"Suomi",
    "woe:name_adm1":"Varsinais-Suomen maakunta",
    "woe:placetype":"Town",
    "wof:name":"Harittu",
    "wof:placetype":"locality"
},
  "geometry": {"coordinates":[22.30602,60.4144],"type":"Point"}
}