{
  "type": "Feature",
  "properties": {
    "gn:admin1_code":"17.0",
    "gn:admin2_code":"171.0",
    "gn:admin3_code":"564.0",
    "gn:asciiname":"Korvenkylae",
    "gn:cc2":"FI",
    "gn:country_code":"FI",
    "gn:dem":40,
    "gn:feature_class":"P",
    "gn:feature_code":"PPL",
    "gn:name":"Korvenkyl\u00e4",
    "gn:population":0,
    "gn:timezone":"Europe/Helsinki",
    "iso:country":"FI",
    "name:eng_x_preferred":[
        "Korpi"
    ],
    "name:rus_x_preferred":[
        "\u041a\u043e\u0440\u0432\u0435\u043d\u043a\u044e\u043b\u044f"
    ],
    "name:und_x_variant":[
        "Iso Korpi",
        "Korvenkyl\u00e4"
    ],
    "wof:name":"Korvenkylae",
    "wof:placetype":"locality"
},
  "geometry": {"coordinates":[25.61737,65.05773000000001],"type":"Point"}
}