{
  "type": "Feature",
  "properties": {
    "gn:admin1_code":"11.0",
    "gn:admin2_code":"113.0",
    "gn:admin3_code":"204.0",
    "gn:asciiname":"Maentyjaervi",
    "gn:country_code":"FI",
    "gn:dem":123,
    "gn:feature_class":"P",
    "gn:feature_code":"PPL",
    "gn:name":"M\u00e4ntyj\u00e4rvi",
    "gn:population":0,
    "gn:timezone":"Europe/Helsinki",
    "iso:country":"FI",
    "wof:name":"Maentyjaervi",
    "wof:placetype":"locality"
},
  "geometry": {"coordinates":[28.69799,63.0786],"type":"Point"}
}