{
  "type": "Feature",
  "properties": {
    "gn:admin1_code":"4.0",
    "gn:admin2_code":"41.0",
    "gn:admin3_code":"50.0",
    "gn:asciiname":"Auvainen",
    "gn:country_code":"FI",
    "gn:dem":51,
    "gn:feature_class":"P",
    "gn:feature_code":"PPL",
    "gn:name":"Auvainen",
    "gn:population":0,
    "gn:timezone":"Europe/Helsinki",
    "iso:country":"FI",
    "wof:name":"Auvainen",
    "wof:placetype":"locality"
},
  "geometry": {"coordinates":[22.07862,60.99493],"type":"Point"}
}