{
  "type": "Feature",
  "properties": {
    "gn:admin1_code":"7.0",
    "gn:admin2_code":"71.0",
    "gn:admin3_code":"560.0",
    "gn:asciiname":"Salmela",
    "gn:country_code":"FI",
    "gn:dem":55,
    "gn:feature_class":"P",
    "gn:feature_code":"PPL",
    "gn:name":"Salmela",
    "gn:population":0,
    "gn:timezone":"Europe/Helsinki",
    "iso:country":"FI",
    "name:eng_x_preferred":[
        "Salmela"
    ],
    "name:rus_x_preferred":[
        "\u0421\u0430\u043b\u043c\u0435\u043b\u0430"
    ],
    "wof:name":"Salmela",
    "wof:placetype":"locality"
},
  "geometry": {"coordinates":[26.05263,60.75026],"type":"Point"}
}