{
  "type": "Feature",
  "properties": {
    "gn:admin1_code":"18.0",
    "gn:admin2_code":"182.0",
    "gn:admin3_code":"765.0",
    "gn:asciiname":"Maeaettaelae",
    "gn:country_code":"FI",
    "gn:dem":158,
    "gn:feature_class":"P",
    "gn:feature_code":"PPL",
    "gn:name":"M\u00e4\u00e4tt\u00e4l\u00e4",
    "gn:population":0,
    "gn:timezone":"Europe/Helsinki",
    "iso:country":"FI",
    "wof:name":"Maeaettaelae",
    "wof:placetype":"locality"
},
  "geometry": {"coordinates":[28.21667,64.16667],"type":"Point"}
}