{
  "type": "Feature",
  "properties": {
    "gn:admin1_code":"17.0",
    "gn:admin2_code":"176.0",
    "gn:admin3_code":"535.0",
    "gn:asciiname":"Sarjankylae",
    "gn:country_code":"FI",
    "gn:dem":95,
    "gn:feature_class":"P",
    "gn:feature_code":"PPL",
    "gn:name":"Sarjankyl\u00e4",
    "gn:population":0,
    "gn:timezone":"Europe/Helsinki",
    "iso:country":"FI",
    "name:und_x_variant":[
        "Sarjakyl\u00e4",
        "Sarjankyl\u00e4"
    ],
    "wof:name":"Sarjankylae",
    "wof:placetype":"locality"
},
  "geometry": {"coordinates":[25.06369,64.00805],"type":"Point"}
}