{
  "type": "Feature",
  "properties": {
    "gn:admin1_code":"14.0",
    "gn:admin2_code":"142.0",
    "gn:admin3_code":"743.0",
    "gn:asciiname":"Karhunkylae",
    "gn:country_code":"FI",
    "gn:dem":58,
    "gn:feature_class":"P",
    "gn:feature_code":"PPL",
    "gn:name":"Karhunkyl\u00e4",
    "gn:population":0,
    "gn:timezone":"Europe/Helsinki",
    "iso:country":"FI",
    "wof:name":"Karhunkylae",
    "wof:placetype":"locality"
},
  "geometry": {"coordinates":[22.65,62.95],"type":"Point"}
}