{
  "type": "Feature",
  "properties": {
    "gn:admin1_code":"2.0",
    "gn:admin2_code":"25.0",
    "gn:admin3_code":"284.0",
    "gn:asciiname":"Liiporla",
    "gn:country_code":"FI",
    "gn:dem":113,
    "gn:feature_class":"P",
    "gn:feature_code":"PPL",
    "gn:name":"Liiporla",
    "gn:population":0,
    "gn:timezone":"Europe/Helsinki",
    "iso:country":"FI",
    "wof:name":"Liiporla",
    "wof:placetype":"locality"
},
  "geometry": {"coordinates":[23.15,60.58333],"type":"Point"}
}