{
  "type": "Feature",
  "properties": {
    "gn:admin1_code":"1.0",
    "gn:admin2_code":"14.0",
    "gn:admin3_code":"710.0",
    "gn:asciiname":"Ovanmalm",
    "gn:country_code":"FI",
    "gn:dem":23,
    "gn:feature_class":"P",
    "gn:feature_code":"PPL",
    "gn:name":"Ovanmalm",
    "gn:population":0,
    "gn:timezone":"Europe/Helsinki",
    "iso:country":"FI",
    "wof:name":"Ovanmalm",
    "wof:placetype":"locality"
},
  "geometry": {"coordinates":[23.30241,60.09987],"type":"Point"}
}