{
  "type": "Feature",
  "properties": {
    "gn:admin1_code":"2.0",
    "gn:admin2_code":"21.0",
    "gn:admin3_code":"322.0",
    "gn:asciiname":"Smedaboele",
    "gn:country_code":"FI",
    "gn:dem":14,
    "gn:feature_class":"P",
    "gn:feature_code":"PPL",
    "gn:name":"Smedab\u00f6le",
    "gn:population":0,
    "gn:timezone":"Europe/Helsinki",
    "iso:country":"FI",
    "name:und_x_variant":[
        "Smedab\u00f6le",
        "Smedsb\u00f6le"
    ],
    "wof:name":"Smedaboele",
    "wof:placetype":"locality"
},
  "geometry": {"coordinates":[22.83841,60.20264],"type":"Point"}
}