{
  "type": "Feature",
  "properties": {
    "gn:admin1_code":"5.0",
    "gn:admin2_code":"53.0",
    "gn:admin3_code":"61.0",
    "gn:asciiname":"Niittymaa",
    "gn:country_code":"FI",
    "gn:dem":123,
    "gn:feature_class":"P",
    "gn:feature_code":"PPL",
    "gn:name":"Niittymaa",
    "gn:population":0,
    "gn:timezone":"Europe/Helsinki",
    "iso:country":"FI",
    "wof:name":"Niittymaa",
    "wof:placetype":"locality"
},
  "geometry": {"coordinates":[23.65,60.91667],"type":"Point"}
}