{
  "type": "Feature",
  "properties": {
    "gn:admin1_code":"17.0",
    "gn:admin2_code":"173.0",
    "gn:admin3_code":"615.0",
    "gn:asciiname":"Yli-Livo",
    "gn:country_code":"FI",
    "gn:dem":128,
    "gn:feature_class":"P",
    "gn:feature_code":"PPL",
    "gn:name":"Yli-Livo",
    "gn:population":0,
    "gn:timezone":"Europe/Helsinki",
    "iso:country":"FI",
    "wof:name":"Yli-Livo",
    "wof:placetype":"locality"
},
  "geometry": {"coordinates":[27.19371,65.60080000000001],"type":"Point"}
}