{
  "type": "Feature",
  "properties": {
    "gn:admin1_code":"11.0",
    "gn:admin2_code":"111.0",
    "gn:admin3_code":"140.0",
    "gn:asciiname":"Korpisjoki",
    "gn:country_code":"FI",
    "gn:dem":152,
    "gn:feature_class":"P",
    "gn:feature_code":"PPL",
    "gn:name":"Korpisjoki",
    "gn:population":0,
    "gn:timezone":"Europe/Helsinki",
    "iso:country":"FI",
    "wof:name":"Korpisjoki",
    "wof:placetype":"locality"
},
  "geometry": {"coordinates":[27.0134,63.45139],"type":"Point"}
}