{
  "type": "Feature",
  "properties": {
    "gn:admin1_code":"17.0",
    "gn:admin2_code":"171.0",
    "gn:admin3_code":"564.0",
    "gn:asciiname":"Saari",
    "gn:country_code":"FI",
    "gn:dem":42,
    "gn:feature_class":"P",
    "gn:feature_code":"PPL",
    "gn:name":"Saari",
    "gn:population":0,
    "gn:timezone":"Europe/Helsinki",
    "iso:country":"FI",
    "name:ceb_x_preferred":[
        "Saari"
    ],
    "name:deu_x_preferred":[
        "Saari"
    ],
    "name:fin_x_preferred":[
        "Saari"
    ],
    "name:fra_x_preferred":[
        "Saari"
    ],
    "name:nld_x_preferred":[
        "Saari"
    ],
    "name:rus_x_preferred":[
        "\u0421\u0430\u0430\u0440\u0438"
    ],
    "name:swe_x_preferred":[
        "Saari"
    ],
    "wof:name":"Saari",
    "wof:placetype":"locality"
},
  "geometry": {"coordinates":[25.75,65.33333],"type":"Point"}
}