{
  "type": "Feature",
  "properties": {
    "gn:admin1_code":"1.0",
    "gn:admin2_code":"16.0",
    "gn:admin3_code":"434.0",
    "gn:asciiname":"Torpparinmaeki",
    "gn:cc2":"FI",
    "gn:country_code":"FI",
    "gn:dem":1,
    "gn:feature_class":"P",
    "gn:feature_code":"PPL",
    "gn:name":"Torpparinm\u00e4ki",
    "gn:population":0,
    "gn:timezone":"Europe/Helsinki",
    "iso:country":"FI",
    "name:swe_x_preferred":[
        "Torparbacken"
    ],
    "wof:name":"Torpparinmaeki",
    "wof:placetype":"locality"
},
  "geometry": {"coordinates":[26.30436,60.47981],"type":"Point"}
}