{
  "type": "Feature",
  "properties": {
    "gn:admin1_code":"15.0",
    "gn:admin2_code":"154.0",
    "gn:admin3_code":"893.0",
    "gn:asciiname":"Dalabacka",
    "gn:country_code":"FI",
    "gn:dem":29,
    "gn:feature_class":"P",
    "gn:feature_code":"PPL",
    "gn:name":"Dalabacka",
    "gn:population":0,
    "gn:timezone":"Europe/Helsinki",
    "iso:country":"FI",
    "wof:name":"Dalabacka",
    "wof:placetype":"locality"
},
  "geometry": {"coordinates":[22.8639,63.42482],"type":"Point"}
}