{
  "type": "Feature",
  "properties": {
    "gn:admin1_code":"14.0",
    "gn:admin2_code":"146.0",
    "gn:admin3_code":"52.0",
    "gn:asciiname":"Niemi",
    "gn:country_code":"FI",
    "gn:dem":65,
    "gn:feature_class":"P",
    "gn:feature_code":"PPL",
    "gn:name":"Niemi",
    "gn:population":0,
    "gn:timezone":"Europe/Helsinki",
    "iso:country":"FI",
    "wof:name":"Niemi",
    "wof:placetype":"locality"
},
  "geometry": {"coordinates":[23.22647000000001,63.36287],"type":"Point"}
}