{
  "type": "Feature",
  "properties": {
    "gn:admin1_code":"1.0",
    "gn:admin2_code":"11.0",
    "gn:admin3_code":"257.0",
    "gn:asciiname":"Mattby",
    "gn:country_code":"FI",
    "gn:dem":8,
    "gn:feature_class":"P",
    "gn:feature_code":"PPL",
    "gn:name":"Mattby",
    "gn:population":0,
    "gn:timezone":"Europe/Helsinki",
    "iso:country":"FI",
    "wof:name":"Mattby",
    "wof:placetype":"locality"
},
  "geometry": {"coordinates":[24.43423,60.08599],"type":"Point"}
}