{
  "type": "Feature",
  "properties": {
    "gn:admin1_code":"17.0",
    "gn:admin2_code":"174.0",
    "gn:admin3_code":"625.0",
    "gn:asciiname":"Pirttikoski",
    "gn:country_code":"FI",
    "gn:dem":28,
    "gn:feature_class":"P",
    "gn:feature_code":"PPL",
    "gn:name":"Pirttikoski",
    "gn:population":0,
    "gn:timezone":"Europe/Helsinki",
    "iso:country":"FI",
    "name:eng_x_preferred":[
        "Pirttikoski"
    ],
    "name:rus_x_preferred":[
        "\u041f\u0438\u0440\u0442\u0442\u0438\u043a\u043e\u0441\u043a\u0438"
    ],
    "wof:name":"Pirttikoski",
    "wof:placetype":"locality"
},
  "geometry": {"coordinates":[24.31111,64.41253],"type":"Point"}
}