{
  "type": "Feature",
  "properties": {
    "gn:admin1_code":"15.0",
    "gn:admin2_code":"151.0",
    "gn:admin3_code":"152.0",
    "gn:asciiname":"Luomanen",
    "gn:country_code":"FI",
    "gn:dem":42,
    "gn:feature_class":"P",
    "gn:feature_code":"PPL",
    "gn:name":"Luomanen",
    "gn:population":0,
    "gn:timezone":"Europe/Helsinki",
    "iso:country":"FI",
    "name:fin_x_preferred":[
        "Luomanen"
    ],
    "wof:name":"Luomanen",
    "wof:placetype":"locality"
},
  "geometry": {"coordinates":[22.27888,62.94407],"type":"Point"}
}