{
  "type": "Feature",
  "properties": {
    "gn:admin1_code":"11.0",
    "gn:admin2_code":"111.0",
    "gn:admin3_code":"762.0",
    "gn:asciiname":"Saelevae",
    "gn:country_code":"FI",
    "gn:dem":180,
    "gn:feature_class":"P",
    "gn:feature_code":"PPL",
    "gn:name":"S\u00e4lev\u00e4",
    "gn:population":0,
    "gn:timezone":"Europe/Helsinki",
    "iso:country":"FI",
    "wof:name":"Saelevae",
    "wof:placetype":"locality"
},
  "geometry": {"coordinates":[27.75,63.56667],"type":"Point"}
}