{
  "type": "Feature",
  "properties": {
    "gn:admin1_code":"1.0",
    "gn:admin2_code":"11.0",
    "gn:admin3_code":"505.0",
    "gn:asciiname":"Kaunismaeki",
    "gn:country_code":"FI",
    "gn:dem":58,
    "gn:feature_class":"P",
    "gn:feature_code":"PPL",
    "gn:name":"Kaunism\u00e4ki",
    "gn:population":0,
    "gn:timezone":"Europe/Helsinki",
    "iso:country":"FI",
    "wof:name":"Kaunismaeki",
    "wof:placetype":"locality"
},
  "geometry": {"coordinates":[25.30261,60.65],"type":"Point"}
}