{
  "type": "Feature",
  "properties": {
    "gn:admin1_code":"2.0",
    "gn:admin2_code":"23.0",
    "gn:admin3_code":"538.0",
    "gn:asciiname":"Alakylae",
    "gn:country_code":"FI",
    "gn:dem":44,
    "gn:feature_class":"P",
    "gn:feature_code":"PPL",
    "gn:name":"Alakyl\u00e4",
    "gn:population":0,
    "gn:timezone":"Europe/Helsinki",
    "iso:country":"FI",
    "wof:name":"Alakylae",
    "wof:placetype":"locality"
},
  "geometry": {"coordinates":[22.14822,60.60984000000001],"type":"Point"}
}