{
  "type": "Feature",
  "properties": {
    "gn:admin1_code":"14.0",
    "gn:admin2_code":"142.0",
    "gn:admin3_code":"408.0",
    "gn:asciiname":"Muilunkylae",
    "gn:country_code":"FI",
    "gn:dem":38,
    "gn:feature_class":"P",
    "gn:feature_code":"PPL",
    "gn:name":"Muilunkyl\u00e4",
    "gn:population":0,
    "gn:timezone":"Europe/Helsinki",
    "iso:country":"FI",
    "name:und_x_variant":[
        "Muilu",
        "Muilunkyl\u00e4"
    ],
    "wof:name":"Muilunkylae",
    "wof:placetype":"locality"
},
  "geometry": {"coordinates":[22.9908,62.90309],"type":"Point"}
}