{
  "type": "Feature",
  "properties": {
    "gn:admin1_code":"2.0",
    "gn:admin2_code":"21.0",
    "gn:admin3_code":"322.0",
    "gn:asciiname":"Sjoelax",
    "gn:country_code":"FI",
    "gn:dem":30,
    "gn:feature_class":"P",
    "gn:feature_code":"PPL",
    "gn:name":"Sj\u00f6lax",
    "gn:population":0,
    "gn:timezone":"Europe/Helsinki",
    "iso:country":"FI",
    "name:und_x_variant":[
        "Syv\u00e4lahti",
        "Sj\u00f6laks",
        "Sielax",
        "Sj\u00f6lax"
    ],
    "wof:name":"Sjoelax",
    "wof:placetype":"locality"
},
  "geometry": {"coordinates":[22.83333,60.13333000000001],"type":"Point"}
}