{
  "type": "Feature",
  "properties": {
    "gn:admin1_code":"2.0",
    "gn:admin2_code":"24.0",
    "gn:admin3_code":"895.0",
    "gn:asciiname":"Vahterus",
    "gn:country_code":"FI",
    "gn:dem":10,
    "gn:feature_class":"P",
    "gn:feature_code":"PPL",
    "gn:name":"Vahterus",
    "gn:population":0,
    "gn:timezone":"Europe/Helsinki",
    "iso:country":"FI",
    "wof:name":"Vahterus",
    "wof:placetype":"locality"
},
  "geometry": {"coordinates":[21.51401,60.74821],"type":"Point"}
}