{
  "type": "Feature",
  "properties": {
    "gn:admin1_code":"15.0",
    "gn:admin2_code":"152.0",
    "gn:admin3_code":"475.0",
    "gn:asciiname":"Tuvesbacken",
    "gn:country_code":"FI",
    "gn:dem":7,
    "gn:feature_class":"P",
    "gn:feature_code":"PPL",
    "gn:name":"Tuvesbacken",
    "gn:population":0,
    "gn:timezone":"Europe/Helsinki",
    "iso:country":"FI",
    "wof:name":"Tuvesbacken",
    "wof:placetype":"locality"
},
  "geometry": {"coordinates":[21.64478,62.89569],"type":"Point"}
}