{
  "type": "Feature",
  "properties": {
    "gn:admin1_code":"14.0",
    "gn:admin2_code":"146.0",
    "gn:admin3_code":"759.0",
    "gn:asciiname":"Raitamaeki",
    "gn:country_code":"FI",
    "gn:dem":226,
    "gn:feature_class":"P",
    "gn:feature_code":"PPL",
    "gn:name":"Raitam\u00e4ki",
    "gn:population":0,
    "gn:timezone":"Europe/Helsinki",
    "iso:country":"FI",
    "wof:name":"Raitamaeki",
    "wof:placetype":"locality"
},
  "geometry": {"coordinates":[24.38333,62.76667],"type":"Point"}
}