{
  "type": "Feature",
  "properties": {
    "gn:admin1_code":"17.0",
    "gn:admin2_code":"171.0",
    "gn:admin3_code":"494.0",
    "gn:asciiname":"Hyrkaes",
    "gn:country_code":"FI",
    "gn:dem":32,
    "gn:feature_class":"P",
    "gn:feature_code":"PPL",
    "gn:name":"Hyrk\u00e4s",
    "gn:population":0,
    "gn:timezone":"Europe/Helsinki",
    "iso:country":"FI",
    "wof:name":"Hyrkaes",
    "wof:placetype":"locality"
},
  "geometry": {"coordinates":[26.12825,64.79083],"type":"Point"}
}