{
  "type": "Feature",
  "properties": {
    "gn:admin1_code":"5.0",
    "gn:admin2_code":"52.0",
    "gn:admin3_code":"694.0",
    "gn:asciiname":"Hiivola",
    "gn:country_code":"FI",
    "gn:dem":123,
    "gn:feature_class":"P",
    "gn:feature_code":"PPL",
    "gn:name":"Hiivola",
    "gn:population":0,
    "gn:timezone":"Europe/Helsinki",
    "iso:country":"FI",
    "wof:name":"Hiivola",
    "wof:placetype":"locality"
},
  "geometry": {"coordinates":[24.69191,60.71044000000001],"type":"Point"}
}