{
  "type": "Feature",
  "properties": {
    "gn:admin1_code":"15.0",
    "gn:admin2_code":"151.0",
    "gn:admin3_code":"399.0",
    "gn:asciiname":"Pahaluoma",
    "gn:country_code":"FI",
    "gn:dem":20,
    "gn:feature_class":"P",
    "gn:feature_code":"PPL",
    "gn:name":"Pahaluoma",
    "gn:population":0,
    "gn:timezone":"Europe/Helsinki",
    "iso:country":"FI",
    "name:fin_x_preferred":[
        "Pahaluoma"
    ],
    "wof:name":"Pahaluoma",
    "wof:placetype":"locality"
},
  "geometry": {"coordinates":[21.82506,62.89816999999999],"type":"Point"}
}