{
  "type": "Feature",
  "properties": {
    "gn:admin1_code":"12.0",
    "gn:admin2_code":"124.0",
    "gn:admin3_code":"848.0",
    "gn:asciiname":"Kemie",
    "gn:country_code":"FI",
    "gn:dem":169,
    "gn:feature_class":"P",
    "gn:feature_code":"PPL",
    "gn:name":"Kemie",
    "gn:population":0,
    "gn:timezone":"Europe/Helsinki",
    "iso:country":"FI",
    "name:eng_x_preferred":[
        "Kemie"
    ],
    "name:rus_x_preferred":[
        "\u041a\u0435\u043c\u0438\u0435"
    ],
    "wof:name":"Kemie",
    "wof:placetype":"locality"
},
  "geometry": {"coordinates":[30.34385,62.22484],"type":"Point"}
}