{
  "type": "Feature",
  "properties": {
    "gn:admin1_code":"19.0",
    "gn:admin2_code":"197.0",
    "gn:admin3_code":"148.0",
    "gn:asciiname":"Angeli",
    "gn:country_code":"FI",
    "gn:dem":207,
    "gn:feature_class":"P",
    "gn:feature_code":"PPL",
    "gn:name":"Angeli",
    "gn:population":0,
    "gn:timezone":"Europe/Helsinki",
    "iso:country":"FI",
    "name:eng_x_preferred":[
        "Angeli"
    ],
    "name:fin_x_preferred":[
        "Angeli"
    ],
    "name:rus_x_preferred":[
        "\u0410\u043d\u0433\u0435\u043b\u0438"
    ],
    "name:sme_x_preferred":[
        "\u00c1\u014b\u014bel"
    ],
    "wof:name":"Angeli",
    "wof:placetype":"locality"
},
  "geometry": {"coordinates":[25.66283,68.91043000000001],"type":"Point"}
}