{
  "type": "Feature",
  "properties": {
    "gn:admin1_code":"7.0",
    "gn:admin2_code":"71.0",
    "gn:admin3_code":"81.0",
    "gn:asciiname":"Siltasuo",
    "gn:country_code":"FI",
    "gn:dem":143,
    "gn:feature_class":"P",
    "gn:feature_code":"PPL",
    "gn:name":"Siltasuo",
    "gn:population":0,
    "gn:timezone":"Europe/Helsinki",
    "iso:country":"FI",
    "wof:name":"Siltasuo",
    "wof:placetype":"locality"
},
  "geometry": {"coordinates":[25.93364,61.62957],"type":"Point"}
}