{
  "type": "Feature",
  "properties": {
    "gn:admin1_code":"9.0",
    "gn:admin2_code":"91.0",
    "gn:admin3_code":"405.0",
    "gn:asciiname":"Kasukkala",
    "gn:country_code":"FI",
    "gn:dem":59,
    "gn:feature_class":"P",
    "gn:feature_code":"PPL",
    "gn:name":"Kasukkala",
    "gn:population":0,
    "gn:timezone":"Europe/Helsinki",
    "iso:country":"FI",
    "wof:name":"Kasukkala",
    "wof:placetype":"locality"
},
  "geometry": {"coordinates":[28.32771,60.96724],"type":"Point"}
}