{
  "type": "Feature",
  "properties": {
    "gn:admin1_code":"10.0",
    "gn:admin2_code":"103.0",
    "gn:admin3_code":"740.0",
    "gn:asciiname":"Otavanniemi",
    "gn:cc2":"FI",
    "gn:country_code":"FI",
    "gn:dem":99,
    "gn:feature_class":"P",
    "gn:feature_code":"PPL",
    "gn:name":"Otavanniemi",
    "gn:population":0,
    "gn:timezone":"Europe/Helsinki",
    "iso:country":"FI",
    "name:und_x_variant":[
        "Otavaniemi",
        "Otavanniemi"
    ],
    "wof:name":"Otavanniemi",
    "wof:placetype":"locality"
},
  "geometry": {"coordinates":[28.521,61.85309],"type":"Point"}
}