{
  "type": "Feature",
  "properties": {
    "gn:admin1_code":"11.0",
    "gn:admin2_code":"111.0",
    "gn:admin3_code":"140.0",
    "gn:asciiname":"Tikankoski",
    "gn:country_code":"FI",
    "gn:dem":85,
    "gn:feature_class":"P",
    "gn:feature_code":"PPL",
    "gn:name":"Tikankoski",
    "gn:population":0,
    "gn:timezone":"Europe/Helsinki",
    "iso:country":"FI",
    "wof:name":"Tikankoski",
    "wof:placetype":"locality"
},
  "geometry": {"coordinates":[27.36667000000001,63.56667],"type":"Point"}
}