{
  "type": "Feature",
  "properties": {
    "gn:admin1_code":"4.0",
    "gn:admin2_code":"43.0",
    "gn:admin3_code":"609.0",
    "gn:asciiname":"Hevosmaeki",
    "gn:country_code":"FI",
    "gn:dem":38,
    "gn:feature_class":"P",
    "gn:feature_code":"PPL",
    "gn:name":"Hevosm\u00e4ki",
    "gn:population":0,
    "gn:timezone":"Europe/Helsinki",
    "iso:country":"FI",
    "name:swa_x_preferred":[
        "H\u00e4sthagen"
    ],
    "wof:name":"Hevosmaeki",
    "wof:placetype":"locality"
},
  "geometry": {"coordinates":[21.8471,61.59544],"type":"Point"}
}