{
  "type": "Feature",
  "properties": {
    "gn:admin1_code":"13.0",
    "gn:admin2_code":"134.0",
    "gn:admin3_code":"182.0",
    "gn:asciiname":"Kelhae",
    "gn:country_code":"FI",
    "gn:dem":83,
    "gn:feature_class":"P",
    "gn:feature_code":"PPL",
    "gn:name":"Kelh\u00e4",
    "gn:population":0,
    "gn:timezone":"Europe/Helsinki",
    "iso:country":"FI",
    "name:fin_x_preferred":[
        "Kelh\u00e4"
    ],
    "wof:name":"Kelhae",
    "wof:placetype":"locality"
},
  "geometry": {"coordinates":[25.18044,61.86431999999999],"type":"Point"}
}