{
  "type": "Feature",
  "properties": {
    "gn:admin1_code":"4.0",
    "gn:admin2_code":"41.0",
    "gn:admin3_code":"50.0",
    "gn:asciiname":"Kuurnamaeki",
    "gn:country_code":"FI",
    "gn:dem":30,
    "gn:feature_class":"P",
    "gn:feature_code":"PPL",
    "gn:name":"Kuurnam\u00e4ki",
    "gn:population":0,
    "gn:timezone":"Europe/Helsinki",
    "iso:country":"FI",
    "name:und_x_variant":[
        "Kuurnem\u00e4ki",
        "Kuurnam\u00e4ki"
    ],
    "wof:name":"Kuurnamaeki",
    "wof:placetype":"locality"
},
  "geometry": {"coordinates":[22.09897,61.15878000000001],"type":"Point"}
}