{
  "type": "Feature",
  "properties": {
    "gn:admin1_code":"6.0",
    "gn:admin2_code":"61.0",
    "gn:admin3_code":"250.0",
    "gn:asciiname":"Nerkoo",
    "gn:cc2":"FI",
    "gn:country_code":"FI",
    "gn:dem":166,
    "gn:feature_class":"P",
    "gn:feature_code":"PPL",
    "gn:name":"Nerkoo",
    "gn:population":0,
    "gn:timezone":"Europe/Helsinki",
    "iso:country":"FI",
    "name:und_x_variant":[
        "Nerko",
        "Nerkoo"
    ],
    "wof:name":"Nerkoo",
    "wof:placetype":"locality"
},
  "geometry": {"coordinates":[23.20525,62.12996999999999],"type":"Point"}
}