{
  "type": "Feature",
  "properties": {
    "iso:country":"FI",
    "qs_pg:aaroncc":"FI",
    "qs_pg:name":"Ketunpes\u00e4t",
    "qs_pg:name_adm0":"Suomi",
    "qs_pg:name_adm1":"Pirkanmaan maakunta",
    "qs_pg:photos":1,
    "qs_pg:photos_1k":1,
    "qs_pg:photos_9k":1,
    "qs_pg:photos_9r":1,
    "qs_pg:photos_all":1,
    "qs_pg:photos_sr":1,
    "qs_pg:pop_sr":0,
    "qs_pg:qs_pg_placetype":"locality",
    "qs_pg:qs_pg_placetype_gp":"Town",
    "qs_pg:woe_adm0":23424812,
    "woe:adm0_id":23424812,
    "woe:name_adm0":"Suomi",
    "woe:name_adm1":"Pirkanmaan maakunta",
    "woe:placetype":"Town",
    "wof:name":"Ketunpes\u00e4t",
    "wof:placetype":"locality"
},
  "geometry": {"coordinates":[23.896388,61.171111],"type":"Point"}
}