{
  "type": "Feature",
  "properties": {
    "gn:admin1_code":"12.0",
    "gn:admin2_code":"125.0",
    "gn:admin3_code":"541.0",
    "gn:asciiname":"Palomaeki",
    "gn:cc2":"FI",
    "gn:country_code":"FI",
    "gn:dem":192,
    "gn:feature_class":"P",
    "gn:feature_code":"PPL",
    "gn:name":"Palom\u00e4ki",
    "gn:population":0,
    "gn:timezone":"Europe/Helsinki",
    "iso:country":"FI",
    "name:eng_x_preferred":[
        "Palom\u00e4ki"
    ],
    "name:rus_x_preferred":[
        "\u041f\u0430\u043b\u043e\u043c\u044f\u043a\u0438"
    ],
    "name:und_x_variant":[
        "Paloj\u00e4rvi"
    ],
    "wof:name":"Palomaeki",
    "wof:placetype":"locality"
},
  "geometry": {"coordinates":[28.76052,63.40536],"type":"Point"}
}