{
  "type": "Feature",
  "properties": {
    "gn:admin1_code":"19.0",
    "gn:admin2_code":"193.0",
    "gn:admin3_code":"976.0",
    "gn:asciiname":"Jolanki",
    "gn:country_code":"FI",
    "gn:dem":117,
    "gn:feature_class":"P",
    "gn:feature_code":"PPL",
    "gn:name":"Jolanki",
    "gn:population":0,
    "gn:timezone":"Europe/Helsinki",
    "iso:country":"FI",
    "wof:name":"Jolanki",
    "wof:placetype":"locality"
},
  "geometry": {"coordinates":[24.55399,66.63553],"type":"Point"}
}