{
  "type": "Feature",
  "properties": {
    "gn:admin1_code":"15.0",
    "gn:admin2_code":"152.0",
    "gn:admin3_code":"475.0",
    "gn:asciiname":"Sanden",
    "gn:country_code":"FI",
    "gn:dem":12,
    "gn:feature_class":"P",
    "gn:feature_code":"PPL",
    "gn:name":"Sanden",
    "gn:population":0,
    "gn:timezone":"Europe/Helsinki",
    "iso:country":"FI",
    "name:ceb_x_preferred":[
        "Sanden"
    ],
    "name:deu_x_preferred":[
        "Sanden"
    ],
    "name:nds_x_preferred":[
        "Sanden"
    ],
    "name:swe_x_preferred":[
        "Sanden"
    ],
    "wof:name":"Sanden",
    "wof:placetype":"locality"
},
  "geometry": {"coordinates":[21.49108,62.96448],"type":"Point"}
}