{
  "type": "Feature",
  "properties": {
    "gn:admin1_code":"17.0",
    "gn:admin2_code":"177.0",
    "gn:admin3_code":"208.0",
    "gn:asciiname":"Kaerkinen",
    "gn:country_code":"FI",
    "gn:dem":33,
    "gn:feature_class":"P",
    "gn:feature_code":"PPL",
    "gn:name":"K\u00e4rkinen",
    "gn:population":0,
    "gn:timezone":"Europe/Helsinki",
    "iso:country":"FI",
    "wof:name":"Kaerkinen",
    "wof:placetype":"locality"
},
  "geometry": {"coordinates":[23.83162,64.06506],"type":"Point"}
}