{
  "type": "Feature",
  "properties": {
    "gn:admin1_code":"15.0",
    "gn:admin2_code":"152.0",
    "gn:admin3_code":"946.0",
    "gn:asciiname":"Lomby",
    "gn:country_code":"FI",
    "gn:dem":20,
    "gn:feature_class":"P",
    "gn:feature_code":"PPL",
    "gn:name":"Lomby",
    "gn:population":0,
    "gn:timezone":"Europe/Helsinki",
    "iso:country":"FI",
    "name:swe_x_preferred":[
        "Lomby"
    ],
    "wof:name":"Lomby",
    "wof:placetype":"locality"
},
  "geometry": {"coordinates":[22.25854,63.12219],"type":"Point"}
}