{
  "type": "Feature",
  "properties": {
    "gn:admin1_code":"9.0",
    "gn:admin2_code":"93.0",
    "gn:admin3_code":"153.0",
    "gn:asciiname":"Kaukopaeae",
    "gn:country_code":"FI",
    "gn:dem":97,
    "gn:feature_class":"P",
    "gn:feature_code":"PPL",
    "gn:name":"Kaukop\u00e4\u00e4",
    "gn:population":0,
    "gn:timezone":"Europe/Helsinki",
    "iso:country":"FI",
    "wof:name":"Kaukopaeae",
    "wof:placetype":"locality"
},
  "geometry": {"coordinates":[28.86186,61.23944],"type":"Point"}
}