{
  "type": "Feature",
  "properties": {
    "gn:admin1_code":"18.0",
    "gn:admin2_code":"181.0",
    "gn:admin3_code":"290.0",
    "gn:asciiname":"Aholanvaara",
    "gn:country_code":"FI",
    "gn:dem":194,
    "gn:feature_class":"P",
    "gn:feature_code":"PPL",
    "gn:name":"Aholanvaara",
    "gn:population":0,
    "gn:timezone":"Europe/Helsinki",
    "iso:country":"FI",
    "name:afr_x_preferred":[
        "Aholanvaara"
    ],
    "name:fin_x_preferred":[
        "Aholanvaara"
    ],
    "wof:name":"Aholanvaara",
    "wof:placetype":"locality"
},
  "geometry": {"coordinates":[29.75646,64.46861],"type":"Point"}
}