{
  "type": "Feature",
  "properties": {
    "gn:admin1_code":"17.0",
    "gn:admin2_code":"173.0",
    "gn:admin3_code":"139.0",
    "gn:asciiname":"Yliranta",
    "gn:country_code":"FI",
    "gn:dem":21,
    "gn:feature_class":"P",
    "gn:feature_code":"PPL",
    "gn:name":"Yliranta",
    "gn:population":0,
    "gn:timezone":"Europe/Helsinki",
    "iso:country":"FI",
    "wof:name":"Yliranta",
    "wof:placetype":"locality"
},
  "geometry": {"coordinates":[25.4809,65.32559000000001],"type":"Point"}
}