{
  "type": "Feature",
  "properties": {
    "gn:admin1_code":"6.0",
    "gn:admin2_code":"69.0",
    "gn:admin3_code":"702.0",
    "gn:asciiname":"Kaukola",
    "gn:country_code":"FI",
    "gn:dem":131,
    "gn:feature_class":"P",
    "gn:feature_code":"PPL",
    "gn:name":"Kaukola",
    "gn:population":0,
    "gn:timezone":"Europe/Helsinki",
    "iso:country":"FI",
    "wof:name":"Kaukola",
    "wof:placetype":"locality"
},
  "geometry": {"coordinates":[24.17387,61.9156],"type":"Point"}
}