{
  "type": "Feature",
  "properties": {
    "gn:admin1_code":"8.0",
    "gn:admin2_code":"82.0",
    "gn:admin3_code":"935.0",
    "gn:asciiname":"Ylae-Virojoki",
    "gn:country_code":"FI",
    "gn:dem":12,
    "gn:feature_class":"P",
    "gn:feature_code":"PPL",
    "gn:name":"Yl\u00e4-Virojoki",
    "gn:population":0,
    "gn:timezone":"Europe/Helsinki",
    "iso:country":"FI",
    "name:eng_x_preferred":[
        "Yl\u00e4-Virojoki"
    ],
    "name:rus_x_preferred":[
        "\u0412\u0438\u0440\u043e\u0439\u043e\u043a\u0438"
    ],
    "name:und_x_variant":[
        "Yl\u00e4-Virojoki"
    ],
    "wof:name":"Ylae-Virojoki",
    "wof:placetype":"locality"
},
  "geometry": {"coordinates":[27.68306,60.58306],"type":"Point"}
}