{
  "type": "Feature",
  "properties": {
    "gn:admin1_code":"2.0",
    "gn:admin2_code":"23.0",
    "gn:admin3_code":"503.0",
    "gn:asciiname":"Sunila",
    "gn:country_code":"FI",
    "gn:dem":17,
    "gn:feature_class":"P",
    "gn:feature_code":"PPL",
    "gn:name":"Sunila",
    "gn:population":0,
    "gn:timezone":"Europe/Helsinki",
    "iso:country":"FI",
    "name:deu_x_preferred":[
        "Sunila"
    ],
    "name:fin_x_preferred":[
        "Sunila"
    ],
    "name:fra_x_preferred":[
        "Sunila"
    ],
    "name:nds_x_preferred":[
        "Sunila"
    ],
    "wof:name":"Sunila",
    "wof:placetype":"locality"
},
  "geometry": {"coordinates":[21.97194,60.66889000000001],"type":"Point"}
}