{
  "type": "Feature",
  "properties": {
    "gn:admin1_code":"1.0",
    "gn:admin2_code":"15.0",
    "gn:admin3_code":"638.0",
    "gn:asciiname":"Henttala",
    "gn:country_code":"FI",
    "gn:dem":34,
    "gn:feature_class":"P",
    "gn:feature_code":"PPL",
    "gn:name":"Henttala",
    "gn:population":0,
    "gn:timezone":"Europe/Helsinki",
    "iso:country":"FI",
    "name:und_x_variant":[
        "Hentala"
    ],
    "wof:name":"Henttala",
    "wof:placetype":"locality"
},
  "geometry": {"coordinates":[25.61667000000001,60.45],"type":"Point"}
}