{
  "type": "Feature",
  "properties": {
    "gn:admin1_code":"10.0",
    "gn:admin2_code":"103.0",
    "gn:admin3_code":"740.0",
    "gn:asciiname":"Saeaeminki",
    "gn:country_code":"FI",
    "gn:dem":68,
    "gn:feature_class":"P",
    "gn:feature_code":"PPL",
    "gn:name":"S\u00e4\u00e4minki",
    "gn:population":0,
    "gn:timezone":"Europe/Helsinki",
    "iso:country":"FI",
    "name:deu_x_preferred":[
        "S\u00e4\u00e4minki"
    ],
    "name:fin_x_preferred":[
        "S\u00e4\u00e4minki"
    ],
    "name:nor_x_preferred":[
        "S\u00e4\u00e4minki"
    ],
    "name:olo_x_preferred":[
        "Si\u00e4minki"
    ],
    "name:swe_x_preferred":[
        "S\u00e4minge"
    ],
    "name:und_x_variant":[
        "S\u00e4\u00e4minge",
        "S\u00e4\u00e4minki"
    ],
    "wof:name":"Saeaeminki",
    "wof:placetype":"locality"
},
  "geometry": {"coordinates":[28.83333,61.86666999999999],"type":"Point"}
}