{
  "type": "Feature",
  "properties": {
    "gn:admin1_code":"18.0",
    "gn:admin2_code":"182.0",
    "gn:admin3_code":"697.0",
    "gn:asciiname":"Uva",
    "gn:country_code":"FI",
    "gn:dem":191,
    "gn:feature_class":"P",
    "gn:feature_code":"PPL",
    "gn:name":"Uva",
    "gn:population":0,
    "gn:timezone":"Europe/Helsinki",
    "iso:country":"FI",
    "name:eng_x_preferred":[
        "Uva"
    ],
    "name:rus_x_preferred":[
        "\u0423\u0432\u0430"
    ],
    "wof:name":"Uva",
    "wof:placetype":"locality"
},
  "geometry": {"coordinates":[28.05284,64.57550000000001],"type":"Point"}
}