{
  "type": "Feature",
  "properties": {
    "gn:admin1_code":"17.0",
    "gn:admin2_code":"177.0",
    "gn:admin3_code":"563.0",
    "gn:asciiname":"Haaranmaeki",
    "gn:country_code":"FI",
    "gn:dem":76,
    "gn:feature_class":"P",
    "gn:feature_code":"PPL",
    "gn:name":"Haaranm\u00e4ki",
    "gn:population":0,
    "gn:timezone":"Europe/Helsinki",
    "iso:country":"FI",
    "wof:name":"Haaranmaeki",
    "wof:placetype":"locality"
},
  "geometry": {"coordinates":[24.84722,64.26966],"type":"Point"}
}