{
  "type": "Feature",
  "properties": {
    "gn:admin1_code":"9.0",
    "gn:admin2_code":"91.0",
    "gn:admin3_code":"405.0",
    "gn:asciiname":"Rikkilae",
    "gn:country_code":"FI",
    "gn:dem":45,
    "gn:feature_class":"P",
    "gn:feature_code":"PPL",
    "gn:name":"Rikkil\u00e4",
    "gn:population":0,
    "gn:timezone":"Europe/Helsinki",
    "iso:country":"FI",
    "wof:name":"Rikkilae",
    "wof:placetype":"locality"
},
  "geometry": {"coordinates":[28.22206,60.89229],"type":"Point"}
}