{
  "type": "Feature",
  "properties": {
    "gn:admin1_code":"10.0",
    "gn:admin2_code":"103.0",
    "gn:admin3_code":"740.0",
    "gn:asciiname":"Hietalahti",
    "gn:country_code":"FI",
    "gn:dem":91,
    "gn:feature_class":"P",
    "gn:feature_code":"PPL",
    "gn:name":"Hietalahti",
    "gn:population":0,
    "gn:timezone":"Europe/Helsinki",
    "iso:country":"FI",
    "name:deu_x_preferred":[
        "Hietalahti"
    ],
    "name:fin_x_preferred":[
        "Hietalahti"
    ],
    "name:rus_x_preferred":[
        "\u0425\u0438\u0435\u0442\u0430\u043b\u0430\u0445\u0442\u0438"
    ],
    "name:swe_x_preferred":[
        "Hietalahti"
    ],
    "wof:name":"Hietalahti",
    "wof:placetype":"locality"
},
  "geometry": {"coordinates":[29.26667,62.03333000000001],"type":"Point"}
}