{
  "type": "Feature",
  "properties": {
    "gn:admin1_code":"17.0",
    "gn:admin2_code":"171.0",
    "gn:admin3_code":"425.0",
    "gn:asciiname":"Jaervenpaeae",
    "gn:country_code":"FI",
    "gn:dem":6,
    "gn:feature_class":"P",
    "gn:feature_code":"PPL",
    "gn:name":"J\u00e4rvenp\u00e4\u00e4",
    "gn:population":0,
    "gn:timezone":"Europe/Helsinki",
    "iso:country":"FI",
    "wof:name":"Jaervenpaeae",
    "wof:placetype":"locality"
},
  "geometry": {"coordinates":[25.40272,64.87964000000001],"type":"Point"}
}