{
  "type": "Feature",
  "properties": {
    "iso:country":"FI",
    "qs_pg:aaroncc":"FI",
    "qs_pg:name":"Hyv\u00e4niemi",
    "qs_pg:name_adm0":"Suomi",
    "qs_pg:name_adm1":"Lapin maakunta",
    "qs_pg:photos":30,
    "qs_pg:photos_1k":6,
    "qs_pg:photos_9k":1,
    "qs_pg:photos_9r":2,
    "qs_pg:photos_all":30,
    "qs_pg:photos_sr":2,
    "qs_pg:pop_sr":0,
    "qs_pg:qs_pg_placetype":"locality",
    "qs_pg:qs_pg_placetype_gp":"Town",
    "qs_pg:woe_adm0":23424812,
    "woe:adm0_id":23424812,
    "woe:name_adm0":"Suomi",
    "woe:name_adm1":"Lapin maakunta",
    "woe:placetype":"Town",
    "wof:name":"Hyv\u00e4niemi",
    "wof:placetype":"locality"
},
  "geometry": {"coordinates":[28.472303,66.028547],"type":"Point"}
}