{
  "type": "Feature",
  "properties": {
    "gn:admin1_code":"1.0",
    "gn:admin2_code":"11.0",
    "gn:admin3_code":"49.0",
    "gn:asciiname":"Mynttilae",
    "gn:cc2":"FI",
    "gn:country_code":"FI",
    "gn:dem":29,
    "gn:feature_class":"P",
    "gn:feature_code":"PPL",
    "gn:name":"Mynttil\u00e4",
    "gn:population":0,
    "gn:timezone":"Europe/Helsinki",
    "iso:country":"FI",
    "name:swe_x_preferred":[
        "Myntb\u00f6le"
    ],
    "wof:name":"Mynttilae",
    "wof:placetype":"locality"
},
  "geometry": {"coordinates":[24.59401,60.20473000000001],"type":"Point"}
}