{
  "type": "Feature",
  "properties": {
    "gn:admin1_code":"2.0",
    "gn:admin2_code":"23.0",
    "gn:admin3_code":"481.0",
    "gn:asciiname":"Rauvola",
    "gn:country_code":"FI",
    "gn:dem":27,
    "gn:feature_class":"P",
    "gn:feature_code":"PPL",
    "gn:name":"Rauvola",
    "gn:population":0,
    "gn:timezone":"Europe/Helsinki",
    "iso:country":"FI",
    "wof:name":"Rauvola",
    "wof:placetype":"locality"
},
  "geometry": {"coordinates":[21.82915,60.52652],"type":"Point"}
}