{
  "type": "Feature",
  "properties": {
    "gn:admin1_code":"14.0",
    "gn:admin2_code":"141.0",
    "gn:admin3_code":"232.0",
    "gn:asciiname":"Kainasto",
    "gn:country_code":"FI",
    "gn:dem":107,
    "gn:feature_class":"P",
    "gn:feature_code":"PPL",
    "gn:name":"Kainasto",
    "gn:population":0,
    "gn:timezone":"Europe/Helsinki",
    "iso:country":"FI",
    "wof:name":"Kainasto",
    "wof:placetype":"locality"
},
  "geometry": {"coordinates":[22.02951,62.46314],"type":"Point"}
}