{
  "type": "Feature",
  "properties": {
    "gn:admin1_code":"6.0",
    "gn:admin2_code":"64.0",
    "gn:admin3_code":"536.0",
    "gn:asciiname":"Metsaekulma",
    "gn:country_code":"FI",
    "gn:dem":114,
    "gn:feature_class":"P",
    "gn:feature_code":"PPL",
    "gn:name":"Mets\u00e4kulma",
    "gn:population":0,
    "gn:timezone":"Europe/Helsinki",
    "iso:country":"FI",
    "wof:name":"Metsaekulma",
    "wof:placetype":"locality"
},
  "geometry": {"coordinates":[23.33153,61.35823000000001],"type":"Point"}
}