{
  "type": "Feature",
  "properties": {
    "gn:admin1_code":"11.0",
    "gn:admin2_code":"115.0",
    "gn:admin3_code":"778.0",
    "gn:asciiname":"Tyyrinmaeki",
    "gn:country_code":"FI",
    "gn:dem":141,
    "gn:feature_class":"P",
    "gn:feature_code":"PPL",
    "gn:name":"Tyyrinm\u00e4ki",
    "gn:population":0,
    "gn:timezone":"Europe/Helsinki",
    "iso:country":"FI",
    "wof:name":"Tyyrinmaeki",
    "wof:placetype":"locality"
},
  "geometry": {"coordinates":[26.9654,62.60768],"type":"Point"}
}