{
  "type": "Feature",
  "properties": {
    "gn:admin1_code":"7.0",
    "gn:admin2_code":"71.0",
    "gn:admin3_code":"781.0",
    "gn:asciiname":"Rapala",
    "gn:country_code":"FI",
    "gn:dem":115,
    "gn:feature_class":"P",
    "gn:feature_code":"PPL",
    "gn:name":"Rapala",
    "gn:population":0,
    "gn:timezone":"Europe/Helsinki",
    "iso:country":"FI",
    "name:deu_x_preferred":[
        "Rapala"
    ],
    "name:eng_x_preferred":[
        "Rapala"
    ],
    "name:fin_x_preferred":[
        "Rapala"
    ],
    "name:fra_x_preferred":[
        "Rapala"
    ],
    "name:ita_x_preferred":[
        "Rapala"
    ],
    "name:mal_x_preferred":[
        "\u0d31\u0d2a\u0d3e\u0d32"
    ],
    "name:rus_x_preferred":[
        "\u0420\u0430\u043f\u0430\u043b\u0430"
    ],
    "name:swe_x_preferred":[
        "Rapala"
    ],
    "name:zho_x_preferred":[
        "\u71d5\u7070\u8776\u5c6c"
    ],
    "wof:name":"Rapala",
    "wof:placetype":"locality"
},
  "geometry": {"coordinates":[25.53333,61.45],"type":"Point"}
}