{
  "type": "Feature",
  "properties": {
    "gn:admin1_code":"14.0",
    "gn:admin2_code":"142.0",
    "gn:admin3_code":"233.0",
    "gn:asciiname":"Haermaelae",
    "gn:country_code":"FI",
    "gn:dem":47,
    "gn:feature_class":"P",
    "gn:feature_code":"PPL",
    "gn:name":"H\u00e4rm\u00e4l\u00e4",
    "gn:population":0,
    "gn:timezone":"Europe/Helsinki",
    "iso:country":"FI",
    "wof:name":"Haermaelae",
    "wof:placetype":"locality"
},
  "geometry": {"coordinates":[22.86667000000001,63.25],"type":"Point"}
}