{
  "type": "Feature",
  "properties": {
    "gn:admin1_code":"2.0",
    "gn:admin2_code":"21.0",
    "gn:admin3_code":"445.0",
    "gn:asciiname":"Kaervois",
    "gn:country_code":"FI",
    "gn:dem":3,
    "gn:feature_class":"P",
    "gn:feature_code":"PPL",
    "gn:name":"K\u00e4rvois",
    "gn:population":0,
    "gn:timezone":"Europe/Helsinki",
    "iso:country":"FI",
    "name:fin_x_preferred":[
        "Kervoinen"
    ],
    "name:und_x_variant":[
        "Kervois",
        "K\u00e4rvois"
    ],
    "wof:name":"Kaervois",
    "wof:placetype":"locality"
},
  "geometry": {"coordinates":[21.60965,60.25397],"type":"Point"}
}