{
  "type": "Feature",
  "properties": {
    "gn:admin1_code":"2.0",
    "gn:admin2_code":"21.0",
    "gn:admin3_code":"445.0",
    "gn:asciiname":"Kyrkaeng",
    "gn:country_code":"FI",
    "gn:dem":17,
    "gn:feature_class":"P",
    "gn:feature_code":"PPL",
    "gn:name":"Kyrk\u00e4ng",
    "gn:population":0,
    "gn:timezone":"Europe/Helsinki",
    "iso:country":"FI",
    "wof:name":"Kyrkaeng",
    "wof:placetype":"locality"
},
  "geometry": {"coordinates":[22.3668,60.32585],"type":"Point"}
}