{
  "type": "Feature",
  "properties": {
    "gn:admin1_code":"4.0",
    "gn:admin2_code":"41.0",
    "gn:admin3_code":"783.0",
    "gn:asciiname":"Paavila",
    "gn:country_code":"FI",
    "gn:dem":57,
    "gn:feature_class":"P",
    "gn:feature_code":"PPL",
    "gn:name":"Paavila",
    "gn:population":0,
    "gn:timezone":"Europe/Helsinki",
    "iso:country":"FI",
    "wof:name":"Paavila",
    "wof:placetype":"locality"
},
  "geometry": {"coordinates":[22.31667,61.16667],"type":"Point"}
}