{
  "type": "Feature",
  "properties": {
    "gn:admin1_code":"2.0",
    "gn:admin2_code":"23.0",
    "gn:admin3_code":"577.0",
    "gn:asciiname":"Askala",
    "gn:cc2":"FI",
    "gn:country_code":"FI",
    "gn:dem":56,
    "gn:feature_class":"P",
    "gn:feature_code":"PPL",
    "gn:name":"Askala",
    "gn:population":0,
    "gn:timezone":"Europe/Helsinki",
    "iso:country":"FI",
    "name:und_x_variant":[
        "Askola",
        "Askala"
    ],
    "wof:name":"Askala",
    "wof:placetype":"locality"
},
  "geometry": {"coordinates":[22.68747,60.48794],"type":"Point"}
}