{
  "type": "Feature",
  "properties": {
    "gn:admin1_code":"12.0",
    "gn:admin2_code":"125.0",
    "gn:admin3_code":"541.0",
    "gn:asciiname":"Bomba",
    "gn:country_code":"FI",
    "gn:dem":109,
    "gn:feature_class":"P",
    "gn:feature_code":"PPL",
    "gn:name":"Bomba",
    "gn:population":0,
    "gn:timezone":"Europe/Helsinki",
    "iso:country":"FI",
    "name:cat_x_preferred":[
        "Bomba"
    ],
    "name:ceb_x_preferred":[
        "Bomba"
    ],
    "name:ces_x_preferred":[
        "Bomba"
    ],
    "name:deu_x_preferred":[
        "Bomba"
    ],
    "name:fin_x_preferred":[
        "Bomba"
    ],
    "name:fra_x_preferred":[
        "Bomba"
    ],
    "name:glg_x_preferred":[
        "Bomba"
    ],
    "name:hrv_x_preferred":[
        "Bomba"
    ],
    "name:ind_x_preferred":[
        "Bomba"
    ],
    "name:ita_x_preferred":[
        "Bomba"
    ],
    "name:lit_x_preferred":[
        "Bomba"
    ],
    "name:nds_x_preferred":[
        "Bomba"
    ],
    "name:pol_x_preferred":[
        "Bomba"
    ],
    "name:por_x_preferred":[
        "Bomba"
    ],
    "name:rus_x_preferred":[
        "\u0411\u043e\u043c\u0431\u0430"
    ],
    "name:slk_x_preferred":[
        "Bomba"
    ],
    "name:spa_x_preferred":[
        "Bomba"
    ],
    "name:swe_x_preferred":[
        "Bomba"
    ],
    "name:tgl_x_preferred":[
        "Bomba"
    ],
    "name:tur_x_preferred":[
        "Bomba"
    ],
    "name:ukr_x_preferred":[
        "\u0411\u043e\u043c\u0431\u0430"
    ],
    "wof:name":"Bomba",
    "wof:placetype":"locality"
},
  "geometry": {"coordinates":[29.17079,63.53375],"type":"Point"}
}