{
  "type": "Feature",
  "properties": {
    "gn:admin1_code":"5.0",
    "gn:admin2_code":"51.0",
    "gn:admin3_code":"109.0",
    "gn:asciiname":"Luolaja",
    "gn:country_code":"FI",
    "gn:dem":121,
    "gn:feature_class":"P",
    "gn:feature_code":"PPL",
    "gn:name":"Luolaja",
    "gn:population":0,
    "gn:timezone":"Europe/Helsinki",
    "iso:country":"FI",
    "wof:name":"Luolaja",
    "wof:placetype":"locality"
},
  "geometry": {"coordinates":[24.43205,60.97548000000001],"type":"Point"}
}