{
  "type": "Feature",
  "properties": {
    "gn:admin1_code":"2.0",
    "gn:admin2_code":"23.0",
    "gn:admin3_code":"529.0",
    "gn:asciiname":"Ruokorauma",
    "gn:country_code":"FI",
    "gn:dem":10,
    "gn:feature_class":"P",
    "gn:feature_code":"PPL",
    "gn:name":"Ruokorauma",
    "gn:population":0,
    "gn:timezone":"Europe/Helsinki",
    "iso:country":"FI",
    "wof:name":"Ruokorauma",
    "wof:placetype":"locality"
},
  "geometry": {"coordinates":[21.95016,60.40241],"type":"Point"}
}