{
  "type": "Feature",
  "properties": {
    "gn:admin1_code":"2.0",
    "gn:admin2_code":"21.0",
    "gn:admin3_code":"445.0",
    "gn:asciiname":"Brattnaes",
    "gn:country_code":"FI",
    "gn:dem":20,
    "gn:feature_class":"P",
    "gn:feature_code":"PPL",
    "gn:name":"Brattn\u00e4s",
    "gn:population":0,
    "gn:timezone":"Europe/Helsinki",
    "iso:country":"FI",
    "wof:name":"Brattnaes",
    "wof:placetype":"locality"
},
  "geometry": {"coordinates":[22.33447,60.26609000000001],"type":"Point"}
}