{
  "type": "Feature",
  "properties": {
    "gn:admin1_code":"16.0",
    "gn:admin2_code":"161.0",
    "gn:admin3_code":"584.0",
    "gn:asciiname":"Korkiakangas",
    "gn:country_code":"FI",
    "gn:dem":218,
    "gn:feature_class":"P",
    "gn:feature_code":"PPL",
    "gn:name":"Korkiakangas",
    "gn:population":0,
    "gn:timezone":"Europe/Helsinki",
    "iso:country":"FI",
    "wof:name":"Korkiakangas",
    "wof:placetype":"locality"
},
  "geometry": {"coordinates":[24.63897,63.18011],"type":"Point"}
}