{
  "type": "Feature",
  "properties": {
    "gn:admin1_code":"12.0",
    "gn:admin2_code":"124.0",
    "gn:admin3_code":"848.0",
    "gn:asciiname":"Jaerventaus",
    "gn:country_code":"FI",
    "gn:dem":103,
    "gn:feature_class":"P",
    "gn:feature_code":"PPL",
    "gn:name":"J\u00e4rventaus",
    "gn:population":0,
    "gn:timezone":"Europe/Helsinki",
    "iso:country":"FI",
    "wof:name":"Jaerventaus",
    "wof:placetype":"locality"
},
  "geometry": {"coordinates":[30.36843,62.13464000000001],"type":"Point"}
}