{
  "type": "Feature",
  "properties": {
    "gn:admin1_code":"1.0",
    "gn:admin2_code":"11.0",
    "gn:admin3_code":"245.0",
    "gn:asciiname":"Kannisto",
    "gn:country_code":"FI",
    "gn:dem":50,
    "gn:feature_class":"P",
    "gn:feature_code":"PPL",
    "gn:name":"Kannisto",
    "gn:population":0,
    "gn:timezone":"Europe/Helsinki",
    "iso:country":"FI",
    "wof:name":"Kannisto",
    "wof:placetype":"locality"
},
  "geometry": {"coordinates":[25.09372,60.39363],"type":"Point"}
}