{
  "type": "Feature",
  "properties": {
    "gn:admin1_code":"17.0",
    "gn:admin2_code":"177.0",
    "gn:admin3_code":"977.0",
    "gn:asciiname":"Kuovila",
    "gn:country_code":"FI",
    "gn:dem":75,
    "gn:feature_class":"P",
    "gn:feature_code":"PPL",
    "gn:name":"Kuovila",
    "gn:population":0,
    "gn:timezone":"Europe/Helsinki",
    "iso:country":"FI",
    "wof:name":"Kuovila",
    "wof:placetype":"locality"
},
  "geometry": {"coordinates":[24.47236,64.02369],"type":"Point"}
}