{
  "type": "Feature",
  "properties": {
    "gn:admin1_code":"11.0",
    "gn:admin2_code":"114.0",
    "gn:admin3_code":"915.0",
    "gn:asciiname":"Joutsenlahti",
    "gn:country_code":"FI",
    "gn:dem":83,
    "gn:feature_class":"P",
    "gn:feature_code":"PPL",
    "gn:name":"Joutsenlahti",
    "gn:population":0,
    "gn:timezone":"Europe/Helsinki",
    "iso:country":"FI",
    "wof:name":"Joutsenlahti",
    "wof:placetype":"locality"
},
  "geometry": {"coordinates":[28.15,62.28333000000001],"type":"Point"}
}