{
  "type": "Feature",
  "properties": {
    "gn:admin1_code":"5.0",
    "gn:admin2_code":"51.0",
    "gn:admin3_code":"82.0",
    "gn:asciiname":"Valtee",
    "gn:country_code":"FI",
    "gn:dem":89,
    "gn:feature_class":"P",
    "gn:feature_code":"PPL",
    "gn:name":"Valtee",
    "gn:population":0,
    "gn:timezone":"Europe/Helsinki",
    "iso:country":"FI",
    "wof:name":"Valtee",
    "wof:placetype":"locality"
},
  "geometry": {"coordinates":[24.4234,61.10536999999999],"type":"Point"}
}