{
  "type": "Feature",
  "properties": {
    "gn:admin1_code":"12.0",
    "gn:admin2_code":"122.0",
    "gn:admin3_code":"607.0",
    "gn:asciiname":"Kupinpuro",
    "gn:country_code":"FI",
    "gn:dem":78,
    "gn:feature_class":"P",
    "gn:feature_code":"PPL",
    "gn:name":"Kupinpuro",
    "gn:population":0,
    "gn:timezone":"Europe/Helsinki",
    "iso:country":"FI",
    "wof:name":"Kupinpuro",
    "wof:placetype":"locality"
},
  "geometry": {"coordinates":[29.36268,62.81657],"type":"Point"}
}