{
  "type": "Feature",
  "properties": {
    "gn:admin1_code":"14.0",
    "gn:admin2_code":"142.0",
    "gn:admin3_code":"145.0",
    "gn:asciiname":"Saha",
    "gn:country_code":"FI",
    "gn:dem":71,
    "gn:feature_class":"P",
    "gn:feature_code":"PPL",
    "gn:name":"Saha",
    "gn:population":0,
    "gn:timezone":"Europe/Helsinki",
    "iso:country":"FI",
    "name:ceb_x_preferred":[
        "Saha"
    ],
    "name:deu_x_preferred":[
        "Saha"
    ],
    "name:epo_x_preferred":[
        "Saha"
    ],
    "name:fin_x_preferred":[
        "Saha"
    ],
    "name:fra_x_preferred":[
        "Saha"
    ],
    "name:swe_x_preferred":[
        "Saha"
    ],
    "wof:name":"Saha",
    "wof:placetype":"locality"
},
  "geometry": {"coordinates":[22.65,62.66667],"type":"Point"}
}