{
  "type": "Feature",
  "properties": {
    "gn:admin1_code":"4.0",
    "gn:admin2_code":"41.0",
    "gn:admin3_code":"51.0",
    "gn:asciiname":"Vaeipaere",
    "gn:country_code":"FI",
    "gn:dem":20,
    "gn:feature_class":"P",
    "gn:feature_code":"PPL",
    "gn:name":"V\u00e4ip\u00e4re",
    "gn:population":0,
    "gn:timezone":"Europe/Helsinki",
    "iso:country":"FI",
    "name:dan_x_preferred":[
        "V\u00e4gby"
    ],
    "name:isl_x_preferred":[
        "V\u00e4gby"
    ],
    "name:nor_x_preferred":[
        "V\u00e4gby"
    ],
    "name:swe_x_preferred":[
        "V\u00e4gby"
    ],
    "name:und_x_variant":[
        "V\u00e4ip\u00e4re"
    ],
    "wof:name":"Vaeipaere",
    "wof:placetype":"locality"
},
  "geometry": {"coordinates":[21.68333,61.36666999999999],"type":"Point"}
}