{
  "type": "Feature",
  "properties": {
    "gn:admin1_code":"8.0",
    "gn:admin2_code":"82.0",
    "gn:admin3_code":"489.0",
    "gn:asciiname":"Tylli",
    "gn:country_code":"FI",
    "gn:dem":22,
    "gn:feature_class":"P",
    "gn:feature_code":"PPL",
    "gn:name":"Tylli",
    "gn:population":0,
    "gn:timezone":"Europe/Helsinki",
    "iso:country":"FI",
    "wof:name":"Tylli",
    "wof:placetype":"locality"
},
  "geometry": {"coordinates":[27.80766,60.66597],"type":"Point"}
}