{
  "type": "Feature",
  "properties": {
    "gn:admin1_code":"11.0",
    "gn:admin2_code":"114.0",
    "gn:admin3_code":"420.0",
    "gn:asciiname":"Palokangas",
    "gn:country_code":"FI",
    "gn:dem":99,
    "gn:feature_class":"P",
    "gn:feature_code":"PPL",
    "gn:name":"Palokangas",
    "gn:population":0,
    "gn:timezone":"Europe/Helsinki",
    "iso:country":"FI",
    "wof:name":"Palokangas",
    "wof:placetype":"locality"
},
  "geometry": {"coordinates":[27.61117,62.54858],"type":"Point"}
}