{
  "type": "Feature",
  "properties": {
    "gn:admin1_code":"2.0",
    "gn:admin2_code":"24.0",
    "gn:admin3_code":"895.0",
    "gn:asciiname":"Edvaeinen",
    "gn:country_code":"FI",
    "gn:dem":11,
    "gn:feature_class":"P",
    "gn:feature_code":"PPL",
    "gn:name":"Edv\u00e4inen",
    "gn:population":0,
    "gn:timezone":"Europe/Helsinki",
    "iso:country":"FI",
    "name:und_x_variant":[
        "Ervesbyu",
        "Edv\u00e4inen"
    ],
    "wof:name":"Edvaeinen",
    "wof:placetype":"locality"
},
  "geometry": {"coordinates":[21.24388,60.90671],"type":"Point"}
}