{
  "type": "Feature",
  "properties": {
    "iso:country":"FI",
    "qs_pg:aaroncc":"FI",
    "qs_pg:name":"Linnoitus",
    "qs_pg:name_adm0":"Suomi",
    "qs_pg:name_adm1":"Etel\u00e4-Karjalan maakunta",
    "qs_pg:photos":189,
    "qs_pg:photos_1k":38,
    "qs_pg:photos_9k":1,
    "qs_pg:photos_9r":4,
    "qs_pg:photos_all":189,
    "qs_pg:photos_sr":4,
    "qs_pg:pop_sr":0,
    "qs_pg:qs_pg_placetype":"locality",
    "qs_pg:qs_pg_placetype_gp":"Town",
    "qs_pg:woe_adm0":23424812,
    "woe:adm0_id":23424812,
    "woe:name_adm0":"Suomi",
    "woe:name_adm1":"Etel\u00e4-Karjalan maakunta",
    "woe:placetype":"Town",
    "wof:name":"Linnoitus",
    "wof:placetype":"locality"
},
  "geometry": {"coordinates":[28.183815,61.064953],"type":"Point"}
}