{
  "type": "Feature",
  "properties": {
    "gn:admin1_code":"13.0",
    "gn:admin2_code":"131.0",
    "gn:admin3_code":"77.0",
    "gn:asciiname":"Kovalanmaeki",
    "gn:country_code":"FI",
    "gn:dem":187,
    "gn:feature_class":"P",
    "gn:feature_code":"PPL",
    "gn:name":"Kovalanm\u00e4ki",
    "gn:population":0,
    "gn:timezone":"Europe/Helsinki",
    "iso:country":"FI",
    "wof:name":"Kovalanmaeki",
    "wof:placetype":"locality"
},
  "geometry": {"coordinates":[26.39465,62.31556],"type":"Point"}
}