{
  "type": "Feature",
  "properties": {
    "gn:admin1_code":"6.0",
    "gn:admin2_code":"68.0",
    "gn:admin3_code":"790.0",
    "gn:asciiname":"Kari",
    "gn:country_code":"FI",
    "gn:dem":82,
    "gn:feature_class":"P",
    "gn:feature_code":"PPL",
    "gn:name":"Kari",
    "gn:population":0,
    "gn:timezone":"Europe/Helsinki",
    "iso:country":"FI",
    "wof:name":"Kari",
    "wof:placetype":"locality"
},
  "geometry": {"coordinates":[22.83333,61.51667],"type":"Point"}
}