{
  "type": "Feature",
  "properties": {
    "gn:admin1_code":"2.0",
    "gn:admin2_code":"23.0",
    "gn:admin3_code":"503.0",
    "gn:asciiname":"Tammisto",
    "gn:country_code":"FI",
    "gn:dem":15,
    "gn:feature_class":"P",
    "gn:feature_code":"PPL",
    "gn:name":"Tammisto",
    "gn:population":0,
    "gn:timezone":"Europe/Helsinki",
    "iso:country":"FI",
    "wof:name":"Tammisto",
    "wof:placetype":"locality"
},
  "geometry": {"coordinates":[21.88694,60.68653000000001],"type":"Point"}
}