{
  "type": "Feature",
  "properties": {
    "gn:admin1_code":"11.0",
    "gn:admin2_code":"114.0",
    "gn:admin3_code":"915.0",
    "gn:asciiname":"Ruokojaervi",
    "gn:cc2":"FI",
    "gn:country_code":"FI",
    "gn:dem":81,
    "gn:feature_class":"P",
    "gn:feature_code":"PPL",
    "gn:name":"Ruokoj\u00e4rvi",
    "gn:population":0,
    "gn:timezone":"Europe/Helsinki",
    "iso:country":"FI",
    "name:und_x_variant":[
        "Ruokokoski",
        "Ruokoj\u00e4rvi"
    ],
    "wof:name":"Ruokojaervi",
    "wof:placetype":"locality"
},
  "geometry": {"coordinates":[27.77653,62.32247],"type":"Point"}
}