{
  "type": "Feature",
  "properties": {
    "gn:admin1_code":"17.0",
    "gn:admin2_code":"177.0",
    "gn:admin3_code":"208.0",
    "gn:asciiname":"Pitkaesenkylae",
    "gn:country_code":"FI",
    "gn:dem":21,
    "gn:feature_class":"P",
    "gn:feature_code":"PPL",
    "gn:name":"Pitk\u00e4senkyl\u00e4",
    "gn:population":0,
    "gn:timezone":"Europe/Helsinki",
    "iso:country":"FI",
    "name:eng_x_preferred":[
        "Pitk\u00e4senkyl\u00e4"
    ],
    "name:rus_x_preferred":[
        "\u041f\u0438\u0442\u043a\u044f\u0441\u0435\u043d\u043a\u044e\u043b\u044f"
    ],
    "name:und_x_variant":[
        "Pitk\u00e4istenkyl\u00e4"
    ],
    "wof:name":"Pitkaesenkylae",
    "wof:placetype":"locality"
},
  "geometry": {"coordinates":[24.01776,64.23226],"type":"Point"}
}