{
  "type": "Feature",
  "properties": {
    "gn:admin1_code":"13.0",
    "gn:admin2_code":"134.0",
    "gn:admin3_code":"182.0",
    "gn:asciiname":"Ruotsinkorpi",
    "gn:country_code":"FI",
    "gn:dem":119,
    "gn:feature_class":"P",
    "gn:feature_code":"PPL",
    "gn:name":"Ruotsinkorpi",
    "gn:population":0,
    "gn:timezone":"Europe/Helsinki",
    "iso:country":"FI",
    "name:fin_x_preferred":[
        "Ruotsinkorpi"
    ],
    "wof:name":"Ruotsinkorpi",
    "wof:placetype":"locality"
},
  "geometry": {"coordinates":[24.95279,61.97533000000001],"type":"Point"}
}