{
  "type": "Feature",
  "properties": {
    "gn:admin1_code":"1.0",
    "gn:admin2_code":"11.0",
    "gn:admin3_code":"753.0",
    "gn:asciiname":"Rux",
    "gn:country_code":"FI",
    "gn:dem":43,
    "gn:feature_class":"P",
    "gn:feature_code":"PPL",
    "gn:name":"Rux",
    "gn:population":0,
    "gn:timezone":"Europe/Helsinki",
    "iso:country":"FI",
    "name:bul_x_preferred":[
        "Rux"
    ],
    "name:deu_x_preferred":[
        "Rux"
    ],
    "name:kor_x_preferred":[
        "\ub7ed\uc2a4"
    ],
    "name:por_x_preferred":[
        "Rux"
    ],
    "name:swe_x_preferred":[
        "Rux"
    ],
    "wof:name":"Rux",
    "wof:placetype":"locality"
},
  "geometry": {"coordinates":[25.28423,60.36621],"type":"Point"}
}