{
  "type": "Feature",
  "properties": {
    "gn:admin1_code":"6.0",
    "gn:admin2_code":"64.0",
    "gn:admin3_code":"837.0",
    "gn:asciiname":"Paarlahti",
    "gn:country_code":"FI",
    "gn:dem":105,
    "gn:feature_class":"P",
    "gn:feature_code":"PPL",
    "gn:name":"Paarlahti",
    "gn:population":0,
    "gn:timezone":"Europe/Helsinki",
    "iso:country":"FI",
    "name:ceb_x_preferred":[
        "Paarlahti"
    ],
    "name:fin_x_preferred":[
        "Paarlahti"
    ],
    "name:swe_x_preferred":[
        "Paarlahti"
    ],
    "wof:name":"Paarlahti",
    "wof:placetype":"locality"
},
  "geometry": {"coordinates":[23.93818,61.64099],"type":"Point"}
}