{
  "type": "Feature",
  "properties": {
    "gn:population":542,
    "iso:country":"FI",
    "name:ceb_x_preferred":[
        "\u00d6stersundom"
    ],
    "name:eng_x_preferred":[
        "\u00d6stersundom"
    ],
    "name:fin_x_preferred":[
        "\u00d6stersundom"
    ],
    "name:fra_x_preferred":[
        "\u00d6stersundom"
    ],
    "name:fre_x_preferred":[
        "\u00d6stersundom"
    ],
    "name:rus_x_preferred":[
        "\u042d\u0441\u0442\u0435\u0440\u0441\u0443\u043d\u0434\u043e\u043c"
    ],
    "name:spa_x_preferred":[
        "\u00d6stersundom"
    ],
    "name:swe_x_preferred":[
        "\u00d6stersundom"
    ],
    "qs:a0":"Suomi#Finland",
    "qs:a1":"*Uusimaa#Nyland",
    "qs:a1r":"0Etel\u00e4-Suomen AVI#S\u00f6dra Finlands RFV",
    "qs:adm0":"Suomi#Finland",
    "qs:la_lc":"*",
    "qs:level":"locality",
    "qs:loc":"\u00d6stersundom",
    "qs:loc_alt":"Ostersundom",
    "qs:pop":0,
    "qs:type":"buffered point",
    "wd:wordcount":30,
    "wof:name":"\u00d6stersundom",
    "wof:placetype":"locality",
    "wof:population":542
},
  "geometry": {"coordinates":[25.198139,60.25486],"type":"Point"}
}