{
  "type": "Feature",
  "properties": {
    "gn:admin1_code":"14.0",
    "gn:admin2_code":"141.0",
    "gn:admin3_code":"151.0",
    "gn:asciiname":"Honkaniemi",
    "gn:country_code":"FI",
    "gn:dem":97,
    "gn:feature_class":"P",
    "gn:feature_code":"PPL",
    "gn:name":"Honkaniemi",
    "gn:population":0,
    "gn:timezone":"Europe/Helsinki",
    "iso:country":"FI",
    "name:fin_x_preferred":[
        "Honkaniemi"
    ],
    "wof:name":"Honkaniemi",
    "wof:placetype":"locality"
},
  "geometry": {"coordinates":[21.93249,62.12409],"type":"Point"}
}