{
  "type": "Feature",
  "properties": {
    "gn:admin1_code":"12.0",
    "gn:admin2_code":"124.0",
    "gn:admin3_code":"848.0",
    "gn:asciiname":"Mattila",
    "gn:country_code":"FI",
    "gn:dem":104,
    "gn:feature_class":"P",
    "gn:feature_code":"PPL",
    "gn:name":"Mattila",
    "gn:population":0,
    "gn:timezone":"Europe/Helsinki",
    "iso:country":"FI",
    "wof:name":"Mattila",
    "wof:placetype":"locality"
},
  "geometry": {"coordinates":[30.37016,62.13001],"type":"Point"}
}