{
  "type": "Feature",
  "properties": {
    "gn:admin1_code":"1.0",
    "gn:admin2_code":"16.0",
    "gn:admin3_code":"434.0",
    "gn:asciiname":"Hiidenniemi",
    "gn:country_code":"FI",
    "gn:dem":36,
    "gn:feature_class":"P",
    "gn:feature_code":"PPL",
    "gn:name":"Hiidenniemi",
    "gn:population":0,
    "gn:timezone":"Europe/Helsinki",
    "iso:country":"FI",
    "wof:name":"Hiidenniemi",
    "wof:placetype":"locality"
},
  "geometry": {"coordinates":[25.85,60.55],"type":"Point"}
}