{
  "type": "Feature",
  "properties": {
    "gn:admin1_code":"10.0",
    "gn:admin2_code":"103.0",
    "gn:admin3_code":"681.0",
    "gn:asciiname":"Paunola",
    "gn:cc2":"FI",
    "gn:country_code":"FI",
    "gn:dem":93,
    "gn:feature_class":"P",
    "gn:feature_code":"PPL",
    "gn:name":"Paunola",
    "gn:population":0,
    "gn:timezone":"Europe/Helsinki",
    "iso:country":"FI",
    "name:und_x_variant":[
        "Pauna",
        "Paunola"
    ],
    "wof:name":"Paunola",
    "wof:placetype":"locality"
},
  "geometry": {"coordinates":[28.38333,62.03333000000001],"type":"Point"}
}