{
  "type": "Feature",
  "properties": {
    "gn:admin1_code":"17.0",
    "gn:admin2_code":"178.0",
    "gn:admin3_code":"305.0",
    "gn:asciiname":"Kiviperae",
    "gn:country_code":"FI",
    "gn:dem":258,
    "gn:feature_class":"P",
    "gn:feature_code":"PPL",
    "gn:name":"Kiviper\u00e4",
    "gn:population":0,
    "gn:timezone":"Europe/Helsinki",
    "iso:country":"FI",
    "name:eng_x_preferred":[
        "Kiviper\u00e4"
    ],
    "name:rus_x_preferred":[
        "\u041a\u0438\u0432\u0438\u043f\u0435\u0440\u044f"
    ],
    "wof:name":"Kiviperae",
    "wof:placetype":"locality"
},
  "geometry": {"coordinates":[29.76997,66.06435],"type":"Point"}
}