{
  "type": "Feature",
  "properties": {
    "gn:admin1_code":"4.0",
    "gn:admin2_code":"44.0",
    "gn:admin3_code":"230.0",
    "gn:asciiname":"Suomijaervi",
    "gn:country_code":"FI",
    "gn:dem":148,
    "gn:feature_class":"P",
    "gn:feature_code":"PPL",
    "gn:name":"Suomij\u00e4rvi",
    "gn:population":0,
    "gn:timezone":"Europe/Helsinki",
    "iso:country":"FI",
    "wof:name":"Suomijaervi",
    "wof:placetype":"locality"
},
  "geometry": {"coordinates":[22.63508,62.10347],"type":"Point"}
}