{
  "type": "Feature",
  "properties": {
    "gn:admin1_code":"8.0",
    "gn:admin2_code":"81.0",
    "gn:admin3_code":"286.0",
    "gn:asciiname":"Verkkosuo",
    "gn:country_code":"FI",
    "gn:dem":79,
    "gn:feature_class":"P",
    "gn:feature_code":"PPL",
    "gn:name":"Verkkosuo",
    "gn:population":0,
    "gn:timezone":"Europe/Helsinki",
    "iso:country":"FI",
    "wof:name":"Verkkosuo",
    "wof:placetype":"locality"
},
  "geometry": {"coordinates":[26.65498,60.96536],"type":"Point"}
}