{
  "type": "Feature",
  "properties": {
    "gn:admin1_code":"15.0",
    "gn:admin2_code":"154.0",
    "gn:admin3_code":"288.0",
    "gn:asciiname":"Bast",
    "gn:country_code":"FI",
    "gn:dem":13,
    "gn:feature_class":"P",
    "gn:feature_code":"PPL",
    "gn:name":"Bast",
    "gn:population":0,
    "gn:timezone":"Europe/Helsinki",
    "iso:country":"FI",
    "name:bos_x_preferred":[
        "Bast"
    ],
    "name:dan_x_preferred":[
        "Bast"
    ],
    "name:deu_x_preferred":[
        "Bast"
    ],
    "name:epo_x_preferred":[
        "Bast"
    ],
    "name:fra_x_preferred":[
        "Bast"
    ],
    "name:hun_x_preferred":[
        "Bast"
    ],
    "name:ita_x_preferred":[
        "Bast"
    ],
    "name:slk_x_preferred":[
        "Bast"
    ],
    "name:swe_x_preferred":[
        "Bast"
    ],
    "wof:name":"Bast",
    "wof:placetype":"locality"
},
  "geometry": {"coordinates":[23.28524,63.71334],"type":"Point"}
}