{
  "type": "Feature",
  "properties": {
    "gn:admin1_code":"14.0",
    "gn:admin2_code":"144.0",
    "gn:admin3_code":"10.0",
    "gn:asciiname":"Kontiainen",
    "gn:country_code":"FI",
    "gn:dem":136,
    "gn:feature_class":"P",
    "gn:feature_code":"PPL",
    "gn:name":"Kontiainen",
    "gn:population":0,
    "gn:timezone":"Europe/Helsinki",
    "iso:country":"FI",
    "wof:name":"Kontiainen",
    "wof:placetype":"locality"
},
  "geometry": {"coordinates":[23.45776,62.54002],"type":"Point"}
}