{
  "type": "Feature",
  "properties": {
    "gn:admin1_code":"15.0",
    "gn:admin2_code":"153.0",
    "gn:admin3_code":"287.0",
    "gn:asciiname":"Rajamaeki",
    "gn:country_code":"FI",
    "gn:dem":29,
    "gn:feature_class":"P",
    "gn:feature_code":"PPL",
    "gn:name":"Rajam\u00e4ki",
    "gn:population":0,
    "gn:timezone":"Europe/Helsinki",
    "iso:country":"FI",
    "wof:name":"Rajamaeki",
    "wof:placetype":"locality"
},
  "geometry": {"coordinates":[21.43333,62.26667],"type":"Point"}
}