{
  "type": "Feature",
  "properties": {
    "gn:admin1_code":"5.0",
    "gn:admin2_code":"51.0",
    "gn:admin3_code":"109.0",
    "gn:asciiname":"Kukostensyrjae",
    "gn:country_code":"FI",
    "gn:dem":94,
    "gn:feature_class":"P",
    "gn:feature_code":"PPL",
    "gn:name":"Kukostensyrj\u00e4",
    "gn:population":0,
    "gn:timezone":"Europe/Helsinki",
    "iso:country":"FI",
    "wof:name":"Kukostensyrjae",
    "wof:placetype":"locality"
},
  "geometry": {"coordinates":[24.51393,61.01442],"type":"Point"}
}