{
  "type": "Feature",
  "properties": {
    "gn:admin1_code":"11.0",
    "gn:admin2_code":"113.0",
    "gn:admin3_code":"687.0",
    "gn:asciiname":"Kettulanmaeki",
    "gn:country_code":"FI",
    "gn:dem":168,
    "gn:feature_class":"P",
    "gn:feature_code":"PPL",
    "gn:name":"Kettulanm\u00e4ki",
    "gn:population":0,
    "gn:timezone":"Europe/Helsinki",
    "iso:country":"FI",
    "wof:name":"Kettulanmaeki",
    "wof:placetype":"locality"
},
  "geometry": {"coordinates":[28.55,63.58333],"type":"Point"}
}