{
  "type": "Feature",
  "properties": {
    "gn:admin1_code":"12.0",
    "gn:admin2_code":"122.0",
    "gn:admin3_code":"309.0",
    "gn:asciiname":"Maljasalmi",
    "gn:country_code":"FI",
    "gn:dem":121,
    "gn:feature_class":"P",
    "gn:feature_code":"PPL",
    "gn:name":"Maljasalmi",
    "gn:population":0,
    "gn:timezone":"Europe/Helsinki",
    "iso:country":"FI",
    "wof:name":"Maljasalmi",
    "wof:placetype":"locality"
},
  "geometry": {"coordinates":[28.80718,62.68234],"type":"Point"}
}