{
  "type": "Feature",
  "properties": {
    "gn:admin1_code":"15.0",
    "gn:admin2_code":"154.0",
    "gn:admin3_code":"599.0",
    "gn:asciiname":"Nederpurmo",
    "gn:country_code":"FI",
    "gn:dem":30,
    "gn:feature_class":"P",
    "gn:feature_code":"PPL",
    "gn:name":"Nederpurmo",
    "gn:population":0,
    "gn:timezone":"Europe/Helsinki",
    "iso:country":"FI",
    "wof:name":"Nederpurmo",
    "wof:placetype":"locality"
},
  "geometry": {"coordinates":[22.96667,63.51667],"type":"Point"}
}