{
  "type": "Feature",
  "properties": {
    "gn:admin1_code":"8.0",
    "gn:admin2_code":"81.0",
    "gn:admin3_code":"142.0",
    "gn:asciiname":"Ylae-Jaervinen",
    "gn:country_code":"FI",
    "gn:dem":111,
    "gn:feature_class":"P",
    "gn:feature_code":"PPL",
    "gn:name":"Yl\u00e4-J\u00e4rvinen",
    "gn:population":0,
    "gn:timezone":"Europe/Helsinki",
    "iso:country":"FI",
    "name:eng_x_preferred":[
        "Yl\u00e4-J\u00e4rvinen"
    ],
    "name:rus_x_preferred":[
        "\u042f\u0440\u0432\u0438\u043d\u0435\u043d"
    ],
    "wof:name":"Ylae-Jaervinen",
    "wof:placetype":"locality"
},
  "geometry": {"coordinates":[26.11667000000001,61.08333],"type":"Point"}
}