{
  "type": "Feature",
  "properties": {
    "gn:admin1_code":"13.0",
    "gn:admin2_code":"134.0",
    "gn:admin3_code":"182.0",
    "gn:asciiname":"Vekkula",
    "gn:country_code":"FI",
    "gn:dem":146,
    "gn:feature_class":"P",
    "gn:feature_code":"PPL",
    "gn:name":"Vekkula",
    "gn:population":0,
    "gn:timezone":"Europe/Helsinki",
    "iso:country":"FI",
    "name:fin_x_preferred":[
        "Vekkula"
    ],
    "wof:name":"Vekkula",
    "wof:placetype":"locality"
},
  "geometry": {"coordinates":[25.27754,62.0156],"type":"Point"}
}