{
  "type": "Feature",
  "properties": {
    "gn:admin1_code":"8.0",
    "gn:admin2_code":"82.0",
    "gn:admin3_code":"285.0",
    "gn:asciiname":"Juurikorpi",
    "gn:country_code":"FI",
    "gn:dem":19,
    "gn:feature_class":"P",
    "gn:feature_code":"PPL",
    "gn:name":"Juurikorpi",
    "gn:population":0,
    "gn:timezone":"Europe/Helsinki",
    "iso:country":"FI",
    "wof:name":"Juurikorpi",
    "wof:placetype":"locality"
},
  "geometry": {"coordinates":[26.93517,60.60589],"type":"Point"}
}