{
  "type": "Feature",
  "properties": {
    "gn:admin1_code":"19.0",
    "gn:admin2_code":"197.0",
    "gn:admin3_code":"758.0",
    "gn:asciiname":"Seipaejaervi",
    "gn:country_code":"FI",
    "gn:dem":259,
    "gn:feature_class":"P",
    "gn:feature_code":"PPL",
    "gn:name":"Seip\u00e4j\u00e4rvi",
    "gn:population":0,
    "gn:timezone":"Europe/Helsinki",
    "iso:country":"FI",
    "name:eng_x_preferred":[
        "Seip\u00e4j\u00e4rvi"
    ],
    "name:rus_x_preferred":[
        "\u0421\u0435\u0439\u043f\u044f\u044f\u0440\u0432\u0438"
    ],
    "name:und_x_variant":[
        "Seip\u00e4joki",
        "Seip\u00e4j\u00e4rvi"
    ],
    "wof:name":"Seipaejaervi",
    "wof:placetype":"locality"
},
  "geometry": {"coordinates":[26.23214,67.16475],"type":"Point"}
}