{
  "type": "Feature",
  "properties": {
    "gn:admin1_code":"18.0",
    "gn:admin2_code":"182.0",
    "gn:admin3_code":"578.0",
    "gn:asciiname":"Raappananmaeki",
    "gn:country_code":"FI",
    "gn:dem":249,
    "gn:feature_class":"P",
    "gn:feature_code":"PPL",
    "gn:name":"Raappananm\u00e4ki",
    "gn:population":0,
    "gn:timezone":"Europe/Helsinki",
    "iso:country":"FI",
    "name:eng_x_preferred":[
        "Raappananm\u00e4ki"
    ],
    "name:rus_x_preferred":[
        "\u0420\u0430\u043f\u043f\u0430\u043d\u0430\u043d\u043c\u044f\u043a\u0438"
    ],
    "name:und_x_variant":[
        "Raappanavaara",
        "Raappana"
    ],
    "wof:name":"Raappananmaeki",
    "wof:placetype":"locality"
},
  "geometry": {"coordinates":[27.58932,64.50624000000001],"type":"Point"}
}