{
  "type": "Feature",
  "properties": {
    "gn:admin1_code":"15.0",
    "gn:admin2_code":"152.0",
    "gn:admin3_code":"946.0",
    "gn:asciiname":"Uppibyn",
    "gn:country_code":"FI",
    "gn:dem":6,
    "gn:feature_class":"P",
    "gn:feature_code":"PPL",
    "gn:name":"Uppibyn",
    "gn:population":0,
    "gn:timezone":"Europe/Helsinki",
    "iso:country":"FI",
    "name:swe_x_preferred":[
        "Uppibyn"
    ],
    "wof:name":"Uppibyn",
    "wof:placetype":"locality"
},
  "geometry": {"coordinates":[22.25589,63.18079],"type":"Point"}
}