{
  "type": "Feature",
  "properties": {
    "gn:admin1_code":"13.0",
    "gn:admin2_code":"131.0",
    "gn:admin3_code":"179.0",
    "gn:asciiname":"Raidanlahti",
    "gn:country_code":"FI",
    "gn:dem":81,
    "gn:feature_class":"P",
    "gn:feature_code":"PPL",
    "gn:name":"Raidanlahti",
    "gn:population":0,
    "gn:timezone":"Europe/Helsinki",
    "iso:country":"FI",
    "wof:name":"Raidanlahti",
    "wof:placetype":"locality"
},
  "geometry": {"coordinates":[25.72725,61.98354000000001],"type":"Point"}
}