{
  "type": "Feature",
  "properties": {
    "gn:admin1_code":"9.0",
    "gn:admin2_code":"91.0",
    "gn:admin3_code":"441.0",
    "gn:asciiname":"Kurvila",
    "gn:country_code":"FI",
    "gn:dem":69,
    "gn:feature_class":"P",
    "gn:feature_code":"PPL",
    "gn:name":"Kurvila",
    "gn:population":0,
    "gn:timezone":"Europe/Helsinki",
    "iso:country":"FI",
    "wof:name":"Kurvila",
    "wof:placetype":"locality"
},
  "geometry": {"coordinates":[27.43225,60.87096],"type":"Point"}
}