{
  "type": "Feature",
  "properties": {
    "gn:admin1_code":"8.0",
    "gn:admin2_code":"82.0",
    "gn:admin3_code":"935.0",
    "gn:asciiname":"Pajulahti",
    "gn:country_code":"FI",
    "gn:dem":3,
    "gn:feature_class":"P",
    "gn:feature_code":"PPL",
    "gn:name":"Pajulahti",
    "gn:population":0,
    "gn:timezone":"Europe/Helsinki",
    "iso:country":"FI",
    "wof:name":"Pajulahti",
    "wof:placetype":"locality"
},
  "geometry": {"coordinates":[27.74795,60.59116],"type":"Point"}
}