{
  "type": "Feature",
  "properties": {
    "gn:admin1_code":"9.0",
    "gn:admin2_code":"91.0",
    "gn:admin3_code":"739.0",
    "gn:asciiname":"Kaskeinkylae",
    "gn:country_code":"FI",
    "gn:dem":93,
    "gn:feature_class":"P",
    "gn:feature_code":"PPL",
    "gn:name":"Kaskeinkyl\u00e4",
    "gn:population":0,
    "gn:timezone":"Europe/Helsinki",
    "iso:country":"FI",
    "wof:name":"Kaskeinkylae",
    "wof:placetype":"locality"
},
  "geometry": {"coordinates":[27.71667,61.16667],"type":"Point"}
}