{
  "type": "Feature",
  "properties": {
    "gn:admin1_code":"1.0",
    "gn:admin2_code":"11.0",
    "gn:admin3_code":"444.0",
    "gn:asciiname":"Hyoenoelae",
    "gn:country_code":"FI",
    "gn:dem":89,
    "gn:feature_class":"P",
    "gn:feature_code":"PPL",
    "gn:name":"Hy\u00f6n\u00f6l\u00e4",
    "gn:population":0,
    "gn:timezone":"Europe/Helsinki",
    "iso:country":"FI",
    "wof:name":"Hyoenoelae",
    "wof:placetype":"locality"
},
  "geometry": {"coordinates":[23.93602000000001,60.46376],"type":"Point"}
}