{
  "type": "Feature",
  "properties": {
    "gn:admin1_code":"13.0",
    "gn:admin2_code":"138.0",
    "gn:admin3_code":"226.0",
    "gn:asciiname":"Iso Moettoelae",
    "gn:country_code":"FI",
    "gn:dem":182,
    "gn:feature_class":"P",
    "gn:feature_code":"PPL",
    "gn:name":"Iso M\u00f6tt\u00f6l\u00e4",
    "gn:population":0,
    "gn:timezone":"Europe/Helsinki",
    "iso:country":"FI",
    "wof:name":"Iso Moettoelae",
    "wof:placetype":"locality"
},
  "geometry": {"coordinates":[24.71667,62.96666999999999],"type":"Point"}
}