{
  "type": "Feature",
  "properties": {
    "gn:admin1_code":"10.0",
    "gn:admin2_code":"105.0",
    "gn:admin3_code":"593.0",
    "gn:asciiname":"Laengelmaeki",
    "gn:country_code":"FI",
    "gn:dem":115,
    "gn:feature_class":"P",
    "gn:feature_code":"PPL",
    "gn:name":"L\u00e4ngelm\u00e4ki",
    "gn:population":0,
    "gn:timezone":"Europe/Helsinki",
    "iso:country":"FI",
    "wof:name":"Laengelmaeki",
    "wof:placetype":"locality"
},
  "geometry": {"coordinates":[27.38908,62.19279],"type":"Point"}
}