{
  "type": "Feature",
  "properties": {
    "gn:admin1_code":"2.0",
    "gn:admin2_code":"21.0",
    "gn:admin3_code":"445.0",
    "gn:asciiname":"Kuitia",
    "gn:country_code":"FI",
    "gn:dem":15,
    "gn:feature_class":"P",
    "gn:feature_code":"PPL",
    "gn:name":"Kuitia",
    "gn:population":0,
    "gn:timezone":"Europe/Helsinki",
    "iso:country":"FI",
    "name:fin_x_preferred":[
        "Kuitia"
    ],
    "name:swe_x_preferred":[
        "Ovidja"
    ],
    "wof:name":"Kuitia",
    "wof:placetype":"locality"
},
  "geometry": {"coordinates":[22.39639,60.29472],"type":"Point"}
}