{
  "type": "Feature",
  "properties": {
    "gn:admin1_code":"19.0",
    "gn:admin2_code":"194.0",
    "gn:admin3_code":"732.0",
    "gn:asciiname":"Hannula",
    "gn:country_code":"FI",
    "gn:dem":188,
    "gn:feature_class":"P",
    "gn:feature_code":"PPL",
    "gn:name":"Hannula",
    "gn:population":0,
    "gn:timezone":"Europe/Helsinki",
    "iso:country":"FI",
    "wof:name":"Hannula",
    "wof:placetype":"locality"
},
  "geometry": {"coordinates":[28.41667,66.81667],"type":"Point"}
}