{
  "type": "Feature",
  "properties": {
    "gn:admin1_code":"17.0",
    "gn:admin2_code":"176.0",
    "gn:admin3_code":"317.0",
    "gn:asciiname":"Hautajoki",
    "gn:country_code":"FI",
    "gn:dem":113,
    "gn:feature_class":"P",
    "gn:feature_code":"PPL",
    "gn:name":"Hautajoki",
    "gn:population":0,
    "gn:timezone":"Europe/Helsinki",
    "iso:country":"FI",
    "wof:name":"Hautajoki",
    "wof:placetype":"locality"
},
  "geometry": {"coordinates":[25.85722,63.90763000000001],"type":"Point"}
}