{
  "type": "Feature",
  "properties": {
    "gn:admin1_code":"8.0",
    "gn:admin2_code":"82.0",
    "gn:admin3_code":"285.0",
    "gn:asciiname":"Wredeby",
    "gn:cc2":"FI",
    "gn:country_code":"FI",
    "gn:dem":25,
    "gn:feature_class":"P",
    "gn:feature_code":"PPL",
    "gn:name":"Wredeby",
    "gn:population":0,
    "gn:timezone":"Europe/Helsinki",
    "iso:country":"FI",
    "name:und_x_variant":[
        "Vredeby",
        "Wredeby"
    ],
    "wof:name":"Wredeby",
    "wof:placetype":"locality"
},
  "geometry": {"coordinates":[26.75,60.66667],"type":"Point"}
}