{
  "type": "Feature",
  "properties": {
    "gn:admin1_code":"6.0",
    "gn:admin2_code":"64.0",
    "gn:admin3_code":"837.0",
    "gn:asciiname":"Kulkkila",
    "gn:country_code":"FI",
    "gn:dem":101,
    "gn:feature_class":"P",
    "gn:feature_code":"PPL",
    "gn:name":"Kulkkila",
    "gn:population":0,
    "gn:timezone":"Europe/Helsinki",
    "iso:country":"FI",
    "wof:name":"Kulkkila",
    "wof:placetype":"locality"
},
  "geometry": {"coordinates":[23.94367,61.65664],"type":"Point"}
}