{
  "type": "Feature",
  "properties": {
    "gn:admin1_code":"15.0",
    "gn:admin2_code":"152.0",
    "gn:admin3_code":"280.0",
    "gn:asciiname":"OEsterholmen",
    "gn:country_code":"FI",
    "gn:dem":19,
    "gn:feature_class":"P",
    "gn:feature_code":"PPL",
    "gn:name":"\u00d6sterholmen",
    "gn:population":0,
    "gn:timezone":"Europe/Helsinki",
    "iso:country":"FI",
    "wof:name":"OEsterholmen",
    "wof:placetype":"locality"
},
  "geometry": {"coordinates":[21.31628,62.87233000000001],"type":"Point"}
}