{
  "type": "Feature",
  "properties": {
    "gn:admin1_code":"15.0",
    "gn:admin2_code":"153.0",
    "gn:admin3_code":"545.0",
    "gn:asciiname":"AElgmossen",
    "gn:country_code":"FI",
    "gn:dem":49,
    "gn:feature_class":"P",
    "gn:feature_code":"PPL",
    "gn:name":"\u00c4lgmossen",
    "gn:population":0,
    "gn:timezone":"Europe/Helsinki",
    "iso:country":"FI",
    "name:und_x_variant":[
        "Elgmossa",
        "\u00c4lgmossa",
        "\u00c4lgmossen"
    ],
    "wof:name":"AElgmossen",
    "wof:placetype":"locality"
},
  "geometry": {"coordinates":[21.71479,62.68459],"type":"Point"}
}