{
  "type": "Feature",
  "properties": {
    "gn:admin1_code":"4.0",
    "gn:admin2_code":"43.0",
    "gn:admin3_code":"886.0",
    "gn:asciiname":"Vihelae",
    "gn:country_code":"FI",
    "gn:dem":13,
    "gn:feature_class":"P",
    "gn:feature_code":"PPL",
    "gn:name":"Vihel\u00e4",
    "gn:population":0,
    "gn:timezone":"Europe/Helsinki",
    "iso:country":"FI",
    "wof:name":"Vihelae",
    "wof:placetype":"locality"
},
  "geometry": {"coordinates":[21.89207,61.45949],"type":"Point"}
}