{
  "type": "Feature",
  "properties": {
    "gn:admin1_code":"9.0",
    "gn:admin2_code":"91.0",
    "gn:admin3_code":"416.0",
    "gn:asciiname":"Kotalahti",
    "gn:country_code":"FI",
    "gn:dem":63,
    "gn:feature_class":"P",
    "gn:feature_code":"PPL",
    "gn:name":"Kotalahti",
    "gn:population":0,
    "gn:timezone":"Europe/Helsinki",
    "iso:country":"FI",
    "wof:name":"Kotalahti",
    "wof:placetype":"locality"
},
  "geometry": {"coordinates":[27.65032,61.01584],"type":"Point"}
}