{
  "type": "Feature",
  "properties": {
    "gn:gn_country":"FI",
    "gn:gn_fcode":"PPL",
    "gn:gn_pop":0,
    "iso:country":"FI",
    "name:eng_x_preferred":[
        "Kollaja"
    ],
    "name:fin_x_preferred":[
        "Kollaja"
    ],
    "qs_pg:aaroncc":"FI",
    "qs_pg:gn_country":"FI",
    "qs_pg:gn_fcode":"PPL",
    "qs_pg:gn_pop":0,
    "qs_pg:name":"Kollaja",
    "qs_pg:name_adm0":"Suomi",
    "qs_pg:name_adm1":"Pohjois-pohjanmaan maakunta",
    "qs_pg:photos_9r":0,
    "qs_pg:photos_sr":0,
    "qs_pg:pop_sr":0,
    "qs_pg:qs_pg_placetype":"locality",
    "qs_pg:qs_pg_placetype_gp":"Town",
    "qs_pg:woe_adm0":23424812,
    "woe:adm0_id":23424812,
    "woe:name_adm0":"Suomi",
    "woe:name_adm1":"Pohjois-pohjanmaan maakunta",
    "woe:placetype":"Town",
    "wof:name":"Kollaja",
    "wof:placetype":"locality"
},
  "geometry": {"coordinates":[26.58333,65.33333],"type":"Point"}
}