{
  "type": "Feature",
  "properties": {
    "gn:admin1_code":"2.0",
    "gn:admin2_code":"23.0",
    "gn:admin3_code":"529.0",
    "gn:asciiname":"Poikko",
    "gn:cc2":"FI",
    "gn:country_code":"FI",
    "gn:dem":12,
    "gn:feature_class":"P",
    "gn:feature_code":"PPL",
    "gn:name":"Poikko",
    "gn:population":0,
    "gn:timezone":"Europe/Helsinki",
    "iso:country":"FI",
    "name:und_x_variant":[
        "Isopoikko",
        "Poikko"
    ],
    "wof:name":"Poikko",
    "wof:placetype":"locality"
},
  "geometry": {"coordinates":[21.89278,60.4138],"type":"Point"}
}