{
  "type": "Feature",
  "properties": {
    "gn:admin1_code":"18.0",
    "gn:admin2_code":"182.0",
    "gn:admin3_code":"578.0",
    "gn:asciiname":"Sutela",
    "gn:country_code":"FI",
    "gn:dem":207,
    "gn:feature_class":"P",
    "gn:feature_code":"PPL",
    "gn:name":"Sutela",
    "gn:population":0,
    "gn:timezone":"Europe/Helsinki",
    "iso:country":"FI",
    "wof:name":"Sutela",
    "wof:placetype":"locality"
},
  "geometry": {"coordinates":[27.68333,64.45],"type":"Point"}
}