{
  "type": "Feature",
  "properties": {
    "gn:admin1_code":"18.0",
    "gn:admin2_code":"181.0",
    "gn:admin3_code":"777.0",
    "gn:asciiname":"Karjoniemi",
    "gn:country_code":"FI",
    "gn:dem":206,
    "gn:feature_class":"P",
    "gn:feature_code":"PPL",
    "gn:name":"Karjoniemi",
    "gn:population":0,
    "gn:timezone":"Europe/Helsinki",
    "iso:country":"FI",
    "wof:name":"Karjoniemi",
    "wof:placetype":"locality"
},
  "geometry": {"coordinates":[29.36667000000001,65.09999999999999],"type":"Point"}
}