{
  "type": "Feature",
  "properties": {
    "gn:admin1_code":"1.0",
    "gn:admin2_code":"14.0",
    "gn:admin3_code":"149.0",
    "gn:asciiname":"Vaesterby",
    "gn:country_code":"FI",
    "gn:dem":31,
    "gn:feature_class":"P",
    "gn:feature_code":"PPL",
    "gn:name":"V\u00e4sterby",
    "gn:population":0,
    "gn:timezone":"Europe/Helsinki",
    "iso:country":"FI",
    "wof:name":"Vaesterby",
    "wof:placetype":"locality"
},
  "geometry": {"coordinates":[23.81667,60.01667],"type":"Point"}
}