{
  "type": "Feature",
  "properties": {
    "gn:admin1_code":"16.0",
    "gn:admin2_code":"161.0",
    "gn:admin3_code":"849.0",
    "gn:asciiname":"Jaemsae",
    "gn:country_code":"FI",
    "gn:dem":106,
    "gn:feature_class":"P",
    "gn:feature_code":"PPL",
    "gn:name":"J\u00e4ms\u00e4",
    "gn:population":0,
    "gn:timezone":"Europe/Helsinki",
    "iso:country":"FI",
    "wof:name":"Jaemsae",
    "wof:placetype":"locality"
},
  "geometry": {"coordinates":[24.18344,63.82313000000001],"type":"Point"}
}