{
  "type": "Feature",
  "properties": {
    "gn:admin1_code":"15.0",
    "gn:admin2_code":"152.0",
    "gn:admin3_code":"905.0",
    "gn:asciiname":"Ojaniemi",
    "gn:country_code":"FI",
    "gn:dem":6,
    "gn:feature_class":"P",
    "gn:feature_code":"PPL",
    "gn:name":"Ojaniemi",
    "gn:population":0,
    "gn:timezone":"Europe/Helsinki",
    "iso:country":"FI",
    "name:fin_x_preferred":[
        "Ojaniemi"
    ],
    "wof:name":"Ojaniemi",
    "wof:placetype":"locality"
},
  "geometry": {"coordinates":[22.11153,63.0669],"type":"Point"}
}