{
  "type": "Feature",
  "properties": {
    "gn:admin1_code":"15.0",
    "gn:admin2_code":"153.0",
    "gn:admin3_code":"287.0",
    "gn:asciiname":"Lintuvuori",
    "gn:country_code":"FI",
    "gn:dem":61,
    "gn:feature_class":"P",
    "gn:feature_code":"PPL",
    "gn:name":"Lintuvuori",
    "gn:population":0,
    "gn:timezone":"Europe/Helsinki",
    "iso:country":"FI",
    "wof:name":"Lintuvuori",
    "wof:placetype":"locality"
},
  "geometry": {"coordinates":[21.67126,62.28673000000001],"type":"Point"}
}