{
  "type": "Feature",
  "properties": {
    "gn:admin1_code":"10.0",
    "gn:admin2_code":"101.0",
    "gn:admin3_code":"588.0",
    "gn:asciiname":"Nipuli",
    "gn:country_code":"FI",
    "gn:dem":140,
    "gn:feature_class":"P",
    "gn:feature_code":"PPL",
    "gn:name":"Nipuli",
    "gn:population":0,
    "gn:timezone":"Europe/Helsinki",
    "iso:country":"FI",
    "wof:name":"Nipuli",
    "wof:placetype":"locality"
},
  "geometry": {"coordinates":[26.37601,61.46229],"type":"Point"}
}