{
  "type": "Feature",
  "properties": {
    "gn:admin1_code":"18.0",
    "gn:admin2_code":"182.0",
    "gn:admin3_code":"697.0",
    "gn:asciiname":"Lumivaara",
    "gn:country_code":"FI",
    "gn:dem":199,
    "gn:feature_class":"P",
    "gn:feature_code":"PPL",
    "gn:name":"Lumivaara",
    "gn:population":0,
    "gn:timezone":"Europe/Helsinki",
    "iso:country":"FI",
    "wof:name":"Lumivaara",
    "wof:placetype":"locality"
},
  "geometry": {"coordinates":[28.23333,64.59999999999999],"type":"Point"}
}