{
  "type": "Feature",
  "properties": {
    "gn:admin1_code":"18.0",
    "gn:admin2_code":"182.0",
    "gn:admin3_code":"697.0",
    "gn:asciiname":"Honkivaara",
    "gn:country_code":"FI",
    "gn:dem":226,
    "gn:feature_class":"P",
    "gn:feature_code":"PPL",
    "gn:name":"Honkivaara",
    "gn:population":0,
    "gn:timezone":"Europe/Helsinki",
    "iso:country":"FI",
    "wof:name":"Honkivaara",
    "wof:placetype":"locality"
},
  "geometry": {"coordinates":[28.41667,64.48333000000001],"type":"Point"}
}