{
  "type": "Feature",
  "properties": {
    "gn:admin1_code":"18.0",
    "gn:admin2_code":"182.0",
    "gn:admin3_code":"785.0",
    "gn:asciiname":"Lassila",
    "gn:country_code":"FI",
    "gn:dem":123,
    "gn:feature_class":"P",
    "gn:feature_code":"PPL",
    "gn:name":"Lassila",
    "gn:population":0,
    "gn:timezone":"Europe/Helsinki",
    "iso:country":"FI",
    "name:fin_x_preferred":[
        "Lassila"
    ],
    "name:fra_x_preferred":[
        "Lassila"
    ],
    "name:rus_x_preferred":[
        "\u041b\u0430\u0441\u0441\u0438\u043b\u0430"
    ],
    "name:swe_x_preferred":[
        "Lassas"
    ],
    "wof:name":"Lassila",
    "wof:placetype":"locality"
},
  "geometry": {"coordinates":[27.13333,64.51666999999999],"type":"Point"}
}