{
  "type": "Feature",
  "properties": {
    "gn:admin1_code":"2.0",
    "gn:admin2_code":"24.0",
    "gn:admin3_code":"400.0",
    "gn:asciiname":"Pihamaeentausta",
    "gn:country_code":"FI",
    "gn:dem":37,
    "gn:feature_class":"P",
    "gn:feature_code":"PPL",
    "gn:name":"Piham\u00e4entausta",
    "gn:population":0,
    "gn:timezone":"Europe/Helsinki",
    "iso:country":"FI",
    "wof:name":"Pihamaeentausta",
    "wof:placetype":"locality"
},
  "geometry": {"coordinates":[21.66694,60.9763],"type":"Point"}
}