{
  "type": "Feature",
  "properties": {
    "gn:admin1_code":"4.0",
    "gn:admin2_code":"41.0",
    "gn:admin3_code":"783.0",
    "gn:asciiname":"Karhia",
    "gn:cc2":"FI",
    "gn:country_code":"FI",
    "gn:dem":67,
    "gn:feature_class":"P",
    "gn:feature_code":"PPL",
    "gn:name":"Karhia",
    "gn:population":0,
    "gn:timezone":"Europe/Helsinki",
    "iso:country":"FI",
    "name:und_x_variant":[
        "Karhi",
        "Karhia"
    ],
    "wof:name":"Karhia",
    "wof:placetype":"locality"
},
  "geometry": {"coordinates":[22.39606,61.10069],"type":"Point"}
}