{
  "type": "Feature",
  "properties": {
    "gn:admin1_code":"11.0",
    "gn:admin2_code":"115.0",
    "gn:admin3_code":"844.0",
    "gn:asciiname":"Haapamaeki",
    "gn:country_code":"FI",
    "gn:dem":152,
    "gn:feature_class":"P",
    "gn:feature_code":"PPL",
    "gn:name":"Haapam\u00e4ki",
    "gn:population":0,
    "gn:timezone":"Europe/Helsinki",
    "iso:country":"FI",
    "name:eng_x_preferred":[
        "Haapam\u00e4ki"
    ],
    "name:rus_x_preferred":[
        "\u0425\u0430\u043f\u0430\u043c\u044f\u043a\u0438"
    ],
    "name:und_x_variant":[
        "Haapam\u00e4ki"
    ],
    "wof:name":"Haapamaeki",
    "wof:placetype":"locality"
},
  "geometry": {"coordinates":[26.73081,62.86284000000001],"type":"Point"}
}