{
  "type": "Feature",
  "properties": {
    "gn:admin1_code":"19.0",
    "gn:admin2_code":"191.0",
    "gn:admin3_code":"683.0",
    "gn:asciiname":"Saeaeskilahti",
    "gn:country_code":"FI",
    "gn:dem":200,
    "gn:feature_class":"P",
    "gn:feature_code":"PPL",
    "gn:name":"S\u00e4\u00e4skilahti",
    "gn:population":0,
    "gn:timezone":"Europe/Helsinki",
    "iso:country":"FI",
    "name:eng_x_preferred":[
        "S\u00e4\u00e4skilahti"
    ],
    "name:rus_x_preferred":[
        "\u0421\u044f\u0441\u043a\u0438\u043b\u0430\u0445\u0442\u0438"
    ],
    "name:und_x_variant":[
        "S\u00e4\u00e4skilahti"
    ],
    "wof:name":"Saeaeskilahti",
    "wof:placetype":"locality"
},
  "geometry": {"coordinates":[27.15,66.06667],"type":"Point"}
}