{
  "type": "Feature",
  "properties": {
    "gn:admin1_code":"10.0",
    "gn:admin2_code":"103.0",
    "gn:admin3_code":"740.0",
    "gn:asciiname":"Kulennoinen",
    "gn:cc2":"FI",
    "gn:country_code":"FI",
    "gn:dem":87,
    "gn:feature_class":"P",
    "gn:feature_code":"PPL",
    "gn:name":"Kulennoinen",
    "gn:population":0,
    "gn:timezone":"Europe/Helsinki",
    "iso:country":"FI",
    "name:eng_x_preferred":[
        "Kulennoinen"
    ],
    "name:rus_x_preferred":[
        "\u041a\u0443\u043b\u0435\u043d\u043d\u043e\u0439\u043d\u0435\u043d"
    ],
    "name:und_x_variant":[
        "Kulenhoinen"
    ],
    "wof:name":"Kulennoinen",
    "wof:placetype":"locality"
},
  "geometry": {"coordinates":[29.20513,61.84028000000001],"type":"Point"}
}