{
  "type": "Feature",
  "properties": {
    "gn:admin1_code":"14.0",
    "gn:admin2_code":"146.0",
    "gn:admin3_code":"5.0",
    "gn:asciiname":"AElajaervi",
    "gn:country_code":"FI",
    "gn:dem":107,
    "gn:elevation":"69.0",
    "gn:feature_class":"P",
    "gn:feature_code":"PPLL",
    "gn:name":"\u00c4laj\u00e4rvi",
    "gn:population":10308,
    "gn:timezone":"Europe/Helsinki",
    "iso:country":"FI",
    "wof:name":"AElajaervi",
    "wof:placetype":"locality",
    "wof:population":10308
},
  "geometry": {"coordinates":[23.81586,63.00026999999999],"type":"Point"}
}