{
  "type": "Feature",
  "properties": {
    "gn:country":"FI",
    "gn:fcode":"PPL",
    "gn:population":0,
    "iso:country":"FI",
    "name:und_x_variant":[
        "Mon\u00e4siin"
    ],
    "qs_pg:aaroncc":"FI",
    "qs_pg:gn_country":"FI",
    "qs_pg:gn_fcode":"PPL",
    "qs_pg:gn_pop":0,
    "qs_pg:name":"Mon\u00e4s",
    "qs_pg:name_adm0":"Suomi",
    "qs_pg:name_adm1":"Pohjanmaan maakunta",
    "qs_pg:photos_9r":0,
    "qs_pg:photos_sr":0,
    "qs_pg:pop_sr":0,
    "qs_pg:qs_pg_placetype":"locality",
    "qs_pg:qs_pg_placetype_gp":"Town",
    "qs_pg:woe_adm0":23424812,
    "woe:adm0_id":23424812,
    "woe:name_adm0":"Suomi",
    "woe:name_adm1":"Pohjanmaan maakunta",
    "woe:placetype":"Town",
    "wof:name":"Mon\u00e4s",
    "wof:placetype":"locality"
},
  "geometry": {"coordinates":[22.33333,63.46667],"type":"Point"}
}