{
  "type": "Feature",
  "properties": {
    "gn:admin1_code":"15.0",
    "gn:admin2_code":"152.0",
    "gn:admin3_code":"905.0",
    "gn:asciiname":"Soedersund",
    "gn:country_code":"FI",
    "gn:dem":18,
    "gn:feature_class":"P",
    "gn:feature_code":"PPL",
    "gn:name":"S\u00f6dersund",
    "gn:population":0,
    "gn:timezone":"Europe/Helsinki",
    "iso:country":"FI",
    "name:swe_x_preferred":[
        "S\u00f6dersund"
    ],
    "wof:name":"Soedersund",
    "wof:placetype":"locality"
},
  "geometry": {"coordinates":[21.55591,63.02848],"type":"Point"}
}