{
  "type": "Feature",
  "properties": {
    "gn:admin1_code":"13.0",
    "gn:admin2_code":"134.0",
    "gn:admin3_code":"182.0",
    "gn:asciiname":"Palsina",
    "gn:country_code":"FI",
    "gn:dem":117,
    "gn:feature_class":"P",
    "gn:feature_code":"PPL",
    "gn:name":"Palsina",
    "gn:population":0,
    "gn:timezone":"Europe/Helsinki",
    "iso:country":"FI",
    "wof:name":"Palsina",
    "wof:placetype":"locality"
},
  "geometry": {"coordinates":[24.88669,61.94668000000001],"type":"Point"}
}