{
  "type": "Feature",
  "properties": {
    "gn:admin1_code":"4.0",
    "gn:admin2_code":"43.0",
    "gn:admin3_code":"609.0",
    "gn:asciiname":"Hanhiluoto",
    "gn:country_code":"FI",
    "gn:dem":5,
    "gn:feature_class":"P",
    "gn:feature_code":"PPL",
    "gn:name":"Hanhiluoto",
    "gn:population":0,
    "gn:timezone":"Europe/Helsinki",
    "iso:country":"FI",
    "name:dan_x_preferred":[
        "G\u00e5sholmen"
    ],
    "name:isl_x_preferred":[
        "G\u00e5sholmen"
    ],
    "name:nno_x_preferred":[
        "G\u00e5sholmen"
    ],
    "name:nob_x_preferred":[
        "G\u00e5sholmen"
    ],
    "name:nor_x_preferred":[
        "G\u00e5sholmen"
    ],
    "name:swe_x_preferred":[
        "G\u00e5sholmen"
    ],
    "wof:name":"Hanhiluoto",
    "wof:placetype":"locality"
},
  "geometry": {"coordinates":[21.76203,61.50272],"type":"Point"}
}