{
  "type": "Feature",
  "properties": {
    "gn:admin1_code":"9.0",
    "gn:admin2_code":"91.0",
    "gn:admin3_code":"405.0",
    "gn:asciiname":"Kanalampi",
    "gn:country_code":"FI",
    "gn:dem":67,
    "gn:feature_class":"P",
    "gn:feature_code":"PPL",
    "gn:name":"Kanalampi",
    "gn:population":0,
    "gn:timezone":"Europe/Helsinki",
    "iso:country":"FI",
    "wof:name":"Kanalampi",
    "wof:placetype":"locality"
},
  "geometry": {"coordinates":[28.07246,60.93863],"type":"Point"}
}