{
  "type": "Feature",
  "properties": {
    "gn:admin1_code":"16.0",
    "gn:admin2_code":"161.0",
    "gn:admin3_code":"236.0",
    "gn:asciiname":"Gasjarvi",
    "gn:cc2":"FI",
    "gn:country_code":"FI",
    "gn:dem":34,
    "gn:feature_class":"P",
    "gn:feature_code":"PPL",
    "gn:name":"G\u00e5sjarvi",
    "gn:population":0,
    "gn:timezone":"Europe/Helsinki",
    "iso:country":"FI",
    "name:und_x_variant":[
        "G\u00e5sj\u00e4rv",
        "G\u00e5sjarvi"
    ],
    "wof:name":"Gasjarvi",
    "wof:placetype":"locality"
},
  "geometry": {"coordinates":[23.48333,63.65],"type":"Point"}
}