{
  "type": "Feature",
  "properties": {
    "gn:admin1_code":"14.0",
    "gn:admin2_code":"142.0",
    "gn:admin3_code":"145.0",
    "gn:asciiname":"Koskenloukko",
    "gn:country_code":"FI",
    "gn:dem":120,
    "gn:feature_class":"P",
    "gn:feature_code":"PPL",
    "gn:name":"Koskenloukko",
    "gn:population":0,
    "gn:timezone":"Europe/Helsinki",
    "iso:country":"FI",
    "name:fin_x_preferred":[
        "Koskenloukko"
    ],
    "wof:name":"Koskenloukko",
    "wof:placetype":"locality"
},
  "geometry": {"coordinates":[22.29322,62.74175],"type":"Point"}
}