{
  "type": "Feature",
  "properties": {
    "gn:admin1_code":"12.0",
    "gn:admin2_code":"122.0",
    "gn:admin3_code":"146.0",
    "gn:asciiname":"Korentovaara",
    "gn:country_code":"FI",
    "gn:dem":209,
    "gn:feature_class":"P",
    "gn:feature_code":"PPL",
    "gn:name":"Korentovaara",
    "gn:population":0,
    "gn:timezone":"Europe/Helsinki",
    "iso:country":"FI",
    "name:eng_x_preferred":[
        "Korentovaara"
    ],
    "name:rus_x_preferred":[
        "\u041a\u0430\u0440\u0435\u043d\u0442\u043e\u0432\u0430\u0440\u0430"
    ],
    "wof:name":"Korentovaara",
    "wof:placetype":"locality"
},
  "geometry": {"coordinates":[31.23116,62.8412],"type":"Point"}
}