{
  "type": "Feature",
  "properties": {
    "gn:admin1_code":"2.0",
    "gn:admin2_code":"23.0",
    "gn:admin3_code":"738.0",
    "gn:asciiname":"Froibele",
    "gn:country_code":"FI",
    "gn:dem":20,
    "gn:feature_class":"P",
    "gn:feature_code":"PPL",
    "gn:name":"Froibele",
    "gn:population":0,
    "gn:timezone":"Europe/Helsinki",
    "iso:country":"FI",
    "name:swe_x_preferred":[
        "Fr\u00f6jdb\u00f6le"
    ],
    "wof:name":"Froibele",
    "wof:placetype":"locality"
},
  "geometry": {"coordinates":[22.55,60.31667],"type":"Point"}
}