{
  "type": "Feature",
  "properties": {
    "gn:admin1_code":"5.0",
    "gn:admin2_code":"53.0",
    "gn:admin3_code":"981.0",
    "gn:asciiname":"Manninen",
    "gn:country_code":"FI",
    "gn:dem":94,
    "gn:feature_class":"P",
    "gn:feature_code":"PPL",
    "gn:name":"Manninen",
    "gn:population":0,
    "gn:timezone":"Europe/Helsinki",
    "iso:country":"FI",
    "name:lav_x_preferred":[
        "Manninens"
    ],
    "name:rus_x_preferred":[
        "\u041c\u0430\u043d\u043d\u0438\u043d\u0435\u043d"
    ],
    "wof:name":"Manninen",
    "wof:placetype":"locality"
},
  "geometry": {"coordinates":[23.21663,60.79914],"type":"Point"}
}