{
  "type": "Feature",
  "properties": {
    "gn:admin1_code":"11.0",
    "gn:admin2_code":"111.0",
    "gn:admin3_code":"762.0",
    "gn:asciiname":"Rutakko",
    "gn:country_code":"FI",
    "gn:dem":88,
    "gn:feature_class":"P",
    "gn:feature_code":"PPL",
    "gn:name":"Rutakko",
    "gn:population":0,
    "gn:timezone":"Europe/Helsinki",
    "iso:country":"FI",
    "wof:name":"Rutakko",
    "wof:placetype":"locality"
},
  "geometry": {"coordinates":[27.55,63.65],"type":"Point"}
}