{
  "type": "Feature",
  "properties": {
    "gn:admin1_code":"2.0",
    "gn:admin2_code":"21.0",
    "gn:admin3_code":"445.0",
    "gn:asciiname":"Traesk",
    "gn:country_code":"FI",
    "gn:dem":17,
    "gn:feature_class":"P",
    "gn:feature_code":"PPL",
    "gn:name":"Tr\u00e4sk",
    "gn:population":0,
    "gn:timezone":"Europe/Helsinki",
    "iso:country":"FI",
    "name:und_x_variant":[
        "Tr\u00e4skholm",
        "Tr\u00e4skby",
        "Tr\u00e4sk"
    ],
    "wof:name":"Traesk",
    "wof:placetype":"locality"
},
  "geometry": {"coordinates":[21.34842,60.21331],"type":"Point"}
}