{
  "type": "Feature",
  "properties": {
    "gn:admin1_code":"10.0",
    "gn:admin2_code":"105.0",
    "gn:admin3_code":"593.0",
    "gn:asciiname":"Kylmaemaeki",
    "gn:country_code":"FI",
    "gn:dem":170,
    "gn:feature_class":"P",
    "gn:feature_code":"PPL",
    "gn:name":"Kylm\u00e4m\u00e4ki",
    "gn:population":0,
    "gn:timezone":"Europe/Helsinki",
    "iso:country":"FI",
    "wof:name":"Kylmaemaeki",
    "wof:placetype":"locality"
},
  "geometry": {"coordinates":[26.77532,62.2122],"type":"Point"}
}