{
  "type": "Feature",
  "properties": {
    "gn:admin1_code":"19.0",
    "gn:admin2_code":"194.0",
    "gn:admin3_code":"320.0",
    "gn:asciiname":"Peraevaara",
    "gn:country_code":"FI",
    "gn:dem":187,
    "gn:feature_class":"P",
    "gn:feature_code":"PPL",
    "gn:name":"Per\u00e4vaara",
    "gn:population":0,
    "gn:timezone":"Europe/Helsinki",
    "iso:country":"FI",
    "wof:name":"Peraevaara",
    "wof:placetype":"locality"
},
  "geometry": {"coordinates":[27.46849000000001,66.7508],"type":"Point"}
}