{
  "type": "Feature",
  "properties": {
    "gn:admin1_code":"9.0",
    "gn:admin2_code":"93.0",
    "gn:admin3_code":"700.0",
    "gn:asciiname":"Kuokkalampi",
    "gn:country_code":"FI",
    "gn:dem":74,
    "gn:feature_class":"P",
    "gn:feature_code":"PPL",
    "gn:name":"Kuokkalampi",
    "gn:population":0,
    "gn:timezone":"Europe/Helsinki",
    "iso:country":"FI",
    "wof:name":"Kuokkalampi",
    "wof:placetype":"locality"
},
  "geometry": {"coordinates":[29.00648,61.2536],"type":"Point"}
}