{
  "type": "Feature",
  "properties": {
    "gn:admin1_code":"6.0",
    "gn:admin2_code":"63.0",
    "gn:admin3_code":"20.0",
    "gn:asciiname":"Kurisjaervi",
    "gn:country_code":"FI",
    "gn:dem":92,
    "gn:feature_class":"P",
    "gn:feature_code":"PPL",
    "gn:name":"Kurisj\u00e4rvi",
    "gn:population":0,
    "gn:timezone":"Europe/Helsinki",
    "iso:country":"FI",
    "wof:name":"Kurisjaervi",
    "wof:placetype":"locality"
},
  "geometry": {"coordinates":[23.8345,61.13445],"type":"Point"}
}