{
  "type": "Feature",
  "properties": {
    "gn:admin1_code":"9.0",
    "gn:admin2_code":"91.0",
    "gn:admin3_code":"405.0",
    "gn:asciiname":"Uusi-Timperi",
    "gn:cc2":"FI",
    "gn:country_code":"FI",
    "gn:dem":39,
    "gn:feature_class":"P",
    "gn:feature_code":"PPL",
    "gn:name":"Uusi-Timperi",
    "gn:population":0,
    "gn:timezone":"Europe/Helsinki",
    "iso:country":"FI",
    "name:und_x_variant":[
        "Timperil\u00e4",
        "Uusi-Timperi"
    ],
    "wof:name":"Uusi-Timperi",
    "wof:placetype":"locality"
},
  "geometry": {"coordinates":[28.20485,60.79127],"type":"Point"}
}