{
  "type": "Feature",
  "properties": {
    "gn:admin1_code":"17.0",
    "gn:admin2_code":"173.0",
    "gn:admin3_code":"139.0",
    "gn:asciiname":"Oijaervi",
    "gn:country_code":"FI",
    "gn:dem":106,
    "gn:feature_class":"P",
    "gn:feature_code":"PPL",
    "gn:name":"Oij\u00e4rvi",
    "gn:population":0,
    "gn:timezone":"Europe/Helsinki",
    "iso:country":"FI",
    "name:eng_x_preferred":[
        "Oij\u00e4rvi"
    ],
    "name:rus_x_preferred":[
        "\u041e\u0439\u044f\u0440\u0432\u0438"
    ],
    "name:und_x_variant":[
        "Oij\u00e4rvi"
    ],
    "wof:name":"Oijaervi",
    "wof:placetype":"locality"
},
  "geometry": {"coordinates":[25.97913,65.63479],"type":"Point"}
}