{
  "type": "Feature",
  "properties": {
    "gn:admin1_code":"16.0",
    "gn:admin2_code":"161.0",
    "gn:admin3_code":"849.0",
    "gn:asciiname":"Lehtimaeki",
    "gn:country_code":"FI",
    "gn:dem":110,
    "gn:feature_class":"P",
    "gn:feature_code":"PPL",
    "gn:name":"Lehtim\u00e4ki",
    "gn:population":0,
    "gn:timezone":"Europe/Helsinki",
    "iso:country":"FI",
    "wof:name":"Lehtimaeki",
    "wof:placetype":"locality"
},
  "geometry": {"coordinates":[24.38333,63.65],"type":"Point"}
}