{
  "type": "Feature",
  "properties": {
    "gn:admin1_code":"6.0",
    "gn:admin2_code":"68.0",
    "gn:admin3_code":"619.0",
    "gn:asciiname":"Haviokoski",
    "gn:country_code":"FI",
    "gn:dem":82,
    "gn:feature_class":"P",
    "gn:feature_code":"PPL",
    "gn:name":"Haviokoski",
    "gn:population":0,
    "gn:timezone":"Europe/Helsinki",
    "iso:country":"FI",
    "wof:name":"Haviokoski",
    "wof:placetype":"locality"
},
  "geometry": {"coordinates":[23.04701,61.12189],"type":"Point"}
}