{
  "type": "Feature",
  "properties": {
    "gn:admin1_code":"14.0",
    "gn:admin2_code":"141.0",
    "gn:admin3_code":"151.0",
    "gn:asciiname":"Heikkilae",
    "gn:country_code":"FI",
    "gn:dem":105,
    "gn:feature_class":"P",
    "gn:feature_code":"PPL",
    "gn:name":"Heikkil\u00e4",
    "gn:population":0,
    "gn:timezone":"Europe/Helsinki",
    "iso:country":"FI",
    "name:und_x_variant":[
        "Heikkil\u00e4njoki",
        "Heikkil\u00e4"
    ],
    "wof:name":"Heikkilae",
    "wof:placetype":"locality"
},
  "geometry": {"coordinates":[21.96415,62.19224000000001],"type":"Point"}
}