{
  "type": "Feature",
  "properties": {
    "gn:admin1_code":"1.0",
    "gn:admin2_code":"11.0",
    "gn:admin3_code":"543.0",
    "gn:asciiname":"Pukkila",
    "gn:country_code":"FI",
    "gn:dem":80,
    "gn:feature_class":"P",
    "gn:feature_code":"PPLF",
    "gn:name":"Pukkila",
    "gn:population":0,
    "gn:timezone":"Europe/Helsinki",
    "iso:country":"FI",
    "wof:name":"Pukkila",
    "wof:placetype":"locality"
},
  "geometry": {"coordinates":[24.81556,60.45472],"type":"Point"}
}