{
  "type": "Feature",
  "properties": {
    "gn:admin1_code":"1.0",
    "gn:admin2_code":"11.0",
    "gn:admin3_code":"543.0",
    "gn:asciiname":"Pukkila",
    "gn:country_code":"FI",
    "gn:dem":80,
    "gn:feature_class":"P",
    "gn:feature_code":"PPLF",
    "gn:name":"Pukkila",
    "gn:population":0,
    "gn:timezone":"Europe/Helsinki",
    "iso:country":"FI",
    "name:ara_x_preferred":[
        "\u0628\u0648\u0643\u064a\u0644\u0627"
    ],
    "name:ceb_x_preferred":[
        "Pukkila"
    ],
    "name:deu_x_preferred":[
        "Pukkila"
    ],
    "name:est_x_preferred":[
        "Pukkila vald"
    ],
    "name:eus_x_preferred":[
        "Pukkila"
    ],
    "name:fin_x_preferred":[
        "Pukkila"
    ],
    "name:fra_x_preferred":[
        "Pukkila"
    ],
    "name:glg_x_preferred":[
        "Pukkila"
    ],
    "name:ita_x_preferred":[
        "Pukkila"
    ],
    "name:nld_x_preferred":[
        "Pukkila"
    ],
    "name:nor_x_preferred":[
        "Pukkila"
    ],
    "name:pol_x_preferred":[
        "Gmina Pukkila"
    ],
    "name:ron_x_preferred":[
        "Pukkila"
    ],
    "name:rus_x_preferred":[
        "\u041f\u0443\u043a\u043a\u0438\u043b\u0430"
    ],
    "name:sco_x_preferred":[
        "Pukkila"
    ],
    "name:sme_x_preferred":[
        "Pukkila"
    ],
    "name:sqi_x_preferred":[
        "Pukkila"
    ],
    "name:swe_x_preferred":[
        "Pukkila"
    ],
    "name:tur_x_preferred":[
        "Pukkila"
    ],
    "name:vie_x_preferred":[
        "Pukkila"
    ],
    "name:zho_x_preferred":[
        "\u666e\u57fa\u62c9"
    ],
    "wof:name":"Pukkila",
    "wof:placetype":"locality"
},
  "geometry": {"coordinates":[24.81556,60.45472],"type":"Point"}
}