{
  "type": "Feature",
  "properties": {
    "gn:admin1_code":"10.0",
    "gn:admin2_code":"101.0",
    "gn:admin3_code":"491.0",
    "gn:asciiname":"Haekkilae",
    "gn:country_code":"FI",
    "gn:dem":123,
    "gn:feature_class":"P",
    "gn:feature_code":"PPL",
    "gn:name":"H\u00e4kkil\u00e4",
    "gn:population":0,
    "gn:timezone":"Europe/Helsinki",
    "iso:country":"FI",
    "wof:name":"Haekkilae",
    "wof:placetype":"locality"
},
  "geometry": {"coordinates":[27.04145,62.0456],"type":"Point"}
}