{
  "type": "Feature",
  "properties": {
    "gn:admin1_code":"18.0",
    "gn:admin2_code":"182.0",
    "gn:admin3_code":"765.0",
    "gn:asciiname":"Mustola",
    "gn:country_code":"FI",
    "gn:dem":163,
    "gn:feature_class":"P",
    "gn:feature_code":"PPL",
    "gn:name":"Mustola",
    "gn:population":0,
    "gn:timezone":"Europe/Helsinki",
    "iso:country":"FI",
    "wof:name":"Mustola",
    "wof:placetype":"locality"
},
  "geometry": {"coordinates":[28.61667000000001,64.15000000000001],"type":"Point"}
}