{
  "type": "Feature",
  "properties": {
    "gn:admin1_code":"5.0",
    "gn:admin2_code":"51.0",
    "gn:admin3_code":"82.0",
    "gn:asciiname":"Monaala",
    "gn:country_code":"FI",
    "gn:dem":92,
    "gn:feature_class":"P",
    "gn:feature_code":"PPLF",
    "gn:name":"Monaala",
    "gn:population":0,
    "gn:timezone":"Europe/Helsinki",
    "iso:country":"FI",
    "wof:name":"Monaala",
    "wof:placetype":"locality"
},
  "geometry": {"coordinates":[24.26846,61.2125],"type":"Point"}
}