{
  "type": "Feature",
  "properties": {
    "gn:admin1_code":"9.0",
    "gn:admin2_code":"91.0",
    "gn:admin3_code":"739.0",
    "gn:asciiname":"Huttusenniemi",
    "gn:cc2":"FI",
    "gn:country_code":"FI",
    "gn:dem":90,
    "gn:feature_class":"P",
    "gn:feature_code":"PPL",
    "gn:name":"Huttusenniemi",
    "gn:population":0,
    "gn:timezone":"Europe/Helsinki",
    "iso:country":"FI",
    "name:und_x_variant":[
        "Huttunen",
        "Huttusenniemi"
    ],
    "wof:name":"Huttusenniemi",
    "wof:placetype":"locality"
},
  "geometry": {"coordinates":[27.60391,61.26718],"type":"Point"}
}