{
  "type": "Feature",
  "properties": {
    "gn:admin1_code":"19.0",
    "gn:admin2_code":"191.0",
    "gn:admin3_code":"698.0",
    "gn:asciiname":"Patokoski",
    "gn:cc2":"FI",
    "gn:country_code":"FI",
    "gn:dem":107,
    "gn:feature_class":"P",
    "gn:feature_code":"PPL",
    "gn:name":"Patokoski",
    "gn:population":0,
    "gn:timezone":"Europe/Helsinki",
    "iso:country":"FI",
    "name:eng_x_preferred":[
        "Patokoski"
    ],
    "name:rus_x_preferred":[
        "\u041f\u0430\u0442\u043e\u043a\u043e\u0441\u043a\u0438"
    ],
    "name:und_x_variant":[
        "Patoski",
        "Patokoski"
    ],
    "wof:name":"Patokoski",
    "wof:placetype":"locality"
},
  "geometry": {"coordinates":[25.45237,66.86787],"type":"Point"}
}