{
  "type": "Feature",
  "properties": {
    "gn:admin1_code":"1.0",
    "gn:admin2_code":"11.0",
    "gn:admin3_code":"543.0",
    "gn:asciiname":"Kuusimaeki",
    "gn:country_code":"FI",
    "gn:dem":80,
    "gn:feature_class":"P",
    "gn:feature_code":"PPL",
    "gn:name":"Kuusim\u00e4ki",
    "gn:population":0,
    "gn:timezone":"Europe/Helsinki",
    "iso:country":"FI",
    "name:fin_x_preferred":[
        "Kuusim\u00e4ki"
    ],
    "wof:name":"Kuusimaeki",
    "wof:placetype":"locality"
},
  "geometry": {"coordinates":[24.84056,60.45862],"type":"Point"}
}