{
  "type": "Feature",
  "properties": {
    "gn:admin1_code":"17.0",
    "gn:admin2_code":"174.0",
    "gn:admin3_code":"678.0",
    "gn:asciiname":"Tuohinnonperae",
    "gn:country_code":"FI",
    "gn:dem":53,
    "gn:feature_class":"P",
    "gn:feature_code":"PPL",
    "gn:name":"Tuohinnonper\u00e4",
    "gn:population":0,
    "gn:timezone":"Europe/Helsinki",
    "iso:country":"FI",
    "name:und_x_variant":[
        "Tuohinto",
        "Tuohinnonper\u00e4"
    ],
    "wof:name":"Tuohinnonperae",
    "wof:placetype":"locality"
},
  "geometry": {"coordinates":[24.70429,64.64426999999999],"type":"Point"}
}