{
  "type": "Feature",
  "properties": {
    "gn:admin1_code":"19.0",
    "gn:admin2_code":"192.0",
    "gn:admin3_code":"851.0",
    "gn:asciiname":"Karunki",
    "gn:country_code":"FI",
    "gn:dem":39,
    "gn:feature_class":"P",
    "gn:feature_code":"PPL",
    "gn:name":"Karunki",
    "gn:population":0,
    "gn:timezone":"Europe/Helsinki",
    "iso:country":"FI",
    "name:deu_x_preferred":[
        "Karunki"
    ],
    "name:eng_x_preferred":[
        "Karunki"
    ],
    "name:fin_x_preferred":[
        "Karunki"
    ],
    "name:glg_x_preferred":[
        "Karunki"
    ],
    "name:nor_x_preferred":[
        "Karunki"
    ],
    "name:rus_x_preferred":[
        "\u041a\u0430\u0440\u0443\u043d\u043a\u0438"
    ],
    "name:swe_x_preferred":[
        "Karungi"
    ],
    "name:swe_x_variant":[
        "Karunki"
    ],
    "wof:name":"Karunki",
    "wof:placetype":"locality"
},
  "geometry": {"coordinates":[24.03785,66.02419],"type":"Point"}
}