{
  "type": "Feature",
  "properties": {
    "gn:admin1_code":"2.0",
    "gn:admin2_code":"22.0",
    "gn:admin3_code":"734.0",
    "gn:asciiname":"Peltola",
    "gn:country_code":"FI",
    "gn:dem":80,
    "gn:feature_class":"P",
    "gn:feature_code":"PPL",
    "gn:name":"Peltola",
    "gn:population":0,
    "gn:timezone":"Europe/Helsinki",
    "iso:country":"FI",
    "name:fin_x_preferred":[
        "Peltola"
    ],
    "name:koi_x_preferred":[
        "\u041f\u0435\u043b\u0442\u043e\u043b\u0430"
    ],
    "name:rus_x_preferred":[
        "\u041f\u0435\u043b\u0442\u043e\u043b\u0430"
    ],
    "wof:name":"Peltola",
    "wof:placetype":"locality"
},
  "geometry": {"coordinates":[23.51487,60.42668000000001],"type":"Point"}
}