{
  "type": "Feature",
  "properties": {
    "gn:admin1_code":"14.0",
    "gn:admin2_code":"142.0",
    "gn:admin3_code":"145.0",
    "gn:asciiname":"Asevelikylae",
    "gn:country_code":"FI",
    "gn:dem":58,
    "gn:feature_class":"P",
    "gn:feature_code":"PPL",
    "gn:name":"Asevelikyl\u00e4",
    "gn:population":0,
    "gn:timezone":"Europe/Helsinki",
    "iso:country":"FI",
    "name:fin_x_preferred":[
        "Asevelikyl\u00e4"
    ],
    "wof:name":"Asevelikylae",
    "wof:placetype":"locality"
},
  "geometry": {"coordinates":[22.4687,62.68303],"type":"Point"}
}