{
  "type": "Feature",
  "properties": {
    "gn:admin1_code":"6.0",
    "gn:admin2_code":"64.0",
    "gn:admin3_code":"980.0",
    "gn:asciiname":"Kaidankylae",
    "gn:country_code":"FI",
    "gn:dem":180,
    "gn:feature_class":"P",
    "gn:feature_code":"PPL",
    "gn:name":"Kaidankyl\u00e4",
    "gn:population":0,
    "gn:timezone":"Europe/Helsinki",
    "iso:country":"FI",
    "name:und_x_variant":[
        "Koidankyl\u00e4",
        "Kaidankyl\u00e4"
    ],
    "wof:name":"Kaidankylae",
    "wof:placetype":"locality"
},
  "geometry": {"coordinates":[23.62124,61.89308000000001],"type":"Point"}
}