{
  "type": "Feature",
  "properties": {
    "gn:admin1_code":"14.0",
    "gn:admin2_code":"142.0",
    "gn:admin3_code":"408.0",
    "gn:asciiname":"Herneshuhta",
    "gn:country_code":"FI",
    "gn:dem":94,
    "gn:feature_class":"P",
    "gn:feature_code":"PPL",
    "gn:name":"Herneshuhta",
    "gn:population":0,
    "gn:timezone":"Europe/Helsinki",
    "iso:country":"FI",
    "wof:name":"Herneshuhta",
    "wof:placetype":"locality"
},
  "geometry": {"coordinates":[23.48333,63.01667],"type":"Point"}
}