{
  "type": "Feature",
  "properties": {
    "iso:country":"FI",
    "name:fin_x_preferred":[
        "Lehtikangas"
    ],
    "qs:gn_fcode":"PPLX",
    "qs:gn_local":0,
    "qs:gn_namadm1":"08",
    "qs:gn_name":"Lehtikangas",
    "qs:local_max":414,
    "qs:local_sum":624,
    "qs:localhoods":3,
    "qs:name":"Lehtikangas",
    "qs:name_adm0":"Suomi",
    "qs:name_adm1":"Kainuun maakunta",
    "qs:name_adm2":"Kajaanin",
    "qs:name_lau":"Kajana",
    "qs:name_local":"Kajaani",
    "qs:photo_max":29,
    "qs:photo_sum":96,
    "qs:placetype":"Suburb",
    "qs:quad_count":27,
    "qs:woe_adm0":23424812,
    "qs:woe_adm1":29389264,
    "qs:woe_adm2":56120859,
    "qs:woe_lau":12590838,
    "qs:woe_local":566574,
    "qs:woe_ver":"7.10.0",
    "wof:lang":[
        "fin"
    ],
    "wof:name":"Lehtikangas",
    "wof:placetype":"neighbourhood"
},
  "geometry": {"coordinates":[27.762381,64.20914999999999],"type":"Point"}
}