{
  "type": "Feature",
  "properties": {
    "gn:admin1_code":"19.0",
    "gn:admin2_code":"196.0",
    "gn:admin3_code":"47.0",
    "gn:asciiname":"Suonttajaervi",
    "gn:country_code":"FI",
    "gn:dem":300,
    "gn:feature_class":"P",
    "gn:feature_code":"PPL",
    "gn:name":"Suonttaj\u00e4rvi",
    "gn:population":0,
    "gn:timezone":"Europe/Helsinki",
    "iso:country":"FI",
    "name:fin_x_preferred":[
        "Suonttaj\u00e4rvi"
    ],
    "name:sme_x_preferred":[
        "Suovditj\u00e1vri"
    ],
    "wof:name":"Suonttajaervi",
    "wof:placetype":"locality"
},
  "geometry": {"coordinates":[23.22082,68.39553000000001],"type":"Point"}
}