{
  "type": "Feature",
  "properties": {
    "gn:admin1_code":"9.0",
    "gn:admin2_code":"91.0",
    "gn:admin3_code":"739.0",
    "gn:asciiname":"Saeaenjaervi",
    "gn:country_code":"FI",
    "gn:dem":110,
    "gn:feature_class":"P",
    "gn:feature_code":"PPL",
    "gn:name":"S\u00e4\u00e4nj\u00e4rvi",
    "gn:population":0,
    "gn:timezone":"Europe/Helsinki",
    "iso:country":"FI",
    "wof:name":"Saeaenjaervi",
    "wof:placetype":"locality"
},
  "geometry": {"coordinates":[27.56741,61.17038],"type":"Point"}
}