{
  "type": "Feature",
  "properties": {
    "gn:admin1_code":"2.0",
    "gn:admin2_code":"24.0",
    "gn:admin3_code":"400.0",
    "gn:asciiname":"Pato",
    "gn:country_code":"FI",
    "gn:dem":44,
    "gn:feature_class":"P",
    "gn:feature_code":"PPL",
    "gn:name":"Pato",
    "gn:population":0,
    "gn:timezone":"Europe/Helsinki",
    "iso:country":"FI",
    "name:ara_x_preferred":[
        "\u0628\u0627\u062a\u0648"
    ],
    "name:cat_x_preferred":[
        "Pato"
    ],
    "name:deu_x_preferred":[
        "Pato"
    ],
    "name:fas_x_preferred":[
        "\u067e\u0627\u062a\u0648"
    ],
    "name:fin_x_preferred":[
        "Pato"
    ],
    "name:fra_x_preferred":[
        "Pato"
    ],
    "name:new_x_preferred":[
        "\u092a\u093e\u091f\u094b"
    ],
    "name:oci_x_preferred":[
        "Pato"
    ],
    "name:por_x_preferred":[
        "Pato"
    ],
    "name:spa_x_preferred":[
        "Pato"
    ],
    "name:swe_x_preferred":[
        "Pato"
    ],
    "wof:name":"Pato",
    "wof:placetype":"locality"
},
  "geometry": {"coordinates":[21.7851,60.9631],"type":"Point"}
}