{
  "type": "Feature",
  "properties": {
    "gn:admin1_code":"6.0",
    "gn:admin2_code":"64.0",
    "gn:admin3_code":"562.0",
    "gn:asciiname":"Lehdistoe",
    "gn:country_code":"FI",
    "gn:dem":123,
    "gn:feature_class":"P",
    "gn:feature_code":"PPL",
    "gn:name":"Lehdist\u00f6",
    "gn:population":0,
    "gn:timezone":"Europe/Helsinki",
    "iso:country":"FI",
    "wof:name":"Lehdistoe",
    "wof:placetype":"locality"
},
  "geometry": {"coordinates":[24.34251,61.69143],"type":"Point"}
}