{
  "type": "Feature",
  "properties": {
    "gn:admin1_code":"6.0",
    "gn:admin2_code":"61.0",
    "gn:admin3_code":"143.0",
    "gn:asciiname":"Vehuvarpee",
    "gn:country_code":"FI",
    "gn:dem":120,
    "gn:feature_class":"P",
    "gn:feature_code":"PPL",
    "gn:name":"Vehuvarpee",
    "gn:population":0,
    "gn:timezone":"Europe/Helsinki",
    "iso:country":"FI",
    "wof:name":"Vehuvarpee",
    "wof:placetype":"locality"
},
  "geometry": {"coordinates":[22.8186,61.71926],"type":"Point"}
}