{
  "type": "Feature",
  "properties": {
    "gn:admin1_code":"6.0",
    "gn:admin2_code":"68.0",
    "gn:admin3_code":"790.0",
    "gn:asciiname":"Taati",
    "gn:country_code":"FI",
    "gn:dem":63,
    "gn:feature_class":"P",
    "gn:feature_code":"PPL",
    "gn:name":"Taati",
    "gn:population":0,
    "gn:timezone":"Europe/Helsinki",
    "iso:country":"FI",
    "wof:name":"Taati",
    "wof:placetype":"locality"
},
  "geometry": {"coordinates":[22.63333,61.41667],"type":"Point"}
}