{
  "type": "Feature",
  "properties": {
    "gn:admin1_code":"15.0",
    "gn:admin2_code":"151.0",
    "gn:admin3_code":"152.0",
    "gn:asciiname":"Pysaekki",
    "gn:country_code":"FI",
    "gn:dem":28,
    "gn:feature_class":"P",
    "gn:feature_code":"PPL",
    "gn:name":"Pys\u00e4kki",
    "gn:population":0,
    "gn:timezone":"Europe/Helsinki",
    "iso:country":"FI",
    "name:fin_x_preferred":[
        "Pys\u00e4kki"
    ],
    "wof:name":"Pysaekki",
    "wof:placetype":"locality"
},
  "geometry": {"coordinates":[22.30285,62.96917],"type":"Point"}
}