{
  "type": "Feature",
  "properties": {
    "gn:admin1_code":"18.0",
    "gn:admin2_code":"182.0",
    "gn:admin3_code":"785.0",
    "gn:asciiname":"Kulma",
    "gn:country_code":"FI",
    "gn:dem":117,
    "gn:feature_class":"P",
    "gn:feature_code":"PPL",
    "gn:name":"Kulma",
    "gn:population":0,
    "gn:timezone":"Europe/Helsinki",
    "iso:country":"FI",
    "wof:name":"Kulma",
    "wof:placetype":"locality"
},
  "geometry": {"coordinates":[26.63333,64.59999999999999],"type":"Point"}
}