{
  "type": "Feature",
  "properties": {
    "gn:admin1_code":"1.0",
    "gn:admin2_code":"11.0",
    "gn:admin3_code":"245.0",
    "gn:asciiname":"Kaleva",
    "gn:country_code":"FI",
    "gn:dem":54,
    "gn:feature_class":"P",
    "gn:feature_code":"PPL",
    "gn:name":"Kaleva",
    "gn:population":0,
    "gn:timezone":"Europe/Helsinki",
    "iso:country":"FI",
    "name:ceb_x_preferred":[
        "Kaleva"
    ],
    "name:deu_x_preferred":[
        "Kaleva"
    ],
    "name:est_x_preferred":[
        "Kaleva"
    ],
    "name:fin_x_preferred":[
        "Kaleva"
    ],
    "name:fra_x_preferred":[
        "Kaleva"
    ],
    "name:nld_x_preferred":[
        "Kaleva"
    ],
    "name:por_x_preferred":[
        "Kaleva"
    ],
    "name:rus_x_preferred":[
        "\u041a\u0430\u043b\u0435\u0432\u0430"
    ],
    "name:swe_x_preferred":[
        "Kaleva"
    ],
    "wof:name":"Kaleva",
    "wof:placetype":"locality"
},
  "geometry": {"coordinates":[25.0944,60.41571999999999],"type":"Point"}
}