{
  "type": "Feature",
  "properties": {
    "gn:admin1_code":"18.0",
    "gn:admin2_code":"182.0",
    "gn:admin3_code":"765.0",
    "gn:asciiname":"Hanhila",
    "gn:country_code":"FI",
    "gn:dem":167,
    "gn:feature_class":"P",
    "gn:feature_code":"PPL",
    "gn:name":"Hanhila",
    "gn:population":0,
    "gn:timezone":"Europe/Helsinki",
    "iso:country":"FI",
    "name:eng_x_preferred":[
        "Hanhila"
    ],
    "name:rus_x_preferred":[
        "\u0425\u0430\u043d\u0445\u0438\u043b\u0430"
    ],
    "wof:name":"Hanhila",
    "wof:placetype":"locality"
},
  "geometry": {"coordinates":[27.92909,64.15555999999999],"type":"Point"}
}