{
  "type": "Feature",
  "properties": {
    "gn:admin1_code":"7.0",
    "gn:admin2_code":"71.0",
    "gn:admin3_code":"781.0",
    "gn:asciiname":"Virtaa",
    "gn:cc2":"FI",
    "gn:country_code":"FI",
    "gn:dem":86,
    "gn:feature_class":"P",
    "gn:feature_code":"PPL",
    "gn:name":"Virtaa",
    "gn:population":0,
    "gn:timezone":"Europe/Helsinki",
    "iso:country":"FI",
    "name:und_x_variant":[
        "Tainio",
        "Virtaa"
    ],
    "wof:name":"Virtaa",
    "wof:placetype":"locality"
},
  "geometry": {"coordinates":[25.72428,61.44955],"type":"Point"}
}