{
  "type": "Feature",
  "properties": {
    "gn:admin1_code":"18.0",
    "gn:admin2_code":"181.0",
    "gn:admin3_code":"290.0",
    "gn:asciiname":"Iivantiira",
    "gn:country_code":"FI",
    "gn:dem":179,
    "gn:feature_class":"P",
    "gn:feature_code":"PPL",
    "gn:name":"Iivantiira",
    "gn:population":0,
    "gn:timezone":"Europe/Helsinki",
    "iso:country":"FI",
    "name:eng_x_preferred":[
        "Iivantiira"
    ],
    "name:rus_x_preferred":[
        "\u0418\u0432\u0430\u043d\u0442\u0438\u0440\u0430"
    ],
    "wof:name":"Iivantiira",
    "wof:placetype":"locality"
},
  "geometry": {"coordinates":[29.50355,64.43674],"type":"Point"}
}