{
  "type": "Feature",
  "properties": {
    "gn:admin1_code":"1.0",
    "gn:admin2_code":"11.0",
    "gn:admin3_code":"257.0",
    "gn:asciiname":"Nyase",
    "gn:country_code":"FI",
    "gn:dem":6,
    "gn:feature_class":"P",
    "gn:feature_code":"PPL",
    "gn:name":"Nyase",
    "gn:population":0,
    "gn:timezone":"Europe/Helsinki",
    "iso:country":"FI",
    "name:und_x_variant":[
        "Nesi",
        "Nyase",
        "N\u00e4se"
    ],
    "wof:name":"Nyase",
    "wof:placetype":"locality"
},
  "geometry": {"coordinates":[24.44472,60.0475],"type":"Point"}
}