{
  "type": "Feature",
  "properties": {
    "gn:admin1_code":"10.0",
    "gn:admin2_code":"103.0",
    "gn:admin3_code":"90.0",
    "gn:asciiname":"Sarvikumpu",
    "gn:cc2":"FI",
    "gn:country_code":"FI",
    "gn:dem":159,
    "gn:feature_class":"P",
    "gn:feature_code":"PPL",
    "gn:name":"Sarvikumpu",
    "gn:population":0,
    "gn:timezone":"Europe/Helsinki",
    "iso:country":"FI",
    "name:eng_x_preferred":[
        "Sarvikumpu"
    ],
    "name:rus_x_preferred":[
        "\u0421\u0430\u0440\u0432\u0438\u043a\u0443\u043c\u043f\u0443"
    ],
    "name:und_x_variant":[
        "Sarvikumpo"
    ],
    "wof:name":"Sarvikumpu",
    "wof:placetype":"locality"
},
  "geometry": {"coordinates":[29.00547000000001,62.46666],"type":"Point"}
}