{
  "type": "Feature",
  "properties": {
    "gn:admin1_code":"13.0",
    "gn:admin2_code":"132.0",
    "gn:admin3_code":"172.0",
    "gn:asciiname":"Mieskonmaeki",
    "gn:country_code":"FI",
    "gn:dem":99,
    "gn:feature_class":"P",
    "gn:feature_code":"PPL",
    "gn:name":"Mieskonm\u00e4ki",
    "gn:population":0,
    "gn:timezone":"Europe/Helsinki",
    "iso:country":"FI",
    "wof:name":"Mieskonmaeki",
    "wof:placetype":"locality"
},
  "geometry": {"coordinates":[26.30752,61.84221],"type":"Point"}
}