{
  "type": "Feature",
  "properties": {
    "gn:admin1_code":"19.0",
    "gn:admin2_code":"194.0",
    "gn:admin3_code":"732.0",
    "gn:asciiname":"Onkamo",
    "gn:cc2":"FI",
    "gn:country_code":"FI",
    "gn:dem":290,
    "gn:feature_class":"P",
    "gn:feature_code":"PPL",
    "gn:name":"Onkamo",
    "gn:population":0,
    "gn:timezone":"Europe/Helsinki",
    "iso:country":"FI",
    "name:eng_x_preferred":[
        "Onkamo"
    ],
    "name:rus_x_preferred":[
        "\u041e\u043d\u043a\u0430\u043c\u043e"
    ],
    "name:und_x_variant":[
        "Onkamoj\u00e4rvi"
    ],
    "wof:name":"Onkamo",
    "wof:placetype":"locality"
},
  "geometry": {"coordinates":[29.0673,66.73743],"type":"Point"}
}