{
  "type": "Feature",
  "properties": {
    "gn:admin1_code":"10.0",
    "gn:admin2_code":"103.0",
    "gn:admin3_code":"90.0",
    "gn:asciiname":"Kotilanmaeki",
    "gn:country_code":"FI",
    "gn:dem":136,
    "gn:feature_class":"P",
    "gn:feature_code":"PPL",
    "gn:name":"Kotilanm\u00e4ki",
    "gn:population":0,
    "gn:timezone":"Europe/Helsinki",
    "iso:country":"FI",
    "wof:name":"Kotilanmaeki",
    "wof:placetype":"locality"
},
  "geometry": {"coordinates":[28.69802,62.4114],"type":"Point"}
}