{
  "type": "Feature",
  "properties": {
    "gn:admin1_code":"11.0",
    "gn:admin2_code":"111.0",
    "gn:admin3_code":"140.0",
    "gn:asciiname":"Kotikylae",
    "gn:country_code":"FI",
    "gn:dem":110,
    "gn:feature_class":"P",
    "gn:feature_code":"PPL",
    "gn:name":"Kotikyl\u00e4",
    "gn:population":0,
    "gn:timezone":"Europe/Helsinki",
    "iso:country":"FI",
    "wof:name":"Kotikylae",
    "wof:placetype":"locality"
},
  "geometry": {"coordinates":[27.1579,63.44845],"type":"Point"}
}