{
  "type": "Feature",
  "properties": {
    "gn:admin1_code":"1.0",
    "gn:admin2_code":"11.0",
    "gn:admin3_code":"444.0",
    "gn:asciiname":"Karisjaervi",
    "gn:country_code":"FI",
    "gn:dem":101,
    "gn:feature_class":"P",
    "gn:feature_code":"PPL",
    "gn:name":"Karisj\u00e4rvi",
    "gn:population":0,
    "gn:timezone":"Europe/Helsinki",
    "iso:country":"FI",
    "wof:name":"Karisjaervi",
    "wof:placetype":"locality"
},
  "geometry": {"coordinates":[24.02729,60.52005],"type":"Point"}
}