{
  "type": "Feature",
  "properties": {
    "gn:admin1_code":"2.0",
    "gn:admin2_code":"23.0",
    "gn:admin3_code":"738.0",
    "gn:asciiname":"Korpela",
    "gn:country_code":"FI",
    "gn:dem":10,
    "gn:feature_class":"P",
    "gn:feature_code":"PPL",
    "gn:name":"Korpela",
    "gn:population":0,
    "gn:timezone":"Europe/Helsinki",
    "iso:country":"FI",
    "wof:name":"Korpela",
    "wof:placetype":"locality"
},
  "geometry": {"coordinates":[22.79982,60.34254],"type":"Point"}
}