{
  "type": "Feature",
  "properties": {
    "gn:admin1_code":"19.0",
    "gn:admin2_code":"193.0",
    "gn:admin3_code":"854.0",
    "gn:asciiname":"Korteniemenpaa",
    "gn:country_code":"FI",
    "gn:dem":90,
    "gn:feature_class":"P",
    "gn:feature_code":"PPL",
    "gn:name":"Korteniemenp\u00e4\u00e4",
    "gn:population":0,
    "gn:timezone":"Europe/Stockholm",
    "iso:country":"FI",
    "name:fin_x_preferred":[
        "Korteniemenp\u00e4\u00e4"
    ],
    "name:und_x_variant":[
        "Kortetniemi"
    ],
    "wof:name":"Korteniemenpaa",
    "wof:placetype":"locality"
},
  "geometry": {"coordinates":[23.99687,66.79890999999999],"type":"Point"}
}