{
  "type": "Feature",
  "properties": {
    "gn:admin1_code":"11.0",
    "gn:admin2_code":"113.0",
    "gn:admin3_code":"204.0",
    "gn:asciiname":"Hovi",
    "gn:country_code":"FI",
    "gn:dem":158,
    "gn:feature_class":"P",
    "gn:feature_code":"PPL",
    "gn:name":"Hovi",
    "gn:population":0,
    "gn:timezone":"Europe/Helsinki",
    "iso:country":"FI",
    "wof:name":"Hovi",
    "wof:placetype":"locality"
},
  "geometry": {"coordinates":[28.88333,63.01667],"type":"Point"}
}