{
  "type": "Feature",
  "properties": {
    "gn:admin1_code":"2.0",
    "gn:admin2_code":"22.0",
    "gn:admin3_code":"734.0",
    "gn:asciiname":"Patala",
    "gn:country_code":"FI",
    "gn:dem":50,
    "gn:feature_class":"P",
    "gn:feature_code":"PPL",
    "gn:name":"Patala",
    "gn:population":0,
    "gn:timezone":"Europe/Helsinki",
    "iso:country":"FI",
    "wof:name":"Patala",
    "wof:placetype":"locality"
},
  "geometry": {"coordinates":[23.34726,60.45101],"type":"Point"}
}