{
  "type": "Feature",
  "properties": {
    "gn:admin1_code":"2.0",
    "gn:admin2_code":"22.0",
    "gn:admin3_code":"734.0",
    "gn:asciiname":"Patala",
    "gn:country_code":"FI",
    "gn:dem":50,
    "gn:feature_class":"P",
    "gn:feature_code":"PPL",
    "gn:name":"Patala",
    "gn:population":0,
    "gn:timezone":"Europe/Helsinki",
    "iso:country":"FI",
    "name:fra_x_preferred":[
        "Patala"
    ],
    "name:guj_x_preferred":[
        "\u0aaa\u0abe\u0aa4\u0abe\u0ab3"
    ],
    "name:hin_x_preferred":[
        "\u092a\u093e\u0924\u093e\u0932"
    ],
    "name:ind_x_preferred":[
        "Patala"
    ],
    "name:ita_x_preferred":[
        "P\u0101t\u0101la"
    ],
    "name:jpn_x_preferred":[
        "\u30d1\u30fc\u30bf\u30fc\u30e9"
    ],
    "name:kan_x_preferred":[
        "\u0caa\u0cbe\u0ca4\u0cbe\u0cb3"
    ],
    "name:lit_x_preferred":[
        "Patala"
    ],
    "name:new_x_preferred":[
        "\u092a\u093e\u0924\u093e\u0932"
    ],
    "name:nld_x_preferred":[
        "Patala"
    ],
    "name:pol_x_preferred":[
        "Patala"
    ],
    "name:rus_x_preferred":[
        "\u041f\u0430\u0442\u0430\u043b\u0430"
    ],
    "name:spa_x_preferred":[
        "Naraka"
    ],
    "name:tam_x_preferred":[
        "\u0baa\u0bbe\u0ba4\u0bbe\u0bb3\u0bae\u0bcd"
    ],
    "name:tel_x_preferred":[
        "\u0c2a\u0c3e\u0c24\u0c3e\u0c33\u0c2e\u0c41"
    ],
    "wof:name":"Patala",
    "wof:placetype":"locality"
},
  "geometry": {"coordinates":[23.34726,60.45101],"type":"Point"}
}