{
  "type": "Feature",
  "properties": {
    "gn:admin1_code":"15.0",
    "gn:admin2_code":"153.0",
    "gn:admin3_code":"287.0",
    "gn:asciiname":"Sandan",
    "gn:country_code":"FI",
    "gn:dem":7,
    "gn:feature_class":"P",
    "gn:feature_code":"PPL",
    "gn:name":"Sandan",
    "gn:population":0,
    "gn:timezone":"Europe/Helsinki",
    "iso:country":"FI",
    "name:ceb_x_preferred":[
        "Sandan"
    ],
    "name:ita_x_preferred":[
        "Sandan"
    ],
    "name:swe_x_preferred":[
        "Sandan"
    ],
    "wof:name":"Sandan",
    "wof:placetype":"locality"
},
  "geometry": {"coordinates":[21.49654,62.26057],"type":"Point"}
}