{
  "type": "Feature",
  "properties": {
    "gn:admin1_code":"4.0",
    "gn:admin2_code":"43.0",
    "gn:admin3_code":"886.0",
    "gn:asciiname":"Tuomi",
    "gn:country_code":"FI",
    "gn:dem":12,
    "gn:feature_class":"P",
    "gn:feature_code":"PPL",
    "gn:name":"Tuomi",
    "gn:population":0,
    "gn:timezone":"Europe/Helsinki",
    "iso:country":"FI",
    "name:rus_x_preferred":[
        "\u0422\u0443\u043e\u043c\u0438"
    ],
    "wof:name":"Tuomi",
    "wof:placetype":"locality"
},
  "geometry": {"coordinates":[21.87275,61.45161],"type":"Point"}
}