{
  "type": "Feature",
  "properties": {
    "gn:admin1_code":"14.0",
    "gn:admin2_code":"146.0",
    "gn:admin3_code":"5.0",
    "gn:asciiname":"Menkijaervi",
    "gn:country_code":"FI",
    "gn:dem":111,
    "gn:feature_class":"P",
    "gn:feature_code":"PPL",
    "gn:name":"Menkij\u00e4rvi",
    "gn:population":0,
    "gn:timezone":"Europe/Helsinki",
    "iso:country":"FI",
    "name:und_x_variant":[
        "Menkij\u00e4rvi",
        "M\u00e4kij\u00e4rvi"
    ],
    "wof:name":"Menkijaervi",
    "wof:placetype":"locality"
},
  "geometry": {"coordinates":[23.51977,62.95681],"type":"Point"}
}