{
  "type": "Feature",
  "properties": {
    "gn:admin1_code":"1.0",
    "gn:admin2_code":"11.0",
    "gn:admin3_code":"505.0",
    "gn:asciiname":"Olkinen",
    "gn:country_code":"FI",
    "gn:dem":86,
    "gn:feature_class":"P",
    "gn:feature_code":"PPL",
    "gn:name":"Olkinen",
    "gn:population":0,
    "gn:timezone":"Europe/Helsinki",
    "iso:country":"FI",
    "wof:name":"Olkinen",
    "wof:placetype":"locality"
},
  "geometry": {"coordinates":[25.11667000000001,60.75],"type":"Point"}
}