{
  "type": "Feature",
  "properties": {
    "gn:admin1_code":"10.0",
    "gn:admin2_code":"101.0",
    "gn:admin3_code":"491.0",
    "gn:asciiname":"Laesaekoski",
    "gn:country_code":"FI",
    "gn:dem":101,
    "gn:feature_class":"P",
    "gn:feature_code":"PPL",
    "gn:name":"L\u00e4s\u00e4koski",
    "gn:population":0,
    "gn:timezone":"Europe/Helsinki",
    "iso:country":"FI",
    "wof:name":"Laesaekoski",
    "wof:placetype":"locality"
},
  "geometry": {"coordinates":[26.91753,61.90995],"type":"Point"}
}