{
  "type": "Feature",
  "properties": {
    "gn:admin1_code":"17.0",
    "gn:admin2_code":"178.0",
    "gn:admin3_code":"832.0",
    "gn:asciiname":"Kaunisto",
    "gn:country_code":"FI",
    "gn:dem":226,
    "gn:feature_class":"P",
    "gn:feature_code":"PPL",
    "gn:name":"Kaunisto",
    "gn:population":0,
    "gn:timezone":"Europe/Helsinki",
    "iso:country":"FI",
    "wof:name":"Kaunisto",
    "wof:placetype":"locality"
},
  "geometry": {"coordinates":[28.75,65.48333000000001],"type":"Point"}
}