{
  "type": "Feature",
  "properties": {
    "gn:admin1_code":"1.0",
    "gn:admin2_code":"11.0",
    "gn:admin3_code":"92.0",
    "gn:asciiname":"Laensimaeki",
    "gn:cc2":"FI",
    "gn:country_code":"FI",
    "gn:dem":14,
    "gn:feature_class":"P",
    "gn:feature_code":"PPL",
    "gn:name":"L\u00e4nsim\u00e4ki",
    "gn:population":0,
    "gn:timezone":"Europe/Helsinki",
    "iso:country":"FI",
    "name:swe_x_preferred":[
        "V\u00e4sterkulla"
    ],
    "wof:name":"Laensimaeki",
    "wof:placetype":"locality"
},
  "geometry": {"coordinates":[25.11775,60.24633000000001],"type":"Point"}
}