{
  "type": "Feature",
  "properties": {
    "gn:admin1_code":"10.0",
    "gn:admin2_code":"105.0",
    "gn:admin3_code":"593.0",
    "gn:asciiname":"Peltoniemi",
    "gn:country_code":"FI",
    "gn:dem":98,
    "gn:feature_class":"P",
    "gn:feature_code":"PPL",
    "gn:name":"Peltoniemi",
    "gn:population":0,
    "gn:timezone":"Europe/Helsinki",
    "iso:country":"FI",
    "wof:name":"Peltoniemi",
    "wof:placetype":"locality"
},
  "geometry": {"coordinates":[27.06667,62.25],"type":"Point"}
}