{
  "type": "Feature",
  "properties": {
    "gn:admin1_code":"16.0",
    "gn:admin2_code":"161.0",
    "gn:admin3_code":"584.0",
    "gn:asciiname":"Kivelae",
    "gn:country_code":"FI",
    "gn:dem":169,
    "gn:feature_class":"P",
    "gn:feature_code":"PPL",
    "gn:name":"Kivel\u00e4",
    "gn:population":0,
    "gn:timezone":"Europe/Helsinki",
    "iso:country":"FI",
    "wof:name":"Kivelae",
    "wof:placetype":"locality"
},
  "geometry": {"coordinates":[24.30538,63.24039000000001],"type":"Point"}
}