{
  "type": "Feature",
  "properties": {
    "gn:admin1_code":"1.0",
    "gn:admin2_code":"11.0",
    "gn:admin3_code":"755.0",
    "gn:asciiname":"Kurkis",
    "gn:country_code":"FI",
    "gn:dem":51,
    "gn:feature_class":"P",
    "gn:feature_code":"PPL",
    "gn:name":"Kurkis",
    "gn:population":0,
    "gn:timezone":"Europe/Helsinki",
    "iso:country":"FI",
    "wof:name":"Kurkis",
    "wof:placetype":"locality"
},
  "geometry": {"coordinates":[24.23175,60.19704],"type":"Point"}
}