{
  "type": "Feature",
  "properties": {
    "gn:admin1_code":"4.0",
    "gn:admin2_code":"44.0",
    "gn:admin3_code":"230.0",
    "gn:asciiname":"Sara",
    "gn:country_code":"FI",
    "gn:dem":149,
    "gn:feature_class":"P",
    "gn:feature_code":"PPL",
    "gn:name":"Sara",
    "gn:population":0,
    "gn:timezone":"Europe/Helsinki",
    "iso:country":"FI",
    "wof:name":"Sara",
    "wof:placetype":"locality"
},
  "geometry": {"coordinates":[22.61677,62.25215],"type":"Point"}
}