{
  "type": "Feature",
  "properties": {
    "iso:country":"FI",
    "qs_pg:aaroncc":"FI",
    "qs_pg:name":"Kaleton",
    "qs_pg:name_adm0":"Suomi",
    "qs_pg:name_adm1":"Keski-Suomen maakunta",
    "qs_pg:photos":11,
    "qs_pg:photos_1k":2,
    "qs_pg:photos_9k":1,
    "qs_pg:photos_9r":1,
    "qs_pg:photos_all":11,
    "qs_pg:photos_sr":1,
    "qs_pg:pop_sr":0,
    "qs_pg:qs_pg_placetype":"locality",
    "qs_pg:qs_pg_placetype_gp":"Town",
    "qs_pg:woe_adm0":23424812,
    "woe:adm0_id":23424812,
    "woe:name_adm0":"Suomi",
    "woe:name_adm1":"Keski-Suomen maakunta",
    "woe:placetype":"Town",
    "wof:name":"Kaleton",
    "wof:placetype":"locality"
},
  "geometry": {"coordinates":[24.796711,62.211269],"type":"Point"}
}