{
  "type": "Feature",
  "properties": {
    "gn:admin1_code":"19.0",
    "gn:admin2_code":"197.0",
    "gn:admin3_code":"148.0",
    "gn:asciiname":"Jankkila",
    "gn:country_code":"FI",
    "gn:dem":100,
    "gn:feature_class":"P",
    "gn:feature_code":"PPL",
    "gn:name":"Jankkila",
    "gn:population":0,
    "gn:timezone":"Europe/Helsinki",
    "iso:country":"FI",
    "name:eng_x_preferred":[
        "Jankkila"
    ],
    "name:rus_x_preferred":[
        "\u042f\u043d\u043a\u043a\u0438\u043b\u0430"
    ],
    "name:sme_x_preferred":[
        "J\u00e1\u014bkkil"
    ],
    "name:smn_x_preferred":[
        "Ja\u014bkkil"
    ],
    "name:sms_x_preferred":[
        "Ja\u00b4\u014b\u01e9\u01e9el"
    ],
    "wof:name":"Jankkila",
    "wof:placetype":"locality"
},
  "geometry": {"coordinates":[29.15881,69.56168000000001],"type":"Point"}
}