{
  "type": "Feature",
  "properties": {
    "gn:gn_country":"FI",
    "gn:gn_fcode":"PPL",
    "gn:gn_pop":0,
    "iso:country":"FI",
    "name:dan_x_preferred":[
        "Mickels"
    ],
    "name:fin_x_preferred":[
        "Mikkel\u00e4"
    ],
    "name:isl_x_preferred":[
        "Mickels"
    ],
    "name:nor_x_preferred":[
        "Mickels"
    ],
    "name:swe_x_preferred":[
        "Mickels"
    ],
    "qs_pg:aaroncc":"FI",
    "qs_pg:gn_country":"FI",
    "qs_pg:gn_fcode":"PPL",
    "qs_pg:gn_pop":0,
    "qs_pg:name":"Mikkel\u00e4",
    "qs_pg:name_adm0":"Suomi",
    "qs_pg:name_adm1":"Uudenmaan maakunta",
    "qs_pg:photos_9r":0,
    "qs_pg:photos_sr":0,
    "qs_pg:pop_sr":0,
    "qs_pg:qs_pg_placetype":"locality",
    "qs_pg:qs_pg_placetype_gp":"Town",
    "qs_pg:woe_adm0":23424812,
    "woe:adm0_id":23424812,
    "woe:name_adm0":"Suomi",
    "woe:name_adm1":"Uudenmaan maakunta",
    "woe:placetype":"Town",
    "wof:name":"Mikkel\u00e4",
    "wof:placetype":"locality"
},
  "geometry": {"coordinates":[24.63169,60.20477],"type":"Point"}
}