{
  "type": "Feature",
  "properties": {
    "gn:admin1_code":"5.0",
    "gn:admin2_code":"52.0",
    "gn:admin3_code":"86.0",
    "gn:asciiname":"Rutajaervi",
    "gn:country_code":"FI",
    "gn:dem":92,
    "gn:feature_class":"P",
    "gn:feature_code":"PPL",
    "gn:name":"Rutaj\u00e4rvi",
    "gn:population":0,
    "gn:timezone":"Europe/Helsinki",
    "iso:country":"FI",
    "wof:name":"Rutajaervi",
    "wof:placetype":"locality"
},
  "geometry": {"coordinates":[25.11943,60.77316999999999],"type":"Point"}
}