{
  "type": "Feature",
  "properties": {
    "gn:admin1_code":"11.0",
    "gn:admin2_code":"111.0",
    "gn:admin3_code":"762.0",
    "gn:asciiname":"Paisua",
    "gn:country_code":"FI",
    "gn:dem":161,
    "gn:feature_class":"P",
    "gn:feature_code":"PPL",
    "gn:name":"Paisua",
    "gn:population":0,
    "gn:timezone":"Europe/Helsinki",
    "iso:country":"FI",
    "name:eng_x_preferred":[
        "Paisua"
    ],
    "name:rus_x_preferred":[
        "\u041f\u0430\u0439\u0441\u0443\u0430"
    ],
    "wof:name":"Paisua",
    "wof:placetype":"locality"
},
  "geometry": {"coordinates":[27.6265,63.56358],"type":"Point"}
}