{
  "type": "Feature",
  "properties": {
    "gn:admin1_code":"12.0",
    "gn:admin2_code":"122.0",
    "gn:admin3_code":"146.0",
    "gn:asciiname":"Rento",
    "gn:cc2":"FI",
    "gn:country_code":"FI",
    "gn:dem":181,
    "gn:feature_class":"P",
    "gn:feature_code":"PPL",
    "gn:name":"Rento",
    "gn:population":0,
    "gn:timezone":"Europe/Helsinki",
    "iso:country":"FI",
    "name:und_x_variant":[
        "Reutovaara",
        "Rento"
    ],
    "wof:name":"Rento",
    "wof:placetype":"locality"
},
  "geometry": {"coordinates":[30.55,62.86666999999999],"type":"Point"}
}