{
  "type": "Feature",
  "properties": {
    "gn:admin1_code":"15.0",
    "gn:admin2_code":"152.0",
    "gn:admin3_code":"946.0",
    "gn:asciiname":"Maekipaeae",
    "gn:country_code":"FI",
    "gn:dem":35,
    "gn:feature_class":"P",
    "gn:feature_code":"PPL",
    "gn:name":"M\u00e4kip\u00e4\u00e4",
    "gn:population":0,
    "gn:timezone":"Europe/Helsinki",
    "iso:country":"FI",
    "name:fin_x_preferred":[
        "M\u00e4kip\u00e4\u00e4"
    ],
    "wof:name":"Maekipaeae",
    "wof:placetype":"locality"
},
  "geometry": {"coordinates":[22.23149,63.14474000000001],"type":"Point"}
}