{
  "type": "Feature",
  "properties": {
    "gn:admin1_code":"4.0",
    "gn:admin2_code":"41.0",
    "gn:admin3_code":"50.0",
    "gn:asciiname":"Ilomaeki",
    "gn:country_code":"FI",
    "gn:dem":40,
    "gn:feature_class":"P",
    "gn:feature_code":"PPL",
    "gn:name":"Ilom\u00e4ki",
    "gn:population":0,
    "gn:timezone":"Europe/Helsinki",
    "iso:country":"FI",
    "name:fin_x_preferred":[
        "Ilom\u00e4ki"
    ],
    "wof:name":"Ilomaeki",
    "wof:placetype":"locality"
},
  "geometry": {"coordinates":[22.00436,60.99595],"type":"Point"}
}