{
  "type": "Feature",
  "properties": {
    "gn:admin1_code":"6.0",
    "gn:admin2_code":"68.0",
    "gn:admin3_code":"790.0",
    "gn:asciiname":"Tupurla",
    "gn:country_code":"FI",
    "gn:dem":64,
    "gn:feature_class":"P",
    "gn:feature_code":"PPL",
    "gn:name":"Tupurla",
    "gn:population":0,
    "gn:timezone":"Europe/Helsinki",
    "iso:country":"FI",
    "wof:name":"Tupurla",
    "wof:placetype":"locality"
},
  "geometry": {"coordinates":[23.13258,61.50086999999999],"type":"Point"}
}