{
  "type": "Feature",
  "properties": {
    "gn:admin1_code":"18.0",
    "gn:admin2_code":"181.0",
    "gn:admin3_code":"290.0",
    "gn:asciiname":"Kattilakoski",
    "gn:country_code":"FI",
    "gn:dem":161,
    "gn:feature_class":"P",
    "gn:feature_code":"PPL",
    "gn:name":"Kattilakoski",
    "gn:population":0,
    "gn:timezone":"Europe/Helsinki",
    "iso:country":"FI",
    "name:fin_x_preferred":[
        "Kattilakoski"
    ],
    "wof:name":"Kattilakoski",
    "wof:placetype":"locality"
},
  "geometry": {"coordinates":[29.79664,64.27462],"type":"Point"}
}