{
  "type": "Feature",
  "properties": {
    "gn:admin1_code":"2.0",
    "gn:admin2_code":"23.0",
    "gn:admin3_code":"529.0",
    "gn:asciiname":"Vuorlahti",
    "gn:country_code":"FI",
    "gn:dem":12,
    "gn:feature_class":"P",
    "gn:feature_code":"PPL",
    "gn:name":"Vuorlahti",
    "gn:population":0,
    "gn:timezone":"Europe/Helsinki",
    "iso:country":"FI",
    "wof:name":"Vuorlahti",
    "wof:placetype":"locality"
},
  "geometry": {"coordinates":[21.76874,60.52072],"type":"Point"}
}