{
  "type": "Feature",
  "properties": {
    "gn:admin1_code":"12.0",
    "gn:admin2_code":"122.0",
    "gn:admin3_code":"167.0",
    "gn:asciiname":"Vihtakoski",
    "gn:country_code":"FI",
    "gn:dem":132,
    "gn:feature_class":"P",
    "gn:feature_code":"PPL",
    "gn:name":"Vihtakoski",
    "gn:population":0,
    "gn:timezone":"Europe/Helsinki",
    "iso:country":"FI",
    "wof:name":"Vihtakoski",
    "wof:placetype":"locality"
},
  "geometry": {"coordinates":[30.46667,62.38333000000001],"type":"Point"}
}