{
  "type": "Feature",
  "properties": {
    "gn:admin1_code":"13.0",
    "gn:admin2_code":"138.0",
    "gn:admin3_code":"729.0",
    "gn:asciiname":"Kolkanlahti",
    "gn:country_code":"FI",
    "gn:dem":157,
    "gn:feature_class":"P",
    "gn:feature_code":"PPL",
    "gn:name":"Kolkanlahti",
    "gn:population":0,
    "gn:timezone":"Europe/Helsinki",
    "iso:country":"FI",
    "name:eng_x_preferred":[
        "Kolkanlahti"
    ],
    "name:rus_x_preferred":[
        "\u041a\u043e\u043b\u043a\u0430\u043d\u043b\u0430\u0445\u0442\u0438"
    ],
    "wof:name":"Kolkanlahti",
    "wof:placetype":"locality"
},
  "geometry": {"coordinates":[25.18327,62.73436],"type":"Point"}
}