{
  "type": "Feature",
  "properties": {
    "gn:admin1_code":"17.0",
    "gn:admin2_code":"176.0",
    "gn:admin3_code":"69.0",
    "gn:asciiname":"Kuusaa",
    "gn:country_code":"FI",
    "gn:dem":112,
    "gn:feature_class":"P",
    "gn:feature_code":"PPL",
    "gn:name":"Kuusaa",
    "gn:population":0,
    "gn:timezone":"Europe/Helsinki",
    "iso:country":"FI",
    "wof:name":"Kuusaa",
    "wof:placetype":"locality"
},
  "geometry": {"coordinates":[25.33333,63.85],"type":"Point"}
}