{
  "type": "Feature",
  "properties": {
    "gn:population":3132,
    "iso:country":"FI",
    "name:ast_x_preferred":[
        "Konnevesi"
    ],
    "name:ceb_x_preferred":[
        "Konnevesi"
    ],
    "name:deu_x_preferred":[
        "Konnevesi"
    ],
    "name:eng_x_preferred":[
        "Konnevesi"
    ],
    "name:epo_x_preferred":[
        "Konnevesi"
    ],
    "name:est_x_preferred":[
        "Konnevesi vald"
    ],
    "name:fin_x_preferred":[
        "Konnevesi"
    ],
    "name:fra_x_preferred":[
        "Konnevesi"
    ],
    "name:glg_x_preferred":[
        "Konnevesi"
    ],
    "name:ita_x_preferred":[
        "Konnevesi"
    ],
    "name:nld_x_preferred":[
        "Konnevesi"
    ],
    "name:nno_x_preferred":[
        "Konnevesi"
    ],
    "name:nob_x_preferred":[
        "Konnevesi"
    ],
    "name:nor_x_preferred":[
        "Konnevesi"
    ],
    "name:pol_x_preferred":[
        "Konnevesi"
    ],
    "name:ron_x_preferred":[
        "Konnevesi"
    ],
    "name:rus_x_preferred":[
        "\u041a\u043e\u043d\u043d\u0435\u0432\u0435\u0441\u0438"
    ],
    "name:sme_x_preferred":[
        "Konnevesi"
    ],
    "name:sqi_x_preferred":[
        "Konnevesi"
    ],
    "name:swe_x_preferred":[
        "Konnevesi"
    ],
    "name:tur_x_preferred":[
        "Konnevesi"
    ],
    "name:vie_x_preferred":[
        "Konnevesi"
    ],
    "name:zho_x_preferred":[
        "\u5b54\u5167\u97cb\u897f"
    ],
    "qs:a0":"Suomi#Finland",
    "qs:a1":"*Keski-Suomi#Mellersta Finland",
    "qs:a1r":"0L\u00e4nsi- ja Sis\u00e4-Suomen AVI#V\u00e4stra och Inre Finlands RFV",
    "qs:adm0":"Suomi#Finland",
    "qs:la_lc":"*",
    "qs:level":"locality",
    "qs:loc":"Konnevesi",
    "qs:loc_alt":"Konnevesi",
    "qs:pop":0,
    "qs:type":"buffered point",
    "wd:wordcount":300,
    "wof:name":"Konnevesi",
    "wof:placetype":"locality",
    "wof:population":3132
},
  "geometry": {"coordinates":[26.325798,62.626407],"type":"Point"}
}