{
  "type": "Feature",
  "properties": {
    "gn:admin1_code":"10.0",
    "gn:admin2_code":"105.0",
    "gn:admin3_code":"593.0",
    "gn:asciiname":"Vanaja",
    "gn:country_code":"FI",
    "gn:dem":180,
    "gn:feature_class":"P",
    "gn:feature_code":"PPL",
    "gn:name":"Vanaja",
    "gn:population":0,
    "gn:timezone":"Europe/Helsinki",
    "iso:country":"FI",
    "name:fin_x_preferred":[
        "Vanaja"
    ],
    "wof:name":"Vanaja",
    "wof:placetype":"locality"
},
  "geometry": {"coordinates":[26.75431,62.39915],"type":"Point"}
}