{
  "type": "Feature",
  "properties": {
    "gn:gn_country":"FI",
    "gn:gn_fcode":"PPLA3",
    "gn:gn_pop":217,
    "gn:population":217,
    "iso:country":"FI",
    "name:deu_x_preferred":[
        "Velkua"
    ],
    "name:eng_x_preferred":[
        "Velkua"
    ],
    "name:fas_x_preferred":[
        "\u0648\u0644\u06a9\u0648\u0627"
    ],
    "name:fin_x_preferred":[
        "Velkua"
    ],
    "name:fra_x_preferred":[
        "Velkua"
    ],
    "name:ita_x_preferred":[
        "Velkua"
    ],
    "name:nld_x_preferred":[
        "Velkua"
    ],
    "name:nob_x_preferred":[
        "Velkua"
    ],
    "name:ron_x_preferred":[
        "Velkua"
    ],
    "name:sme_x_preferred":[
        "Velkua"
    ],
    "name:swe_x_preferred":[
        "Velkua"
    ],
    "name:vie_x_preferred":[
        "Velkua"
    ],
    "qs_pg:aaroncc":"FI",
    "qs_pg:gn_country":"FI",
    "qs_pg:gn_fcode":"PPLA3",
    "qs_pg:gn_pop":217,
    "qs_pg:name":"Velkua",
    "qs_pg:photos_9r":0,
    "qs_pg:photos_sr":0,
    "qs_pg:pop_sr":2,
    "qs_pg:qs_pg_placetype":"locality",
    "wof:name":"Velkua",
    "wof:placetype":"locality",
    "wof:population":217
},
  "geometry": {"coordinates":[21.66667,60.46667],"type":"Point"}
}