{
  "type": "Feature",
  "properties": {
    "gn:admin1_code":"11.0",
    "gn:admin2_code":"111.0",
    "gn:admin3_code":"140.0",
    "gn:asciiname":"Hirviaho",
    "gn:country_code":"FI",
    "gn:dem":112,
    "gn:feature_class":"P",
    "gn:feature_code":"PPL",
    "gn:name":"Hirviaho",
    "gn:population":0,
    "gn:timezone":"Europe/Helsinki",
    "iso:country":"FI",
    "wof:name":"Hirviaho",
    "wof:placetype":"locality"
},
  "geometry": {"coordinates":[26.81667,63.56667],"type":"Point"}
}