{
  "type": "Feature",
  "properties": {
    "gn:admin1_code":"8.0",
    "gn:admin2_code":"81.0",
    "gn:admin3_code":"142.0",
    "gn:asciiname":"Kujansuu",
    "gn:country_code":"FI",
    "gn:dem":86,
    "gn:feature_class":"P",
    "gn:feature_code":"PPL",
    "gn:name":"Kujansuu",
    "gn:population":0,
    "gn:timezone":"Europe/Helsinki",
    "iso:country":"FI",
    "wof:name":"Kujansuu",
    "wof:placetype":"locality"
},
  "geometry": {"coordinates":[26.26237,60.86038000000001],"type":"Point"}
}