{
  "type": "Feature",
  "properties": {
    "gn:admin1_code":"10.0",
    "gn:admin2_code":"101.0",
    "gn:admin3_code":"491.0",
    "gn:asciiname":"Hauhala",
    "gn:cc2":"FI",
    "gn:country_code":"FI",
    "gn:dem":96,
    "gn:feature_class":"P",
    "gn:feature_code":"PPL",
    "gn:name":"Hauhala",
    "gn:population":0,
    "gn:timezone":"Europe/Helsinki",
    "iso:country":"FI",
    "name:und_x_variant":[
        "Hauhola"
    ],
    "wof:name":"Hauhala",
    "wof:placetype":"locality"
},
  "geometry": {"coordinates":[27.73838,61.53252],"type":"Point"}
}