{
  "type": "Feature",
  "properties": {
    "gn:admin1_code":"15.0",
    "gn:admin2_code":"153.0",
    "gn:admin3_code":"287.0",
    "gn:asciiname":"Langasmossen",
    "gn:country_code":"FI",
    "gn:dem":23,
    "gn:feature_class":"P",
    "gn:feature_code":"PPL",
    "gn:name":"L\u00e5ng\u00e5smossen",
    "gn:population":0,
    "gn:timezone":"Europe/Helsinki",
    "iso:country":"FI",
    "wof:name":"Langasmossen",
    "wof:placetype":"locality"
},
  "geometry": {"coordinates":[21.45094,62.33075],"type":"Point"}
}