{
  "type": "Feature",
  "properties": {
    "gn:admin1_code":"15.0",
    "gn:admin2_code":"154.0",
    "gn:admin3_code":"288.0",
    "gn:asciiname":"OEverbratoe",
    "gn:country_code":"FI",
    "gn:dem":12,
    "gn:feature_class":"P",
    "gn:feature_code":"PPL",
    "gn:name":"\u00d6verbr\u00e5t\u00f6",
    "gn:population":0,
    "gn:timezone":"Europe/Helsinki",
    "iso:country":"FI",
    "wof:name":"OEverbratoe",
    "wof:placetype":"locality"
},
  "geometry": {"coordinates":[23.03932,63.7288],"type":"Point"}
}