{
  "type": "Feature",
  "properties": {
    "gn:admin1_code":"16.0",
    "gn:admin2_code":"161.0",
    "gn:admin3_code":"74.0",
    "gn:asciiname":"Kanala",
    "gn:country_code":"FI",
    "gn:dem":150,
    "gn:feature_class":"P",
    "gn:feature_code":"PPL",
    "gn:name":"Kanala",
    "gn:population":0,
    "gn:timezone":"Europe/Helsinki",
    "iso:country":"FI",
    "wof:name":"Kanala",
    "wof:placetype":"locality"
},
  "geometry": {"coordinates":[24.40935,63.47034],"type":"Point"}
}