{
  "type": "Feature",
  "properties": {
    "gn:admin1_code":"1.0",
    "gn:admin2_code":"11.0",
    "gn:admin3_code":"755.0",
    "gn:asciiname":"Poelans",
    "gn:country_code":"FI",
    "gn:dem":36,
    "gn:feature_class":"P",
    "gn:feature_code":"PPL",
    "gn:name":"P\u00f6lans",
    "gn:population":0,
    "gn:timezone":"Europe/Helsinki",
    "iso:country":"FI",
    "wof:name":"Poelans",
    "wof:placetype":"locality"
},
  "geometry": {"coordinates":[24.03174,60.16741999999999],"type":"Point"}
}