{
  "type": "Feature",
  "properties": {
    "iso:country":"FI",
    "qs:a0":"Suomi#Finland",
    "qs:a1":"*Etel\u00e4-Karjala#S\u00f6dra Karelen",
    "qs:a1r":"0Etel\u00e4-Suomen AVI#S\u00f6dra Finlands RFV",
    "qs:adm0":"Suomi#Finland",
    "qs:la_lc":"*",
    "qs:level":"locality",
    "qs:loc":"Rautj\u00e4rven kk.",
    "qs:loc_alt":"Rautjarven kk.",
    "qs:pop":0,
    "qs:type":"buffered point",
    "wof:name":"Rautj\u00e4rven kk.",
    "wof:placetype":"locality"
},
  "geometry": {"coordinates":[29.076915,61.294155],"type":"Point"}
}