{
  "type": "Feature",
  "properties": {
    "gn:admin1_code":"11.0",
    "gn:admin2_code":"111.0",
    "gn:admin3_code":"263.0",
    "gn:asciiname":"Rytky",
    "gn:country_code":"FI",
    "gn:dem":116,
    "gn:feature_class":"P",
    "gn:feature_code":"PPL",
    "gn:name":"Rytky",
    "gn:population":0,
    "gn:timezone":"Europe/Helsinki",
    "iso:country":"FI",
    "wof:name":"Rytky",
    "wof:placetype":"locality"
},
  "geometry": {"coordinates":[26.56881,63.51084],"type":"Point"}
}