{
  "type": "Feature",
  "properties": {
    "gn:country":"FI",
    "gn:fcode":"PPL",
    "gn:population":0,
    "iso:country":"FI",
    "name:eng_x_preferred":[
        "Onkiniemi"
    ],
    "name:rus_x_preferred":[
        "\u041e\u043d\u043a\u0438\u043d\u0438\u0435\u043c\u0438"
    ],
    "qs_pg:aaroncc":"FI",
    "qs_pg:gn_country":"FI",
    "qs_pg:gn_fcode":"PPL",
    "qs_pg:gn_pop":0,
    "qs_pg:name":"Onkiniemi",
    "qs_pg:name_adm0":"Suomi",
    "qs_pg:name_adm1":"P\u00e4ijat-H\u00e4meen maakunta",
    "qs_pg:photos":17,
    "qs_pg:photos_1k":3,
    "qs_pg:photos_9k":1,
    "qs_pg:photos_9r":1,
    "qs_pg:photos_all":17,
    "qs_pg:photos_sr":1,
    "qs_pg:pop_sr":0,
    "qs_pg:qs_pg_placetype":"locality",
    "qs_pg:qs_pg_placetype_gp":"Town",
    "qs_pg:woe_adm0":23424812,
    "woe:adm0_id":23424812,
    "woe:name_adm0":"Suomi",
    "woe:name_adm1":"P\u00e4ijat-H\u00e4meen maakunta",
    "woe:placetype":"Town",
    "wof:name":"Onkiniemi",
    "wof:placetype":"locality"
},
  "geometry": {"coordinates":[26.03333,61.41667],"type":"Point"}
}