{
  "type": "Feature",
  "properties": {
    "gn:admin1_code":"8.0",
    "gn:admin2_code":"82.0",
    "gn:admin3_code":"75.0",
    "gn:asciiname":"Suortti",
    "gn:country_code":"FI",
    "gn:dem":2,
    "gn:feature_class":"P",
    "gn:feature_code":"PPL",
    "gn:name":"Suortti",
    "gn:population":0,
    "gn:timezone":"Europe/Helsinki",
    "iso:country":"FI",
    "wof:name":"Suortti",
    "wof:placetype":"locality"
},
  "geometry": {"coordinates":[27.09924,60.5576],"type":"Point"}
}