{
  "type": "Feature",
  "properties": {
    "gn:admin1_code":"9.0",
    "gn:admin2_code":"91.0",
    "gn:admin3_code":"416.0",
    "gn:asciiname":"Narttu",
    "gn:country_code":"FI",
    "gn:dem":97,
    "gn:feature_class":"P",
    "gn:feature_code":"PPLF",
    "gn:name":"Narttu",
    "gn:population":0,
    "gn:timezone":"Europe/Helsinki",
    "iso:country":"FI",
    "wof:name":"Narttu",
    "wof:placetype":"locality"
},
  "geometry": {"coordinates":[27.78786,61.04664],"type":"Point"}
}