{
  "type": "Feature",
  "properties": {
    "gn:admin1_code":"2.0",
    "gn:admin2_code":"23.0",
    "gn:admin3_code":"503.0",
    "gn:asciiname":"Lemmi",
    "gn:cc2":"FI",
    "gn:country_code":"FI",
    "gn:dem":29,
    "gn:feature_class":"P",
    "gn:feature_code":"PPL",
    "gn:name":"Lemmi",
    "gn:population":0,
    "gn:timezone":"Europe/Helsinki",
    "iso:country":"FI",
    "name:und_x_variant":[
        "Lemminkulma"
    ],
    "wof:name":"Lemmi",
    "wof:placetype":"locality"
},
  "geometry": {"coordinates":[21.92065,60.79111],"type":"Point"}
}