{
  "type": "Feature",
  "properties": {
    "gn:admin1_code":"2.0",
    "gn:admin2_code":"23.0",
    "gn:admin3_code":"202.0",
    "gn:asciiname":"Hiirlae",
    "gn:country_code":"FI",
    "gn:dem":-9999,
    "gn:feature_class":"P",
    "gn:feature_code":"PPL",
    "gn:name":"Hiirl\u00e4",
    "gn:population":0,
    "gn:timezone":"Europe/Helsinki",
    "iso:country":"FI",
    "wof:name":"Hiirlae",
    "wof:placetype":"locality"
},
  "geometry": {"coordinates":[22.53333,60.38333000000001],"type":"Point"}
}