{
  "type": "Feature",
  "properties": {
    "gn:admin1_code":"18.0",
    "gn:admin2_code":"181.0",
    "gn:admin3_code":"290.0",
    "gn:asciiname":"Huuskonvaara",
    "gn:country_code":"FI",
    "gn:dem":237,
    "gn:feature_class":"P",
    "gn:feature_code":"PPL",
    "gn:name":"Huuskonvaara",
    "gn:population":0,
    "gn:timezone":"Europe/Helsinki",
    "iso:country":"FI",
    "wof:name":"Huuskonvaara",
    "wof:placetype":"locality"
},
  "geometry": {"coordinates":[30.26667,64.18333],"type":"Point"}
}