{
  "type": "Feature",
  "properties": {
    "gn:admin1_code":"12.0",
    "gn:admin2_code":"122.0",
    "gn:admin3_code":"176.0",
    "gn:asciiname":"Kuhnusta",
    "gn:country_code":"FI",
    "gn:dem":109,
    "gn:feature_class":"P",
    "gn:feature_code":"PPL",
    "gn:name":"Kuhnusta",
    "gn:population":0,
    "gn:timezone":"Europe/Helsinki",
    "iso:country":"FI",
    "wof:name":"Kuhnusta",
    "wof:placetype":"locality"
},
  "geometry": {"coordinates":[29.46705,63.08812],"type":"Point"}
}