{
  "type": "Feature",
  "properties": {
    "gn:admin1_code":"13.0",
    "gn:admin2_code":"134.0",
    "gn:admin3_code":"182.0",
    "gn:asciiname":"Yijaelae",
    "gn:country_code":"FI",
    "gn:dem":98,
    "gn:feature_class":"P",
    "gn:feature_code":"PPL",
    "gn:name":"Yij\u00e4l\u00e4",
    "gn:population":0,
    "gn:timezone":"Europe/Helsinki",
    "iso:country":"FI",
    "name:fin_x_preferred":[
        "Yij\u00e4l\u00e4"
    ],
    "wof:name":"Yijaelae",
    "wof:placetype":"locality"
},
  "geometry": {"coordinates":[25.2623,61.88947],"type":"Point"}
}