{
  "type": "Feature",
  "properties": {
    "gn:admin1_code":"8.0",
    "gn:admin2_code":"82.0",
    "gn:admin3_code":"75.0",
    "gn:asciiname":"Turkia",
    "gn:country_code":"FI",
    "gn:dem":54,
    "gn:feature_class":"P",
    "gn:feature_code":"PPL",
    "gn:name":"Turkia",
    "gn:population":0,
    "gn:timezone":"Europe/Helsinki",
    "iso:country":"FI",
    "wof:name":"Turkia",
    "wof:placetype":"locality"
},
  "geometry": {"coordinates":[27.31044,60.7632],"type":"Point"}
}