{
  "type": "Feature",
  "properties": {
    "gn:admin1_code":"8.0",
    "gn:admin2_code":"82.0",
    "gn:admin3_code":"624.0",
    "gn:asciiname":"Mokra",
    "gn:country_code":"FI",
    "gn:dem":1,
    "gn:feature_class":"P",
    "gn:feature_code":"PPL",
    "gn:name":"Mokra",
    "gn:population":0,
    "gn:timezone":"Europe/Helsinki",
    "iso:country":"FI",
    "name:bul_x_preferred":[
        "\u041c\u043e\u043a\u0440\u0430"
    ],
    "name:ceb_x_preferred":[
        "Mokra"
    ],
    "name:fra_x_preferred":[
        "Mokra"
    ],
    "name:hun_x_preferred":[
        "Mokra"
    ],
    "name:pol_x_preferred":[
        "Mokra"
    ],
    "name:slv_x_preferred":[
        "Mokra"
    ],
    "name:swe_x_preferred":[
        "Mokra"
    ],
    "name:ukr_x_preferred":[
        "\u041c\u043e\u043a\u0440\u0430"
    ],
    "wof:name":"Mokra",
    "wof:placetype":"locality"
},
  "geometry": {"coordinates":[26.80488,60.48985],"type":"Point"}
}