{
  "type": "Feature",
  "properties": {
    "gn:admin1_code":"2.0",
    "gn:admin2_code":"22.0",
    "gn:admin3_code":"734.0",
    "gn:asciiname":"Pettu",
    "gn:country_code":"FI",
    "gn:dem":-9999,
    "gn:feature_class":"P",
    "gn:feature_code":"PPL",
    "gn:name":"Pettu",
    "gn:population":0,
    "gn:timezone":"Europe/Helsinki",
    "iso:country":"FI",
    "wof:name":"Pettu",
    "wof:placetype":"locality"
},
  "geometry": {"coordinates":[22.96667,60.03333000000001],"type":"Point"}
}