{
  "type": "Feature",
  "properties": {
    "gn:admin1_code":"15.0",
    "gn:admin2_code":"154.0",
    "gn:admin3_code":"599.0",
    "gn:asciiname":"Bonds",
    "gn:country_code":"FI",
    "gn:dem":28,
    "gn:feature_class":"P",
    "gn:feature_code":"PPL",
    "gn:name":"Bonds",
    "gn:population":0,
    "gn:timezone":"Europe/Helsinki",
    "iso:country":"FI",
    "name:deu_x_preferred":[
        "Bonds"
    ],
    "name:rus_x_preferred":[
        "\u0411\u043e\u043d\u0434\u0441"
    ],
    "wof:name":"Bonds",
    "wof:placetype":"locality"
},
  "geometry": {"coordinates":[22.93637,63.53534000000001],"type":"Point"}
}