{
  "type": "Feature",
  "properties": {
    "gn:admin1_code":"8.0",
    "gn:admin2_code":"81.0",
    "gn:admin3_code":"286.0",
    "gn:asciiname":"Lapinniemi",
    "gn:country_code":"FI",
    "gn:dem":115,
    "gn:feature_class":"P",
    "gn:feature_code":"PPL",
    "gn:name":"Lapinniemi",
    "gn:population":0,
    "gn:timezone":"Europe/Helsinki",
    "iso:country":"FI",
    "wof:name":"Lapinniemi",
    "wof:placetype":"locality"
},
  "geometry": {"coordinates":[26.78333,61.18333000000001],"type":"Point"}
}