{
  "type": "Feature",
  "properties": {
    "gn:admin1_code":"14.0",
    "gn:admin2_code":"141.0",
    "gn:admin3_code":"218.0",
    "gn:asciiname":"Alakuja",
    "gn:country_code":"FI",
    "gn:dem":41,
    "gn:feature_class":"P",
    "gn:feature_code":"PPL",
    "gn:name":"Alakuja",
    "gn:population":0,
    "gn:timezone":"Europe/Helsinki",
    "iso:country":"FI",
    "wof:name":"Alakuja",
    "wof:placetype":"locality"
},
  "geometry": {"coordinates":[21.68878,62.2674],"type":"Point"}
}