{
  "type": "Feature",
  "properties": {
    "gn:admin1_code":"15.0",
    "gn:admin2_code":"153.0",
    "gn:admin3_code":"545.0",
    "gn:asciiname":"Stalgrinden",
    "gn:country_code":"FI",
    "gn:dem":23,
    "gn:feature_class":"P",
    "gn:feature_code":"PPL",
    "gn:name":"St\u00e5lgrinden",
    "gn:population":0,
    "gn:timezone":"Europe/Helsinki",
    "iso:country":"FI",
    "wof:name":"Stalgrinden",
    "wof:placetype":"locality"
},
  "geometry": {"coordinates":[21.44308,62.75095],"type":"Point"}
}