{
  "type": "Feature",
  "properties": {
    "gn:admin1_code":"19.0",
    "gn:admin2_code":"193.0",
    "gn:admin3_code":"854.0",
    "gn:asciiname":"Riipisenvaara",
    "gn:country_code":"FI",
    "gn:dem":141,
    "gn:feature_class":"P",
    "gn:feature_code":"PPL",
    "gn:name":"Riipisenvaara",
    "gn:population":0,
    "gn:timezone":"Europe/Helsinki",
    "iso:country":"FI",
    "name:fin_x_preferred":[
        "Riipisenvaara"
    ],
    "wof:name":"Riipisenvaara",
    "wof:placetype":"locality"
},
  "geometry": {"coordinates":[24.07788,66.93758000000001],"type":"Point"}
}