{
  "type": "Feature",
  "properties": {
    "gn:admin1_code":"12.0",
    "gn:admin2_code":"124.0",
    "gn:admin3_code":"260.0",
    "gn:asciiname":"Asikkala",
    "gn:country_code":"FI",
    "gn:dem":103,
    "gn:feature_class":"P",
    "gn:feature_code":"PPL",
    "gn:name":"Asikkala",
    "gn:population":0,
    "gn:timezone":"Europe/Helsinki",
    "iso:country":"FI",
    "name:ceb_x_preferred":[
        "Asikkala"
    ],
    "name:deu_x_preferred":[
        "Asikkala"
    ],
    "name:est_x_preferred":[
        "Asikkala vald"
    ],
    "name:fin_x_preferred":[
        "Asikkala"
    ],
    "name:fra_x_preferred":[
        "Asikkala"
    ],
    "name:glg_x_preferred":[
        "Asikkala"
    ],
    "name:ita_x_preferred":[
        "Asikkala"
    ],
    "name:kor_x_preferred":[
        "\uc544\uc2dc\uce7c\ub77c"
    ],
    "name:nld_x_preferred":[
        "Asikkala"
    ],
    "name:nno_x_preferred":[
        "Asikkala"
    ],
    "name:nor_x_preferred":[
        "Asikkala"
    ],
    "name:pol_x_preferred":[
        "Asikkala"
    ],
    "name:ron_x_preferred":[
        "Asikkala"
    ],
    "name:rus_x_preferred":[
        "\u0410\u0441\u0438\u043a\u043a\u0430\u043b\u0430"
    ],
    "name:sme_x_preferred":[
        "Asikkala"
    ],
    "name:spa_x_preferred":[
        "Asikkala"
    ],
    "name:sqi_x_preferred":[
        "Asikkala"
    ],
    "name:swe_x_preferred":[
        "Asikkala"
    ],
    "name:szl_x_preferred":[
        "Asikkala"
    ],
    "name:tur_x_preferred":[
        "Asikkala"
    ],
    "name:zho_x_preferred":[
        "\u963f\u897f\u5361\u62c9"
    ],
    "wof:name":"Asikkala",
    "wof:placetype":"locality"
},
  "geometry": {"coordinates":[29.66667,62.06667],"type":"Point"}
}