{
  "type": "Feature",
  "properties": {
    "gn:admin1_code":"19.0",
    "gn:admin2_code":"192.0",
    "gn:admin3_code":"851.0",
    "gn:asciiname":"Roeyttae",
    "gn:country_code":"FI",
    "gn:dem":5,
    "gn:feature_class":"P",
    "gn:feature_code":"PPL",
    "gn:name":"R\u00f6ytt\u00e4",
    "gn:population":0,
    "gn:timezone":"Europe/Helsinki",
    "iso:country":"FI",
    "wof:name":"Roeyttae",
    "wof:placetype":"locality"
},
  "geometry": {"coordinates":[24.15237,65.76058],"type":"Point"}
}