{
  "type": "Feature",
  "properties": {
    "gn:admin1_code":"6.0",
    "gn:admin2_code":"61.0",
    "gn:admin3_code":"143.0",
    "gn:asciiname":"Kotamaeenperae",
    "gn:country_code":"FI",
    "gn:dem":133,
    "gn:feature_class":"P",
    "gn:feature_code":"PPL",
    "gn:name":"Kotam\u00e4enper\u00e4",
    "gn:population":0,
    "gn:timezone":"Europe/Helsinki",
    "iso:country":"FI",
    "name:und_x_variant":[
        "Kotam\u00e4enper\u00e4",
        "Kotam\u00e4ki"
    ],
    "wof:name":"Kotamaeenperae",
    "wof:placetype":"locality"
},
  "geometry": {"coordinates":[22.83954,61.85625],"type":"Point"}
}