{
  "type": "Feature",
  "properties": {
    "gn:admin1_code":"15.0",
    "gn:admin2_code":"154.0",
    "gn:admin3_code":"893.0",
    "gn:asciiname":"Romar",
    "gn:country_code":"FI",
    "gn:dem":19,
    "gn:feature_class":"P",
    "gn:feature_code":"PPL",
    "gn:name":"Romar",
    "gn:population":0,
    "gn:timezone":"Europe/Helsinki",
    "iso:country":"FI",
    "wof:name":"Romar",
    "wof:placetype":"locality"
},
  "geometry": {"coordinates":[22.63684,63.41552],"type":"Point"}
}