{
  "type": "Feature",
  "properties": {
    "gn:admin1_code":"10.0",
    "gn:admin2_code":"103.0",
    "gn:admin3_code":"740.0",
    "gn:asciiname":"Nikaniemi",
    "gn:country_code":"FI",
    "gn:dem":88,
    "gn:feature_class":"P",
    "gn:feature_code":"PPL",
    "gn:name":"Nikaniemi",
    "gn:population":0,
    "gn:timezone":"Europe/Helsinki",
    "iso:country":"FI",
    "wof:name":"Nikaniemi",
    "wof:placetype":"locality"
},
  "geometry": {"coordinates":[29.17018,61.68474000000001],"type":"Point"}
}