{
  "type": "Feature",
  "properties": {
    "gn:admin1_code":"13.0",
    "gn:admin2_code":"134.0",
    "gn:admin3_code":"291.0",
    "gn:asciiname":"Harmoinen",
    "gn:country_code":"FI",
    "gn:dem":135,
    "gn:feature_class":"P",
    "gn:feature_code":"PPL",
    "gn:name":"Harmoinen",
    "gn:population":0,
    "gn:timezone":"Europe/Helsinki",
    "iso:country":"FI",
    "name:eng_x_preferred":[
        "Harmoinen"
    ],
    "name:rus_x_preferred":[
        "\u0425\u0430\u0440\u043c\u043e\u0439\u043d\u0435\u043d"
    ],
    "wof:name":"Harmoinen",
    "wof:placetype":"locality"
},
  "geometry": {"coordinates":[25.12852,61.48848],"type":"Point"}
}