{
  "type": "Feature",
  "properties": {
    "gn:country":"FI",
    "gn:fcode":"PPL",
    "gn:population":0,
    "iso:country":"FI",
    "name:dan_x_preferred":[
        "Dunkars"
    ],
    "name:isl_x_preferred":[
        "Dunkars"
    ],
    "name:nor_x_preferred":[
        "Dunkars"
    ],
    "name:swe_x_preferred":[
        "Dunkars"
    ],
    "qs_pg:aaroncc":"FI",
    "qs_pg:gn_country":"FI",
    "qs_pg:gn_fcode":"PPL",
    "qs_pg:gn_pop":0,
    "qs_pg:name":"Tunkkari",
    "qs_pg:name_adm0":"Suomi",
    "qs_pg:name_adm1":"Keski-Pohjanmaan maakunta",
    "qs_pg:photos":7,
    "qs_pg:photos_1k":1,
    "qs_pg:photos_9k":1,
    "qs_pg:photos_9r":1,
    "qs_pg:photos_all":7,
    "qs_pg:photos_sr":1,
    "qs_pg:pop_sr":0,
    "qs_pg:qs_pg_placetype":"locality",
    "qs_pg:qs_pg_placetype_gp":"Town",
    "qs_pg:woe_adm0":23424812,
    "woe:adm0_id":23424812,
    "woe:name_adm0":"Suomi",
    "woe:name_adm1":"Keski-Pohjanmaan maakunta",
    "woe:placetype":"Town",
    "wof:name":"Tunkkari",
    "wof:placetype":"locality"
},
  "geometry": {"coordinates":[23.75,63.48333],"type":"Point"}
}