{
  "type": "Feature",
  "properties": {
    "gn:admin1_code":"17.0",
    "gn:admin2_code":"175.0",
    "gn:admin3_code":"630.0",
    "gn:asciiname":"Kamula",
    "gn:country_code":"FI",
    "gn:dem":146,
    "gn:feature_class":"P",
    "gn:feature_code":"PPL",
    "gn:name":"Kamula",
    "gn:population":0,
    "gn:timezone":"Europe/Helsinki",
    "iso:country":"FI",
    "name:eng_x_preferred":[
        "Kamula"
    ],
    "name:rus_x_preferred":[
        "\u041a\u0430\u043c\u0443\u043b\u0430"
    ],
    "wof:name":"Kamula",
    "wof:placetype":"locality"
},
  "geometry": {"coordinates":[26.28333,64.11667],"type":"Point"}
}