{
  "type": "Feature",
  "properties": {
    "gn:admin1_code":"14.0",
    "gn:admin2_code":"142.0",
    "gn:admin3_code":"145.0",
    "gn:asciiname":"Nikkola",
    "gn:country_code":"FI",
    "gn:dem":43,
    "gn:feature_class":"P",
    "gn:feature_code":"PPL",
    "gn:name":"Nikkola",
    "gn:population":0,
    "gn:timezone":"Europe/Helsinki",
    "iso:country":"FI",
    "wof:name":"Nikkola",
    "wof:placetype":"locality"
},
  "geometry": {"coordinates":[22.59033,62.75614],"type":"Point"}
}