{
  "type": "Feature",
  "properties": {
    "iso:country":"FI",
    "name:eng_x_preferred":[
        "Etel\u00e4inen"
    ],
    "name:rus_x_preferred":[
        "\u042d\u0442\u0435\u043b\u044f\u0439\u043d\u0435\u043d"
    ],
    "qs:a0":"Suomi#Finland",
    "qs:a1":"*Kanta-H\u00e4me#Egentliga Tavastland",
    "qs:a1r":"0Etel\u00e4-Suomen AVI#S\u00f6dra Finlands RFV",
    "qs:adm0":"Suomi#Finland",
    "qs:la_lc":"*",
    "qs:level":"locality",
    "qs:loc":"Etel\u00e4inen",
    "qs:loc_alt":"Etelainen",
    "qs:pop":0,
    "qs:type":"buffered point",
    "wof:name":"Etel\u00e4inen",
    "wof:placetype":"locality"
},
  "geometry": {"coordinates":[24.699219,61.070973],"type":"Point"}
}