{
  "type": "Feature",
  "properties": {
    "gn:admin1_code":"17.0",
    "gn:admin2_code":"177.0",
    "gn:admin3_code":"746.0",
    "gn:asciiname":"Koivuoja",
    "gn:country_code":"FI",
    "gn:dem":81,
    "gn:feature_class":"P",
    "gn:feature_code":"PPL",
    "gn:name":"Koivuoja",
    "gn:population":0,
    "gn:timezone":"Europe/Helsinki",
    "iso:country":"FI",
    "wof:name":"Koivuoja",
    "wof:placetype":"locality"
},
  "geometry": {"coordinates":[24.22939,63.92231],"type":"Point"}
}