{
  "type": "Feature",
  "properties": {
    "gn:admin1_code":"2.0",
    "gn:admin2_code":"25.0",
    "gn:admin3_code":"430.0",
    "gn:asciiname":"Kojo",
    "gn:country_code":"FI",
    "gn:dem":90,
    "gn:feature_class":"P",
    "gn:feature_code":"PPL",
    "gn:name":"Kojo",
    "gn:population":0,
    "gn:timezone":"Europe/Helsinki",
    "iso:country":"FI",
    "wof:name":"Kojo",
    "wof:placetype":"locality"
},
  "geometry": {"coordinates":[22.95337,60.95462],"type":"Point"}
}