{
  "type": "Feature",
  "properties": {
    "gn:admin1_code":"11.0",
    "gn:admin2_code":"111.0",
    "gn:admin3_code":"595.0",
    "gn:asciiname":"Laensi-Saeviae",
    "gn:country_code":"FI",
    "gn:dem":113,
    "gn:feature_class":"P",
    "gn:feature_code":"PPL",
    "gn:name":"L\u00e4nsi-S\u00e4vi\u00e4",
    "gn:population":0,
    "gn:timezone":"Europe/Helsinki",
    "iso:country":"FI",
    "wof:name":"Laensi-Saeviae",
    "wof:placetype":"locality"
},
  "geometry": {"coordinates":[26.51898,63.21543000000001],"type":"Point"}
}