{
  "type": "Feature",
  "properties": {
    "gn:admin1_code":"6.0",
    "gn:admin2_code":"61.0",
    "gn:admin3_code":"143.0",
    "gn:asciiname":"Latovesi",
    "gn:country_code":"FI",
    "gn:dem":158,
    "gn:feature_class":"P",
    "gn:feature_code":"PPL",
    "gn:name":"Latovesi",
    "gn:population":0,
    "gn:timezone":"Europe/Helsinki",
    "iso:country":"FI",
    "wof:name":"Latovesi",
    "wof:placetype":"locality"
},
  "geometry": {"coordinates":[23.31667,61.88333000000001],"type":"Point"}
}