{
  "type": "Feature",
  "properties": {
    "gn:admin1_code":"13.0",
    "gn:admin2_code":"135.0",
    "gn:admin3_code":"992.0",
    "gn:asciiname":"Jaervenpaeae",
    "gn:country_code":"FI",
    "gn:dem":157,
    "gn:feature_class":"P",
    "gn:feature_code":"PPL",
    "gn:name":"J\u00e4rvenp\u00e4\u00e4",
    "gn:population":0,
    "gn:timezone":"Europe/Helsinki",
    "iso:country":"FI",
    "wof:name":"Jaervenpaeae",
    "wof:placetype":"locality"
},
  "geometry": {"coordinates":[25.55826,62.70865],"type":"Point"}
}