{
  "type": "Feature",
  "properties": {
    "gn:admin1_code":"8.0",
    "gn:admin2_code":"82.0",
    "gn:admin3_code":"489.0",
    "gn:asciiname":"Muurola",
    "gn:cc2":"FI",
    "gn:country_code":"FI",
    "gn:dem":47,
    "gn:feature_class":"P",
    "gn:feature_code":"PPL",
    "gn:name":"Muurola",
    "gn:population":0,
    "gn:timezone":"Europe/Helsinki",
    "iso:country":"FI",
    "name:eng_x_preferred":[
        "Muurola"
    ],
    "name:rus_x_preferred":[
        "\u041c\u0443\u0440\u043e\u043b\u0430"
    ],
    "name:und_x_variant":[
        "Muurala"
    ],
    "wof:name":"Muurola",
    "wof:placetype":"locality"
},
  "geometry": {"coordinates":[27.62956,60.77443],"type":"Point"}
}