{
  "type": "Feature",
  "properties": {
    "gn:admin1_code":"1.0",
    "gn:admin2_code":"14.0",
    "gn:admin3_code":"149.0",
    "gn:asciiname":"Gumboele",
    "gn:country_code":"FI",
    "gn:dem":45,
    "gn:feature_class":"P",
    "gn:feature_code":"PPL",
    "gn:name":"Gumb\u00f6le",
    "gn:population":0,
    "gn:timezone":"Europe/Helsinki",
    "iso:country":"FI",
    "wof:name":"Gumboele",
    "wof:placetype":"locality"
},
  "geometry": {"coordinates":[23.91271,60.08886],"type":"Point"}
}