{
  "type": "Feature",
  "properties": {
    "gn:admin1_code":"5.0",
    "gn:admin2_code":"51.0",
    "gn:admin3_code":"109.0",
    "gn:asciiname":"Ohtinen",
    "gn:country_code":"FI",
    "gn:dem":104,
    "gn:feature_class":"P",
    "gn:feature_code":"PPL",
    "gn:name":"Ohtinen",
    "gn:population":0,
    "gn:timezone":"Europe/Helsinki",
    "iso:country":"FI",
    "wof:name":"Ohtinen",
    "wof:placetype":"locality"
},
  "geometry": {"coordinates":[23.94733,61.05891999999999],"type":"Point"}
}