{
  "type": "Feature",
  "properties": {
    "gn:admin1_code":"6.0",
    "gn:admin2_code":"69.0",
    "gn:admin3_code":"702.0",
    "gn:asciiname":"Mommo",
    "gn:cc2":"FI",
    "gn:country_code":"FI",
    "gn:dem":161,
    "gn:feature_class":"P",
    "gn:feature_code":"PPL",
    "gn:name":"Mommo",
    "gn:population":0,
    "gn:timezone":"Europe/Helsinki",
    "iso:country":"FI",
    "name:und_x_variant":[
        "Memmo",
        "Mommo"
    ],
    "wof:name":"Mommo",
    "wof:placetype":"locality"
},
  "geometry": {"coordinates":[24.03333,61.88333000000001],"type":"Point"}
}