{
  "type": "Feature",
  "properties": {
    "gn:gn_country":"FI",
    "gn:gn_fcode":"PPL",
    "gn:gn_pop":0,
    "iso:country":"FI",
    "name:eng_x_preferred":[
        "Oravi"
    ],
    "name:rus_x_preferred":[
        "\u041e\u0440\u0430\u0432\u0438"
    ],
    "qs_pg:aaroncc":"FI",
    "qs_pg:gn_country":"FI",
    "qs_pg:gn_fcode":"PPL",
    "qs_pg:gn_pop":0,
    "qs_pg:name":"Oravi",
    "qs_pg:name_adm0":"Suomi",
    "qs_pg:name_adm1":"Etel\u00e4-Savon maakunta",
    "qs_pg:photos":379,
    "qs_pg:photos_1k":77,
    "qs_pg:photos_9k":2,
    "qs_pg:photos_9r":5,
    "qs_pg:photos_all":379,
    "qs_pg:photos_sr":6,
    "qs_pg:pop_sr":0,
    "qs_pg:qs_pg_placetype":"locality",
    "qs_pg:qs_pg_placetype_gp":"Town",
    "qs_pg:woe_adm0":23424812,
    "woe:adm0_id":23424812,
    "woe:name_adm0":"Suomi",
    "woe:name_adm1":"Etel\u00e4-Savon maakunta",
    "woe:placetype":"Town",
    "wof:name":"Oravi",
    "wof:placetype":"locality"
},
  "geometry": {"coordinates":[28.61667,62.11667],"type":"Point"}
}