{
  "type": "Feature",
  "properties": {
    "gn:admin1_code":"6.0",
    "gn:admin2_code":"68.0",
    "gn:admin3_code":"619.0",
    "gn:asciiname":"Kouvola",
    "gn:country_code":"FI",
    "gn:dem":85,
    "gn:feature_class":"P",
    "gn:feature_code":"PPL",
    "gn:name":"Kouvola",
    "gn:population":0,
    "gn:timezone":"Europe/Helsinki",
    "iso:country":"FI",
    "wof:name":"Kouvola",
    "wof:placetype":"locality"
},
  "geometry": {"coordinates":[22.99517,61.04056],"type":"Point"}
}