{
  "type": "Feature",
  "properties": {
    "gn:admin1_code":"11.0",
    "gn:admin2_code":"112.0",
    "gn:admin3_code":"297.0",
    "gn:asciiname":"Riitavaara",
    "gn:country_code":"FI",
    "gn:dem":149,
    "gn:feature_class":"P",
    "gn:feature_code":"PPL",
    "gn:name":"Riitavaara",
    "gn:population":0,
    "gn:timezone":"Europe/Helsinki",
    "iso:country":"FI",
    "wof:name":"Riitavaara",
    "wof:placetype":"locality"
},
  "geometry": {"coordinates":[28.52961,63.12639],"type":"Point"}
}