{
  "type": "Feature",
  "properties": {
    "gn:admin1_code":"2.0",
    "gn:admin2_code":"23.0",
    "gn:admin3_code":"577.0",
    "gn:asciiname":"Preitilae",
    "gn:country_code":"FI",
    "gn:dem":40,
    "gn:feature_class":"P",
    "gn:feature_code":"PPL",
    "gn:name":"Preitil\u00e4",
    "gn:population":0,
    "gn:timezone":"Europe/Helsinki",
    "iso:country":"FI",
    "name:und_x_variant":[
        "Preil\u00e4",
        "Iso-Preitil\u00e4"
    ],
    "wof:name":"Preitilae",
    "wof:placetype":"locality"
},
  "geometry": {"coordinates":[22.73781,60.46203000000001],"type":"Point"}
}