{
  "type": "Feature",
  "properties": {
    "gn:admin1_code":"16.0",
    "gn:admin2_code":"161.0",
    "gn:admin3_code":"924.0",
    "gn:asciiname":"Vesisenaho",
    "gn:country_code":"FI",
    "gn:dem":93,
    "gn:feature_class":"P",
    "gn:feature_code":"PPL",
    "gn:name":"Vesisenaho",
    "gn:population":0,
    "gn:timezone":"Europe/Helsinki",
    "iso:country":"FI",
    "wof:name":"Vesisenaho",
    "wof:placetype":"locality"
},
  "geometry": {"coordinates":[23.75,63.41667],"type":"Point"}
}