{
  "type": "Feature",
  "properties": {
    "gn:admin1_code":"14.0",
    "gn:admin2_code":"142.0",
    "gn:admin3_code":"233.0",
    "gn:asciiname":"Lammi",
    "gn:country_code":"FI",
    "gn:dem":69,
    "gn:feature_class":"P",
    "gn:feature_code":"PPL",
    "gn:name":"Lammi",
    "gn:population":0,
    "gn:timezone":"Europe/Helsinki",
    "iso:country":"FI",
    "name:ceb_x_preferred":[
        "Lammi"
    ],
    "name:deu_x_preferred":[
        "Lammi"
    ],
    "name:est_x_preferred":[
        "Lammi vald"
    ],
    "name:eus_x_preferred":[
        "Lammi"
    ],
    "name:fin_x_preferred":[
        "Lammi"
    ],
    "name:fra_x_preferred":[
        "Lammi"
    ],
    "name:ita_x_preferred":[
        "Lammi"
    ],
    "name:nld_x_preferred":[
        "Lammi"
    ],
    "name:nor_x_preferred":[
        "Lammi"
    ],
    "name:ron_x_preferred":[
        "Lammi"
    ],
    "name:sme_x_preferred":[
        "Lammi"
    ],
    "name:swe_x_preferred":[
        "Lampis"
    ],
    "wof:name":"Lammi",
    "wof:placetype":"locality"
},
  "geometry": {"coordinates":[22.99617000000001,63.15285],"type":"Point"}
}