{
  "type": "Feature",
  "properties": {
    "gn:admin1_code":"10.0",
    "gn:admin2_code":"103.0",
    "gn:admin3_code":"46.0",
    "gn:asciiname":"Karvila",
    "gn:country_code":"FI",
    "gn:dem":135,
    "gn:feature_class":"P",
    "gn:feature_code":"PPL",
    "gn:name":"Karvila",
    "gn:population":0,
    "gn:timezone":"Europe/Helsinki",
    "iso:country":"FI",
    "wof:name":"Karvila",
    "wof:placetype":"locality"
},
  "geometry": {"coordinates":[28.89618,62.03275],"type":"Point"}
}