{
  "type": "Feature",
  "properties": {
    "gn:admin1_code":"4.0",
    "gn:admin2_code":"41.0",
    "gn:admin3_code":"51.0",
    "gn:asciiname":"Sydaenmaa",
    "gn:country_code":"FI",
    "gn:dem":31,
    "gn:feature_class":"P",
    "gn:feature_code":"PPL",
    "gn:name":"Syd\u00e4nmaa",
    "gn:population":0,
    "gn:timezone":"Europe/Helsinki",
    "iso:country":"FI",
    "wof:name":"Sydaenmaa",
    "wof:placetype":"locality"
},
  "geometry": {"coordinates":[21.85104,61.19642],"type":"Point"}
}