{
  "type": "Feature",
  "properties": {
    "gn:admin1_code":"13.0",
    "gn:admin2_code":"135.0",
    "gn:admin3_code":"275.0",
    "gn:asciiname":"Saitta",
    "gn:country_code":"FI",
    "gn:dem":103,
    "gn:feature_class":"P",
    "gn:feature_code":"PPL",
    "gn:name":"Saitta",
    "gn:population":0,
    "gn:timezone":"Europe/Helsinki",
    "iso:country":"FI",
    "wof:name":"Saitta",
    "wof:placetype":"locality"
},
  "geometry": {"coordinates":[26.31667,62.68333000000001],"type":"Point"}
}