{
  "type": "Feature",
  "properties": {
    "gn:admin1_code":"1.0",
    "gn:admin2_code":"11.0",
    "gn:admin3_code":"186.0",
    "gn:asciiname":"Heljaemaeki",
    "gn:country_code":"FI",
    "gn:dem":45,
    "gn:feature_class":"P",
    "gn:feature_code":"PPL",
    "gn:name":"Helj\u00e4m\u00e4ki",
    "gn:population":0,
    "gn:timezone":"Europe/Helsinki",
    "iso:country":"FI",
    "wof:name":"Heljaemaeki",
    "wof:placetype":"locality"
},
  "geometry": {"coordinates":[25.05083,60.45944],"type":"Point"}
}