{
  "type": "Feature",
  "properties": {
    "gn:admin1_code":"1.0",
    "gn:admin2_code":"15.0",
    "gn:admin3_code":"18.0",
    "gn:asciiname":"Vaehaekylae",
    "gn:country_code":"FI",
    "gn:dem":54,
    "gn:feature_class":"P",
    "gn:feature_code":"PPL",
    "gn:name":"V\u00e4h\u00e4kyl\u00e4",
    "gn:population":0,
    "gn:timezone":"Europe/Helsinki",
    "iso:country":"FI",
    "wof:name":"Vaehaekylae",
    "wof:placetype":"locality"
},
  "geometry": {"coordinates":[25.50515,60.49536],"type":"Point"}
}