{
  "type": "Feature",
  "properties": {
    "gn:admin1_code":"17.0",
    "gn:admin2_code":"176.0",
    "gn:admin3_code":"626.0",
    "gn:asciiname":"Kuusenmaeki",
    "gn:country_code":"FI",
    "gn:dem":191,
    "gn:feature_class":"P",
    "gn:feature_code":"PPL",
    "gn:name":"Kuusenm\u00e4ki",
    "gn:population":0,
    "gn:timezone":"Europe/Helsinki",
    "iso:country":"FI",
    "wof:name":"Kuusenmaeki",
    "wof:placetype":"locality"
},
  "geometry": {"coordinates":[26.17736,63.68745],"type":"Point"}
}