{
  "type": "Feature",
  "properties": {
    "gn:gn_country":"FI",
    "gn:gn_fcode":"PPL",
    "gn:gn_pop":5834,
    "iso:country":"FI",
    "name:dut_x_preferred":[
        "Pieks\u00e4m\u00e4en maalaiskunta"
    ],
    "name:eng_x_preferred":[
        "Pieks\u00e4m\u00e4en maalaiskunta"
    ],
    "name:fin_x_preferred":[
        "Pieks\u00e4m\u00e4en maalaiskunta"
    ],
    "name:ger_x_preferred":[
        "Pieks\u00e4m\u00e4en maalaiskunta"
    ],
    "name:nob_x_preferred":[
        "Pieks\u00e4m\u00e4ki landkommune"
    ],
    "name:swe_x_preferred":[
        "Pieks\u00e4m\u00e4ki landskommun"
    ],
    "qs_pg:aaroncc":"FI",
    "qs_pg:gn_country":"FI",
    "qs_pg:gn_fcode":"PPL",
    "qs_pg:gn_pop":5834,
    "qs_pg:name":"Pieks\u00e4m\u00e4en Maalaiskunta",
    "qs_pg:photos_9r":0,
    "qs_pg:photos_sr":0,
    "qs_pg:pop_sr":5,
    "qs_pg:qs_pg_placetype":"locality",
    "wof:name":"Pieks\u00e4m\u00e4en Maalaiskunta",
    "wof:placetype":"locality",
    "wof:population":5834
},
  "geometry": {"coordinates":[27.06667,62.28333],"type":"Point"}
}