{
  "type": "Feature",
  "properties": {
    "gn:gn_country":"FI",
    "gn:gn_fcode":"PPL",
    "gn:gn_pop":0,
    "iso:country":"FI",
    "name:eng_x_preferred":[
        "Jokij\u00e4rvi"
    ],
    "name:rus_x_preferred":[
        "\u0419\u043e\u043a\u0438\u044f\u0440\u0432\u0438"
    ],
    "qs_pg:aaroncc":"FI",
    "qs_pg:gn_country":"FI",
    "qs_pg:gn_fcode":"PPL",
    "qs_pg:gn_pop":0,
    "qs_pg:name":"Jokij\u00e4rvi",
    "qs_pg:name_adm0":"Suomi",
    "qs_pg:name_adm1":"Pohjois-pohjanmaan maakunta",
    "qs_pg:photos":30,
    "qs_pg:photos_1k":6,
    "qs_pg:photos_9k":1,
    "qs_pg:photos_9r":2,
    "qs_pg:photos_all":30,
    "qs_pg:photos_sr":2,
    "qs_pg:pop_sr":0,
    "qs_pg:qs_pg_placetype":"locality",
    "qs_pg:qs_pg_placetype_gp":"Town",
    "qs_pg:woe_adm0":23424812,
    "woe:adm0_id":23424812,
    "woe:name_adm0":"Suomi",
    "woe:name_adm1":"Pohjois-pohjanmaan maakunta",
    "woe:placetype":"Town",
    "wof:name":"Jokij\u00e4rvi",
    "wof:placetype":"locality"
},
  "geometry": {"coordinates":[28.65,65.46666999999999],"type":"Point"}
}