{
  "type": "Feature",
  "properties": {
    "gn:admin1_code":"19.0",
    "gn:admin2_code":"192.0",
    "gn:admin3_code":"851.0",
    "gn:asciiname":"Aapajaervi",
    "gn:country_code":"FI",
    "gn:dem":77,
    "gn:feature_class":"P",
    "gn:feature_code":"PPL",
    "gn:name":"Aapaj\u00e4rvi",
    "gn:population":0,
    "gn:timezone":"Europe/Helsinki",
    "iso:country":"FI",
    "wof:name":"Aapajaervi",
    "wof:placetype":"locality"
},
  "geometry": {"coordinates":[24.16473,66.08377],"type":"Point"}
}