{
  "type": "Feature",
  "properties": {
    "gn:admin1_code":"14.0",
    "gn:admin2_code":"142.0",
    "gn:admin3_code":"301.0",
    "gn:asciiname":"Ruotsinpuoli",
    "gn:country_code":"FI",
    "gn:dem":93,
    "gn:feature_class":"P",
    "gn:feature_code":"PPL",
    "gn:name":"Ruotsinpuoli",
    "gn:population":0,
    "gn:timezone":"Europe/Helsinki",
    "iso:country":"FI",
    "name:fin_x_preferred":[
        "Ruotsinpuoli"
    ],
    "wof:name":"Ruotsinpuoli",
    "wof:placetype":"locality"
},
  "geometry": {"coordinates":[22.06264,62.73226],"type":"Point"}
}