{
  "type": "Feature",
  "properties": {
    "gn:admin1_code":"15.0",
    "gn:admin2_code":"151.0",
    "gn:admin3_code":"152.0",
    "gn:asciiname":"Reinilae",
    "gn:country_code":"FI",
    "gn:dem":29,
    "gn:feature_class":"P",
    "gn:feature_code":"PPL",
    "gn:name":"Reinil\u00e4",
    "gn:population":0,
    "gn:timezone":"Europe/Helsinki",
    "iso:country":"FI",
    "name:fin_x_preferred":[
        "Reinil\u00e4"
    ],
    "wof:name":"Reinilae",
    "wof:placetype":"locality"
},
  "geometry": {"coordinates":[22.32822,63.00364],"type":"Point"}
}