{
  "type": "Feature",
  "properties": {
    "gn:admin1_code":"8.0",
    "gn:admin2_code":"81.0",
    "gn:admin3_code":"286.0",
    "gn:asciiname":"Mustila",
    "gn:country_code":"FI",
    "gn:dem":31,
    "gn:feature_class":"P",
    "gn:feature_code":"PPL",
    "gn:name":"Mustila",
    "gn:population":0,
    "gn:timezone":"Europe/Helsinki",
    "iso:country":"FI",
    "wof:name":"Mustila",
    "wof:placetype":"locality"
},
  "geometry": {"coordinates":[26.43333,60.73333],"type":"Point"}
}