{
  "type": "Feature",
  "properties": {
    "gn:admin1_code":"9.0",
    "gn:admin2_code":"91.0",
    "gn:admin3_code":"441.0",
    "gn:asciiname":"Kontula",
    "gn:country_code":"FI",
    "gn:dem":81,
    "gn:feature_class":"P",
    "gn:feature_code":"PPL",
    "gn:name":"Kontula",
    "gn:population":0,
    "gn:timezone":"Europe/Helsinki",
    "iso:country":"FI",
    "name:cat_x_preferred":[
        "Kontula"
    ],
    "name:est_x_preferred":[
        "Kontula"
    ],
    "name:fin_x_preferred":[
        "Kontula"
    ],
    "name:fra_x_preferred":[
        "Kontula"
    ],
    "name:rus_x_preferred":[
        "\u041a\u043e\u043d\u0442\u0443\u043b\u0430"
    ],
    "name:swe_x_preferred":[
        "G\u00e5rdsbacka"
    ],
    "name:ukr_x_preferred":[
        "\u041a\u043e\u043d\u0442\u0443\u043b\u0430"
    ],
    "wof:name":"Kontula",
    "wof:placetype":"locality"
},
  "geometry": {"coordinates":[27.56817,60.99028000000001],"type":"Point"}
}