{
  "type": "Feature",
  "properties": {
    "gn:admin1_code":"14.0",
    "gn:admin2_code":"142.0",
    "gn:admin3_code":"233.0",
    "gn:asciiname":"Ylikantola",
    "gn:country_code":"FI",
    "gn:dem":80,
    "gn:feature_class":"P",
    "gn:feature_code":"PPL",
    "gn:name":"Ylikantola",
    "gn:population":0,
    "gn:timezone":"Europe/Helsinki",
    "iso:country":"FI",
    "wof:name":"Ylikantola",
    "wof:placetype":"locality"
},
  "geometry": {"coordinates":[23.33333,63.08333],"type":"Point"}
}