{
  "type": "Feature",
  "properties": {
    "gn:admin1_code":"1.0",
    "gn:admin2_code":"11.0",
    "gn:admin3_code":"858.0",
    "gn:asciiname":"Krapi",
    "gn:country_code":"FI",
    "gn:dem":53,
    "gn:feature_class":"P",
    "gn:feature_code":"PPL",
    "gn:name":"Krapi",
    "gn:population":0,
    "gn:timezone":"Europe/Helsinki",
    "iso:country":"FI",
    "wof:name":"Krapi",
    "wof:placetype":"locality"
},
  "geometry": {"coordinates":[25.04709,60.42046],"type":"Point"}
}