{
  "type": "Feature",
  "properties": {
    "gn:admin1_code":"10.0",
    "gn:admin2_code":"103.0",
    "gn:admin3_code":"740.0",
    "gn:asciiname":"Pihlajaniemi",
    "gn:cc2":"FI",
    "gn:country_code":"FI",
    "gn:dem":98,
    "gn:feature_class":"P",
    "gn:feature_code":"PPL",
    "gn:name":"Pihlajaniemi",
    "gn:population":0,
    "gn:timezone":"Europe/Helsinki",
    "iso:country":"FI",
    "name:fin_x_preferred":[
        "Pihlajaniemi"
    ],
    "name:koi_x_preferred":[
        "\u041f\u0438\u0445\u043b\u0430\u044f\u043d\u0438\u0435\u043c\u0438"
    ],
    "name:rus_x_preferred":[
        "\u041f\u0438\u0445\u043b\u0430\u044f\u043d\u0438\u0435\u043c\u0438"
    ],
    "name:und_x_variant":[
        "Pihlajanniemi"
    ],
    "wof:name":"Pihlajaniemi",
    "wof:placetype":"locality"
},
  "geometry": {"coordinates":[29.55096,62.0054],"type":"Point"}
}