{
  "type": "Feature",
  "properties": {
    "gn:admin1_code":"1.0",
    "gn:admin2_code":"15.0",
    "gn:admin3_code":"616.0",
    "gn:asciiname":"Seppaelae",
    "gn:country_code":"FI",
    "gn:dem":50,
    "gn:feature_class":"P",
    "gn:feature_code":"PPL",
    "gn:name":"Sepp\u00e4l\u00e4",
    "gn:population":0,
    "gn:timezone":"Europe/Helsinki",
    "iso:country":"FI",
    "wof:name":"Seppaelae",
    "wof:placetype":"locality"
},
  "geometry": {"coordinates":[25.66667,60.66667],"type":"Point"}
}