{
  "type": "Feature",
  "properties": {
    "gn:admin1_code":"11.0",
    "gn:admin2_code":"112.0",
    "gn:admin3_code":"297.0",
    "gn:asciiname":"Karjalankoski",
    "gn:country_code":"FI",
    "gn:dem":87,
    "gn:feature_class":"P",
    "gn:feature_code":"PPL",
    "gn:name":"Karjalankoski",
    "gn:population":0,
    "gn:timezone":"Europe/Helsinki",
    "iso:country":"FI",
    "name:swe_x_historical":[
        "Ryssforsen"
    ],
    "name:swe_x_preferred":[
        "Ryssforsen"
    ],
    "wof:name":"Karjalankoski",
    "wof:placetype":"locality"
},
  "geometry": {"coordinates":[28.29845,63.04679],"type":"Point"}
}