{
  "type": "Feature",
  "properties": {
    "gn:admin1_code":"2.0",
    "gn:admin2_code":"23.0",
    "gn:admin3_code":"853.0",
    "gn:asciiname":"Kaarlejoki",
    "gn:country_code":"FI",
    "gn:dem":59,
    "gn:feature_class":"P",
    "gn:feature_code":"PPL",
    "gn:name":"Kaarlejoki",
    "gn:population":0,
    "gn:timezone":"Europe/Helsinki",
    "iso:country":"FI",
    "wof:name":"Kaarlejoki",
    "wof:placetype":"locality"
},
  "geometry": {"coordinates":[22.42204,60.65231],"type":"Point"}
}