{
  "type": "Feature",
  "properties": {
    "gn:admin1_code":"7.0",
    "gn:admin2_code":"71.0",
    "gn:admin3_code":"398.0",
    "gn:asciiname":"Lankila",
    "gn:country_code":"FI",
    "gn:dem":83,
    "gn:feature_class":"P",
    "gn:feature_code":"PPL",
    "gn:name":"Lankila",
    "gn:population":0,
    "gn:timezone":"Europe/Helsinki",
    "iso:country":"FI",
    "wof:name":"Lankila",
    "wof:placetype":"locality"
},
  "geometry": {"coordinates":[25.76199,60.9249],"type":"Point"}
}