{
  "type": "Feature",
  "properties": {
    "gn:admin1_code":"10.0",
    "gn:admin2_code":"105.0",
    "gn:admin3_code":"171.0",
    "gn:asciiname":"Ruokoniemi",
    "gn:country_code":"FI",
    "gn:dem":98,
    "gn:feature_class":"P",
    "gn:feature_code":"PPL",
    "gn:name":"Ruokoniemi",
    "gn:population":0,
    "gn:timezone":"Europe/Helsinki",
    "iso:country":"FI",
    "wof:name":"Ruokoniemi",
    "wof:placetype":"locality"
},
  "geometry": {"coordinates":[27.70498,62.19016],"type":"Point"}
}