{
  "type": "Feature",
  "properties": {
    "gn:admin1_code":"12.0",
    "gn:admin2_code":"125.0",
    "gn:admin3_code":"422.0",
    "gn:asciiname":"Putaansalmi",
    "gn:country_code":"FI",
    "gn:dem":128,
    "gn:feature_class":"P",
    "gn:feature_code":"PPL",
    "gn:name":"Putaansalmi",
    "gn:population":0,
    "gn:timezone":"Europe/Helsinki",
    "iso:country":"FI",
    "wof:name":"Putaansalmi",
    "wof:placetype":"locality"
},
  "geometry": {"coordinates":[30.26667,63.33333],"type":"Point"}
}