{
  "type": "Feature",
  "properties": {
    "gn:admin1_code":"10.0",
    "gn:admin2_code":"101.0",
    "gn:admin3_code":"491.0",
    "gn:asciiname":"Ikola",
    "gn:country_code":"FI",
    "gn:dem":80,
    "gn:feature_class":"P",
    "gn:feature_code":"PPL",
    "gn:name":"Ikola",
    "gn:population":0,
    "gn:timezone":"Europe/Helsinki",
    "iso:country":"FI",
    "name:deu_x_preferred":[
        "Ikola"
    ],
    "name:fin_x_preferred":[
        "Ikola"
    ],
    "name:rus_x_preferred":[
        "\u0418\u043a\u043e\u043b\u0430"
    ],
    "wof:name":"Ikola",
    "wof:placetype":"locality"
},
  "geometry": {"coordinates":[27.73512,61.5585],"type":"Point"}
}