{
  "type": "Feature",
  "properties": {
    "gn:admin1_code":"6.0",
    "gn:admin2_code":"68.0",
    "gn:admin3_code":"619.0",
    "gn:asciiname":"Vihalaita",
    "gn:country_code":"FI",
    "gn:dem":104,
    "gn:feature_class":"P",
    "gn:feature_code":"PPL",
    "gn:name":"Vihalaita",
    "gn:population":0,
    "gn:timezone":"Europe/Helsinki",
    "iso:country":"FI",
    "wof:name":"Vihalaita",
    "wof:placetype":"locality"
},
  "geometry": {"coordinates":[23.13567,61.03797],"type":"Point"}
}