{
  "type": "Feature",
  "properties": {
    "gn:admin1_code":"19.0",
    "gn:admin2_code":"197.0",
    "gn:admin3_code":"758.0",
    "gn:asciiname":"Kuusiniemi",
    "gn:country_code":"FI",
    "gn:dem":186,
    "gn:feature_class":"P",
    "gn:feature_code":"PPL",
    "gn:name":"Kuusiniemi",
    "gn:population":0,
    "gn:timezone":"Europe/Helsinki",
    "iso:country":"FI",
    "wof:name":"Kuusiniemi",
    "wof:placetype":"locality"
},
  "geometry": {"coordinates":[26.81667,67.34999999999999],"type":"Point"}
}