{
  "type": "Feature",
  "properties": {
    "gn:admin1_code":"19.0",
    "gn:admin2_code":"191.0",
    "gn:admin3_code":"683.0",
    "gn:asciiname":"Putkivaara",
    "gn:country_code":"FI",
    "gn:dem":198,
    "gn:feature_class":"P",
    "gn:feature_code":"PPL",
    "gn:name":"Putkivaara",
    "gn:population":0,
    "gn:timezone":"Europe/Helsinki",
    "iso:country":"FI",
    "wof:name":"Putkivaara",
    "wof:placetype":"locality"
},
  "geometry": {"coordinates":[26.94776,66.20354],"type":"Point"}
}