{
  "type": "Feature",
  "properties": {
    "gn:admin1_code":"6.0",
    "gn:admin2_code":"63.0",
    "gn:admin3_code":"887.0",
    "gn:asciiname":"Huhti",
    "gn:country_code":"FI",
    "gn:dem":116,
    "gn:feature_class":"P",
    "gn:feature_code":"PPL",
    "gn:name":"Huhti",
    "gn:population":0,
    "gn:timezone":"Europe/Helsinki",
    "iso:country":"FI",
    "wof:name":"Huhti",
    "wof:placetype":"locality"
},
  "geometry": {"coordinates":[23.63153,61.06229],"type":"Point"}
}