{
  "type": "Feature",
  "properties": {
    "gn:admin1_code":"1.0",
    "gn:admin2_code":"14.0",
    "gn:admin3_code":"710.0",
    "gn:asciiname":"OEjby",
    "gn:country_code":"FI",
    "gn:dem":12,
    "gn:feature_class":"P",
    "gn:feature_code":"PPL",
    "gn:name":"\u00d6jby",
    "gn:population":0,
    "gn:timezone":"Europe/Helsinki",
    "iso:country":"FI",
    "name:und_x_variant":[
        "Oe",
        "\u00d6jby",
        "\u00d6by"
    ],
    "wof:name":"OEjby",
    "wof:placetype":"locality"
},
  "geometry": {"coordinates":[23.16667,59.91667],"type":"Point"}
}