{
  "type": "Feature",
  "properties": {
    "gn:admin1_code":"2.0",
    "gn:admin2_code":"21.0",
    "gn:admin3_code":"322.0",
    "gn:asciiname":"Kalkila",
    "gn:cc2":"FI",
    "gn:country_code":"FI",
    "gn:dem":25,
    "gn:feature_class":"P",
    "gn:feature_code":"PPL",
    "gn:name":"Kalkila",
    "gn:population":0,
    "gn:timezone":"Europe/Helsinki",
    "iso:country":"FI",
    "name:fin_x_preferred":[
        "Kalkkila"
    ],
    "name:swe_x_preferred":[
        "Kalkila"
    ],
    "wof:name":"Kalkila",
    "wof:placetype":"locality"
},
  "geometry": {"coordinates":[22.79861,60.20564],"type":"Point"}
}