{
  "type": "Feature",
  "properties": {
    "gn:admin1_code":"17.0",
    "gn:admin2_code":"173.0",
    "gn:admin3_code":"615.0",
    "gn:asciiname":"Paerjaensuo",
    "gn:country_code":"FI",
    "gn:dem":126,
    "gn:feature_class":"P",
    "gn:feature_code":"PPL",
    "gn:name":"P\u00e4rj\u00e4nsuo",
    "gn:population":0,
    "gn:timezone":"Europe/Helsinki",
    "iso:country":"FI",
    "name:eng_x_preferred":[
        "P\u00e4rj\u00e4nsuo"
    ],
    "name:rus_x_preferred":[
        "\u041f\u044f\u0440\u044c\u044f\u043d\u0441\u0443\u043e"
    ],
    "name:und_x_variant":[
        "P\u00e4rj\u00e4nsuo"
    ],
    "wof:name":"Paerjaensuo",
    "wof:placetype":"locality"
},
  "geometry": {"coordinates":[27.1726,65.58133000000001],"type":"Point"}
}