{
  "type": "Feature",
  "properties": {
    "gn:admin1_code":"6.0",
    "gn:admin2_code":"68.0",
    "gn:admin3_code":"790.0",
    "gn:asciiname":"Pikku-Kojola",
    "gn:country_code":"FI",
    "gn:dem":97,
    "gn:feature_class":"P",
    "gn:feature_code":"PPL",
    "gn:name":"Pikku-Kojola",
    "gn:population":0,
    "gn:timezone":"Europe/Helsinki",
    "iso:country":"FI",
    "wof:name":"Pikku-Kojola",
    "wof:placetype":"locality"
},
  "geometry": {"coordinates":[23.13209,61.38734],"type":"Point"}
}