{
  "type": "Feature",
  "properties": {
    "gn:admin1_code":"12.0",
    "gn:admin2_code":"124.0",
    "gn:admin3_code":"707.0",
    "gn:asciiname":"Hypoenniemi",
    "gn:country_code":"FI",
    "gn:dem":92,
    "gn:feature_class":"P",
    "gn:feature_code":"PPL",
    "gn:name":"Hyp\u00f6nniemi",
    "gn:population":0,
    "gn:timezone":"Europe/Helsinki",
    "iso:country":"FI",
    "name:und_x_variant":[
        "Hypanniemi",
        "Hyp\u00f6nniemi"
    ],
    "wof:name":"Hypoenniemi",
    "wof:placetype":"locality"
},
  "geometry": {"coordinates":[29.42903,62.35491],"type":"Point"}
}