{
  "type": "Feature",
  "properties": {
    "gn:admin1_code":"18.0",
    "gn:admin2_code":"182.0",
    "gn:admin3_code":"578.0",
    "gn:asciiname":"Niemelae",
    "gn:country_code":"FI",
    "gn:dem":127,
    "gn:feature_class":"P",
    "gn:feature_code":"PPL",
    "gn:name":"Niemel\u00e4",
    "gn:population":0,
    "gn:timezone":"Europe/Helsinki",
    "iso:country":"FI",
    "wof:name":"Niemelae",
    "wof:placetype":"locality"
},
  "geometry": {"coordinates":[27.91667,64.51666999999999],"type":"Point"}
}