{
  "type": "Feature",
  "properties": {
    "gn:admin1_code":"6.0",
    "gn:admin2_code":"63.0",
    "gn:admin3_code":"20.0",
    "gn:asciiname":"Metsae-Paavola",
    "gn:country_code":"FI",
    "gn:dem":95,
    "gn:feature_class":"P",
    "gn:feature_code":"PPL",
    "gn:name":"Mets\u00e4-Paavola",
    "gn:population":0,
    "gn:timezone":"Europe/Helsinki",
    "iso:country":"FI",
    "wof:name":"Metsae-Paavola",
    "wof:placetype":"locality"
},
  "geometry": {"coordinates":[23.90816,61.12004],"type":"Point"}
}