{
  "type": "Feature",
  "properties": {
    "gn:admin1_code":"10.0",
    "gn:admin2_code":"101.0",
    "gn:admin3_code":"213.0",
    "gn:asciiname":"Seppaelae",
    "gn:country_code":"FI",
    "gn:dem":117,
    "gn:feature_class":"P",
    "gn:feature_code":"PPL",
    "gn:name":"Sepp\u00e4l\u00e4",
    "gn:population":0,
    "gn:timezone":"Europe/Helsinki",
    "iso:country":"FI",
    "wof:name":"Seppaelae",
    "wof:placetype":"locality"
},
  "geometry": {"coordinates":[26.54958,62.01408000000001],"type":"Point"}
}