{
  "type": "Feature",
  "properties": {
    "gn:admin1_code":"17.0",
    "gn:admin2_code":"178.0",
    "gn:admin3_code":"832.0",
    "gn:asciiname":"Elkonniemi",
    "gn:country_code":"FI",
    "gn:dem":154,
    "gn:feature_class":"P",
    "gn:feature_code":"PPL",
    "gn:name":"Elkonniemi",
    "gn:population":0,
    "gn:timezone":"Europe/Helsinki",
    "iso:country":"FI",
    "name:fin_x_preferred":[
        "Elkonniemi"
    ],
    "wof:name":"Elkonniemi",
    "wof:placetype":"locality"
},
  "geometry": {"coordinates":[27.84543,65.42036999999999],"type":"Point"}
}