{
  "type": "Feature",
  "properties": {
    "gn:admin1_code":"15.0",
    "gn:admin2_code":"154.0",
    "gn:admin3_code":"598.0",
    "gn:asciiname":"Vaestersundsby",
    "gn:country_code":"FI",
    "gn:dem":13,
    "gn:feature_class":"P",
    "gn:feature_code":"PPL",
    "gn:name":"V\u00e4stersundsby",
    "gn:population":0,
    "gn:timezone":"Europe/Helsinki",
    "iso:country":"FI",
    "name:und_x_variant":[
        "V\u00e4stersund",
        "V\u00e4stersundsby"
    ],
    "wof:name":"Vaestersundsby",
    "wof:placetype":"locality"
},
  "geometry": {"coordinates":[22.65012,63.67293000000001],"type":"Point"}
}