{
  "type": "Feature",
  "properties": {
    "gn:admin1_code":"6.0",
    "gn:admin2_code":"64.0",
    "gn:admin3_code":"562.0",
    "gn:asciiname":"Saerkijaervi",
    "gn:country_code":"FI",
    "gn:dem":168,
    "gn:feature_class":"P",
    "gn:feature_code":"PPL",
    "gn:name":"S\u00e4rkij\u00e4rvi",
    "gn:population":0,
    "gn:timezone":"Europe/Helsinki",
    "iso:country":"FI",
    "wof:name":"Saerkijaervi",
    "wof:placetype":"locality"
},
  "geometry": {"coordinates":[24.7049,61.78696],"type":"Point"}
}