{
  "type": "Feature",
  "properties": {
    "gn:admin1_code":"1.0",
    "gn:admin2_code":"11.0",
    "gn:admin3_code":"91.0",
    "gn:asciiname":"Kaisaniemi",
    "gn:country_code":"FI",
    "gn:dem":32,
    "gn:feature_class":"P",
    "gn:feature_code":"PPL",
    "gn:name":"Kaisaniemi",
    "gn:population":0,
    "gn:timezone":"Europe/Helsinki",
    "iso:country":"FI",
    "name:cat_x_preferred":[
        "Kaisaniemi"
    ],
    "name:dan_x_preferred":[
        "Kajsaniemi"
    ],
    "name:deu_x_preferred":[
        "Kaisaniemi"
    ],
    "name:isl_x_preferred":[
        "Kajsaniemi"
    ],
    "name:nld_x_preferred":[
        "Kaisaniemi"
    ],
    "name:nno_x_preferred":[
        "Kajsaniemi"
    ],
    "name:nob_x_preferred":[
        "Kajsaniemi"
    ],
    "name:spa_x_preferred":[
        "Kaisaniemi"
    ],
    "name:swe_x_preferred":[
        "Kajsaniemi"
    ],
    "wof:name":"Kaisaniemi",
    "wof:placetype":"locality"
},
  "geometry": {"coordinates":[24.94575,60.17501],"type":"Point"}
}