{
  "type": "Feature",
  "properties": {
    "gn:admin1_code":"18.0",
    "gn:admin2_code":"182.0",
    "gn:admin3_code":"697.0",
    "gn:asciiname":"Sepaentalo",
    "gn:country_code":"FI",
    "gn:dem":170,
    "gn:feature_class":"P",
    "gn:feature_code":"PPL",
    "gn:name":"Sep\u00e4ntalo",
    "gn:population":0,
    "gn:timezone":"Europe/Helsinki",
    "iso:country":"FI",
    "wof:name":"Sepaentalo",
    "wof:placetype":"locality"
},
  "geometry": {"coordinates":[28.63333,64.34999999999999],"type":"Point"}
}