{
  "type": "Feature",
  "properties": {
    "gn:admin1_code":"17.0",
    "gn:admin2_code":"177.0",
    "gn:admin3_code":"208.0",
    "gn:asciiname":"Vasanneva",
    "gn:country_code":"FI",
    "gn:dem":26,
    "gn:feature_class":"P",
    "gn:feature_code":"PPL",
    "gn:name":"Vasanneva",
    "gn:population":0,
    "gn:timezone":"Europe/Helsinki",
    "iso:country":"FI",
    "wof:name":"Vasanneva",
    "wof:placetype":"locality"
},
  "geometry": {"coordinates":[24.0497,64.33671],"type":"Point"}
}