{
  "type": "Feature",
  "properties": {
    "gn:admin1_code":"13.0",
    "gn:admin2_code":"133.0",
    "gn:admin3_code":"249.0",
    "gn:asciiname":"Lammasperae",
    "gn:country_code":"FI",
    "gn:dem":115,
    "gn:feature_class":"P",
    "gn:feature_code":"PPL",
    "gn:name":"Lammasper\u00e4",
    "gn:population":0,
    "gn:timezone":"Europe/Helsinki",
    "iso:country":"FI",
    "name:und_x_variant":[
        "Lammasalo",
        "Lammasper\u00e4"
    ],
    "wof:name":"Lammasperae",
    "wof:placetype":"locality"
},
  "geometry": {"coordinates":[24.61726,62.27913],"type":"Point"}
}