{
  "type": "Feature",
  "properties": {
    "gn:admin1_code":"13.0",
    "gn:admin2_code":"138.0",
    "gn:admin3_code":"601.0",
    "gn:asciiname":"Pohja",
    "gn:country_code":"FI",
    "gn:dem":176,
    "gn:feature_class":"P",
    "gn:feature_code":"PPL",
    "gn:name":"Pohja",
    "gn:population":0,
    "gn:timezone":"Europe/Helsinki",
    "iso:country":"FI",
    "name:ceb_x_preferred":[
        "Pohja"
    ],
    "name:deu_x_preferred":[
        "Pohja"
    ],
    "name:est_x_preferred":[
        "Pohja vald"
    ],
    "name:fin_x_preferred":[
        "Pohja"
    ],
    "name:fra_x_preferred":[
        "Pohja"
    ],
    "name:ita_x_preferred":[
        "Pohja"
    ],
    "name:kor_x_preferred":[
        "\ud3ec\ud750\uc57c"
    ],
    "name:nld_x_preferred":[
        "Pohja"
    ],
    "name:nor_x_preferred":[
        "Pojo"
    ],
    "name:pol_x_preferred":[
        "Pohja"
    ],
    "name:ron_x_preferred":[
        "Pohja"
    ],
    "name:sme_x_preferred":[
        "Pohja"
    ],
    "name:swe_x_preferred":[
        "Pojo"
    ],
    "name:vie_x_preferred":[
        "Pohja"
    ],
    "wof:name":"Pohja",
    "wof:placetype":"locality"
},
  "geometry": {"coordinates":[26.02412,63.39399],"type":"Point"}
}