{
  "type": "Feature",
  "properties": {
    "gn:admin1_code":"4.0",
    "gn:admin2_code":"41.0",
    "gn:admin3_code":"51.0",
    "gn:asciiname":"Lemlahti",
    "gn:country_code":"FI",
    "gn:dem":14,
    "gn:feature_class":"P",
    "gn:feature_code":"PPL",
    "gn:name":"Lemlahti",
    "gn:population":0,
    "gn:timezone":"Europe/Helsinki",
    "iso:country":"FI",
    "name:swe_x_historical":[
        "Lemlax"
    ],
    "name:swe_x_preferred":[
        "Lemlax"
    ],
    "wof:name":"Lemlahti",
    "wof:placetype":"locality"
},
  "geometry": {"coordinates":[21.58951,61.31941],"type":"Point"}
}