{
  "type": "Feature",
  "properties": {
    "gn:admin1_code":"13.0",
    "gn:admin2_code":"135.0",
    "gn:admin3_code":"992.0",
    "gn:asciiname":"Kapeenkylae",
    "gn:country_code":"FI",
    "gn:dem":111,
    "gn:feature_class":"P",
    "gn:feature_code":"PPL",
    "gn:name":"Kapeenkyl\u00e4",
    "gn:population":0,
    "gn:timezone":"Europe/Helsinki",
    "iso:country":"FI",
    "wof:name":"Kapeenkylae",
    "wof:placetype":"locality"
},
  "geometry": {"coordinates":[25.82093,62.53234000000001],"type":"Point"}
}