{
  "type": "Feature",
  "properties": {
    "gn:admin1_code":"10.0",
    "gn:admin2_code":"101.0",
    "gn:admin3_code":"588.0",
    "gn:asciiname":"Joutsjaervi",
    "gn:country_code":"FI",
    "gn:dem":130,
    "gn:feature_class":"P",
    "gn:feature_code":"PPL",
    "gn:name":"Joutsj\u00e4rvi",
    "gn:population":0,
    "gn:timezone":"Europe/Helsinki",
    "iso:country":"FI",
    "wof:name":"Joutsjaervi",
    "wof:placetype":"locality"
},
  "geometry": {"coordinates":[26.35858,61.56811],"type":"Point"}
}