{
  "type": "Feature",
  "properties": {
    "gn:admin1_code":"13.0",
    "gn:admin2_code":"138.0",
    "gn:admin3_code":"601.0",
    "gn:asciiname":"Korppinen",
    "gn:country_code":"FI",
    "gn:dem":196,
    "gn:feature_class":"P",
    "gn:feature_code":"PPL",
    "gn:name":"Korppinen",
    "gn:population":0,
    "gn:timezone":"Europe/Helsinki",
    "iso:country":"FI",
    "name:eng_x_preferred":[
        "Korppinen"
    ],
    "name:rus_x_preferred":[
        "\u041a\u043e\u0440\u043f\u043f\u0438\u043d\u0435\u043d"
    ],
    "wof:name":"Korppinen",
    "wof:placetype":"locality"
},
  "geometry": {"coordinates":[25.90813,63.35528000000001],"type":"Point"}
}