{
  "type": "Feature",
  "properties": {
    "gn:admin1_code":"8.0",
    "gn:admin2_code":"82.0",
    "gn:admin3_code":"285.0",
    "gn:asciiname":"Suurikylae",
    "gn:country_code":"FI",
    "gn:dem":1,
    "gn:feature_class":"P",
    "gn:feature_code":"PPL",
    "gn:name":"Suurikyl\u00e4",
    "gn:population":0,
    "gn:timezone":"Europe/Helsinki",
    "iso:country":"FI",
    "wof:name":"Suurikylae",
    "wof:placetype":"locality"
},
  "geometry": {"coordinates":[27.03541,60.44072],"type":"Point"}
}