{
  "type": "Feature",
  "properties": {
    "gn:admin1_code":"6.0",
    "gn:admin2_code":"69.0",
    "gn:admin3_code":"702.0",
    "gn:asciiname":"Pappilankulma",
    "gn:country_code":"FI",
    "gn:dem":107,
    "gn:feature_class":"P",
    "gn:feature_code":"PPL",
    "gn:name":"Pappilankulma",
    "gn:population":0,
    "gn:timezone":"Europe/Helsinki",
    "iso:country":"FI",
    "wof:name":"Pappilankulma",
    "wof:placetype":"locality"
},
  "geometry": {"coordinates":[24.04976,62.01056],"type":"Point"}
}