{
  "type": "Feature",
  "properties": {
    "gn:admin1_code":"14.0",
    "gn:admin2_code":"142.0",
    "gn:admin3_code":"233.0",
    "gn:asciiname":"Salo",
    "gn:country_code":"FI",
    "gn:dem":62,
    "gn:feature_class":"P",
    "gn:feature_code":"PPL",
    "gn:name":"Salo",
    "gn:population":0,
    "gn:timezone":"Europe/Helsinki",
    "iso:country":"FI",
    "wof:name":"Salo",
    "wof:placetype":"locality"
},
  "geometry": {"coordinates":[23.02896,63.32712],"type":"Point"}
}