{
  "type": "Feature",
  "properties": {
    "gn:admin1_code":"18.0",
    "gn:admin2_code":"181.0",
    "gn:admin3_code":"290.0",
    "gn:asciiname":"Lentiira",
    "gn:country_code":"FI",
    "gn:dem":166,
    "gn:feature_class":"P",
    "gn:feature_code":"PPL",
    "gn:name":"Lentiira",
    "gn:population":0,
    "gn:timezone":"Europe/Helsinki",
    "iso:country":"FI",
    "name:eng_x_preferred":[
        "Lentiira"
    ],
    "name:rus_x_preferred":[
        "\u041b\u0435\u043d\u0442\u0438\u0440\u0430"
    ],
    "wof:name":"Lentiira",
    "wof:placetype":"locality"
},
  "geometry": {"coordinates":[29.83714,64.38861999999999],"type":"Point"}
}