{
  "type": "Feature",
  "properties": {
    "gn:admin1_code":"2.0",
    "gn:admin2_code":"23.0",
    "gn:admin3_code":"577.0",
    "gn:asciiname":"Aakoinen",
    "gn:country_code":"FI",
    "gn:dem":14,
    "gn:feature_class":"P",
    "gn:feature_code":"PPL",
    "gn:name":"Aakoinen",
    "gn:population":0,
    "gn:timezone":"Europe/Helsinki",
    "iso:country":"FI",
    "wof:name":"Aakoinen",
    "wof:placetype":"locality"
},
  "geometry": {"coordinates":[22.66693,60.37987],"type":"Point"}
}