{
  "type": "Feature",
  "properties": {
    "gn:admin1_code":"9.0",
    "gn:admin2_code":"91.0",
    "gn:admin3_code":"739.0",
    "gn:asciiname":"Poentylae",
    "gn:country_code":"FI",
    "gn:dem":96,
    "gn:feature_class":"P",
    "gn:feature_code":"PPL",
    "gn:name":"P\u00f6ntyl\u00e4",
    "gn:population":0,
    "gn:timezone":"Europe/Helsinki",
    "iso:country":"FI",
    "wof:name":"Poentylae",
    "wof:placetype":"locality"
},
  "geometry": {"coordinates":[27.71883,61.21104],"type":"Point"}
}