{
  "type": "Feature",
  "properties": {
    "gn:admin1_code":"9.0",
    "gn:admin2_code":"91.0",
    "gn:admin3_code":"405.0",
    "gn:asciiname":"Melkkola",
    "gn:cc2":"FI",
    "gn:country_code":"FI",
    "gn:dem":68,
    "gn:feature_class":"P",
    "gn:feature_code":"PPL",
    "gn:name":"Melkkola",
    "gn:population":0,
    "gn:timezone":"Europe/Helsinki",
    "iso:country":"FI",
    "name:und_x_variant":[
        "Melkola",
        "Melkkola"
    ],
    "wof:name":"Melkkola",
    "wof:placetype":"locality"
},
  "geometry": {"coordinates":[28.12274,60.93474000000001],"type":"Point"}
}