{
  "type": "Feature",
  "properties": {
    "gn:admin1_code":"9.0",
    "gn:admin2_code":"91.0",
    "gn:admin3_code":"831.0",
    "gn:asciiname":"Peltoi",
    "gn:country_code":"FI",
    "gn:dem":79,
    "gn:feature_class":"P",
    "gn:feature_code":"PPL",
    "gn:name":"Peltoi",
    "gn:population":0,
    "gn:timezone":"Europe/Helsinki",
    "iso:country":"FI",
    "name:fin_x_historical":[
        "Peltoinen"
    ],
    "name:fin_x_preferred":[
        "Peltoi"
    ],
    "name:fin_x_variant":[
        "Peltoinen"
    ],
    "wof:name":"Peltoi",
    "wof:placetype":"locality"
},
  "geometry": {"coordinates":[27.98333,61.21666999999999],"type":"Point"}
}