{
  "type": "Feature",
  "properties": {
    "iso:country":"FI",
    "name:fin_x_preferred":[
        "Pajam\u00e4ki"
    ],
    "name:fra_x_preferred":[
        "Pajam\u00e4ki"
    ],
    "name:swe_x_preferred":[
        "Smedjebacka"
    ],
    "qs_pg:aaroncc":"FI",
    "qs_pg:name":"Pajam\u00e4ki",
    "qs_pg:name_adm0":"Suomi",
    "qs_pg:name_adm1":"Kymeenlaakson maakunta",
    "qs_pg:photos":26,
    "qs_pg:photos_1k":5,
    "qs_pg:photos_9k":1,
    "qs_pg:photos_9r":2,
    "qs_pg:photos_all":26,
    "qs_pg:photos_sr":2,
    "qs_pg:pop_sr":0,
    "qs_pg:qs_pg_placetype":"locality",
    "qs_pg:qs_pg_placetype_gp":"Town",
    "qs_pg:woe_adm0":23424812,
    "woe:adm0_id":23424812,
    "woe:name_adm0":"Suomi",
    "woe:name_adm1":"Kymeenlaakson maakunta",
    "woe:placetype":"Town",
    "wof:name":"Pajam\u00e4ki",
    "wof:placetype":"locality"
},
  "geometry": {"coordinates":[26.639184,60.912182],"type":"Point"}
}