{
  "type": "Feature",
  "properties": {
    "gn:admin1_code":"11.0",
    "gn:admin2_code":"115.0",
    "gn:admin3_code":"921.0",
    "gn:asciiname":"Horonkylae",
    "gn:country_code":"FI",
    "gn:dem":117,
    "gn:feature_class":"P",
    "gn:feature_code":"PPL",
    "gn:name":"Horonkyl\u00e4",
    "gn:population":0,
    "gn:timezone":"Europe/Helsinki",
    "iso:country":"FI",
    "name:und_x_variant":[
        "Horontaipale",
        "Horontaival",
        "Horonkyl\u00e4"
    ],
    "wof:name":"Horonkylae",
    "wof:placetype":"locality"
},
  "geometry": {"coordinates":[26.26114,62.88405],"type":"Point"}
}