{
  "type": "Feature",
  "properties": {
    "gn:admin1_code":"6.0",
    "gn:admin2_code":"64.0",
    "gn:admin3_code":"562.0",
    "gn:asciiname":"Neulaniemi",
    "gn:country_code":"FI",
    "gn:dem":142,
    "gn:feature_class":"P",
    "gn:feature_code":"PPL",
    "gn:name":"Neulaniemi",
    "gn:population":0,
    "gn:timezone":"Europe/Helsinki",
    "iso:country":"FI",
    "wof:name":"Neulaniemi",
    "wof:placetype":"locality"
},
  "geometry": {"coordinates":[24.41607,61.62283000000001],"type":"Point"}
}