{
  "type": "Feature",
  "properties": {
    "gn:admin1_code":"14.0",
    "gn:admin2_code":"141.0",
    "gn:admin3_code":"151.0",
    "gn:asciiname":"Pihlaja",
    "gn:country_code":"FI",
    "gn:dem":98,
    "gn:feature_class":"P",
    "gn:feature_code":"PPL",
    "gn:name":"Pihlaja",
    "gn:population":0,
    "gn:timezone":"Europe/Helsinki",
    "iso:country":"FI",
    "name:fin_x_preferred":[
        "Pihlaja"
    ],
    "wof:name":"Pihlaja",
    "wof:placetype":"locality"
},
  "geometry": {"coordinates":[21.92682000000001,62.11551],"type":"Point"}
}