{
  "type": "Feature",
  "properties": {
    "iso:country":"FI",
    "qs_pg:aaroncc":"FI",
    "qs_pg:name":"Parikanm\u00e4ki",
    "qs_pg:name_adm0":"Suomi",
    "qs_pg:name_adm1":"P\u00e4ijat-H\u00e4meen maakunta",
    "qs_pg:photos":96,
    "qs_pg:photos_1k":19,
    "qs_pg:photos_9k":1,
    "qs_pg:photos_9r":3,
    "qs_pg:photos_all":96,
    "qs_pg:photos_sr":3,
    "qs_pg:pop_sr":0,
    "qs_pg:qs_pg_placetype":"locality",
    "qs_pg:qs_pg_placetype_gp":"Town",
    "qs_pg:woe_adm0":23424812,
    "woe:adm0_id":23424812,
    "woe:name_adm0":"Suomi",
    "woe:name_adm1":"P\u00e4ijat-H\u00e4meen maakunta",
    "woe:placetype":"Town",
    "wof:name":"Parikanm\u00e4ki",
    "wof:placetype":"locality"
},
  "geometry": {"coordinates":[25.703449,60.990161],"type":"Point"}
}