{
  "type": "Feature",
  "properties": {
    "gn:admin1_code":"12.0",
    "gn:admin2_code":"122.0",
    "gn:admin3_code":"146.0",
    "gn:asciiname":"Haukivaara",
    "gn:country_code":"FI",
    "gn:dem":174,
    "gn:feature_class":"P",
    "gn:feature_code":"PPL",
    "gn:name":"Haukivaara",
    "gn:population":0,
    "gn:timezone":"Europe/Helsinki",
    "iso:country":"FI",
    "wof:name":"Haukivaara",
    "wof:placetype":"locality"
},
  "geometry": {"coordinates":[30.94457,62.552],"type":"Point"}
}