{
  "type": "Feature",
  "properties": {
    "gn:admin1_code":"7.0",
    "gn:admin2_code":"71.0",
    "gn:admin3_code":"111.0",
    "gn:asciiname":"Marjoniemi",
    "gn:cc2":"FI",
    "gn:country_code":"FI",
    "gn:dem":94,
    "gn:feature_class":"P",
    "gn:feature_code":"PPL",
    "gn:name":"Marjoniemi",
    "gn:population":0,
    "gn:timezone":"Europe/Helsinki",
    "iso:country":"FI",
    "name:und_x_variant":[
        "Marjakyl\u00e4",
        "Marjoniemi"
    ],
    "wof:name":"Marjoniemi",
    "wof:placetype":"locality"
},
  "geometry": {"coordinates":[25.89467,61.28319000000001],"type":"Point"}
}