{
  "type": "Feature",
  "properties": {
    "gn:admin1_code":"4.0",
    "gn:admin2_code":"43.0",
    "gn:admin3_code":"484.0",
    "gn:asciiname":"Tuorila",
    "gn:country_code":"FI",
    "gn:dem":40,
    "gn:feature_class":"P",
    "gn:feature_code":"PPL",
    "gn:name":"Tuorila",
    "gn:population":0,
    "gn:timezone":"Europe/Helsinki",
    "iso:country":"FI",
    "name:dan_x_historical":[
        "Torsby"
    ],
    "name:dan_x_preferred":[
        "Torsby"
    ],
    "name:isl_x_historical":[
        "Torsby"
    ],
    "name:isl_x_preferred":[
        "Torsby"
    ],
    "name:nor_x_historical":[
        "Torsby"
    ],
    "name:nor_x_preferred":[
        "Torsby"
    ],
    "name:swe_x_historical":[
        "Torsby"
    ],
    "name:swe_x_preferred":[
        "Torsby"
    ],
    "wof:name":"Tuorila",
    "wof:placetype":"locality"
},
  "geometry": {"coordinates":[21.63534,61.87226],"type":"Point"}
}