{
  "type": "Feature",
  "properties": {
    "gn:admin1_code":"18.0",
    "gn:admin2_code":"182.0",
    "gn:admin3_code":"578.0",
    "gn:asciiname":"Mustola",
    "gn:country_code":"FI",
    "gn:dem":137,
    "gn:feature_class":"P",
    "gn:feature_code":"PPL",
    "gn:name":"Mustola",
    "gn:population":0,
    "gn:timezone":"Europe/Helsinki",
    "iso:country":"FI",
    "wof:name":"Mustola",
    "wof:placetype":"locality"
},
  "geometry": {"coordinates":[27.45,64.40000000000001],"type":"Point"}
}