{
  "type": "Feature",
  "properties": {
    "gn:admin1_code":"1.0",
    "gn:admin2_code":"15.0",
    "gn:admin3_code":"638.0",
    "gn:asciiname":"Virtaala",
    "gn:country_code":"FI",
    "gn:dem":31,
    "gn:feature_class":"P",
    "gn:feature_code":"PPL",
    "gn:name":"Virtaala",
    "gn:population":0,
    "gn:timezone":"Europe/Helsinki",
    "iso:country":"FI",
    "name:fin_x_preferred":[
        "Virtaala"
    ],
    "name:swe_x_preferred":[
        "Str\u00f6msberg"
    ],
    "wof:name":"Virtaala",
    "wof:placetype":"locality"
},
  "geometry": {"coordinates":[25.59569,60.44121],"type":"Point"}
}