{
  "type": "Feature",
  "properties": {
    "gn:admin1_code":"15.0",
    "gn:admin2_code":"152.0",
    "gn:admin3_code":"499.0",
    "gn:asciiname":"Byn",
    "gn:country_code":"FI",
    "gn:dem":10,
    "gn:feature_class":"P",
    "gn:feature_code":"PPL",
    "gn:name":"Byn",
    "gn:population":0,
    "gn:timezone":"Europe/Helsinki",
    "iso:country":"FI",
    "name:swe_x_preferred":[
        "Byn"
    ],
    "wof:name":"Byn",
    "wof:placetype":"locality"
},
  "geometry": {"coordinates":[21.93202,63.08412],"type":"Point"}
}