{
  "type": "Feature",
  "properties": {
    "gn:admin1_code":"2.0",
    "gn:admin2_code":"24.0",
    "gn:admin3_code":"895.0",
    "gn:asciiname":"Kuivarauma",
    "gn:cc2":"FI",
    "gn:country_code":"FI",
    "gn:dem":5,
    "gn:feature_class":"P",
    "gn:feature_code":"PPL",
    "gn:name":"Kuivarauma",
    "gn:population":0,
    "gn:timezone":"Europe/Helsinki",
    "iso:country":"FI",
    "name:und_x_variant":[
        "Kuivirauma",
        "Kuiviraumo",
        "Kuivarauma"
    ],
    "wof:name":"Kuivarauma",
    "wof:placetype":"locality"
},
  "geometry": {"coordinates":[21.34174,60.9294],"type":"Point"}
}