{
  "type": "Feature",
  "properties": {
    "gn:admin1_code":"17.0",
    "gn:admin2_code":"175.0",
    "gn:admin3_code":"791.0",
    "gn:asciiname":"Vaeyrylaensaari",
    "gn:country_code":"FI",
    "gn:dem":87,
    "gn:feature_class":"P",
    "gn:feature_code":"PPL",
    "gn:name":"V\u00e4yryl\u00e4nsaari",
    "gn:population":0,
    "gn:timezone":"Europe/Helsinki",
    "iso:country":"FI",
    "name:und_x_variant":[
        "V\u00e4yryl\u00e4nsaari",
        "V\u00e4yrynen"
    ],
    "wof:name":"Vaeyrylaensaari",
    "wof:placetype":"locality"
},
  "geometry": {"coordinates":[26.00153,64.32550999999999],"type":"Point"}
}