{
  "type": "Feature",
  "properties": {
    "gn:admin1_code":"11.0",
    "gn:admin2_code":"111.0",
    "gn:admin3_code":"925.0",
    "gn:asciiname":"Marttisenjaervi",
    "gn:country_code":"FI",
    "gn:dem":161,
    "gn:feature_class":"P",
    "gn:feature_code":"PPL",
    "gn:name":"Marttisenj\u00e4rvi",
    "gn:population":0,
    "gn:timezone":"Europe/Helsinki",
    "iso:country":"FI",
    "name:eng_x_preferred":[
        "Marttisenj\u00e4rvi"
    ],
    "name:rus_x_preferred":[
        "\u041c\u0430\u0440\u0442\u0442\u0438\u0441\u0435\u043d\u0438\u043e\u043a\u0438"
    ],
    "wof:name":"Marttisenjaervi",
    "wof:placetype":"locality"
},
  "geometry": {"coordinates":[26.95042,63.89559000000001],"type":"Point"}
}