{
  "type": "Feature",
  "properties": {
    "gn:admin1_code":"13.0",
    "gn:admin2_code":"134.0",
    "gn:admin3_code":"182.0",
    "gn:asciiname":"Nuorlahti",
    "gn:country_code":"FI",
    "gn:dem":89,
    "gn:feature_class":"P",
    "gn:feature_code":"PPL",
    "gn:name":"Nuorlahti",
    "gn:population":0,
    "gn:timezone":"Europe/Helsinki",
    "iso:country":"FI",
    "name:fin_x_preferred":[
        "Nuorlahti"
    ],
    "wof:name":"Nuorlahti",
    "wof:placetype":"locality"
},
  "geometry": {"coordinates":[25.39703,61.93571],"type":"Point"}
}