{
  "type": "Feature",
  "properties": {
    "iso:country":"FI",
    "qs_pg:aaroncc":"FI",
    "qs_pg:name":"Breds",
    "qs_pg:name_adm0":"Suomi",
    "qs_pg:name_adm1":"Uudenmaan maakunta",
    "qs_pg:photos":14,
    "qs_pg:photos_1k":3,
    "qs_pg:photos_9k":1,
    "qs_pg:photos_9r":1,
    "qs_pg:photos_all":14,
    "qs_pg:photos_sr":1,
    "qs_pg:pop_sr":0,
    "qs_pg:qs_pg_placetype":"locality",
    "qs_pg:qs_pg_placetype_gp":"Town",
    "qs_pg:woe_adm0":23424812,
    "woe:adm0_id":23424812,
    "woe:name_adm0":"Suomi",
    "woe:name_adm1":"Uudenmaan maakunta",
    "woe:placetype":"Town",
    "wof:name":"Breds",
    "wof:placetype":"locality"
},
  "geometry": {"coordinates":[23.96852,60.049655],"type":"Point"}
}