{
  "type": "Feature",
  "properties": {
    "gn:admin1_code":"10.0",
    "gn:admin2_code":"101.0",
    "gn:admin3_code":"491.0",
    "gn:asciiname":"Laehemaeki",
    "gn:country_code":"FI",
    "gn:dem":103,
    "gn:feature_class":"P",
    "gn:feature_code":"PPL",
    "gn:name":"L\u00e4hem\u00e4ki",
    "gn:population":0,
    "gn:timezone":"Europe/Helsinki",
    "iso:country":"FI",
    "wof:name":"Laehemaeki",
    "wof:placetype":"locality"
},
  "geometry": {"coordinates":[27.29835,61.69224000000001],"type":"Point"}
}