{
  "type": "Feature",
  "properties": {
    "gn:admin1_code":"1.0",
    "gn:admin2_code":"11.0",
    "gn:admin3_code":"257.0",
    "gn:asciiname":"Bondarby",
    "gn:country_code":"FI",
    "gn:dem":13,
    "gn:feature_class":"P",
    "gn:feature_code":"PPL",
    "gn:name":"Bondarby",
    "gn:population":0,
    "gn:timezone":"Europe/Helsinki",
    "iso:country":"FI",
    "wof:name":"Bondarby",
    "wof:placetype":"locality"
},
  "geometry": {"coordinates":[24.49977,60.09772],"type":"Point"}
}