{
  "type": "Feature",
  "properties": {
    "gn:admin1_code":"18.0",
    "gn:admin2_code":"181.0",
    "gn:admin3_code":"105.0",
    "gn:asciiname":"Heikkilae",
    "gn:country_code":"FI",
    "gn:dem":187,
    "gn:feature_class":"P",
    "gn:feature_code":"PPL",
    "gn:name":"Heikkil\u00e4",
    "gn:population":0,
    "gn:timezone":"Europe/Helsinki",
    "iso:country":"FI",
    "wof:name":"Heikkilae",
    "wof:placetype":"locality"
},
  "geometry": {"coordinates":[29.13333,64.58333],"type":"Point"}
}