{
  "type": "Feature",
  "properties": {
    "gn:admin1_code":"15.0",
    "gn:admin2_code":"151.0",
    "gn:admin3_code":"152.0",
    "gn:asciiname":"Palhojainen",
    "gn:country_code":"FI",
    "gn:dem":21,
    "gn:feature_class":"P",
    "gn:feature_code":"PPL",
    "gn:name":"Palhojainen",
    "gn:population":0,
    "gn:timezone":"Europe/Helsinki",
    "iso:country":"FI",
    "name:fin_x_preferred":[
        "Palhojainen"
    ],
    "wof:name":"Palhojainen",
    "wof:placetype":"locality"
},
  "geometry": {"coordinates":[22.21254,63.01195],"type":"Point"}
}