{
  "type": "Feature",
  "properties": {
    "gn:admin1_code":"6.0",
    "gn:admin2_code":"69.0",
    "gn:admin3_code":"702.0",
    "gn:asciiname":"Harakka",
    "gn:cc2":"FI",
    "gn:country_code":"FI",
    "gn:dem":96,
    "gn:feature_class":"P",
    "gn:feature_code":"PPL",
    "gn:name":"Harakka",
    "gn:population":0,
    "gn:timezone":"Europe/Helsinki",
    "iso:country":"FI",
    "name:fin_x_preferred":[
        "Harakka"
    ],
    "name:und_x_variant":[
        "Harakkala"
    ],
    "wof:name":"Harakka",
    "wof:placetype":"locality"
},
  "geometry": {"coordinates":[24.08993,61.97583],"type":"Point"}
}