{
  "type": "Feature",
  "properties": {
    "gn:admin1_code":"7.0",
    "gn:admin2_code":"71.0",
    "gn:admin3_code":"98.0",
    "gn:asciiname":"Hyvaeneula",
    "gn:country_code":"FI",
    "gn:dem":111,
    "gn:feature_class":"P",
    "gn:feature_code":"PPL",
    "gn:name":"Hyv\u00e4neula",
    "gn:population":0,
    "gn:timezone":"Europe/Helsinki",
    "iso:country":"FI",
    "wof:name":"Hyvaeneula",
    "wof:placetype":"locality"
},
  "geometry": {"coordinates":[25.17619,60.99732],"type":"Point"}
}