{
  "type": "Feature",
  "properties": {
    "gn:admin1_code":"15.0",
    "gn:admin2_code":"153.0",
    "gn:admin3_code":"545.0",
    "gn:asciiname":"Poertbaecken",
    "gn:cc2":"FI",
    "gn:country_code":"FI",
    "gn:dem":28,
    "gn:feature_class":"P",
    "gn:feature_code":"PPL",
    "gn:name":"P\u00f6rtb\u00e4cken",
    "gn:population":0,
    "gn:timezone":"Europe/Helsinki",
    "iso:country":"FI",
    "name:und_x_variant":[
        "P\u00f6rtmossa",
        "P\u00f6rtfors"
    ],
    "wof:name":"Poertbaecken",
    "wof:placetype":"locality"
},
  "geometry": {"coordinates":[21.55646,62.68919],"type":"Point"}
}