{
  "type": "Feature",
  "properties": {
    "gn:admin1_code":"17.0",
    "gn:admin2_code":"178.0",
    "gn:admin3_code":"305.0",
    "gn:asciiname":"Peuravaara",
    "gn:country_code":"FI",
    "gn:dem":300,
    "gn:feature_class":"P",
    "gn:feature_code":"PPL",
    "gn:name":"Peuravaara",
    "gn:population":0,
    "gn:timezone":"Europe/Helsinki",
    "iso:country":"FI",
    "wof:name":"Peuravaara",
    "wof:placetype":"locality"
},
  "geometry": {"coordinates":[30.01667,65.76666999999999],"type":"Point"}
}