{
  "type": "Feature",
  "properties": {
    "gn:admin1_code":"2.0",
    "gn:admin2_code":"24.0",
    "gn:admin3_code":"400.0",
    "gn:asciiname":"Syrjaemaeki",
    "gn:country_code":"FI",
    "gn:dem":13,
    "gn:feature_class":"P",
    "gn:feature_code":"PPL",
    "gn:name":"Syrj\u00e4m\u00e4ki",
    "gn:population":0,
    "gn:timezone":"Europe/Helsinki",
    "iso:country":"FI",
    "wof:name":"Syrjaemaeki",
    "wof:placetype":"locality"
},
  "geometry": {"coordinates":[21.61755,60.87532],"type":"Point"}
}