{
  "type": "Feature",
  "properties": {
    "gn:admin1_code":"1.0",
    "gn:admin2_code":"15.0",
    "gn:admin3_code":"638.0",
    "gn:asciiname":"Boe",
    "gn:country_code":"FI",
    "gn:dem":22,
    "gn:feature_class":"P",
    "gn:feature_code":"PPL",
    "gn:name":"Boe",
    "gn:population":0,
    "gn:timezone":"Europe/Helsinki",
    "iso:country":"FI",
    "name:ceb_x_preferred":[
        "Boe"
    ],
    "name:deu_x_preferred":[
        "Boe"
    ],
    "name:eus_x_preferred":[
        "BOE"
    ],
    "name:fin_x_preferred":[
        "Boe"
    ],
    "name:hrv_x_preferred":[
        "Boe"
    ],
    "name:hun_x_preferred":[
        "Boe"
    ],
    "name:ind_x_preferred":[
        "Boe"
    ],
    "name:nld_x_preferred":[
        "Boe"
    ],
    "name:por_x_preferred":[
        "Boe"
    ],
    "name:ron_x_preferred":[
        "Boe"
    ],
    "name:rus_x_preferred":[
        "\u0411\u043e\u044d"
    ],
    "name:spa_x_preferred":[
        "Boe"
    ],
    "name:swe_x_preferred":[
        "Boe"
    ],
    "wof:name":"Boe",
    "wof:placetype":"locality"
},
  "geometry": {"coordinates":[25.4858,60.39013],"type":"Point"}
}