{
  "type": "Feature",
  "properties": {
    "gn:admin1_code":"19.0",
    "gn:admin2_code":"194.0",
    "gn:admin3_code":"742.0",
    "gn:asciiname":"Ruuvaoja",
    "gn:country_code":"FI",
    "gn:dem":212,
    "gn:feature_class":"P",
    "gn:feature_code":"PPL",
    "gn:name":"Ruuvaoja",
    "gn:population":0,
    "gn:timezone":"Europe/Helsinki",
    "iso:country":"FI",
    "name:eng_x_preferred":[
        "Ruuvaoja"
    ],
    "name:rus_x_preferred":[
        "\u0420\u0443\u0432\u0430\u043e\u044f"
    ],
    "wof:name":"Ruuvaoja",
    "wof:placetype":"locality"
},
  "geometry": {"coordinates":[28.71867,67.65698],"type":"Point"}
}