{
  "type": "Feature",
  "properties": {
    "gn:admin1_code":"19.0",
    "gn:admin2_code":"194.0",
    "gn:admin3_code":"320.0",
    "gn:asciiname":"Kumpu",
    "gn:country_code":"FI",
    "gn:dem":160,
    "gn:feature_class":"P",
    "gn:feature_code":"PPL",
    "gn:name":"Kumpu",
    "gn:population":0,
    "gn:timezone":"Europe/Helsinki",
    "iso:country":"FI",
    "wof:name":"Kumpu",
    "wof:placetype":"locality"
},
  "geometry": {"coordinates":[27.43333,66.88333],"type":"Point"}
}