{
  "type": "Feature",
  "properties": {
    "gn:admin1_code":"15.0",
    "gn:admin2_code":"152.0",
    "gn:admin3_code":"499.0",
    "gn:asciiname":"Helsingby",
    "gn:country_code":"FI",
    "gn:dem":7,
    "gn:feature_class":"P",
    "gn:feature_code":"PPL",
    "gn:name":"Helsingby",
    "gn:population":0,
    "gn:timezone":"Europe/Helsinki",
    "iso:country":"FI",
    "wof:name":"Helsingby",
    "wof:placetype":"locality"
},
  "geometry": {"coordinates":[21.8058,63.02805],"type":"Point"}
}