{
  "type": "Feature",
  "properties": {
    "gn:admin1_code":"11.0",
    "gn:admin2_code":"113.0",
    "gn:admin3_code":"204.0",
    "gn:asciiname":"Salokylae",
    "gn:country_code":"FI",
    "gn:dem":132,
    "gn:feature_class":"P",
    "gn:feature_code":"PPL",
    "gn:name":"Salokyl\u00e4",
    "gn:population":0,
    "gn:timezone":"Europe/Helsinki",
    "iso:country":"FI",
    "name:und_x_variant":[
        "Salonkyl\u00e4",
        "Salokyl\u00e4"
    ],
    "wof:name":"Salokylae",
    "wof:placetype":"locality"
},
  "geometry": {"coordinates":[28.73333,63.06667],"type":"Point"}
}