{
  "type": "Feature",
  "properties": {
    "gn:admin1_code":"19.0",
    "gn:admin2_code":"197.0",
    "gn:admin3_code":"148.0",
    "gn:asciiname":"Avveel-Matti",
    "gn:country_code":"FI",
    "gn:dem":264,
    "gn:feature_class":"P",
    "gn:feature_code":"PPL",
    "gn:name":"Avveel-Matti",
    "gn:population":0,
    "gn:timezone":"Europe/Helsinki",
    "iso:country":"FI",
    "name:eng_x_preferred":[
        "Ivalon-Matti"
    ],
    "name:fin_x_preferred":[
        "Ivalon Matti"
    ],
    "name:rus_x_preferred":[
        "\u0418\u0432\u0430\u043b\u043e\u043d-\u041c\u0430\u0442\u0442\u0438"
    ],
    "name:sme_x_preferred":[
        "Avvil-M\u00e1htte"
    ],
    "name:smn_x_preferred":[
        "Avveel-Matti"
    ],
    "wof:name":"Avveel-Matti",
    "wof:placetype":"locality"
},
  "geometry": {"coordinates":[25.89034,68.36669999999999],"type":"Point"}
}