{
  "type": "Feature",
  "properties": {
    "gn:admin1_code":"12.0",
    "gn:admin2_code":"122.0",
    "gn:admin3_code":"167.0",
    "gn:asciiname":"Haermi",
    "gn:country_code":"FI",
    "gn:dem":172,
    "gn:feature_class":"P",
    "gn:feature_code":"PPL",
    "gn:name":"H\u00e4rmi",
    "gn:population":0,
    "gn:timezone":"Europe/Helsinki",
    "iso:country":"FI",
    "wof:name":"Haermi",
    "wof:placetype":"locality"
},
  "geometry": {"coordinates":[30.62884,62.5238],"type":"Point"}
}