{
  "type": "Feature",
  "properties": {
    "gn:admin1_code":"18.0",
    "gn:admin2_code":"182.0",
    "gn:admin3_code":"765.0",
    "gn:asciiname":"Piippola",
    "gn:country_code":"FI",
    "gn:dem":143,
    "gn:feature_class":"P",
    "gn:feature_code":"PPL",
    "gn:name":"Piippola",
    "gn:population":0,
    "gn:timezone":"Europe/Helsinki",
    "iso:country":"FI",
    "name:ceb_x_preferred":[
        "Piippola"
    ],
    "name:ces_x_preferred":[
        "Piippola"
    ],
    "name:deu_x_preferred":[
        "Piippola"
    ],
    "name:ell_x_preferred":[
        "\u03a0\u03af\u03b9\u03c0\u03bf\u03bb\u03b1"
    ],
    "name:epo_x_preferred":[
        "Piippola"
    ],
    "name:fin_x_preferred":[
        "Piippola"
    ],
    "name:fra_x_preferred":[
        "Piippola"
    ],
    "name:ita_x_preferred":[
        "Piippola"
    ],
    "name:nld_x_preferred":[
        "Piippola"
    ],
    "name:nor_x_preferred":[
        "Piippola"
    ],
    "name:ron_x_preferred":[
        "Piippola"
    ],
    "name:sme_x_preferred":[
        "Piippola"
    ],
    "name:swe_x_preferred":[
        "Piippola"
    ],
    "name:vie_x_preferred":[
        "Piippola"
    ],
    "wof:name":"Piippola",
    "wof:placetype":"locality"
},
  "geometry": {"coordinates":[28.63333,64.03333000000001],"type":"Point"}
}