{
  "type": "Feature",
  "properties": {
    "gn:admin1_code":"15.0",
    "gn:admin2_code":"151.0",
    "gn:admin3_code":"399.0",
    "gn:asciiname":"Toeninmaeki",
    "gn:country_code":"FI",
    "gn:dem":29,
    "gn:feature_class":"P",
    "gn:feature_code":"PPL",
    "gn:name":"T\u00f6ninm\u00e4ki",
    "gn:population":0,
    "gn:timezone":"Europe/Helsinki",
    "iso:country":"FI",
    "name:fin_x_preferred":[
        "T\u00f6ninm\u00e4ki"
    ],
    "wof:name":"Toeninmaeki",
    "wof:placetype":"locality"
},
  "geometry": {"coordinates":[22.04885,62.93551],"type":"Point"}
}