{
  "type": "Feature",
  "properties": {
    "gn:admin1_code":"5.0",
    "gn:admin2_code":"53.0",
    "gn:admin3_code":"981.0",
    "gn:asciiname":"Palikkala",
    "gn:country_code":"FI",
    "gn:dem":87,
    "gn:feature_class":"P",
    "gn:feature_code":"PPL",
    "gn:name":"Palikkala",
    "gn:population":0,
    "gn:timezone":"Europe/Helsinki",
    "iso:country":"FI",
    "wof:name":"Palikkala",
    "wof:placetype":"locality"
},
  "geometry": {"coordinates":[23.35938,60.77423],"type":"Point"}
}