{
  "type": "Feature",
  "properties": {
    "gn:admin1_code":"12.0",
    "gn:admin2_code":"124.0",
    "gn:admin3_code":"260.0",
    "gn:asciiname":"Hirvola",
    "gn:country_code":"FI",
    "gn:dem":125,
    "gn:feature_class":"P",
    "gn:feature_code":"PPL",
    "gn:name":"Hirvola",
    "gn:population":0,
    "gn:timezone":"Europe/Helsinki",
    "iso:country":"FI",
    "wof:name":"Hirvola",
    "wof:placetype":"locality"
},
  "geometry": {"coordinates":[30.16667,62.15],"type":"Point"}
}