{
  "type": "Feature",
  "properties": {
    "gn:admin1_code":"17.0",
    "gn:admin2_code":"177.0",
    "gn:admin3_code":"563.0",
    "gn:asciiname":"Mattisaari",
    "gn:country_code":"FI",
    "gn:dem":85,
    "gn:feature_class":"P",
    "gn:feature_code":"PPL",
    "gn:name":"Mattisaari",
    "gn:population":0,
    "gn:timezone":"Europe/Helsinki",
    "iso:country":"FI",
    "wof:name":"Mattisaari",
    "wof:placetype":"locality"
},
  "geometry": {"coordinates":[24.92599,64.29078],"type":"Point"}
}