{
  "type": "Feature",
  "properties": {
    "gn:admin1_code":"15.0",
    "gn:admin2_code":"154.0",
    "gn:admin3_code":"288.0",
    "gn:asciiname":"Hopsala",
    "gn:cc2":"FI",
    "gn:country_code":"FI",
    "gn:dem":13,
    "gn:feature_class":"P",
    "gn:feature_code":"PPL",
    "gn:name":"Hopsala",
    "gn:population":0,
    "gn:timezone":"Europe/Helsinki",
    "iso:country":"FI",
    "name:und_x_variant":[
        "H\u00e5psala"
    ],
    "wof:name":"Hopsala",
    "wof:placetype":"locality"
},
  "geometry": {"coordinates":[22.97256,63.71417],"type":"Point"}
}