{
  "type": "Feature",
  "properties": {
    "gn:admin1_code":"15.0",
    "gn:admin2_code":"151.0",
    "gn:admin3_code":"399.0",
    "gn:asciiname":"Alhonloukko",
    "gn:country_code":"FI",
    "gn:dem":23,
    "gn:feature_class":"P",
    "gn:feature_code":"PPL",
    "gn:name":"Alhonloukko",
    "gn:population":0,
    "gn:timezone":"Europe/Helsinki",
    "iso:country":"FI",
    "name:fin_x_preferred":[
        "Alhonloukko"
    ],
    "wof:name":"Alhonloukko",
    "wof:placetype":"locality"
},
  "geometry": {"coordinates":[22.02866,63.00597],"type":"Point"}
}