{
  "type": "Feature",
  "properties": {
    "gn:admin1_code":"17.0",
    "gn:admin2_code":"178.0",
    "gn:admin3_code":"832.0",
    "gn:asciiname":"Isokumpu",
    "gn:country_code":"FI",
    "gn:dem":260,
    "gn:feature_class":"P",
    "gn:feature_code":"PPL",
    "gn:name":"Isokumpu",
    "gn:population":0,
    "gn:timezone":"Europe/Helsinki",
    "iso:country":"FI",
    "name:eng_x_preferred":[
        "Isokumpu"
    ],
    "name:rus_x_preferred":[
        "\u0418\u0441\u043e\u043a\u0443\u043c\u043f\u0443"
    ],
    "wof:name":"Isokumpu",
    "wof:placetype":"locality"
},
  "geometry": {"coordinates":[28.42617000000001,65.55956],"type":"Point"}
}