{
  "type": "Feature",
  "properties": {
    "gn:admin1_code":"8.0",
    "gn:admin2_code":"81.0",
    "gn:admin3_code":"286.0",
    "gn:asciiname":"Pieni-Liikkala",
    "gn:country_code":"FI",
    "gn:dem":45,
    "gn:feature_class":"P",
    "gn:feature_code":"PPL",
    "gn:name":"Pieni-Liikkala",
    "gn:population":0,
    "gn:timezone":"Europe/Helsinki",
    "iso:country":"FI",
    "wof:name":"Pieni-Liikkala",
    "wof:placetype":"locality"
},
  "geometry": {"coordinates":[27.01415,60.7182],"type":"Point"}
}