{
  "type": "Feature",
  "properties": {
    "gn:admin1_code":"11.0",
    "gn:admin2_code":"113.0",
    "gn:admin3_code":"687.0",
    "gn:asciiname":"Hiirenjaervi",
    "gn:country_code":"FI",
    "gn:dem":203,
    "gn:feature_class":"P",
    "gn:feature_code":"PPL",
    "gn:name":"Hiirenj\u00e4rvi",
    "gn:population":0,
    "gn:timezone":"Europe/Helsinki",
    "iso:country":"FI",
    "wof:name":"Hiirenjaervi",
    "wof:placetype":"locality"
},
  "geometry": {"coordinates":[28.51667,63.68333000000001],"type":"Point"}
}