{
  "type": "Feature",
  "properties": {
    "gn:admin1_code":"4.0",
    "gn:admin2_code":"43.0",
    "gn:admin3_code":"271.0",
    "gn:asciiname":"Villioe",
    "gn:country_code":"FI",
    "gn:dem":48,
    "gn:feature_class":"P",
    "gn:feature_code":"PPL",
    "gn:name":"Villi\u00f6",
    "gn:population":0,
    "gn:timezone":"Europe/Helsinki",
    "iso:country":"FI",
    "wof:name":"Villioe",
    "wof:placetype":"locality"
},
  "geometry": {"coordinates":[22.33206,61.27054],"type":"Point"}
}