{
  "type": "Feature",
  "properties": {
    "gn:admin1_code":"6.0",
    "gn:admin2_code":"69.0",
    "gn:admin3_code":"936.0",
    "gn:asciiname":"Kantoperae",
    "gn:country_code":"FI",
    "gn:dem":178,
    "gn:feature_class":"P",
    "gn:feature_code":"PPL",
    "gn:name":"Kantoper\u00e4",
    "gn:population":0,
    "gn:timezone":"Europe/Helsinki",
    "iso:country":"FI",
    "name:und_x_variant":[
        "Kantoniemi",
        "Kantoper\u00e4"
    ],
    "wof:name":"Kantoperae",
    "wof:placetype":"locality"
},
  "geometry": {"coordinates":[23.50374,62.19208],"type":"Point"}
}