{
  "type": "Feature",
  "properties": {
    "gn:admin1_code":"6.0",
    "gn:admin2_code":"64.0",
    "gn:admin3_code":"980.0",
    "gn:asciiname":"Teivaala",
    "gn:country_code":"FI",
    "gn:dem":100,
    "gn:feature_class":"P",
    "gn:feature_code":"PPL",
    "gn:name":"Teivaala",
    "gn:population":0,
    "gn:timezone":"Europe/Helsinki",
    "iso:country":"FI",
    "wof:name":"Teivaala",
    "wof:placetype":"locality"
},
  "geometry": {"coordinates":[23.64387,61.53841],"type":"Point"}
}