{
  "type": "Feature",
  "properties": {
    "gn:admin1_code":"16.0",
    "gn:admin2_code":"162.0",
    "gn:admin3_code":"272.0",
    "gn:asciiname":"Alikylae",
    "gn:country_code":"FI",
    "gn:dem":74,
    "gn:feature_class":"P",
    "gn:feature_code":"PPL",
    "gn:name":"Alikyl\u00e4",
    "gn:population":0,
    "gn:timezone":"Europe/Helsinki",
    "iso:country":"FI",
    "name:und_x_variant":[
        "Alikyl\u00e4",
        "Alakyl\u00e4"
    ],
    "wof:name":"Alikylae",
    "wof:placetype":"locality"
},
  "geometry": {"coordinates":[23.79881,63.72626],"type":"Point"}
}