{
  "type": "Feature",
  "properties": {
    "gn:admin1_code":"12.0",
    "gn:admin2_code":"124.0",
    "gn:admin3_code":"260.0",
    "gn:asciiname":"Varmo",
    "gn:cc2":"FI",
    "gn:country_code":"FI",
    "gn:dem":92,
    "gn:feature_class":"P",
    "gn:feature_code":"PPL",
    "gn:name":"Varmo",
    "gn:population":0,
    "gn:timezone":"Europe/Helsinki",
    "iso:country":"FI",
    "name:azb_x_preferred":[
        "\u0648\u0631\u0645\u0648"
    ],
    "name:bel_x_preferred":[
        "\u0412\u0430\u0440\u043c\u0430"
    ],
    "name:bul_x_preferred":[
        "\u0412\u0430\u0440\u043c\u043e"
    ],
    "name:cat_x_preferred":[
        "Varmo"
    ],
    "name:ceb_x_preferred":[
        "Varmo"
    ],
    "name:deu_x_preferred":[
        "Varmo"
    ],
    "name:epo_x_preferred":[
        "Varmo"
    ],
    "name:eus_x_preferred":[
        "Varmo"
    ],
    "name:fas_x_preferred":[
        "\u0648\u0631\u0645\u0648"
    ],
    "name:fra_x_preferred":[
        "Varmo"
    ],
    "name:fur_x_preferred":[
        "Vildivar"
    ],
    "name:hun_x_preferred":[
        "Varmo"
    ],
    "name:hye_x_preferred":[
        "\u054e\u0561\u0580\u0574\u0578"
    ],
    "name:ina_x_preferred":[
        "Varmo"
    ],
    "name:ind_x_preferred":[
        "Varmo"
    ],
    "name:ita_x_preferred":[
        "Varmo"
    ],
    "name:jpn_x_preferred":[
        "\u30f4\u30a1\u30eb\u30e2"
    ],
    "name:kaz_x_preferred":[
        "\u0412\u0430\u0440\u043c\u043e"
    ],
    "name:lat_x_preferred":[
        "Varmum"
    ],
    "name:lmo_x_preferred":[
        "Varmo"
    ],
    "name:msa_x_preferred":[
        "Varmo"
    ],
    "name:nap_x_preferred":[
        "Varmo"
    ],
    "name:nld_x_preferred":[
        "Varmo"
    ],
    "name:pms_x_preferred":[
        "Varmo"
    ],
    "name:pol_x_preferred":[
        "Varmo"
    ],
    "name:por_x_preferred":[
        "Varmo"
    ],
    "name:ron_x_preferred":[
        "Varmo"
    ],
    "name:rus_x_preferred":[
        "\u0412\u0430\u0440\u043c\u043e"
    ],
    "name:scn_x_preferred":[
        "Varmo"
    ],
    "name:spa_x_preferred":[
        "Varmo"
    ],
    "name:srp_x_preferred":[
        "\u0412\u0430\u0440\u043c\u043e"
    ],
    "name:ukr_x_preferred":[
        "\u0412\u0430\u0440\u043c\u043e"
    ],
    "name:und_x_variant":[
        "Varmonniemi"
    ],
    "name:uzb_x_preferred":[
        "Varmo"
    ],
    "name:vec_x_preferred":[
        "Varmo"
    ],
    "name:vie_x_preferred":[
        "Varmo"
    ],
    "name:vol_x_preferred":[
        "Varmo"
    ],
    "name:war_x_preferred":[
        "Varmo"
    ],
    "name:zho_x_preferred":[
        "\u74e6\u5c14\u83ab"
    ],
    "wof:name":"Varmo",
    "wof:placetype":"locality"
},
  "geometry": {"coordinates":[29.93632,61.94023000000001],"type":"Point"}
}