{
  "type": "Feature",
  "properties": {
    "gn:admin1_code":"13.0",
    "gn:admin2_code":"131.0",
    "gn:admin3_code":"892.0",
    "gn:asciiname":"Hankala",
    "gn:country_code":"FI",
    "gn:dem":171,
    "gn:feature_class":"P",
    "gn:feature_code":"PPL",
    "gn:name":"Hankala",
    "gn:population":0,
    "gn:timezone":"Europe/Helsinki",
    "iso:country":"FI",
    "wof:name":"Hankala",
    "wof:placetype":"locality"
},
  "geometry": {"coordinates":[25.48141,62.43393],"type":"Point"}
}