{
  "type": "Feature",
  "properties": {
    "gn:admin1_code":"2.0",
    "gn:admin2_code":"24.0",
    "gn:admin3_code":"304.0",
    "gn:asciiname":"Etelae-Vartsala",
    "gn:country_code":"FI",
    "gn:dem":11,
    "gn:feature_class":"P",
    "gn:feature_code":"PPL",
    "gn:name":"Etel\u00e4-Vartsala",
    "gn:population":0,
    "gn:timezone":"Europe/Helsinki",
    "iso:country":"FI",
    "name:und_x_variant":[
        "S\u00f6derby",
        "Etel\u00e4-Vartsala"
    ],
    "wof:name":"Etelae-Vartsala",
    "wof:placetype":"locality"
},
  "geometry": {"coordinates":[21.30215,60.51075],"type":"Point"}
}