{
  "type": "Feature",
  "properties": {
    "gn:admin1_code":"11.0",
    "gn:admin2_code":"115.0",
    "gn:admin3_code":"921.0",
    "gn:asciiname":"Ahveninen",
    "gn:country_code":"FI",
    "gn:dem":118,
    "gn:feature_class":"P",
    "gn:feature_code":"PPL",
    "gn:name":"Ahveninen",
    "gn:population":0,
    "gn:timezone":"Europe/Helsinki",
    "iso:country":"FI",
    "name:eng_x_preferred":[
        "Ahveninen"
    ],
    "name:rus_x_preferred":[
        "\u0410\u0445\u0432\u0435\u043d\u0438\u043d\u0435\u043d"
    ],
    "wof:name":"Ahveninen",
    "wof:placetype":"locality"
},
  "geometry": {"coordinates":[26.2869,62.91259],"type":"Point"}
}