{
  "type": "Feature",
  "properties": {
    "gn:admin1_code":"17.0",
    "gn:admin2_code":"177.0",
    "gn:admin3_code":"9.0",
    "gn:asciiname":"Kahma",
    "gn:country_code":"FI",
    "gn:dem":46,
    "gn:feature_class":"P",
    "gn:feature_code":"PPL",
    "gn:name":"Kahma",
    "gn:population":0,
    "gn:timezone":"Europe/Helsinki",
    "iso:country":"FI",
    "wof:name":"Kahma",
    "wof:placetype":"locality"
},
  "geometry": {"coordinates":[24.26667,64.16667],"type":"Point"}
}