{
  "type": "Feature",
  "properties": {
    "gn:admin1_code":"4.0",
    "gn:admin2_code":"43.0",
    "gn:admin3_code":"531.0",
    "gn:asciiname":"Kivialho",
    "gn:cc2":"FI",
    "gn:country_code":"FI",
    "gn:dem":29,
    "gn:feature_class":"P",
    "gn:feature_code":"PPL",
    "gn:name":"Kivialho",
    "gn:population":0,
    "gn:timezone":"Europe/Helsinki",
    "iso:country":"FI",
    "name:und_x_variant":[
        "Alho",
        "Kivialho"
    ],
    "wof:name":"Kivialho",
    "wof:placetype":"locality"
},
  "geometry": {"coordinates":[22.05108,61.408],"type":"Point"}
}