{
  "type": "Feature",
  "properties": {
    "gn:country":"FI",
    "gn:fcode":"PPL",
    "gn:population":542,
    "iso:country":"FI",
    "name:ceb_x_preferred":[
        "\u00d6stersundom"
    ],
    "name:eng_x_preferred":[
        "\u00d6stersundom"
    ],
    "name:fas_x_preferred":[
        "\u0627\u0648\u0633\u062a\u0631\u0633\u0648\u0646\u062f\u0648\u0645"
    ],
    "name:fin_x_preferred":[
        "\u00d6stersundom"
    ],
    "name:fra_x_preferred":[
        "\u00d6stersundom"
    ],
    "name:rus_x_preferred":[
        "\u042d\u0441\u0442\u0435\u0440\u0441\u0443\u043d\u0434\u043e\u043c"
    ],
    "name:spa_x_preferred":[
        "\u00d6stersundom"
    ],
    "name:swe_x_preferred":[
        "\u00d6stersundom"
    ],
    "name:tur_x_preferred":[
        "\u00d6stersundom"
    ],
    "qs_pg:aaroncc":"FI",
    "qs_pg:gn_country":"FI",
    "qs_pg:gn_fcode":"PPL",
    "qs_pg:gn_pop":542,
    "qs_pg:name":"It\u00e4salmi",
    "qs_pg:name_adm0":"Suomi",
    "qs_pg:name_adm1":"Uudenmaan maakunta",
    "qs_pg:photos_9r":0,
    "qs_pg:photos_sr":0,
    "qs_pg:pop_sr":2,
    "qs_pg:qs_pg_placetype":"locality",
    "qs_pg:qs_pg_placetype_gp":"Town",
    "qs_pg:woe_adm0":23424812,
    "woe:adm0_id":23424812,
    "woe:name_adm0":"Suomi",
    "woe:name_adm1":"Uudenmaan maakunta",
    "woe:placetype":"Town",
    "wof:name":"It\u00e4salmi",
    "wof:placetype":"locality",
    "wof:population":542
},
  "geometry": {"coordinates":[25.19278,60.25778],"type":"Point"}
}