{
  "type": "Feature",
  "properties": {
    "gn:admin1_code":"2.0",
    "gn:admin2_code":"23.0",
    "gn:admin3_code":"853.0",
    "gn:asciiname":"Paimala",
    "gn:country_code":"FI",
    "gn:dem":11,
    "gn:feature_class":"P",
    "gn:feature_code":"PPL",
    "gn:name":"Paimala",
    "gn:population":0,
    "gn:timezone":"Europe/Helsinki",
    "iso:country":"FI",
    "name:deu_x_preferred":[
        "Paimala"
    ],
    "name:est_x_preferred":[
        "Paimala"
    ],
    "name:fra_x_preferred":[
        "Paimala"
    ],
    "name:hye_x_preferred":[
        "\u054a\u0561\u056b\u0574\u0561\u056c\u0561"
    ],
    "name:pol_x_preferred":[
        "Paimala"
    ],
    "name:spa_x_preferred":[
        "Paimala"
    ],
    "name:ukr_x_preferred":[
        "\u041f\u0430\u0439\u043c\u0430\u043b\u0430"
    ],
    "name:vol_x_preferred":[
        "Paimala"
    ],
    "wof:name":"Paimala",
    "wof:placetype":"locality"
},
  "geometry": {"coordinates":[22.34558,60.51309000000001],"type":"Point"}
}