{
  "type": "Feature",
  "properties": {
    "gn:admin1_code":"1.0",
    "gn:admin2_code":"11.0",
    "gn:admin3_code":"257.0",
    "gn:asciiname":"Tanskarla",
    "gn:cc2":"FI",
    "gn:country_code":"FI",
    "gn:dem":11,
    "gn:feature_class":"P",
    "gn:feature_code":"PPL",
    "gn:name":"Tanskarla",
    "gn:population":0,
    "gn:timezone":"Europe/Helsinki",
    "iso:country":"FI",
    "name:fin_x_preferred":[
        "Tanskarla"
    ],
    "name:swe_x_preferred":[
        "Danskarby"
    ],
    "wof:name":"Tanskarla",
    "wof:placetype":"locality"
},
  "geometry": {"coordinates":[24.57296,60.11163000000001],"type":"Point"}
}