{
  "type": "Feature",
  "properties": {
    "gn:admin1_code":"2.0",
    "gn:admin2_code":"25.0",
    "gn:admin3_code":"284.0",
    "gn:asciiname":"Patakoski",
    "gn:country_code":"FI",
    "gn:dem":79,
    "gn:feature_class":"P",
    "gn:feature_code":"PPL",
    "gn:name":"Patakoski",
    "gn:population":0,
    "gn:timezone":"Europe/Helsinki",
    "iso:country":"FI",
    "wof:name":"Patakoski",
    "wof:placetype":"locality"
},
  "geometry": {"coordinates":[23.16347,60.65195],"type":"Point"}
}