{
  "type": "Feature",
  "properties": {
    "gn:admin1_code":"13.0",
    "gn:admin2_code":"131.0",
    "gn:admin3_code":"850.0",
    "gn:asciiname":"Ilmapohja",
    "gn:cc2":"FI",
    "gn:country_code":"FI",
    "gn:dem":112,
    "gn:feature_class":"P",
    "gn:feature_code":"PPL",
    "gn:name":"Ilmapohja",
    "gn:population":0,
    "gn:timezone":"Europe/Helsinki",
    "iso:country":"FI",
    "name:und_x_variant":[
        "Ilmoj\u00e4rvi",
        "Ilmapohja"
    ],
    "wof:name":"Ilmapohja",
    "wof:placetype":"locality"
},
  "geometry": {"coordinates":[25.85,62.13333000000001],"type":"Point"}
}