{
  "type": "Feature",
  "properties": {
    "gn:admin1_code":"14.0",
    "gn:admin2_code":"141.0",
    "gn:admin3_code":"232.0",
    "gn:asciiname":"Havuskylae",
    "gn:country_code":"FI",
    "gn:dem":106,
    "gn:feature_class":"P",
    "gn:feature_code":"PPL",
    "gn:name":"Havuskyl\u00e4",
    "gn:population":0,
    "gn:timezone":"Europe/Helsinki",
    "iso:country":"FI",
    "name:und_x_variant":[
        "Havunen",
        "Havuskyl\u00e4"
    ],
    "wof:name":"Havuskylae",
    "wof:placetype":"locality"
},
  "geometry": {"coordinates":[22.22643,62.39468000000001],"type":"Point"}
}