{
  "type": "Feature",
  "properties": {
    "gn:admin1_code":"1.0",
    "gn:admin2_code":"11.0",
    "gn:admin3_code":"49.0",
    "gn:asciiname":"Koskelo",
    "gn:country_code":"FI",
    "gn:dem":30,
    "gn:feature_class":"P",
    "gn:feature_code":"PPL",
    "gn:name":"Koskelo",
    "gn:population":0,
    "gn:timezone":"Europe/Helsinki",
    "iso:country":"FI",
    "name:dan_x_preferred":[
        "Skrakaby"
    ],
    "name:isl_x_preferred":[
        "Skrakaby"
    ],
    "name:nor_x_preferred":[
        "Skrakaby"
    ],
    "name:swe_x_preferred":[
        "Skrakaby"
    ],
    "wof:name":"Koskelo",
    "wof:placetype":"locality"
},
  "geometry": {"coordinates":[24.73065,60.25442],"type":"Point"}
}