{
  "type": "Feature",
  "properties": {
    "gn:admin1_code":"19.0",
    "gn:admin2_code":"194.0",
    "gn:admin3_code":"320.0",
    "gn:asciiname":"Niemelae",
    "gn:country_code":"FI",
    "gn:dem":157,
    "gn:feature_class":"P",
    "gn:feature_code":"PPL",
    "gn:name":"Niemel\u00e4",
    "gn:population":0,
    "gn:timezone":"Europe/Helsinki",
    "iso:country":"FI",
    "wof:name":"Niemelae",
    "wof:placetype":"locality"
},
  "geometry": {"coordinates":[27.35,66.46666999999999],"type":"Point"}
}