{
  "type": "Feature",
  "properties": {
    "gn:admin1_code":"14.0",
    "gn:admin2_code":"142.0",
    "gn:admin3_code":"743.0",
    "gn:asciiname":"Juupakylae",
    "gn:country_code":"FI",
    "gn:dem":144,
    "gn:feature_class":"P",
    "gn:feature_code":"PPL",
    "gn:name":"Juupakyl\u00e4",
    "gn:population":0,
    "gn:timezone":"Europe/Helsinki",
    "iso:country":"FI",
    "name:und_x_variant":[
        "Juupasalo",
        "Juupakyl\u00e4"
    ],
    "wof:name":"Juupakylae",
    "wof:placetype":"locality"
},
  "geometry": {"coordinates":[23.32717,62.45285],"type":"Point"}
}