{
  "type": "Feature",
  "properties": {
    "gn:admin1_code":"11.0",
    "gn:admin2_code":"115.0",
    "gn:admin3_code":"778.0",
    "gn:asciiname":"Lempyy",
    "gn:country_code":"FI",
    "gn:dem":99,
    "gn:feature_class":"P",
    "gn:feature_code":"PPL",
    "gn:name":"Lempyy",
    "gn:population":0,
    "gn:timezone":"Europe/Helsinki",
    "iso:country":"FI",
    "name:eng_x_preferred":[
        "Lempyy"
    ],
    "name:rus_x_preferred":[
        "\u041b\u0435\u043c\u043f\u044e"
    ],
    "wof:name":"Lempyy",
    "wof:placetype":"locality"
},
  "geometry": {"coordinates":[27.36818,62.65049000000001],"type":"Point"}
}