{
  "type": "Feature",
  "properties": {
    "gn:admin1_code":"18.0",
    "gn:admin2_code":"181.0",
    "gn:admin3_code":"290.0",
    "gn:asciiname":"Kuusamonkylae",
    "gn:country_code":"FI",
    "gn:dem":171,
    "gn:feature_class":"P",
    "gn:feature_code":"PPL",
    "gn:name":"Kuusamonkyl\u00e4",
    "gn:population":0,
    "gn:timezone":"Europe/Helsinki",
    "iso:country":"FI",
    "name:fin_x_preferred":[
        "Kuusamonkyl\u00e4"
    ],
    "wof:name":"Kuusamonkylae",
    "wof:placetype":"locality"
},
  "geometry": {"coordinates":[29.27209,64.42346999999999],"type":"Point"}
}