{
  "type": "Feature",
  "properties": {
    "gn:population":1486,
    "iso:country":"FI",
    "name:bul_x_preferred":[
        "\u041c\u0443\u0440\u043b\u0430"
    ],
    "name:ceb_x_preferred":[
        "Muurla"
    ],
    "name:deu_x_preferred":[
        "Muurla"
    ],
    "name:eng_x_preferred":[
        "Muurla"
    ],
    "name:fin_x_preferred":[
        "Muurla"
    ],
    "name:fra_x_preferred":[
        "Muurla"
    ],
    "name:ita_x_preferred":[
        "Muurla"
    ],
    "name:nld_x_preferred":[
        "Muurla"
    ],
    "name:nob_x_preferred":[
        "Muurla"
    ],
    "name:nor_x_preferred":[
        "Muurla"
    ],
    "name:ron_x_preferred":[
        "Muurla"
    ],
    "name:sme_x_preferred":[
        "Muurla"
    ],
    "name:swe_x_preferred":[
        "Muurla"
    ],
    "name:vie_x_preferred":[
        "Muurla"
    ],
    "qs:a0":"Suomi#Finland",
    "qs:a1":"*Varsinais-Suomi#Egentliga Finland",
    "qs:a1r":"0Lounais-Suomen AVI#Sydv\u00e4stra Finlands RFV",
    "qs:adm0":"Suomi#Finland",
    "qs:la_lc":"*",
    "qs:level":"locality",
    "qs:loc":"Muurla",
    "qs:loc_alt":"Muurla",
    "qs:pop":0,
    "qs:type":"buffered point",
    "wd:wordcount":108,
    "wof:name":"Muurla",
    "wof:placetype":"locality",
    "wof:population":1486
},
  "geometry": {"coordinates":[23.287718,60.345265],"type":"Point"}
}