{
  "type": "Feature",
  "properties": {
    "gn:admin1_code":"12.0",
    "gn:admin2_code":"125.0",
    "gn:admin3_code":"422.0",
    "gn:asciiname":"Inari",
    "gn:country_code":"FI",
    "gn:dem":230,
    "gn:feature_class":"P",
    "gn:feature_code":"PPL",
    "gn:name":"Inari",
    "gn:population":0,
    "gn:timezone":"Europe/Helsinki",
    "iso:country":"FI",
    "name:eng_x_preferred":[
        "Inari"
    ],
    "name:rus_x_preferred":[
        "\u0418\u043d\u0430\u0440\u0438"
    ],
    "wof:name":"Inari",
    "wof:placetype":"locality"
},
  "geometry": {"coordinates":[30.95327,63.29979],"type":"Point"}
}