{
  "type": "Feature",
  "properties": {
    "gn:admin1_code":"2.0",
    "gn:admin2_code":"24.0",
    "gn:admin3_code":"631.0",
    "gn:asciiname":"Kukola",
    "gn:country_code":"FI",
    "gn:dem":1,
    "gn:feature_class":"P",
    "gn:feature_code":"PPL",
    "gn:name":"Kukola",
    "gn:population":0,
    "gn:timezone":"Europe/Helsinki",
    "iso:country":"FI",
    "wof:name":"Kukola",
    "wof:placetype":"locality"
},
  "geometry": {"coordinates":[21.3954,61.05021],"type":"Point"}
}