{
  "type": "Feature",
  "properties": {
    "gn:admin1_code":"17.0",
    "gn:admin2_code":"178.0",
    "gn:admin3_code":"305.0",
    "gn:asciiname":"Nissi",
    "gn:cc2":"FI",
    "gn:country_code":"FI",
    "gn:dem":277,
    "gn:feature_class":"P",
    "gn:feature_code":"PPL",
    "gn:name":"Nissi",
    "gn:population":0,
    "gn:timezone":"Europe/Helsinki",
    "iso:country":"FI",
    "name:eng_x_preferred":[
        "Nissi"
    ],
    "name:rus_x_preferred":[
        "\u041d\u0438\u0441\u0441\u0438\u043d\u0432\u0430\u0440\u0430"
    ],
    "name:und_x_variant":[
        "Nissivaara"
    ],
    "wof:name":"Nissi",
    "wof:placetype":"locality"
},
  "geometry": {"coordinates":[29.13333,66.05],"type":"Point"}
}