{
  "type": "Feature",
  "properties": {
    "gn:admin1_code":"14.0",
    "gn:admin2_code":"144.0",
    "gn:admin3_code":"10.0",
    "gn:asciiname":"Kattelus",
    "gn:country_code":"FI",
    "gn:dem":166,
    "gn:feature_class":"P",
    "gn:feature_code":"PPL",
    "gn:name":"Kattelus",
    "gn:population":0,
    "gn:timezone":"Europe/Helsinki",
    "iso:country":"FI",
    "wof:name":"Kattelus",
    "wof:placetype":"locality"
},
  "geometry": {"coordinates":[23.76767000000001,62.47702],"type":"Point"}
}