{
  "type": "Feature",
  "properties": {
    "gn:admin1_code":"17.0",
    "gn:admin2_code":"171.0",
    "gn:admin3_code":"494.0",
    "gn:asciiname":"Paelli",
    "gn:country_code":"FI",
    "gn:dem":72,
    "gn:feature_class":"P",
    "gn:feature_code":"PPL",
    "gn:name":"P\u00e4lli",
    "gn:population":0,
    "gn:timezone":"Europe/Helsinki",
    "iso:country":"FI",
    "wof:name":"Paelli",
    "wof:placetype":"locality"
},
  "geometry": {"coordinates":[26.18669,64.83807],"type":"Point"}
}