{
  "type": "Feature",
  "properties": {
    "gn:admin1_code":"5.0",
    "gn:admin2_code":"52.0",
    "gn:admin3_code":"433.0",
    "gn:asciiname":"Leppaelahti",
    "gn:country_code":"FI",
    "gn:dem":113,
    "gn:feature_class":"P",
    "gn:feature_code":"PPL",
    "gn:name":"Lepp\u00e4lahti",
    "gn:population":0,
    "gn:timezone":"Europe/Helsinki",
    "iso:country":"FI",
    "wof:name":"Leppaelahti",
    "wof:placetype":"locality"
},
  "geometry": {"coordinates":[24.41667,60.66667],"type":"Point"}
}