{
  "type": "Feature",
  "properties": {
    "gn:admin1_code":"18.0",
    "gn:admin2_code":"181.0",
    "gn:admin3_code":"620.0",
    "gn:asciiname":"Aittokylae",
    "gn:country_code":"FI",
    "gn:dem":213,
    "gn:feature_class":"P",
    "gn:feature_code":"PPL",
    "gn:name":"Aittokyl\u00e4",
    "gn:population":0,
    "gn:timezone":"Europe/Helsinki",
    "iso:country":"FI",
    "wof:name":"Aittokylae",
    "wof:placetype":"locality"
},
  "geometry": {"coordinates":[27.737,64.92685999999999],"type":"Point"}
}