{
  "type": "Feature",
  "properties": {
    "gn:admin1_code":"14.0",
    "gn:admin2_code":"146.0",
    "gn:admin3_code":"934.0",
    "gn:asciiname":"Pokela",
    "gn:country_code":"FI",
    "gn:dem":78,
    "gn:feature_class":"P",
    "gn:feature_code":"PPL",
    "gn:name":"Pokela",
    "gn:population":0,
    "gn:timezone":"Europe/Helsinki",
    "iso:country":"FI",
    "name:fin_x_preferred":[
        "Pokela"
    ],
    "wof:name":"Pokela",
    "wof:placetype":"locality"
},
  "geometry": {"coordinates":[23.78281,63.13864],"type":"Point"}
}