{
  "type": "Feature",
  "properties": {
    "gn:admin1_code":"1.0",
    "gn:admin2_code":"11.0",
    "gn:admin3_code":"92.0",
    "gn:asciiname":"Groenkulla",
    "gn:country_code":"FI",
    "gn:dem":38,
    "gn:feature_class":"P",
    "gn:feature_code":"PPL",
    "gn:name":"Gr\u00f6nkulla",
    "gn:population":0,
    "gn:timezone":"Europe/Helsinki",
    "iso:country":"FI",
    "name:fin_x_preferred":[
        "Viherkumpu"
    ],
    "name:swe_x_preferred":[
        "Gr\u00f6nkulla"
    ],
    "wof:name":"Groenkulla",
    "wof:placetype":"locality"
},
  "geometry": {"coordinates":[24.87791,60.28006],"type":"Point"}
}