{
  "type": "Feature",
  "properties": {
    "gn:admin1_code":"14.0",
    "gn:admin2_code":"142.0",
    "gn:admin3_code":"301.0",
    "gn:asciiname":"Korvenkylae",
    "gn:country_code":"FI",
    "gn:dem":121,
    "gn:feature_class":"P",
    "gn:feature_code":"PPL",
    "gn:name":"Korvenkyl\u00e4",
    "gn:population":0,
    "gn:timezone":"Europe/Helsinki",
    "iso:country":"FI",
    "name:und_x_variant":[
        "Per\u00e4korvenkyl\u00e4",
        "Per\u00e4korpi",
        "Korvenkyl\u00e4"
    ],
    "wof:name":"Korvenkylae",
    "wof:placetype":"locality"
},
  "geometry": {"coordinates":[22.20939,62.56657],"type":"Point"}
}