{
  "type": "Feature",
  "properties": {
    "gn:admin1_code":"1.0",
    "gn:admin2_code":"11.0",
    "gn:admin3_code":"927.0",
    "gn:asciiname":"Moksi",
    "gn:country_code":"FI",
    "gn:dem":103,
    "gn:feature_class":"P",
    "gn:feature_code":"PPLL",
    "gn:name":"Moksi",
    "gn:population":0,
    "gn:timezone":"Europe/Helsinki",
    "iso:country":"FI",
    "wof:name":"Moksi",
    "wof:placetype":"locality"
},
  "geometry": {"coordinates":[24.419,60.48366],"type":"Point"}
}