{
  "type": "Feature",
  "properties": {
    "gn:admin1_code":"15.0",
    "gn:admin2_code":"152.0",
    "gn:admin3_code":"905.0",
    "gn:asciiname":"Sausolannurkka",
    "gn:country_code":"FI",
    "gn:dem":16,
    "gn:feature_class":"P",
    "gn:feature_code":"PPL",
    "gn:name":"Sausolannurkka",
    "gn:population":0,
    "gn:timezone":"Europe/Helsinki",
    "iso:country":"FI",
    "name:fin_x_preferred":[
        "Sausolannurkka"
    ],
    "wof:name":"Sausolannurkka",
    "wof:placetype":"locality"
},
  "geometry": {"coordinates":[21.9687,63.06438000000001],"type":"Point"}
}