{
  "type": "Feature",
  "properties": {
    "gn:gn_country":"FI",
    "gn:gn_fcode":"PPL",
    "gn:gn_pop":0,
    "iso:country":"FI",
    "name:eng_x_preferred":[
        "Raaj\u00e4rvi"
    ],
    "name:rus_x_preferred":[
        "\u0420\u0430\u044f\u0440\u0432\u0438"
    ],
    "qs_pg:aaroncc":"FI",
    "qs_pg:gn_country":"FI",
    "qs_pg:gn_fcode":"PPL",
    "qs_pg:gn_pop":0,
    "qs_pg:name":"Raaj\u00e4rvi",
    "qs_pg:name_adm0":"Suomi",
    "qs_pg:name_adm1":"Lapin maakunta",
    "qs_pg:photos_9r":0,
    "qs_pg:photos_sr":0,
    "qs_pg:pop_sr":0,
    "qs_pg:qs_pg_placetype":"locality",
    "qs_pg:qs_pg_placetype_gp":"Town",
    "qs_pg:woe_adm0":23424812,
    "woe:adm0_id":23424812,
    "woe:name_adm0":"Suomi",
    "woe:name_adm1":"Lapin maakunta",
    "woe:placetype":"Town",
    "wof:name":"Raaj\u00e4rvi",
    "wof:placetype":"locality"
},
  "geometry": {"coordinates":[27.06667,66.68333],"type":"Point"}
}