{
  "type": "Feature",
  "properties": {
    "gn:admin1_code":"6.0",
    "gn:admin2_code":"64.0",
    "gn:admin3_code":"980.0",
    "gn:asciiname":"Haveri",
    "gn:cc2":"FI",
    "gn:country_code":"FI",
    "gn:dem":93,
    "gn:feature_class":"P",
    "gn:feature_code":"PPL",
    "gn:name":"Haveri",
    "gn:population":0,
    "gn:timezone":"Europe/Helsinki",
    "iso:country":"FI",
    "name:bar_x_preferred":[
        "Haveri"
    ],
    "name:ben_x_preferred":[
        "\u09b9\u09be\u09ac\u09c7\u09b0\u09c0"
    ],
    "name:bpy_x_preferred":[
        "\u09b9\u09be\u09ac\u09c7\u09b0\u09c0"
    ],
    "name:ceb_x_preferred":[
        "Haveri"
    ],
    "name:deu_x_preferred":[
        "Haveri"
    ],
    "name:fra_x_preferred":[
        "Haveri"
    ],
    "name:guj_x_preferred":[
        "\u0ab9\u0abe\u0ab5\u0ac7\u0ab0\u0ac0"
    ],
    "name:hin_x_preferred":[
        "\u0939\u093e\u0935\u0947\u0930\u0940"
    ],
    "name:ita_x_preferred":[
        "Haveri"
    ],
    "name:mar_x_preferred":[
        "\u0939\u093e\u0935\u0947\u0930\u0940"
    ],
    "name:mlg_x_preferred":[
        "Haveri"
    ],
    "name:msa_x_preferred":[
        "Haveri"
    ],
    "name:new_x_preferred":[
        "\u0939\u093e\u0935\u0947\u0930\u0940"
    ],
    "name:nld_x_preferred":[
        "Haveri"
    ],
    "name:rus_x_preferred":[
        "\u0425\u0430\u0432\u0435\u0440\u0438"
    ],
    "name:san_x_preferred":[
        "\u0939\u093e\u0935\u0947\u0930\u0940"
    ],
    "name:spa_x_preferred":[
        "Haveri"
    ],
    "name:swe_x_preferred":[
        "Haveri"
    ],
    "name:tam_x_preferred":[
        "\u0b86\u0bb5\u0bc7\u0bb0\u0bbf"
    ],
    "name:und_x_variant":[
        "Salo-Haveri"
    ],
    "name:urd_x_preferred":[
        "\u06c1\u0627\u0648\u06cc\u0631\u06cc"
    ],
    "name:vie_x_preferred":[
        "Haveri"
    ],
    "name:zho_x_preferred":[
        "\u54c8\u97e6\u91cc"
    ],
    "wof:name":"Haveri",
    "wof:placetype":"locality"
},
  "geometry": {"coordinates":[23.24921,61.7114],"type":"Point"}
}