{
  "type": "Feature",
  "properties": {
    "gn:admin1_code":"6.0",
    "gn:admin2_code":"64.0",
    "gn:admin3_code":"980.0",
    "gn:asciiname":"Haveri",
    "gn:cc2":"FI",
    "gn:country_code":"FI",
    "gn:dem":93,
    "gn:feature_class":"P",
    "gn:feature_code":"PPL",
    "gn:name":"Haveri",
    "gn:population":0,
    "gn:timezone":"Europe/Helsinki",
    "iso:country":"FI",
    "name:und_x_variant":[
        "Salo-Haveri"
    ],
    "wof:name":"Haveri",
    "wof:placetype":"locality"
},
  "geometry": {"coordinates":[23.24921,61.7114],"type":"Point"}
}