{
  "type": "Feature",
  "properties": {
    "gn:admin1_code":"15.0",
    "gn:admin2_code":"152.0",
    "gn:admin3_code":"499.0",
    "gn:asciiname":"Lansor",
    "gn:country_code":"FI",
    "gn:dem":5,
    "gn:feature_class":"P",
    "gn:feature_code":"PPL",
    "gn:name":"Lansor",
    "gn:population":0,
    "gn:timezone":"Europe/Helsinki",
    "iso:country":"FI",
    "name:swe_x_preferred":[
        "Lansor"
    ],
    "wof:name":"Lansor",
    "wof:placetype":"locality"
},
  "geometry": {"coordinates":[21.87477,63.11324000000001],"type":"Point"}
}