{
  "type": "Feature",
  "properties": {
    "gn:admin1_code":"15.0",
    "gn:admin2_code":"154.0",
    "gn:admin3_code":"893.0",
    "gn:asciiname":"Rank",
    "gn:country_code":"FI",
    "gn:dem":6,
    "gn:feature_class":"P",
    "gn:feature_code":"PPL",
    "gn:name":"Rank",
    "gn:population":0,
    "gn:timezone":"Europe/Helsinki",
    "iso:country":"FI",
    "name:arz_x_preferred":[
        "\u0631\u0646\u0643"
    ],
    "name:deu_x_preferred":[
        "Rank"
    ],
    "name:epo_x_preferred":[
        "Rank"
    ],
    "name:fas_x_preferred":[
        "\u0631\u062a\u0628\u0647"
    ],
    "name:fra_x_preferred":[
        "Rank"
    ],
    "name:hun_x_preferred":[
        "Rang"
    ],
    "name:jpn_x_preferred":[
        "\u30e9\u30f3\u30af"
    ],
    "name:rus_x_preferred":[
        "\u0420\u0430\u043d\u043a"
    ],
    "name:spa_x_preferred":[
        "Rank"
    ],
    "name:swe_x_preferred":[
        "Rank"
    ],
    "wof:name":"Rank",
    "wof:placetype":"locality"
},
  "geometry": {"coordinates":[22.55,63.56667],"type":"Point"}
}