{
  "type": "Feature",
  "properties": {
    "gn:admin1_code":"14.0",
    "gn:admin2_code":"146.0",
    "gn:admin3_code":"5.0",
    "gn:asciiname":"Leuna",
    "gn:country_code":"FI",
    "gn:dem":150,
    "gn:feature_class":"P",
    "gn:feature_code":"PPL",
    "gn:name":"Leuna",
    "gn:population":0,
    "gn:timezone":"Europe/Helsinki",
    "iso:country":"FI",
    "name:ara_x_preferred":[
        "\u0644\u0648\u064a\u0646\u0627"
    ],
    "name:azb_x_preferred":[
        "\u0644\u0648\u06cc\u0646\u0627"
    ],
    "name:bak_x_preferred":[
        "\u041b\u043e\u0439\u043d\u0430"
    ],
    "name:ceb_x_preferred":[
        "Leuna"
    ],
    "name:ces_x_preferred":[
        "Leuna"
    ],
    "name:dan_x_preferred":[
        "Leuna"
    ],
    "name:deu_x_preferred":[
        "Leuna"
    ],
    "name:epo_x_preferred":[
        "Leuna"
    ],
    "name:fas_x_preferred":[
        "\u0644\u0648\u06cc\u0646\u0627"
    ],
    "name:fra_x_preferred":[
        "Leuna"
    ],
    "name:hun_x_preferred":[
        "Leuna"
    ],
    "name:ita_x_preferred":[
        "Leuna"
    ],
    "name:lat_x_preferred":[
        "Leuna"
    ],
    "name:mkd_x_preferred":[
        "\u041b\u043e\u0458\u043d\u0430"
    ],
    "name:msa_x_preferred":[
        "Leuna"
    ],
    "name:nld_x_preferred":[
        "Leuna"
    ],
    "name:pol_x_preferred":[
        "Leuna"
    ],
    "name:por_x_preferred":[
        "Leuna"
    ],
    "name:ron_x_preferred":[
        "Leuna"
    ],
    "name:rus_x_preferred":[
        "\u041b\u043e\u0439\u043d\u0430"
    ],
    "name:spa_x_preferred":[
        "Leuna"
    ],
    "name:srp_x_preferred":[
        "\u041b\u043e\u0458\u043d\u0430"
    ],
    "name:swe_x_preferred":[
        "Leuna"
    ],
    "name:szl_x_preferred":[
        "Leuna"
    ],
    "name:ukr_x_preferred":[
        "\u041b\u043e\u0439\u043d\u0430"
    ],
    "name:uzb_x_preferred":[
        "Leuna"
    ],
    "name:vie_x_preferred":[
        "Leuna"
    ],
    "name:vol_x_preferred":[
        "Leuna"
    ],
    "name:war_x_preferred":[
        "Leuna"
    ],
    "name:zho_x_preferred":[
        "\u6d1b\u4f0a\u7eb3"
    ],
    "wof:name":"Leuna",
    "wof:placetype":"locality"
},
  "geometry": {"coordinates":[23.66667,62.88333000000001],"type":"Point"}
}