{
  "type": "Feature",
  "properties": {
    "gn:admin1_code":"9.0",
    "gn:admin2_code":"93.0",
    "gn:admin3_code":"689.0",
    "gn:asciiname":"Pallaitniemi",
    "gn:country_code":"FI",
    "gn:dem":108,
    "gn:feature_class":"P",
    "gn:feature_code":"PPL",
    "gn:name":"Pallaitniemi",
    "gn:population":0,
    "gn:timezone":"Europe/Helsinki",
    "iso:country":"FI",
    "wof:name":"Pallaitniemi",
    "wof:placetype":"locality"
},
  "geometry": {"coordinates":[29.22743,61.41435],"type":"Point"}
}