{
  "type": "Feature",
  "properties": {
    "gn:admin1_code":"17.0",
    "gn:admin2_code":"174.0",
    "gn:admin3_code":"678.0",
    "gn:asciiname":"Ohimaanperae",
    "gn:country_code":"FI",
    "gn:dem":91,
    "gn:feature_class":"P",
    "gn:feature_code":"PPL",
    "gn:name":"Ohimaanper\u00e4",
    "gn:population":0,
    "gn:timezone":"Europe/Helsinki",
    "iso:country":"FI",
    "name:und_x_variant":[
        "Ohimaa",
        "Ohimaanper\u00e4"
    ],
    "wof:name":"Ohimaanperae",
    "wof:placetype":"locality"
},
  "geometry": {"coordinates":[25.04499,64.49351],"type":"Point"}
}