{
  "type": "Feature",
  "properties": {
    "gn:admin1_code":"17.0",
    "gn:admin2_code":"177.0",
    "gn:admin3_code":"208.0",
    "gn:asciiname":"Oja-Matti",
    "gn:country_code":"FI",
    "gn:dem":38,
    "gn:feature_class":"P",
    "gn:feature_code":"PPL",
    "gn:name":"Oja-Matti",
    "gn:population":0,
    "gn:timezone":"Europe/Helsinki",
    "iso:country":"FI",
    "wof:name":"Oja-Matti",
    "wof:placetype":"locality"
},
  "geometry": {"coordinates":[23.88289,64.04167],"type":"Point"}
}