{
  "type": "Feature",
  "properties": {
    "gn:admin1_code":"17.0",
    "gn:admin2_code":"174.0",
    "gn:admin3_code":"678.0",
    "gn:asciiname":"Olkijoki",
    "gn:country_code":"FI",
    "gn:dem":13,
    "gn:feature_class":"P",
    "gn:feature_code":"PPL",
    "gn:name":"Olkijoki",
    "gn:population":0,
    "gn:timezone":"Europe/Helsinki",
    "iso:country":"FI",
    "name:eng_x_preferred":[
        "Olkijoki"
    ],
    "name:rus_x_preferred":[
        "\u041e\u043b\u043a\u0438\u0439\u043e\u043a\u0438"
    ],
    "wof:name":"Olkijoki",
    "wof:placetype":"locality"
},
  "geometry": {"coordinates":[24.60999,64.72884999999999],"type":"Point"}
}