{
  "type": "Feature",
  "properties": {
    "gn:admin1_code":"14.0",
    "gn:admin2_code":"146.0",
    "gn:admin3_code":"5.0",
    "gn:asciiname":"Korkiaaho",
    "gn:country_code":"FI",
    "gn:dem":124,
    "gn:feature_class":"P",
    "gn:feature_code":"PPL",
    "gn:name":"Korkiaaho",
    "gn:population":0,
    "gn:timezone":"Europe/Helsinki",
    "iso:country":"FI",
    "wof:name":"Korkiaaho",
    "wof:placetype":"locality"
},
  "geometry": {"coordinates":[23.88333,63.08333],"type":"Point"}
}