{
  "type": "Feature",
  "properties": {
    "gn:gn_country":"FI",
    "gn:gn_fcode":"PPL",
    "gn:gn_pop":0,
    "iso:country":"FI",
    "name:fin_x_preferred":[
        "Sotka"
    ],
    "qs_pg:aaroncc":"FI",
    "qs_pg:gn_country":"FI",
    "qs_pg:gn_fcode":"PPL",
    "qs_pg:gn_pop":0,
    "qs_pg:name":"Sotka",
    "qs_pg:name_adm0":"Suomi",
    "qs_pg:name_adm1":"Kanta-H\u00e4meen maakunta",
    "qs_pg:photos_9k":1,
    "qs_pg:photos_9r":1,
    "qs_pg:photos_all":4,
    "qs_pg:photos_sr":0,
    "qs_pg:pop_sr":0,
    "qs_pg:qs_pg_placetype":"locality",
    "qs_pg:qs_pg_placetype_gp":"Town",
    "qs_pg:woe_adm0":23424812,
    "woe:adm0_id":23424812,
    "woe:name_adm0":"Suomi",
    "woe:name_adm1":"Kanta-H\u00e4meen maakunta",
    "woe:placetype":"Town",
    "wof:name":"Sotka",
    "wof:placetype":"locality"
},
  "geometry": {"coordinates":[23.79913,61.1434],"type":"Point"}
}