{
  "type": "Feature",
  "properties": {
    "gn:admin1_code":"2.0",
    "gn:admin2_code":"23.0",
    "gn:admin3_code":"481.0",
    "gn:asciiname":"Vilunen",
    "gn:country_code":"FI",
    "gn:dem":23,
    "gn:feature_class":"P",
    "gn:feature_code":"PPL",
    "gn:name":"Vilunen",
    "gn:population":0,
    "gn:timezone":"Europe/Helsinki",
    "iso:country":"FI",
    "wof:name":"Vilunen",
    "wof:placetype":"locality"
},
  "geometry": {"coordinates":[21.89417000000001,60.585],"type":"Point"}
}