{
  "type": "Feature",
  "properties": {
    "gn:admin1_code":"10.0",
    "gn:admin2_code":"101.0",
    "gn:admin3_code":"491.0",
    "gn:asciiname":"Seppaelae",
    "gn:country_code":"FI",
    "gn:dem":116,
    "gn:feature_class":"P",
    "gn:feature_code":"PPL",
    "gn:name":"Sepp\u00e4l\u00e4",
    "gn:population":0,
    "gn:timezone":"Europe/Helsinki",
    "iso:country":"FI",
    "name:eng_x_preferred":[
        "Sepp\u00e4l\u00e4"
    ],
    "name:rus_x_preferred":[
        "\u0421\u0435\u043f\u043f\u044f\u043b\u044f"
    ],
    "name:und_x_variant":[
        "Sepp\u00e4l\u00e4"
    ],
    "wof:name":"Seppaelae",
    "wof:placetype":"locality"
},
  "geometry": {"coordinates":[27.41667,61.76667],"type":"Point"}
}