{
  "type": "Feature",
  "properties": {
    "gn:admin1_code":"19.0",
    "gn:admin2_code":"192.0",
    "gn:admin3_code":"751.0",
    "gn:asciiname":"Simonkylae",
    "gn:country_code":"FI",
    "gn:dem":14,
    "gn:feature_class":"P",
    "gn:feature_code":"PPL",
    "gn:name":"Simonkyl\u00e4",
    "gn:population":0,
    "gn:timezone":"Europe/Helsinki",
    "iso:country":"FI",
    "name:eng_x_preferred":[
        "Simonkyl\u00e4"
    ],
    "name:rus_x_preferred":[
        "\u0421\u0438\u043c\u043e\u043d\u043a\u044e\u043b\u044f"
    ],
    "wof:name":"Simonkylae",
    "wof:placetype":"locality"
},
  "geometry": {"coordinates":[25.01415,65.63951999999999],"type":"Point"}
}