{
  "type": "Feature",
  "properties": {
    "gn:admin1_code":"17.0",
    "gn:admin2_code":"177.0",
    "gn:admin3_code":"977.0",
    "gn:asciiname":"Someronperae",
    "gn:country_code":"FI",
    "gn:dem":60,
    "gn:feature_class":"P",
    "gn:feature_code":"PPL",
    "gn:name":"Someronper\u00e4",
    "gn:population":0,
    "gn:timezone":"Europe/Helsinki",
    "iso:country":"FI",
    "name:und_x_variant":[
        "Somero",
        "Someronper\u00e4"
    ],
    "wof:name":"Someronperae",
    "wof:placetype":"locality"
},
  "geometry": {"coordinates":[24.43611,64.07778],"type":"Point"}
}