{
  "type": "Feature",
  "properties": {
    "gn:admin1_code":"19.0",
    "gn:admin2_code":"194.0",
    "gn:admin3_code":"583.0",
    "gn:asciiname":"Luiro",
    "gn:country_code":"FI",
    "gn:dem":163,
    "gn:feature_class":"P",
    "gn:feature_code":"PPL",
    "gn:name":"Luiro",
    "gn:population":0,
    "gn:timezone":"Europe/Helsinki",
    "iso:country":"FI",
    "name:ceb_x_preferred":[
        "Luiro"
    ],
    "name:deu_x_preferred":[
        "Luiro"
    ],
    "name:eus_x_preferred":[
        "Luiro"
    ],
    "name:fin_x_preferred":[
        "Luiro"
    ],
    "name:lit_x_preferred":[
        "Luiras"
    ],
    "name:pol_x_preferred":[
        "Luiro"
    ],
    "name:swe_x_preferred":[
        "Luiro"
    ],
    "wof:name":"Luiro",
    "wof:placetype":"locality"
},
  "geometry": {"coordinates":[27.53654,67.22173000000001],"type":"Point"}
}