{
  "type": "Feature",
  "properties": {
    "gn:admin1_code":"8.0",
    "gn:admin2_code":"82.0",
    "gn:admin3_code":"75.0",
    "gn:asciiname":"Ylae-Jaeaeski",
    "gn:country_code":"FI",
    "gn:dem":49,
    "gn:feature_class":"P",
    "gn:feature_code":"PPL",
    "gn:name":"Yl\u00e4-J\u00e4\u00e4ski",
    "gn:population":0,
    "gn:timezone":"Europe/Helsinki",
    "iso:country":"FI",
    "wof:name":"Ylae-Jaeaeski",
    "wof:placetype":"locality"
},
  "geometry": {"coordinates":[27.36667000000001,60.75],"type":"Point"}
}