{
  "type": "Feature",
  "properties": {
    "gn:admin1_code":"19.0",
    "gn:admin2_code":"194.0",
    "gn:admin3_code":"614.0",
    "gn:asciiname":"Haeme",
    "gn:country_code":"FI",
    "gn:dem":238,
    "gn:feature_class":"P",
    "gn:feature_code":"PPL",
    "gn:name":"H\u00e4me",
    "gn:population":0,
    "gn:timezone":"Europe/Helsinki",
    "iso:country":"FI",
    "wof:name":"Haeme",
    "wof:placetype":"locality"
},
  "geometry": {"coordinates":[28.16667,66.26666999999999],"type":"Point"}
}