{
  "type": "Feature",
  "properties": {
    "gn:admin1_code":"7.0",
    "gn:admin2_code":"71.0",
    "gn:admin3_code":"316.0",
    "gn:asciiname":"Koukunmaa",
    "gn:country_code":"FI",
    "gn:dem":94,
    "gn:feature_class":"P",
    "gn:feature_code":"PPL",
    "gn:name":"Koukunmaa",
    "gn:population":0,
    "gn:timezone":"Europe/Helsinki",
    "iso:country":"FI",
    "wof:name":"Koukunmaa",
    "wof:placetype":"locality"
},
  "geometry": {"coordinates":[25.29077,60.80405],"type":"Point"}
}