{
  "type": "Feature",
  "properties": {
    "gn:admin1_code":"17.0",
    "gn:admin2_code":"173.0",
    "gn:admin3_code":"615.0",
    "gn:asciiname":"Hemmilae",
    "gn:country_code":"FI",
    "gn:dem":180,
    "gn:feature_class":"P",
    "gn:feature_code":"PPL",
    "gn:name":"Hemmil\u00e4",
    "gn:population":0,
    "gn:timezone":"Europe/Helsinki",
    "iso:country":"FI",
    "name:fin_x_preferred":[
        "Hemmil\u00e4"
    ],
    "wof:name":"Hemmilae",
    "wof:placetype":"locality"
},
  "geometry": {"coordinates":[27.63127,65.44847],"type":"Point"}
}