{
  "type": "Feature",
  "properties": {
    "gn:admin1_code":"2.0",
    "gn:admin2_code":"23.0",
    "gn:admin3_code":"503.0",
    "gn:asciiname":"Lausti",
    "gn:country_code":"FI",
    "gn:dem":70,
    "gn:feature_class":"P",
    "gn:feature_code":"PPL",
    "gn:name":"Lausti",
    "gn:population":0,
    "gn:timezone":"Europe/Helsinki",
    "iso:country":"FI",
    "name:fin_x_preferred":[
        "Lausti"
    ],
    "wof:name":"Lausti",
    "wof:placetype":"locality"
},
  "geometry": {"coordinates":[22.12443,60.88112],"type":"Point"}
}