{
  "type": "Feature",
  "properties": {
    "gn:admin1_code":"2.0",
    "gn:admin2_code":"23.0",
    "gn:admin3_code":"423.0",
    "gn:asciiname":"Suopohja",
    "gn:country_code":"FI",
    "gn:dem":23,
    "gn:feature_class":"P",
    "gn:feature_code":"PPL",
    "gn:name":"Suopohja",
    "gn:population":0,
    "gn:timezone":"Europe/Helsinki",
    "iso:country":"FI",
    "wof:name":"Suopohja",
    "wof:placetype":"locality"
},
  "geometry": {"coordinates":[22.45548,60.46411],"type":"Point"}
}