{
  "type": "Feature",
  "properties": {
    "gn:admin1_code":"13.0",
    "gn:admin2_code":"138.0",
    "gn:admin3_code":"312.0",
    "gn:asciiname":"Peuralinna",
    "gn:country_code":"FI",
    "gn:dem":186,
    "gn:feature_class":"P",
    "gn:feature_code":"PPL",
    "gn:name":"Peuralinna",
    "gn:population":0,
    "gn:timezone":"Europe/Helsinki",
    "iso:country":"FI",
    "wof:name":"Peuralinna",
    "wof:placetype":"locality"
},
  "geometry": {"coordinates":[24.40393,63.07429000000001],"type":"Point"}
}