{
  "type": "Feature",
  "properties": {
    "gn:admin1_code":"15.0",
    "gn:admin2_code":"153.0",
    "gn:admin3_code":"287.0",
    "gn:asciiname":"Abacken",
    "gn:country_code":"FI",
    "gn:dem":36,
    "gn:feature_class":"P",
    "gn:feature_code":"PPL",
    "gn:name":"\u00c5backen",
    "gn:population":0,
    "gn:timezone":"Europe/Helsinki",
    "iso:country":"FI",
    "wof:name":"Abacken",
    "wof:placetype":"locality"
},
  "geometry": {"coordinates":[21.65947,62.24521],"type":"Point"}
}