{
  "type": "Feature",
  "properties": {
    "gn:admin1_code":"2.0",
    "gn:admin2_code":"24.0",
    "gn:admin3_code":"304.0",
    "gn:asciiname":"Ruola",
    "gn:country_code":"FI",
    "gn:dem":7,
    "gn:feature_class":"P",
    "gn:feature_code":"PPL",
    "gn:name":"Ruola",
    "gn:population":0,
    "gn:timezone":"Europe/Helsinki",
    "iso:country":"FI",
    "wof:name":"Ruola",
    "wof:placetype":"locality"
},
  "geometry": {"coordinates":[21.461,60.5222],"type":"Point"}
}