{
  "type": "Feature",
  "properties": {
    "gn:admin1_code":"6.0",
    "gn:admin2_code":"61.0",
    "gn:admin3_code":"143.0",
    "gn:asciiname":"Vaskimaeki",
    "gn:country_code":"FI",
    "gn:dem":161,
    "gn:feature_class":"P",
    "gn:feature_code":"PPL",
    "gn:name":"Vaskim\u00e4ki",
    "gn:population":0,
    "gn:timezone":"Europe/Helsinki",
    "iso:country":"FI",
    "name:und_x_variant":[
        "Vaskiper\u00e4",
        "Vaskim\u00e4ki"
    ],
    "wof:name":"Vaskimaeki",
    "wof:placetype":"locality"
},
  "geometry": {"coordinates":[22.91667,61.95],"type":"Point"}
}