{
  "type": "Feature",
  "properties": {
    "gn:admin1_code":"2.0",
    "gn:admin2_code":"23.0",
    "gn:admin3_code":"704.0",
    "gn:asciiname":"Kirkonkylae",
    "gn:country_code":"FI",
    "gn:dem":15,
    "gn:feature_class":"P",
    "gn:feature_code":"PPL",
    "gn:name":"Kirkonkyl\u00e4",
    "gn:population":0,
    "gn:timezone":"Europe/Helsinki",
    "iso:country":"FI",
    "wof:name":"Kirkonkylae",
    "wof:placetype":"locality"
},
  "geometry": {"coordinates":[22.22164,60.53446],"type":"Point"}
}