{
  "type": "Feature",
  "properties": {
    "iso:country":"FI",
    "qs:a0":"Suomi#Finland",
    "qs:a1":"*Varsinais-Suomi#Egentliga Finland",
    "qs:a1r":"0Lounais-Suomen AVI#Sydv\u00e4stra Finlands RFV",
    "qs:adm0":"Suomi#Finland",
    "qs:la_lc":"*",
    "qs:level":"locality",
    "qs:loc":"Vaskio",
    "qs:loc_alt":"Vaskio",
    "qs:pop":0,
    "qs:type":"buffered point",
    "wof:name":"Vaskio",
    "wof:placetype":"locality"
},
  "geometry": {"coordinates":[23.008886,60.481842],"type":"Point"}
}