{
  "type": "Feature",
  "properties": {
    "gn:admin1_code":"18.0",
    "gn:admin2_code":"181.0",
    "gn:admin3_code":"290.0",
    "gn:asciiname":"Palo",
    "gn:cc2":"FI",
    "gn:country_code":"FI",
    "gn:dem":222,
    "gn:feature_class":"P",
    "gn:feature_code":"PPL",
    "gn:name":"Palo",
    "gn:population":0,
    "gn:timezone":"Europe/Helsinki",
    "iso:country":"FI",
    "name:ceb_x_preferred":[
        "Palo"
    ],
    "name:deu_x_preferred":[
        "Palo"
    ],
    "name:fin_x_preferred":[
        "Palo"
    ],
    "name:ita_x_preferred":[
        "Palo"
    ],
    "name:nld_x_preferred":[
        "Palo"
    ],
    "name:pol_x_preferred":[
        "Palo"
    ],
    "name:slk_x_preferred":[
        "Palo"
    ],
    "name:spa_x_preferred":[
        "Palo"
    ],
    "name:swe_x_preferred":[
        "Palo"
    ],
    "name:tgl_x_preferred":[
        "Palo"
    ],
    "name:und_x_variant":[
        "Palovaara",
        "Palo"
    ],
    "name:vol_x_preferred":[
        "Palo"
    ],
    "name:war_x_preferred":[
        "Palo"
    ],
    "wof:name":"Palo",
    "wof:placetype":"locality"
},
  "geometry": {"coordinates":[29.05,64.45],"type":"Point"}
}