{
  "type": "Feature",
  "properties": {
    "gn:admin1_code":"12.0",
    "gn:admin2_code":"122.0",
    "gn:admin3_code":"167.0",
    "gn:asciiname":"Hoilola",
    "gn:country_code":"FI",
    "gn:dem":96,
    "gn:feature_class":"P",
    "gn:feature_code":"PPL",
    "gn:name":"Hoilola",
    "gn:population":0,
    "gn:timezone":"Europe/Helsinki",
    "iso:country":"FI",
    "name:eng_x_preferred":[
        "Hoilola"
    ],
    "name:rus_x_preferred":[
        "\u0425\u043e\u0439\u043b\u043e\u043b\u0430"
    ],
    "wof:name":"Hoilola",
    "wof:placetype":"locality"
},
  "geometry": {"coordinates":[30.84155,62.34005],"type":"Point"}
}