{
  "type": "Feature",
  "properties": {
    "gn:admin1_code":"15.0",
    "gn:admin2_code":"151.0",
    "gn:admin3_code":"152.0",
    "gn:asciiname":"Kleemolanmaeki",
    "gn:country_code":"FI",
    "gn:dem":36,
    "gn:feature_class":"P",
    "gn:feature_code":"PPL",
    "gn:name":"Kleemolanm\u00e4ki",
    "gn:population":0,
    "gn:timezone":"Europe/Helsinki",
    "iso:country":"FI",
    "name:fin_x_preferred":[
        "Kleemolanm\u00e4ki"
    ],
    "wof:name":"Kleemolanmaeki",
    "wof:placetype":"locality"
},
  "geometry": {"coordinates":[22.41116,63.06853],"type":"Point"}
}