{
  "type": "Feature",
  "properties": {
    "gn:admin1_code":"15.0",
    "gn:admin2_code":"151.0",
    "gn:admin3_code":"399.0",
    "gn:asciiname":"Kuusistonmaeki",
    "gn:country_code":"FI",
    "gn:dem":45,
    "gn:feature_class":"P",
    "gn:feature_code":"PPL",
    "gn:name":"Kuusistonm\u00e4ki",
    "gn:population":0,
    "gn:timezone":"Europe/Helsinki",
    "iso:country":"FI",
    "name:fin_x_preferred":[
        "Kuusistonm\u00e4ki"
    ],
    "wof:name":"Kuusistonmaeki",
    "wof:placetype":"locality"
},
  "geometry": {"coordinates":[22.09735,62.88876],"type":"Point"}
}