{
  "type": "Feature",
  "properties": {
    "gn:admin1_code":"4.0",
    "gn:admin2_code":"43.0",
    "gn:admin3_code":"609.0",
    "gn:asciiname":"Kynttilaekylae",
    "gn:country_code":"FI",
    "gn:dem":8,
    "gn:feature_class":"P",
    "gn:feature_code":"PPL",
    "gn:name":"Kynttil\u00e4kyl\u00e4",
    "gn:population":0,
    "gn:timezone":"Europe/Helsinki",
    "iso:country":"FI",
    "name:fin_x_preferred":[
        "Kynttil\u00e4kyl\u00e4"
    ],
    "wof:name":"Kynttilaekylae",
    "wof:placetype":"locality"
},
  "geometry": {"coordinates":[21.69892,61.52397],"type":"Point"}
}