{
  "type": "Feature",
  "properties": {
    "gn:admin1_code":"17.0",
    "gn:admin2_code":"177.0",
    "gn:admin3_code":"9.0",
    "gn:asciiname":"Klemetti",
    "gn:cc2":"FI",
    "gn:country_code":"FI",
    "gn:dem":51,
    "gn:feature_class":"P",
    "gn:feature_code":"PPL",
    "gn:name":"Klemetti",
    "gn:population":0,
    "gn:timezone":"Europe/Helsinki",
    "iso:country":"FI",
    "name:und_x_variant":[
        "Klemettil\u00e4",
        "Klemetti"
    ],
    "wof:name":"Klemetti",
    "wof:placetype":"locality"
},
  "geometry": {"coordinates":[24.35,64.23333000000001],"type":"Point"}
}