{
  "type": "Feature",
  "properties": {
    "gn:admin1_code":"15.0",
    "gn:admin2_code":"152.0",
    "gn:admin3_code":"475.0",
    "gn:asciiname":"Strandkaerr",
    "gn:country_code":"FI",
    "gn:dem":8,
    "gn:feature_class":"P",
    "gn:feature_code":"PPL",
    "gn:name":"Strandk\u00e4rr",
    "gn:population":0,
    "gn:timezone":"Europe/Helsinki",
    "iso:country":"FI",
    "wof:name":"Strandkaerr",
    "wof:placetype":"locality"
},
  "geometry": {"coordinates":[21.39908,62.84052],"type":"Point"}
}