{
  "type": "Feature",
  "properties": {
    "gn:admin1_code":"19.0",
    "gn:admin2_code":"197.0",
    "gn:admin3_code":"758.0",
    "gn:asciiname":"Maenty",
    "gn:country_code":"FI",
    "gn:dem":222,
    "gn:feature_class":"P",
    "gn:feature_code":"PPL",
    "gn:name":"M\u00e4nty",
    "gn:population":0,
    "gn:timezone":"Europe/Helsinki",
    "iso:country":"FI",
    "wof:name":"Maenty",
    "wof:placetype":"locality"
},
  "geometry": {"coordinates":[26.45,67.41667],"type":"Point"}
}