{
  "type": "Feature",
  "properties": {
    "gn:admin1_code":"14.0",
    "gn:admin2_code":"141.0",
    "gn:admin3_code":"151.0",
    "gn:asciiname":"Jaemikkae",
    "gn:country_code":"FI",
    "gn:dem":111,
    "gn:feature_class":"P",
    "gn:feature_code":"PPL",
    "gn:name":"J\u00e4mikk\u00e4",
    "gn:population":0,
    "gn:timezone":"Europe/Helsinki",
    "iso:country":"FI",
    "name:fin_x_preferred":[
        "J\u00e4mikk\u00e4"
    ],
    "wof:name":"Jaemikkae",
    "wof:placetype":"locality"
},
  "geometry": {"coordinates":[21.91751,62.14434],"type":"Point"}
}