{
  "type": "Feature",
  "properties": {
    "gn:admin1_code":"11.0",
    "gn:admin2_code":"113.0",
    "gn:admin3_code":"687.0",
    "gn:asciiname":"Rannankylae",
    "gn:country_code":"FI",
    "gn:dem":144,
    "gn:feature_class":"P",
    "gn:feature_code":"PPL",
    "gn:name":"Rannankyl\u00e4",
    "gn:population":0,
    "gn:timezone":"Europe/Helsinki",
    "iso:country":"FI",
    "wof:name":"Rannankylae",
    "wof:placetype":"locality"
},
  "geometry": {"coordinates":[28.35766,63.41336],"type":"Point"}
}