{
  "type": "Feature",
  "properties": {
    "gn:admin1_code":"6.0",
    "gn:admin2_code":"69.0",
    "gn:admin3_code":"508.0",
    "gn:asciiname":"Pynnoeskylae",
    "gn:country_code":"FI",
    "gn:dem":117,
    "gn:feature_class":"P",
    "gn:feature_code":"PPL",
    "gn:name":"Pynn\u00f6skyl\u00e4",
    "gn:population":0,
    "gn:timezone":"Europe/Helsinki",
    "iso:country":"FI",
    "wof:name":"Pynnoeskylae",
    "wof:placetype":"locality"
},
  "geometry": {"coordinates":[24.48383,61.97973],"type":"Point"}
}