{
  "type": "Feature",
  "properties": {
    "gn:admin1_code":"17.0",
    "gn:admin2_code":"177.0",
    "gn:admin3_code":"977.0",
    "gn:asciiname":"Hautamaeki",
    "gn:cc2":"FI",
    "gn:country_code":"FI",
    "gn:dem":81,
    "gn:feature_class":"P",
    "gn:feature_code":"PPL",
    "gn:name":"Hautam\u00e4ki",
    "gn:population":0,
    "gn:timezone":"Europe/Helsinki",
    "iso:country":"FI",
    "name:und_x_variant":[
        "Hautam\u00e4ki",
        "Hautala",
        "Hautaniemi"
    ],
    "wof:name":"Hautamaeki",
    "wof:placetype":"locality"
},
  "geometry": {"coordinates":[24.64301,64.15949999999999],"type":"Point"}
}