{
  "type": "Feature",
  "properties": {
    "gn:admin1_code":"2.0",
    "gn:admin2_code":"24.0",
    "gn:admin3_code":"400.0",
    "gn:asciiname":"Koukkela",
    "gn:country_code":"FI",
    "gn:dem":11,
    "gn:feature_class":"P",
    "gn:feature_code":"PPL",
    "gn:name":"Koukkela",
    "gn:population":0,
    "gn:timezone":"Europe/Helsinki",
    "iso:country":"FI",
    "wof:name":"Koukkela",
    "wof:placetype":"locality"
},
  "geometry": {"coordinates":[21.71808,60.84544],"type":"Point"}
}