{
  "type": "Feature",
  "properties": {
    "gn:admin1_code":"11.0",
    "gn:admin2_code":"113.0",
    "gn:admin3_code":"204.0",
    "gn:asciiname":"Kortteinen",
    "gn:country_code":"FI",
    "gn:dem":121,
    "gn:feature_class":"P",
    "gn:feature_code":"PPL",
    "gn:name":"Kortteinen",
    "gn:population":0,
    "gn:timezone":"Europe/Helsinki",
    "iso:country":"FI",
    "name:eng_x_preferred":[
        "Kortteinen"
    ],
    "name:rus_x_preferred":[
        "\u041a\u043e\u0440\u0442\u0442\u0435\u0439\u043d\u0435\u043d"
    ],
    "wof:name":"Kortteinen",
    "wof:placetype":"locality"
},
  "geometry": {"coordinates":[28.65031,63.02461],"type":"Point"}
}