{
  "type": "Feature",
  "properties": {
    "gn:admin1_code":"13.0",
    "gn:admin2_code":"138.0",
    "gn:admin3_code":"931.0",
    "gn:asciiname":"Toulat",
    "gn:country_code":"FI",
    "gn:dem":122,
    "gn:feature_class":"P",
    "gn:feature_code":"PPL",
    "gn:name":"Toulat",
    "gn:population":0,
    "gn:timezone":"Europe/Helsinki",
    "iso:country":"FI",
    "wof:name":"Toulat",
    "wof:placetype":"locality"
},
  "geometry": {"coordinates":[26.09991,63.12992],"type":"Point"}
}