{
  "type": "Feature",
  "properties": {
    "gn:admin1_code":"4.0",
    "gn:admin2_code":"43.0",
    "gn:admin3_code":"271.0",
    "gn:asciiname":"Kiettare",
    "gn:country_code":"FI",
    "gn:dem":53,
    "gn:feature_class":"P",
    "gn:feature_code":"PPL",
    "gn:name":"Kiettare",
    "gn:population":0,
    "gn:timezone":"Europe/Helsinki",
    "iso:country":"FI",
    "wof:name":"Kiettare",
    "wof:placetype":"locality"
},
  "geometry": {"coordinates":[22.48961,61.24116],"type":"Point"}
}