{
  "type": "Feature",
  "properties": {
    "gn:admin1_code":"9.0",
    "gn:admin2_code":"93.0",
    "gn:admin3_code":"689.0",
    "gn:asciiname":"Ridanmaeki",
    "gn:country_code":"FI",
    "gn:dem":99,
    "gn:feature_class":"P",
    "gn:feature_code":"PPL",
    "gn:name":"Ridanm\u00e4ki",
    "gn:population":0,
    "gn:timezone":"Europe/Helsinki",
    "iso:country":"FI",
    "wof:name":"Ridanmaeki",
    "wof:placetype":"locality"
},
  "geometry": {"coordinates":[29.19654,61.38999],"type":"Point"}
}