{
  "type": "Feature",
  "properties": {
    "gn:admin1_code":"4.0",
    "gn:admin2_code":"43.0",
    "gn:admin3_code":"531.0",
    "gn:asciiname":"Hormisto",
    "gn:country_code":"FI",
    "gn:dem":18,
    "gn:feature_class":"P",
    "gn:feature_code":"PPL",
    "gn:name":"Hormisto",
    "gn:population":0,
    "gn:timezone":"Europe/Helsinki",
    "iso:country":"FI",
    "wof:name":"Hormisto",
    "wof:placetype":"locality"
},
  "geometry": {"coordinates":[21.95,61.33333],"type":"Point"}
}