{
  "type": "Feature",
  "properties": {
    "gn:admin1_code":"12.0",
    "gn:admin2_code":"124.0",
    "gn:admin3_code":"260.0",
    "gn:asciiname":"Poroniemi",
    "gn:country_code":"FI",
    "gn:dem":107,
    "gn:feature_class":"P",
    "gn:feature_code":"PPL",
    "gn:name":"Poroniemi",
    "gn:population":0,
    "gn:timezone":"Europe/Helsinki",
    "iso:country":"FI",
    "wof:name":"Poroniemi",
    "wof:placetype":"locality"
},
  "geometry": {"coordinates":[29.76632,61.90201999999999],"type":"Point"}
}