{
  "type": "Feature",
  "properties": {
    "gn:admin1_code":"6.0",
    "gn:admin2_code":"63.0",
    "gn:admin3_code":"908.0",
    "gn:asciiname":"Pispantalli",
    "gn:country_code":"FI",
    "gn:dem":86,
    "gn:feature_class":"P",
    "gn:feature_code":"PPL",
    "gn:name":"Pispantalli",
    "gn:population":0,
    "gn:timezone":"Europe/Helsinki",
    "iso:country":"FI",
    "wof:name":"Pispantalli",
    "wof:placetype":"locality"
},
  "geometry": {"coordinates":[23.97006,61.28168],"type":"Point"}
}