{
  "type": "Feature",
  "properties": {
    "gn:admin1_code":"2.0",
    "gn:admin2_code":"21.0",
    "gn:admin3_code":"322.0",
    "gn:asciiname":"Sirnaes",
    "gn:country_code":"FI",
    "gn:dem":11,
    "gn:feature_class":"P",
    "gn:feature_code":"PPL",
    "gn:name":"Sirn\u00e4s",
    "gn:population":0,
    "gn:timezone":"Europe/Helsinki",
    "iso:country":"FI",
    "name:und_x_variant":[
        "Sirn\u00e4sby",
        "Sirn\u00e4s"
    ],
    "wof:name":"Sirnaes",
    "wof:placetype":"locality"
},
  "geometry": {"coordinates":[22.59978,60.03271],"type":"Point"}
}