{
  "type": "Feature",
  "properties": {
    "gn:admin1_code":"18.0",
    "gn:admin2_code":"182.0",
    "gn:admin3_code":"205.0",
    "gn:asciiname":"Mikkola",
    "gn:country_code":"FI",
    "gn:dem":151,
    "gn:feature_class":"P",
    "gn:feature_code":"PPL",
    "gn:name":"Mikkola",
    "gn:population":0,
    "gn:timezone":"Europe/Helsinki",
    "iso:country":"FI",
    "name:deu_x_preferred":[
        "Mikkola"
    ],
    "name:fin_x_preferred":[
        "Mikkola"
    ],
    "name:fra_x_preferred":[
        "Mikkola"
    ],
    "name:jpn_x_preferred":[
        "\u30df\u30c3\u30b3\u30e9"
    ],
    "name:nds_x_preferred":[
        "Mikkola"
    ],
    "name:rus_x_preferred":[
        "\u041c\u0438\u043a\u043a\u043e\u043b\u0430"
    ],
    "name:swe_x_preferred":[
        "Mikkola"
    ],
    "wof:name":"Mikkola",
    "wof:placetype":"locality"
},
  "geometry": {"coordinates":[27.46667,64.11667],"type":"Point"}
}