{
  "type": "Feature",
  "properties": {
    "gn:admin1_code":"18.0",
    "gn:admin2_code":"182.0",
    "gn:admin3_code":"205.0",
    "gn:asciiname":"Mikkola",
    "gn:country_code":"FI",
    "gn:dem":151,
    "gn:feature_class":"P",
    "gn:feature_code":"PPL",
    "gn:name":"Mikkola",
    "gn:population":0,
    "gn:timezone":"Europe/Helsinki",
    "iso:country":"FI",
    "wof:name":"Mikkola",
    "wof:placetype":"locality"
},
  "geometry": {"coordinates":[27.46667,64.11667],"type":"Point"}
}