{
  "type": "Feature",
  "properties": {
    "gn:admin1_code":"8.0",
    "gn:admin2_code":"81.0",
    "gn:admin3_code":"286.0",
    "gn:asciiname":"Pyoeriaelae",
    "gn:country_code":"FI",
    "gn:dem":109,
    "gn:feature_class":"P",
    "gn:feature_code":"PPL",
    "gn:name":"Py\u00f6ri\u00e4l\u00e4",
    "gn:population":0,
    "gn:timezone":"Europe/Helsinki",
    "iso:country":"FI",
    "wof:name":"Pyoeriaelae",
    "wof:placetype":"locality"
},
  "geometry": {"coordinates":[27.02937,61.08818],"type":"Point"}
}