{
  "type": "Feature",
  "properties": {
    "gn:admin1_code":"2.0",
    "gn:admin2_code":"25.0",
    "gn:admin3_code":"430.0",
    "gn:asciiname":"Moekkoeinen",
    "gn:country_code":"FI",
    "gn:dem":86,
    "gn:feature_class":"P",
    "gn:feature_code":"PPL",
    "gn:name":"M\u00f6kk\u00f6inen",
    "gn:population":0,
    "gn:timezone":"Europe/Helsinki",
    "iso:country":"FI",
    "wof:name":"Moekkoeinen",
    "wof:placetype":"locality"
},
  "geometry": {"coordinates":[22.86534,60.8978],"type":"Point"}
}