{
  "type": "Feature",
  "properties": {
    "gn:admin1_code":"9.0",
    "gn:admin2_code":"93.0",
    "gn:admin3_code":"580.0",
    "gn:asciiname":"Ukko-Juhon salo",
    "gn:cc2":"FI",
    "gn:country_code":"FI",
    "gn:dem":100,
    "gn:feature_class":"P",
    "gn:feature_code":"PPL",
    "gn:name":"Ukko-Juhon salo",
    "gn:population":0,
    "gn:timezone":"Europe/Helsinki",
    "iso:country":"FI",
    "name:und_x_variant":[
        "Ukko-Juhonkyl\u00e4",
        "Ukko-Juhonsalo"
    ],
    "wof:name":"Ukko-Juhon salo",
    "wof:placetype":"locality"
},
  "geometry": {"coordinates":[29.79708,61.74497],"type":"Point"}
}