{
  "type": "Feature",
  "properties": {
    "gn:admin1_code":"4.0",
    "gn:admin2_code":"41.0",
    "gn:admin3_code":"51.0",
    "gn:asciiname":"Pihlaus",
    "gn:country_code":"FI",
    "gn:dem":6,
    "gn:feature_class":"P",
    "gn:feature_code":"PPL",
    "gn:name":"Pihlaus",
    "gn:population":0,
    "gn:timezone":"Europe/Helsinki",
    "iso:country":"FI",
    "wof:name":"Pihlaus",
    "wof:placetype":"locality"
},
  "geometry": {"coordinates":[21.56667,61.28333000000001],"type":"Point"}
}