{
  "type": "Feature",
  "properties": {
    "gn:admin1_code":"18.0",
    "gn:admin2_code":"182.0",
    "gn:admin3_code":"765.0",
    "gn:asciiname":"Sapsoperae",
    "gn:country_code":"FI",
    "gn:dem":163,
    "gn:feature_class":"P",
    "gn:feature_code":"PPL",
    "gn:name":"Sapsoper\u00e4",
    "gn:population":0,
    "gn:timezone":"Europe/Helsinki",
    "iso:country":"FI",
    "name:und_x_variant":[
        "Sapsaper\u00e4",
        "Sapsoper\u00e4"
    ],
    "wof:name":"Sapsoperae",
    "wof:placetype":"locality"
},
  "geometry": {"coordinates":[28.55142,64.0526],"type":"Point"}
}