{
  "type": "Feature",
  "properties": {
    "gn:admin1_code":"8.0",
    "gn:admin2_code":"82.0",
    "gn:admin3_code":"75.0",
    "gn:asciiname":"Sivatti",
    "gn:country_code":"FI",
    "gn:dem":8,
    "gn:feature_class":"P",
    "gn:feature_code":"PPL",
    "gn:name":"Sivatti",
    "gn:population":0,
    "gn:timezone":"Europe/Helsinki",
    "iso:country":"FI",
    "name:sun_x_preferred":[
        "Sivatti"
    ],
    "name:swe_x_preferred":[
        "Sigvartsby"
    ],
    "wof:name":"Sivatti",
    "wof:placetype":"locality"
},
  "geometry": {"coordinates":[27.22172,60.58805],"type":"Point"}
}