{
  "type": "Feature",
  "properties": {
    "gn:admin1_code":"2.0",
    "gn:admin2_code":"22.0",
    "gn:admin3_code":"734.0",
    "gn:asciiname":"Marttila",
    "gn:country_code":"FI",
    "gn:dem":44,
    "gn:feature_class":"P",
    "gn:feature_code":"PPL",
    "gn:name":"Marttila",
    "gn:population":0,
    "gn:timezone":"Europe/Helsinki",
    "iso:country":"FI",
    "name:ara_x_preferred":[
        "\u0645\u0627\u0631\u062a\u064a\u0644\u0627"
    ],
    "name:ceb_x_preferred":[
        "Marttila"
    ],
    "name:deu_x_preferred":[
        "Marttila"
    ],
    "name:est_x_preferred":[
        "Marttila vald"
    ],
    "name:fin_x_preferred":[
        "Marttila"
    ],
    "name:fra_x_preferred":[
        "Marttila"
    ],
    "name:glg_x_preferred":[
        "Marttila"
    ],
    "name:ita_x_preferred":[
        "Marttila"
    ],
    "name:koi_x_preferred":[
        "\u041c\u0430\u0440\u0442\u0442\u0438\u043b\u0430"
    ],
    "name:nld_x_preferred":[
        "Marttila"
    ],
    "name:nor_x_preferred":[
        "Marttila"
    ],
    "name:pol_x_preferred":[
        "Marttila"
    ],
    "name:ron_x_preferred":[
        "Marttila"
    ],
    "name:rus_x_preferred":[
        "\u041c\u0430\u0440\u0442\u0442\u0438\u043b\u0430"
    ],
    "name:sme_x_preferred":[
        "Marttila"
    ],
    "name:sqi_x_preferred":[
        "Marttila"
    ],
    "name:swe_x_preferred":[
        "S:t M\u00e5rtens"
    ],
    "name:tur_x_preferred":[
        "Marttila"
    ],
    "name:vie_x_preferred":[
        "Marttila"
    ],
    "name:zho_x_preferred":[
        "\u99ac\u723e\u8482\u62c9"
    ],
    "wof:name":"Marttila",
    "wof:placetype":"locality"
},
  "geometry": {"coordinates":[23.40059,60.33989],"type":"Point"}
}