{
  "type": "Feature",
  "properties": {
    "gn:admin1_code":"2.0",
    "gn:admin2_code":"23.0",
    "gn:admin3_code":"738.0",
    "gn:asciiname":"Salmi",
    "gn:country_code":"FI",
    "gn:dem":17,
    "gn:feature_class":"P",
    "gn:feature_code":"PPL",
    "gn:name":"Salmi",
    "gn:population":0,
    "gn:timezone":"Europe/Helsinki",
    "iso:country":"FI",
    "name:ceb_x_preferred":[
        "Salmi"
    ],
    "name:deu_x_preferred":[
        "Salmi"
    ],
    "name:fin_x_preferred":[
        "Salmi"
    ],
    "name:fra_x_preferred":[
        "Salmi"
    ],
    "name:rus_x_preferred":[
        "\u0421\u0430\u043b\u043c\u0438"
    ],
    "wof:name":"Salmi",
    "wof:placetype":"locality"
},
  "geometry": {"coordinates":[22.66304,60.34506999999999],"type":"Point"}
}