{
  "type": "Feature",
  "properties": {
    "gn:admin1_code":"1.0",
    "gn:admin2_code":"11.0",
    "gn:admin3_code":"858.0",
    "gn:asciiname":"Vaunukangas",
    "gn:country_code":"FI",
    "gn:dem":64,
    "gn:feature_class":"P",
    "gn:feature_code":"PPL",
    "gn:name":"Vaunukangas",
    "gn:population":0,
    "gn:timezone":"Europe/Helsinki",
    "iso:country":"FI",
    "wof:name":"Vaunukangas",
    "wof:placetype":"locality"
},
  "geometry": {"coordinates":[24.99044,60.40776],"type":"Point"}
}