{
  "type": "Feature",
  "properties": {
    "gn:admin1_code":"11.0",
    "gn:admin2_code":"111.0",
    "gn:admin3_code":"925.0",
    "gn:asciiname":"Kaarakkala",
    "gn:country_code":"FI",
    "gn:dem":200,
    "gn:feature_class":"P",
    "gn:feature_code":"PPL",
    "gn:name":"Kaarakkala",
    "gn:population":0,
    "gn:timezone":"Europe/Helsinki",
    "iso:country":"FI",
    "wof:name":"Kaarakkala",
    "wof:placetype":"locality"
},
  "geometry": {"coordinates":[27.22138,63.82674],"type":"Point"}
}