{
  "type": "Feature",
  "properties": {
    "gn:admin1_code":"13.0",
    "gn:admin2_code":"134.0",
    "gn:admin3_code":"182.0",
    "gn:asciiname":"Rekola",
    "gn:country_code":"FI",
    "gn:dem":124,
    "gn:feature_class":"P",
    "gn:feature_code":"PPL",
    "gn:name":"Rekola",
    "gn:population":0,
    "gn:timezone":"Europe/Helsinki",
    "iso:country":"FI",
    "name:ces_x_preferred":[
        "Rekola"
    ],
    "wof:name":"Rekola",
    "wof:placetype":"locality"
},
  "geometry": {"coordinates":[25.15541,61.94821999999999],"type":"Point"}
}