{
  "type": "Feature",
  "properties": {
    "iso:country":"FI",
    "name:ara_x_preferred":[
        "\u0644\u0627\u0648\u062a\u0627\u0633\u0627\u0631\u064a"
    ],
    "name:cat_x_preferred":[
        "Lauttasaari"
    ],
    "name:ceb_x_preferred":[
        "Lauttasaari"
    ],
    "name:deu_x_preferred":[
        "Lauttasaari"
    ],
    "name:eng_x_preferred":[
        "Lauttasaari"
    ],
    "name:est_x_preferred":[
        "Lauttasaari"
    ],
    "name:fas_x_preferred":[
        "\u0644\u0627\u0648\u062a\u062a\u0627\u0633\u0627\u0631\u06cc"
    ],
    "name:fin_x_preferred":[
        "Lauttasaari"
    ],
    "name:fra_x_preferred":[
        "Lauttasaari"
    ],
    "name:jpn_x_preferred":[
        "\u30e9\u30a6\u30c3\u30bf\u5cf6"
    ],
    "name:nld_x_preferred":[
        "Lauttasaari"
    ],
    "name:nno_x_preferred":[
        "Drums\u00f6"
    ],
    "name:nob_x_preferred":[
        "Drums\u00f6"
    ],
    "name:pol_x_preferred":[
        "Lauttasaari"
    ],
    "name:rus_x_preferred":[
        "\u041b\u0430\u0443\u0442\u0442\u0430\u0441\u0430\u0430\u0440\u0438"
    ],
    "name:spa_x_preferred":[
        "Lauttasaari"
    ],
    "name:swe_x_preferred":[
        "Drums\u00f6"
    ],
    "name:tur_x_preferred":[
        "Lauttasaari"
    ],
    "name:zho_x_preferred":[
        "\u52b3\u5854\u8428\u91cc"
    ],
    "wof:name":"Lauttasaari",
    "wof:placetype":"neighbourhood"
},
  "geometry": {"coordinates":[24.870532,60.158427],"type":"Point"}
}