{
  "type": "Feature",
  "properties": {
    "gn:admin1_code":"5.0",
    "gn:admin2_code":"52.0",
    "gn:admin3_code":"86.0",
    "gn:asciiname":"Mommila",
    "gn:cc2":"FI",
    "gn:country_code":"FI",
    "gn:dem":93,
    "gn:feature_class":"P",
    "gn:feature_code":"PPL",
    "gn:name":"Mommila",
    "gn:population":0,
    "gn:timezone":"Europe/Helsinki",
    "iso:country":"FI",
    "name:und_x_variant":[
        "Mommila Hietoinen"
    ],
    "wof:name":"Mommila",
    "wof:placetype":"locality"
},
  "geometry": {"coordinates":[25.06536,60.8212],"type":"Point"}
}