{
  "type": "Feature",
  "properties": {
    "gn:admin1_code":"11.0",
    "gn:admin2_code":"114.0",
    "gn:admin3_code":"420.0",
    "gn:asciiname":"Salonkylae",
    "gn:country_code":"FI",
    "gn:dem":135,
    "gn:feature_class":"P",
    "gn:feature_code":"PPL",
    "gn:name":"Salonkyl\u00e4",
    "gn:population":0,
    "gn:timezone":"Europe/Helsinki",
    "iso:country":"FI",
    "wof:name":"Salonkylae",
    "wof:placetype":"locality"
},
  "geometry": {"coordinates":[28.01185,62.58821],"type":"Point"}
}