{
  "type": "Feature",
  "properties": {
    "gn:admin1_code":"2.0",
    "gn:admin2_code":"24.0",
    "gn:admin3_code":"400.0",
    "gn:asciiname":"Laitila",
    "gn:country_code":"FI",
    "gn:dem":18,
    "gn:feature_class":"P",
    "gn:feature_code":"PPLA3",
    "gn:name":"Laitila",
    "gn:population":8403,
    "gn:timezone":"Europe/Helsinki",
    "iso:country":"FI",
    "name:bel_x_preferred":[
        "\u041b\u0430\u0439\u0446\u0456\u043b\u0430"
    ],
    "name:ceb_x_preferred":[
        "Laitila"
    ],
    "name:deu_x_preferred":[
        "Laitila"
    ],
    "name:eng_x_preferred":[
        "Laitila"
    ],
    "name:est_x_preferred":[
        "Laitila"
    ],
    "name:fas_x_preferred":[
        "\u0644\u0627\u06cc\u062a\u06cc\u0644\u0627"
    ],
    "name:fin_x_preferred":[
        "Laitila"
    ],
    "name:fra_x_preferred":[
        "Laitila"
    ],
    "name:glg_x_preferred":[
        "Laitila"
    ],
    "name:ita_x_preferred":[
        "Laitila"
    ],
    "name:koi_x_preferred":[
        "\u041b\u0430\u0439\u0442\u0438\u043b\u0430"
    ],
    "name:lat_x_preferred":[
        "Laetala"
    ],
    "name:nld_x_preferred":[
        "Laitila"
    ],
    "name:nor_x_preferred":[
        "Laitila"
    ],
    "name:pol_x_preferred":[
        "Laitila"
    ],
    "name:ron_x_preferred":[
        "Laitila"
    ],
    "name:rus_x_preferred":[
        "\u041b\u0430\u0439\u0442\u0438\u043b\u0430"
    ],
    "name:slk_x_preferred":[
        "Laitila"
    ],
    "name:sme_x_preferred":[
        "Laitila"
    ],
    "name:sqi_x_preferred":[
        "Laitila"
    ],
    "name:swe_x_preferred":[
        "Letala"
    ],
    "name:tur_x_preferred":[
        "Laitila"
    ],
    "name:ukr_x_preferred":[
        "\u041b\u0430\u0439\u0442\u0456\u043b\u0430"
    ],
    "name:urd_x_preferred":[
        "\u0644\u0627\u0626\u06cc\u062a\u06cc\u0644\u0627"
    ],
    "name:vie_x_preferred":[
        "Laitila"
    ],
    "name:zho_x_preferred":[
        "\u840a\u8482\u62c9"
    ],
    "wof:name":"Laitila",
    "wof:placetype":"locality",
    "wof:population":8403
},
  "geometry": {"coordinates":[21.69765,60.87575],"type":"Point"}
}