{
  "type": "Feature",
  "properties": {
    "gn:admin1_code":"2.0",
    "gn:admin2_code":"24.0",
    "gn:admin3_code":"400.0",
    "gn:asciiname":"Laitila",
    "gn:country_code":"FI",
    "gn:dem":18,
    "gn:feature_class":"P",
    "gn:feature_code":"PPLA3",
    "gn:name":"Laitila",
    "gn:population":8403,
    "gn:timezone":"Europe/Helsinki",
    "iso:country":"FI",
    "name:eng_x_preferred":[
        "Laitila"
    ],
    "name:swe_x_preferred":[
        "Letala"
    ],
    "name:und_x_variant":[
        "Letala"
    ],
    "wof:name":"Laitila",
    "wof:placetype":"locality",
    "wof:population":8403
},
  "geometry": {"coordinates":[21.69765,60.87575],"type":"Point"}
}