{
  "type": "Feature",
  "properties": {
    "gn:admin1_code":"15.0",
    "gn:admin2_code":"152.0",
    "gn:admin3_code":"499.0",
    "gn:asciiname":"OEstersidan",
    "gn:country_code":"FI",
    "gn:dem":1,
    "gn:feature_class":"P",
    "gn:feature_code":"PPL",
    "gn:name":"\u00d6stersidan",
    "gn:population":0,
    "gn:timezone":"Europe/Helsinki",
    "iso:country":"FI",
    "name:swe_x_preferred":[
        "\u00d6stersidan"
    ],
    "wof:name":"OEstersidan",
    "wof:placetype":"locality"
},
  "geometry": {"coordinates":[21.86615,63.16741],"type":"Point"}
}