{
  "type": "Feature",
  "properties": {
    "gn:admin1_code":"13.0",
    "gn:admin2_code":"133.0",
    "gn:admin3_code":"249.0",
    "gn:asciiname":"Ampiala",
    "gn:country_code":"FI",
    "gn:dem":183,
    "gn:feature_class":"P",
    "gn:feature_code":"PPL",
    "gn:name":"Ampiala",
    "gn:population":0,
    "gn:timezone":"Europe/Helsinki",
    "iso:country":"FI",
    "wof:name":"Ampiala",
    "wof:placetype":"locality"
},
  "geometry": {"coordinates":[24.92945,62.28811999999999],"type":"Point"}
}