{
  "type": "Feature",
  "properties": {
    "gn:admin1_code":"8.0",
    "gn:admin2_code":"82.0",
    "gn:admin3_code":"489.0",
    "gn:asciiname":"Valkonen",
    "gn:country_code":"FI",
    "gn:dem":63,
    "gn:feature_class":"P",
    "gn:feature_code":"PPL",
    "gn:name":"Valkonen",
    "gn:population":0,
    "gn:timezone":"Europe/Helsinki",
    "iso:country":"FI",
    "name:deu_x_preferred":[
        "Valkonen"
    ],
    "name:fin_x_preferred":[
        "Valkonen"
    ],
    "wof:name":"Valkonen",
    "wof:placetype":"locality"
},
  "geometry": {"coordinates":[27.50219,60.79747],"type":"Point"}
}