{
  "type": "Feature",
  "properties": {
    "gn:admin1_code":"8.0",
    "gn:admin2_code":"82.0",
    "gn:admin3_code":"624.0",
    "gn:asciiname":"Peltolabacken",
    "gn:country_code":"FI",
    "gn:dem":2,
    "gn:feature_class":"P",
    "gn:feature_code":"PPL",
    "gn:name":"Peltolabacken",
    "gn:population":0,
    "gn:timezone":"Europe/Helsinki",
    "iso:country":"FI",
    "name:fin_x_preferred":[
        "Peltolanm\u00e4ki"
    ],
    "wof:name":"Peltolabacken",
    "wof:placetype":"locality"
},
  "geometry": {"coordinates":[26.78364,60.49571],"type":"Point"}
}