{
  "type": "Feature",
  "properties": {
    "gn:admin1_code":"4.0",
    "gn:admin2_code":"41.0",
    "gn:admin3_code":"50.0",
    "gn:asciiname":"Maekelae",
    "gn:country_code":"FI",
    "gn:dem":33,
    "gn:feature_class":"P",
    "gn:feature_code":"PPL",
    "gn:name":"M\u00e4kel\u00e4",
    "gn:population":0,
    "gn:timezone":"Europe/Helsinki",
    "iso:country":"FI",
    "wof:name":"Maekelae",
    "wof:placetype":"locality"
},
  "geometry": {"coordinates":[22.06912,61.19761999999999],"type":"Point"}
}