{
  "type": "Feature",
  "properties": {
    "gn:admin1_code":"1.0",
    "gn:admin2_code":"11.0",
    "gn:admin3_code":"257.0",
    "gn:asciiname":"Stroemsby",
    "gn:country_code":"FI",
    "gn:dem":25,
    "gn:feature_class":"P",
    "gn:feature_code":"PPL",
    "gn:name":"Str\u00f6msby",
    "gn:population":0,
    "gn:timezone":"Europe/Helsinki",
    "iso:country":"FI",
    "name:und_x_variant":[
        "Stremsbyu",
        "Str\u00f6msby"
    ],
    "wof:name":"Stroemsby",
    "wof:placetype":"locality"
},
  "geometry": {"coordinates":[24.39426,60.07925],"type":"Point"}
}