{
  "type": "Feature",
  "properties": {
    "gn:admin1_code":"18.0",
    "gn:admin2_code":"181.0",
    "gn:admin3_code":"777.0",
    "gn:asciiname":"Kaepylae",
    "gn:country_code":"FI",
    "gn:dem":263,
    "gn:feature_class":"P",
    "gn:feature_code":"PPL",
    "gn:name":"K\u00e4pyl\u00e4",
    "gn:population":0,
    "gn:timezone":"Europe/Helsinki",
    "iso:country":"FI",
    "wof:name":"Kaepylae",
    "wof:placetype":"locality"
},
  "geometry": {"coordinates":[28.91455,65.10249],"type":"Point"}
}