{
  "type": "Feature",
  "properties": {
    "gn:admin1_code":"6.0",
    "gn:admin2_code":"64.0",
    "gn:admin3_code":"562.0",
    "gn:asciiname":"Attila",
    "gn:country_code":"FI",
    "gn:dem":96,
    "gn:feature_class":"P",
    "gn:feature_code":"PPL",
    "gn:name":"Attila",
    "gn:population":0,
    "gn:timezone":"Europe/Helsinki",
    "iso:country":"FI",
    "name:eng_x_preferred":[
        "Attila"
    ],
    "name:rus_x_preferred":[
        "\u0412\u044f\u0441\u0442\u0438\u043b\u0430"
    ],
    "wof:name":"Attila",
    "wof:placetype":"locality"
},
  "geometry": {"coordinates":[24.67115,61.65026999999999],"type":"Point"}
}