{
  "type": "Feature",
  "properties": {
    "gn:admin1_code":"14.0",
    "gn:admin2_code":"146.0",
    "gn:admin3_code":"5.0",
    "gn:asciiname":"Puumala",
    "gn:country_code":"FI",
    "gn:dem":111,
    "gn:feature_class":"P",
    "gn:feature_code":"PPL",
    "gn:name":"Puumala",
    "gn:population":0,
    "gn:timezone":"Europe/Helsinki",
    "iso:country":"FI",
    "name:ceb_x_preferred":[
        "Puumala"
    ],
    "name:dan_x_preferred":[
        "Puumala"
    ],
    "name:deu_x_preferred":[
        "Puumala"
    ],
    "name:est_x_preferred":[
        "Puumala vald"
    ],
    "name:fin_x_preferred":[
        "Puumala"
    ],
    "name:fra_x_preferred":[
        "Puumala"
    ],
    "name:glg_x_preferred":[
        "Puumala"
    ],
    "name:hye_x_preferred":[
        "\u054a\u0578\u0582\u0578\u0582\u0574\u0561\u056c\u0561"
    ],
    "name:ita_x_preferred":[
        "Puumala"
    ],
    "name:nld_x_preferred":[
        "Puumala"
    ],
    "name:nor_x_preferred":[
        "Puumala"
    ],
    "name:pol_x_preferred":[
        "Puumala"
    ],
    "name:ron_x_preferred":[
        "Puumala"
    ],
    "name:rus_x_preferred":[
        "\u041f\u0443\u0443\u043c\u0430\u043b\u0430"
    ],
    "name:sme_x_preferred":[
        "Puumala"
    ],
    "name:spa_x_preferred":[
        "Puumala"
    ],
    "name:sqi_x_preferred":[
        "Puumala"
    ],
    "name:swe_x_preferred":[
        "Puumala"
    ],
    "name:tur_x_preferred":[
        "Puumala"
    ],
    "name:zho_x_preferred":[
        "\u666e\u99ac\u62c9"
    ],
    "wof:name":"Puumala",
    "wof:placetype":"locality"
},
  "geometry": {"coordinates":[23.83333,63.01667],"type":"Point"}
}