{
  "type": "Feature",
  "properties": {
    "gn:admin1_code":"11.0",
    "gn:admin2_code":"111.0",
    "gn:admin3_code":"595.0",
    "gn:asciiname":"Kairila",
    "gn:country_code":"FI",
    "gn:dem":111,
    "gn:feature_class":"P",
    "gn:feature_code":"PPL",
    "gn:name":"Kairila",
    "gn:population":0,
    "gn:timezone":"Europe/Helsinki",
    "iso:country":"FI",
    "wof:name":"Kairila",
    "wof:placetype":"locality"
},
  "geometry": {"coordinates":[26.40656,63.33572],"type":"Point"}
}