{
  "type": "Feature",
  "properties": {
    "gn:admin1_code":"13.0",
    "gn:admin2_code":"134.0",
    "gn:admin3_code":"291.0",
    "gn:asciiname":"Rantala",
    "gn:country_code":"FI",
    "gn:dem":115,
    "gn:feature_class":"P",
    "gn:feature_code":"PPL",
    "gn:name":"Rantala",
    "gn:population":0,
    "gn:timezone":"Europe/Helsinki",
    "iso:country":"FI",
    "wof:name":"Rantala",
    "wof:placetype":"locality"
},
  "geometry": {"coordinates":[25.25,61.55],"type":"Point"}
}