{
  "type": "Feature",
  "properties": {
    "gn:admin1_code":"4.0",
    "gn:admin2_code":"43.0",
    "gn:admin3_code":"609.0",
    "gn:asciiname":"Tiilimaeki",
    "gn:country_code":"FI",
    "gn:dem":16,
    "gn:feature_class":"P",
    "gn:feature_code":"PPL",
    "gn:name":"Tiilim\u00e4ki",
    "gn:population":0,
    "gn:timezone":"Europe/Helsinki",
    "iso:country":"FI",
    "name:swe_x_preferred":[
        "Tegelbacken"
    ],
    "wof:name":"Tiilimaeki",
    "wof:placetype":"locality"
},
  "geometry": {"coordinates":[21.78141,61.47476],"type":"Point"}
}