{
  "type": "Feature",
  "properties": {
    "gn:admin1_code":"2.0",
    "gn:admin2_code":"24.0",
    "gn:admin3_code":"895.0",
    "gn:asciiname":"Hallu",
    "gn:country_code":"FI",
    "gn:dem":19,
    "gn:feature_class":"P",
    "gn:feature_code":"PPL",
    "gn:name":"Hallu",
    "gn:population":0,
    "gn:timezone":"Europe/Helsinki",
    "iso:country":"FI",
    "name:bug_x_preferred":[
        "Hallu"
    ],
    "name:cat_x_preferred":[
        "Hallu"
    ],
    "name:ceb_x_preferred":[
        "Hallu"
    ],
    "name:deu_x_preferred":[
        "Hallu"
    ],
    "name:eus_x_preferred":[
        "Hallu"
    ],
    "name:fra_x_preferred":[
        "Hallu"
    ],
    "name:hun_x_preferred":[
        "Hallu"
    ],
    "name:hye_x_preferred":[
        "\u0531\u056c\u0578\u0582"
    ],
    "name:ita_x_preferred":[
        "Hallu"
    ],
    "name:lat_x_preferred":[
        "Hallu"
    ],
    "name:mlg_x_preferred":[
        "Hallu"
    ],
    "name:msa_x_preferred":[
        "Hallu"
    ],
    "name:nld_x_preferred":[
        "Hallu"
    ],
    "name:oci_x_preferred":[
        "Hallu"
    ],
    "name:pcd_x_preferred":[
        "Hallu"
    ],
    "name:pms_x_preferred":[
        "Hallu"
    ],
    "name:pol_x_preferred":[
        "Hallu"
    ],
    "name:por_x_preferred":[
        "Hallu"
    ],
    "name:ron_x_preferred":[
        "Hallu"
    ],
    "name:slk_x_preferred":[
        "Hallu"
    ],
    "name:spa_x_preferred":[
        "Hallu"
    ],
    "name:srp_x_preferred":[
        "\u0410\u043b\u0438"
    ],
    "name:swe_x_preferred":[
        "Hallu"
    ],
    "name:ukr_x_preferred":[
        "\u0410\u043b\u043b\u044e"
    ],
    "name:uzb_x_preferred":[
        "Hallu"
    ],
    "name:vie_x_preferred":[
        "Hallu"
    ],
    "name:vol_x_preferred":[
        "Hallu"
    ],
    "name:war_x_preferred":[
        "Hallu"
    ],
    "wof:name":"Hallu",
    "wof:placetype":"locality"
},
  "geometry": {"coordinates":[21.63518,60.82816],"type":"Point"}
}