{
  "type": "Feature",
  "properties": {
    "gn:admin1_code":"1.0",
    "gn:admin2_code":"11.0",
    "gn:admin3_code":"444.0",
    "gn:asciiname":"Hyrsylae",
    "gn:country_code":"FI",
    "gn:dem":42,
    "gn:feature_class":"P",
    "gn:feature_code":"PPL",
    "gn:name":"Hyrsyl\u00e4",
    "gn:population":0,
    "gn:timezone":"Europe/Helsinki",
    "iso:country":"FI",
    "name:und_x_variant":[
        "Hyrsynummi",
        "Hyrsyl\u00e4"
    ],
    "wof:name":"Hyrsylae",
    "wof:placetype":"locality"
},
  "geometry": {"coordinates":[24.02081,60.39151999999999],"type":"Point"}
}