{
  "type": "Feature",
  "properties": {
    "gn:admin1_code":"10.0",
    "gn:admin2_code":"101.0",
    "gn:admin3_code":"623.0",
    "gn:asciiname":"Keriniemi",
    "gn:country_code":"FI",
    "gn:dem":97,
    "gn:feature_class":"P",
    "gn:feature_code":"PPL",
    "gn:name":"Keriniemi",
    "gn:population":0,
    "gn:timezone":"Europe/Helsinki",
    "iso:country":"FI",
    "name:eng_x_preferred":[
        "Keriniemi"
    ],
    "name:rus_x_preferred":[
        "\u041a\u0435\u0440\u0438\u043d\u0438\u0435\u043c\u0438"
    ],
    "wof:name":"Keriniemi",
    "wof:placetype":"locality"
},
  "geometry": {"coordinates":[28.28829,61.62506],"type":"Point"}
}