{
  "type": "Feature",
  "properties": {
    "gn:admin1_code":"12.0",
    "gn:admin2_code":"122.0",
    "gn:admin3_code":"309.0",
    "gn:asciiname":"Suvisranta",
    "gn:cc2":"FI",
    "gn:country_code":"FI",
    "gn:dem":90,
    "gn:feature_class":"P",
    "gn:feature_code":"PPL",
    "gn:name":"Suvisranta",
    "gn:population":0,
    "gn:timezone":"Europe/Helsinki",
    "iso:country":"FI",
    "name:und_x_variant":[
        "Antilla"
    ],
    "wof:name":"Suvisranta",
    "wof:placetype":"locality"
},
  "geometry": {"coordinates":[29.03719,62.67097],"type":"Point"}
}