{
  "type": "Feature",
  "properties": {
    "gn:admin1_code":"2.0",
    "gn:admin2_code":"21.0",
    "gn:admin3_code":"445.0",
    "gn:asciiname":"Galtby Brygga",
    "gn:country_code":"FI",
    "gn:dem":-9999,
    "gn:feature_class":"P",
    "gn:feature_code":"PPL",
    "gn:name":"Galtby Brygga",
    "gn:population":0,
    "gn:timezone":"Europe/Helsinki",
    "iso:country":"FI",
    "wof:name":"Galtby Brygga",
    "wof:placetype":"locality"
},
  "geometry": {"coordinates":[21.59528,60.18361],"type":"Point"}
}