{
  "type": "Feature",
  "properties": {
    "gn:admin1_code":"13.0",
    "gn:admin2_code":"138.0",
    "gn:admin3_code":"312.0",
    "gn:asciiname":"Saunakylae",
    "gn:country_code":"FI",
    "gn:dem":217,
    "gn:feature_class":"P",
    "gn:feature_code":"PPL",
    "gn:name":"Saunakyl\u00e4",
    "gn:population":0,
    "gn:timezone":"Europe/Helsinki",
    "iso:country":"FI",
    "wof:name":"Saunakylae",
    "wof:placetype":"locality"
},
  "geometry": {"coordinates":[24.73999,63.09412],"type":"Point"}
}