{
  "type": "Feature",
  "properties": {
    "gn:admin1_code":"17.0",
    "gn:admin2_code":"178.0",
    "gn:admin3_code":"832.0",
    "gn:asciiname":"Inkee",
    "gn:cc2":"FI",
    "gn:country_code":"FI",
    "gn:dem":230,
    "gn:feature_class":"P",
    "gn:feature_code":"PPL",
    "gn:name":"Inkee",
    "gn:population":0,
    "gn:timezone":"Europe/Helsinki",
    "iso:country":"FI",
    "name:eng_x_preferred":[
        "Inkee"
    ],
    "name:rus_x_preferred":[
        "\u0418\u043d\u043a\u0435"
    ],
    "name:und_x_variant":[
        "Inkoe",
        "Inget",
        "Inkee"
    ],
    "wof:name":"Inkee",
    "wof:placetype":"locality"
},
  "geometry": {"coordinates":[28.55913,65.73577],"type":"Point"}
}