{
  "type": "Feature",
  "properties": {
    "gn:admin1_code":"9.0",
    "gn:admin2_code":"91.0",
    "gn:admin3_code":"405.0",
    "gn:asciiname":"Kontu",
    "gn:country_code":"FI",
    "gn:dem":44,
    "gn:feature_class":"P",
    "gn:feature_code":"PPL",
    "gn:name":"Kontu",
    "gn:population":0,
    "gn:timezone":"Europe/Helsinki",
    "iso:country":"FI",
    "wof:name":"Kontu",
    "wof:placetype":"locality"
},
  "geometry": {"coordinates":[28.67503,60.98655],"type":"Point"}
}