{
  "type": "Feature",
  "properties": {
    "gn:admin1_code":"15.0",
    "gn:admin2_code":"152.0",
    "gn:admin3_code":"499.0",
    "gn:asciiname":"Yxpil",
    "gn:country_code":"FI",
    "gn:dem":8,
    "gn:feature_class":"P",
    "gn:feature_code":"PPL",
    "gn:name":"Yxpil",
    "gn:population":0,
    "gn:timezone":"Europe/Helsinki",
    "iso:country":"FI",
    "name:swe_x_preferred":[
        "Yxpil"
    ],
    "wof:name":"Yxpil",
    "wof:placetype":"locality"
},
  "geometry": {"coordinates":[21.80665,63.01939],"type":"Point"}
}