{
  "type": "Feature",
  "properties": {
    "gn:admin1_code":"2.0",
    "gn:admin2_code":"24.0",
    "gn:admin3_code":"895.0",
    "gn:asciiname":"Rohijaervi",
    "gn:country_code":"FI",
    "gn:dem":25,
    "gn:feature_class":"P",
    "gn:feature_code":"PPL",
    "gn:name":"Rohij\u00e4rvi",
    "gn:population":0,
    "gn:timezone":"Europe/Helsinki",
    "iso:country":"FI",
    "wof:name":"Rohijaervi",
    "wof:placetype":"locality"
},
  "geometry": {"coordinates":[21.56667,60.83333],"type":"Point"}
}