{
  "type": "Feature",
  "properties": {
    "gn:admin1_code":"15.0",
    "gn:admin2_code":"154.0",
    "gn:admin3_code":"440.0",
    "gn:asciiname":"Krok",
    "gn:country_code":"FI",
    "gn:dem":21,
    "gn:feature_class":"P",
    "gn:feature_code":"PPL",
    "gn:name":"Krok",
    "gn:population":0,
    "gn:timezone":"Europe/Helsinki",
    "iso:country":"FI",
    "name:ceb_x_preferred":[
        "Krok"
    ],
    "name:ces_x_preferred":[
        "Krok"
    ],
    "name:deu_x_preferred":[
        "Krok"
    ],
    "name:fra_x_preferred":[
        "Krok"
    ],
    "name:nor_x_preferred":[
        "Krok"
    ],
    "name:pol_x_preferred":[
        "Krok"
    ],
    "name:rus_x_preferred":[
        "\u041a\u0440\u043e\u043a"
    ],
    "name:slk_x_preferred":[
        "Krok"
    ],
    "name:spa_x_preferred":[
        "Krok"
    ],
    "name:srp_x_preferred":[
        "\u041a\u0440\u043e\u043a"
    ],
    "name:swe_x_preferred":[
        "Krok"
    ],
    "name:ukr_x_preferred":[
        "\u041a\u0440\u043e\u043a"
    ],
    "wof:name":"Krok",
    "wof:placetype":"locality"
},
  "geometry": {"coordinates":[22.71017,63.81464],"type":"Point"}
}