{
  "type": "Feature",
  "properties": {
    "gn:admin1_code":"5.0",
    "gn:admin2_code":"51.0",
    "gn:admin3_code":"82.0",
    "gn:asciiname":"Ihalempi",
    "gn:cc2":"FI",
    "gn:country_code":"FI",
    "gn:dem":88,
    "gn:feature_class":"P",
    "gn:feature_code":"PPL",
    "gn:name":"Ihalempi",
    "gn:population":0,
    "gn:timezone":"Europe/Helsinki",
    "iso:country":"FI",
    "name:und_x_variant":[
        "Ihaniemi",
        "Ihalempi"
    ],
    "wof:name":"Ihalempi",
    "wof:placetype":"locality"
},
  "geometry": {"coordinates":[24.31255,61.06165],"type":"Point"}
}