{
  "type": "Feature",
  "properties": {
    "gn:admin1_code":"2.0",
    "gn:admin2_code":"24.0",
    "gn:admin3_code":"918.0",
    "gn:asciiname":"Vilu",
    "gn:country_code":"FI",
    "gn:dem":20,
    "gn:feature_class":"P",
    "gn:feature_code":"PPL",
    "gn:name":"Vilu",
    "gn:population":0,
    "gn:timezone":"Europe/Helsinki",
    "iso:country":"FI",
    "wof:name":"Vilu",
    "wof:placetype":"locality"
},
  "geometry": {"coordinates":[21.70875,60.61203],"type":"Point"}
}