{
  "type": "Feature",
  "properties": {
    "gn:admin1_code":"15.0",
    "gn:admin2_code":"152.0",
    "gn:admin3_code":"280.0",
    "gn:asciiname":"Vaesterdal",
    "gn:country_code":"FI",
    "gn:dem":12,
    "gn:feature_class":"P",
    "gn:feature_code":"PPL",
    "gn:name":"V\u00e4sterdal",
    "gn:population":0,
    "gn:timezone":"Europe/Helsinki",
    "iso:country":"FI",
    "wof:name":"Vaesterdal",
    "wof:placetype":"locality"
},
  "geometry": {"coordinates":[21.21667,62.68333000000001],"type":"Point"}
}