{
  "type": "Feature",
  "properties": {
    "gn:admin1_code":"11.0",
    "gn:admin2_code":"111.0",
    "gn:admin3_code":"402.0",
    "gn:asciiname":"Pitkaemaeki",
    "gn:country_code":"FI",
    "gn:dem":157,
    "gn:feature_class":"P",
    "gn:feature_code":"PPL",
    "gn:name":"Pitk\u00e4m\u00e4ki",
    "gn:population":0,
    "gn:timezone":"Europe/Helsinki",
    "iso:country":"FI",
    "name:und_x_variant":[
        "Pitk\u00e4m\u00e4ki",
        "Pitk\u00e4l\u00e4nm\u00e4ki"
    ],
    "wof:name":"Pitkaemaeki",
    "wof:placetype":"locality"
},
  "geometry": {"coordinates":[27.61156,63.39556],"type":"Point"}
}