{
  "type": "Feature",
  "properties": {
    "gn:admin1_code":"6.0",
    "gn:admin2_code":"68.0",
    "gn:admin3_code":"790.0",
    "gn:asciiname":"Makkonen",
    "gn:country_code":"FI",
    "gn:dem":99,
    "gn:feature_class":"P",
    "gn:feature_code":"PPL",
    "gn:name":"Makkonen",
    "gn:population":0,
    "gn:timezone":"Europe/Helsinki",
    "iso:country":"FI",
    "wof:name":"Makkonen",
    "wof:placetype":"locality"
},
  "geometry": {"coordinates":[22.8454,61.58668],"type":"Point"}
}