{
  "type": "Feature",
  "properties": {
    "gn:admin1_code":"14.0",
    "gn:admin2_code":"142.0",
    "gn:admin3_code":"743.0",
    "gn:asciiname":"Isokylae",
    "gn:country_code":"FI",
    "gn:dem":39,
    "gn:feature_class":"P",
    "gn:feature_code":"PPL",
    "gn:name":"Isokyl\u00e4",
    "gn:population":0,
    "gn:timezone":"Europe/Helsinki",
    "iso:country":"FI",
    "name:fin_x_preferred":[
        "Isokyl\u00e4"
    ],
    "wof:name":"Isokylae",
    "wof:placetype":"locality"
},
  "geometry": {"coordinates":[22.43865,62.95083],"type":"Point"}
}