{
  "type": "Feature",
  "properties": {
    "gn:admin1_code":"19.0",
    "gn:admin2_code":"194.0",
    "gn:admin3_code":"614.0",
    "gn:asciiname":"Iso Syoete",
    "gn:country_code":"FI",
    "gn:dem":284,
    "gn:feature_class":"P",
    "gn:feature_code":"PPL",
    "gn:name":"Iso Sy\u00f6te",
    "gn:population":0,
    "gn:timezone":"Europe/Helsinki",
    "iso:country":"FI",
    "wof:name":"Iso Syoete",
    "wof:placetype":"locality"
},
  "geometry": {"coordinates":[27.94373,65.8708],"type":"Point"}
}