{
  "type": "Feature",
  "properties": {
    "gn:admin1_code":"9.0",
    "gn:admin2_code":"91.0",
    "gn:admin3_code":"739.0",
    "gn:asciiname":"Pettilae",
    "gn:country_code":"FI",
    "gn:dem":100,
    "gn:feature_class":"P",
    "gn:feature_code":"PPL",
    "gn:name":"Pettil\u00e4",
    "gn:population":0,
    "gn:timezone":"Europe/Helsinki",
    "iso:country":"FI",
    "wof:name":"Pettilae",
    "wof:placetype":"locality"
},
  "geometry": {"coordinates":[27.76457000000001,61.29922],"type":"Point"}
}