{
  "type": "Feature",
  "properties": {
    "gn:admin1_code":"5.0",
    "gn:admin2_code":"51.0",
    "gn:admin3_code":"109.0",
    "gn:asciiname":"Arrankorpi",
    "gn:country_code":"FI",
    "gn:dem":132,
    "gn:feature_class":"P",
    "gn:feature_code":"PPL",
    "gn:name":"Arrankorpi",
    "gn:population":0,
    "gn:timezone":"Europe/Helsinki",
    "iso:country":"FI",
    "name:eng_x_preferred":[
        "Arrankorpi"
    ],
    "name:rus_x_preferred":[
        "\u0410\u0440\u0440\u0430\u043d\u043a\u043e\u0440\u043f\u0438"
    ],
    "wof:name":"Arrankorpi",
    "wof:placetype":"locality"
},
  "geometry": {"coordinates":[24.99448,60.95316],"type":"Point"}
}