{
  "type": "Feature",
  "properties": {
    "gn:admin1_code":"6.0",
    "gn:admin2_code":"61.0",
    "gn:admin3_code":"581.0",
    "gn:asciiname":"Raivaluoma",
    "gn:country_code":"FI",
    "gn:dem":140,
    "gn:feature_class":"P",
    "gn:feature_code":"PPL",
    "gn:name":"Raivaluoma",
    "gn:population":0,
    "gn:timezone":"Europe/Helsinki",
    "iso:country":"FI",
    "wof:name":"Raivaluoma",
    "wof:placetype":"locality"
},
  "geometry": {"coordinates":[22.76671,61.95091],"type":"Point"}
}