{
  "type": "Feature",
  "properties": {
    "gn:admin1_code":"19.0",
    "gn:admin2_code":"192.0",
    "gn:admin3_code":"851.0",
    "gn:asciiname":"Yli-Vojakkala",
    "gn:country_code":"FI",
    "gn:dem":16,
    "gn:feature_class":"P",
    "gn:feature_code":"PPL",
    "gn:name":"Yli-Vojakkala",
    "gn:population":0,
    "gn:timezone":"Europe/Helsinki",
    "iso:country":"FI",
    "name:und_x_variant":[
        "Vojakkala"
    ],
    "wof:name":"Yli-Vojakkala",
    "wof:placetype":"locality"
},
  "geometry": {"coordinates":[24.11073,65.93958000000001],"type":"Point"}
}