{
  "type": "Feature",
  "properties": {
    "gn:admin1_code":"5.0",
    "gn:admin2_code":"53.0",
    "gn:admin3_code":"103.0",
    "gn:asciiname":"Koivisto",
    "gn:country_code":"FI",
    "gn:dem":124,
    "gn:feature_class":"P",
    "gn:feature_code":"PPL",
    "gn:name":"Koivisto",
    "gn:population":0,
    "gn:timezone":"Europe/Helsinki",
    "iso:country":"FI",
    "name:ceb_x_preferred":[
        "Koivisto"
    ],
    "name:deu_x_preferred":[
        "Koivisto"
    ],
    "name:fin_x_preferred":[
        "Koivisto"
    ],
    "name:fra_x_preferred":[
        "Koivisto"
    ],
    "name:nds_x_preferred":[
        "Koivisto"
    ],
    "name:pol_x_preferred":[
        "Koivisto"
    ],
    "name:rus_x_preferred":[
        "\u041a\u043e\u0439\u0432\u0438\u0441\u0442\u043e"
    ],
    "name:swe_x_preferred":[
        "Koivisto"
    ],
    "wof:name":"Koivisto",
    "wof:placetype":"locality"
},
  "geometry": {"coordinates":[23.38333,60.93333000000001],"type":"Point"}
}