{
  "type": "Feature",
  "properties": {
    "iso:country":"FI",
    "name:ast_x_preferred":[
        "Kultaranta"
    ],
    "name:deu_x_preferred":[
        "Kultaranta"
    ],
    "name:est_x_preferred":[
        "Kultaranta"
    ],
    "name:fin_x_preferred":[
        "Kultaranta"
    ],
    "name:fra_x_preferred":[
        "Kultaranta"
    ],
    "name:nld_x_preferred":[
        "Kultaranta"
    ],
    "name:rus_x_preferred":[
        "\u041a\u0443\u043b\u0442\u0430\u0440\u0430\u043d\u0442\u0430"
    ],
    "name:spa_x_preferred":[
        "Kultaranta"
    ],
    "name:swe_x_preferred":[
        "Gullranda"
    ],
    "qs_pg:aaroncc":"FI",
    "qs_pg:name":"Kultaranta",
    "qs_pg:name_adm0":"Suomi",
    "qs_pg:name_adm1":"Varsinais-Suomen maakunta",
    "qs_pg:photos":11,
    "qs_pg:photos_1k":2,
    "qs_pg:photos_9k":1,
    "qs_pg:photos_9r":1,
    "qs_pg:photos_all":11,
    "qs_pg:photos_sr":1,
    "qs_pg:pop_sr":0,
    "qs_pg:qs_pg_placetype":"locality",
    "qs_pg:qs_pg_placetype_gp":"Town",
    "qs_pg:woe_adm0":23424812,
    "woe:adm0_id":23424812,
    "woe:name_adm0":"Suomi",
    "woe:name_adm1":"Varsinais-Suomen maakunta",
    "woe:placetype":"Town",
    "wof:name":"Kultaranta",
    "wof:placetype":"locality"
},
  "geometry": {"coordinates":[22.004928,60.473549],"type":"Point"}
}