{
  "type": "Feature",
  "properties": {
    "gn:admin1_code":"2.0",
    "gn:admin2_code":"22.0",
    "gn:admin3_code":"761.0",
    "gn:asciiname":"Kaskisto",
    "gn:country_code":"FI",
    "gn:dem":85,
    "gn:feature_class":"P",
    "gn:feature_code":"PPL",
    "gn:name":"Kaskisto",
    "gn:population":0,
    "gn:timezone":"Europe/Helsinki",
    "iso:country":"FI",
    "wof:name":"Kaskisto",
    "wof:placetype":"locality"
},
  "geometry": {"coordinates":[23.64257000000001,60.51816],"type":"Point"}
}