{
  "type": "Feature",
  "properties": {
    "gn:admin1_code":"2.0",
    "gn:admin2_code":"23.0",
    "gn:admin3_code":"503.0",
    "gn:asciiname":"Lahdenkulma",
    "gn:country_code":"FI",
    "gn:dem":9,
    "gn:feature_class":"P",
    "gn:feature_code":"PPL",
    "gn:name":"Lahdenkulma",
    "gn:population":0,
    "gn:timezone":"Europe/Helsinki",
    "iso:country":"FI",
    "wof:name":"Lahdenkulma",
    "wof:placetype":"locality"
},
  "geometry": {"coordinates":[21.90333,60.65083000000001],"type":"Point"}
}