{
  "type": "Feature",
  "properties": {
    "gn:country":"FI",
    "gn:fcode":"PPL",
    "gn:population":0,
    "iso:country":"FI",
    "name:deu_x_preferred":[
        "Tottij\u00e4rvi"
    ],
    "name:eng_x_preferred":[
        "Tottij\u00e4rvi"
    ],
    "name:fin_x_preferred":[
        "Tottij\u00e4rvi"
    ],
    "name:nob_x_preferred":[
        "Tottij\u00e4rvi"
    ],
    "name:swe_x_preferred":[
        "Tottij\u00e4rvi"
    ],
    "qs_pg:aaroncc":"FI",
    "qs_pg:gn_country":"FI",
    "qs_pg:gn_fcode":"PPL",
    "qs_pg:gn_pop":0,
    "qs_pg:name":"Tottij\u00e4rvi",
    "qs_pg:name_adm0":"Suomi",
    "qs_pg:name_adm1":"Pirkanmaan maakunta",
    "qs_pg:photos":108,
    "qs_pg:photos_1k":22,
    "qs_pg:photos_9k":1,
    "qs_pg:photos_9r":3,
    "qs_pg:photos_all":108,
    "qs_pg:photos_sr":3,
    "qs_pg:pop_sr":0,
    "qs_pg:qs_pg_placetype":"locality",
    "qs_pg:qs_pg_placetype_gp":"Town",
    "qs_pg:woe_adm0":23424812,
    "woe:adm0_id":23424812,
    "woe:name_adm0":"Suomi",
    "woe:name_adm1":"Pirkanmaan maakunta",
    "woe:placetype":"Town",
    "wof:name":"Tottij\u00e4rvi",
    "wof:placetype":"locality"
},
  "geometry": {"coordinates":[23.34337,61.40033],"type":"Point"}
}