{
  "type": "Feature",
  "properties": {
    "gn:admin1_code":"12.0",
    "gn:admin2_code":"122.0",
    "gn:admin3_code":"167.0",
    "gn:asciiname":"Nesterinsaari",
    "gn:country_code":"FI",
    "gn:dem":203,
    "gn:feature_class":"P",
    "gn:feature_code":"PPL",
    "gn:name":"Nesterinsaari",
    "gn:population":0,
    "gn:timezone":"Europe/Helsinki",
    "iso:country":"FI",
    "wof:name":"Nesterinsaari",
    "wof:placetype":"locality"
},
  "geometry": {"coordinates":[30.25,62.71666999999999],"type":"Point"}
}