{
  "type": "Feature",
  "properties": {
    "gn:admin1_code":"17.0",
    "gn:admin2_code":"176.0",
    "gn:admin3_code":"317.0",
    "gn:asciiname":"Ruhankangas",
    "gn:country_code":"FI",
    "gn:dem":107,
    "gn:feature_class":"P",
    "gn:feature_code":"PPL",
    "gn:name":"Ruhankangas",
    "gn:population":0,
    "gn:timezone":"Europe/Helsinki",
    "iso:country":"FI",
    "wof:name":"Ruhankangas",
    "wof:placetype":"locality"
},
  "geometry": {"coordinates":[25.78099,63.94298000000001],"type":"Point"}
}