{
  "type": "Feature",
  "properties": {
    "gn:admin1_code":"1.0",
    "gn:admin2_code":"11.0",
    "gn:admin3_code":"753.0",
    "gn:asciiname":"Vaakkola",
    "gn:country_code":"FI",
    "gn:dem":26,
    "gn:feature_class":"P",
    "gn:feature_code":"PPL",
    "gn:name":"Vaakkola",
    "gn:population":0,
    "gn:timezone":"Europe/Helsinki",
    "iso:country":"FI",
    "wof:name":"Vaakkola",
    "wof:placetype":"locality"
},
  "geometry": {"coordinates":[25.29127,60.28188000000001],"type":"Point"}
}