{
  "type": "Feature",
  "properties": {
    "gn:admin1_code":"1.0",
    "gn:admin2_code":"11.0",
    "gn:admin3_code":"49.0",
    "gn:asciiname":"Soederskog",
    "gn:country_code":"FI",
    "gn:dem":26,
    "gn:feature_class":"P",
    "gn:feature_code":"PPL",
    "gn:name":"S\u00f6derskog",
    "gn:population":0,
    "gn:timezone":"Europe/Helsinki",
    "iso:country":"FI",
    "name:fin_x_preferred":[
        "Suvimets\u00e4"
    ],
    "wof:name":"Soederskog",
    "wof:placetype":"locality"
},
  "geometry": {"coordinates":[24.66654,60.18843],"type":"Point"}
}