{
  "type": "Feature",
  "properties": {
    "gn:admin1_code":"12.0",
    "gn:admin2_code":"122.0",
    "gn:admin3_code":"426.0",
    "gn:asciiname":"Juojaervi",
    "gn:country_code":"FI",
    "gn:dem":115,
    "gn:feature_class":"P",
    "gn:feature_code":"PPL",
    "gn:name":"Juoj\u00e4rvi",
    "gn:population":0,
    "gn:timezone":"Europe/Helsinki",
    "iso:country":"FI",
    "name:eng_x_preferred":[
        "Juoj\u00e4rvi"
    ],
    "name:rus_x_preferred":[
        "\u042e\u043e\u044f\u0440\u0432\u0438"
    ],
    "name:und_x_variant":[
        "Juoj\u00e4rvi"
    ],
    "wof:name":"Juojaervi",
    "wof:placetype":"locality"
},
  "geometry": {"coordinates":[29.04439,62.5351],"type":"Point"}
}