{
  "type": "Feature",
  "properties": {
    "gn:admin1_code":"2.0",
    "gn:admin2_code":"21.0",
    "gn:admin3_code":"322.0",
    "gn:asciiname":"Vaestankaerr",
    "gn:country_code":"FI",
    "gn:dem":10,
    "gn:feature_class":"P",
    "gn:feature_code":"PPL",
    "gn:name":"V\u00e4stank\u00e4rr",
    "gn:population":0,
    "gn:timezone":"Europe/Helsinki",
    "iso:country":"FI",
    "name:und_x_variant":[
        "Vestankar",
        "V\u00e4stank\u00e4rr"
    ],
    "wof:name":"Vaestankaerr",
    "wof:placetype":"locality"
},
  "geometry": {"coordinates":[22.52482,60.19538000000001],"type":"Point"}
}