{
  "type": "Feature",
  "properties": {
    "gn:admin1_code":"2.0",
    "gn:admin2_code":"22.0",
    "gn:admin3_code":"734.0",
    "gn:asciiname":"Isopakapyoeli",
    "gn:country_code":"FI",
    "gn:dem":85,
    "gn:feature_class":"P",
    "gn:feature_code":"PPL",
    "gn:name":"Isopakapy\u00f6li",
    "gn:population":0,
    "gn:timezone":"Europe/Helsinki",
    "iso:country":"FI",
    "name:swe_x_preferred":[
        "Storbaggb\u00f6le"
    ],
    "wof:name":"Isopakapyoeli",
    "wof:placetype":"locality"
},
  "geometry": {"coordinates":[23.18333,60.15],"type":"Point"}
}