{
  "type": "Feature",
  "properties": {
    "gn:admin1_code":"4.0",
    "gn:admin2_code":"43.0",
    "gn:admin3_code":"609.0",
    "gn:asciiname":"Viikeri",
    "gn:country_code":"FI",
    "gn:dem":47,
    "gn:feature_class":"P",
    "gn:feature_code":"PPL",
    "gn:name":"Viikeri",
    "gn:population":0,
    "gn:timezone":"Europe/Helsinki",
    "iso:country":"FI",
    "name:dan_x_preferred":[
        "Vidk\u00e4rr"
    ],
    "name:isl_x_preferred":[
        "Vidk\u00e4rr"
    ],
    "name:nde_x_preferred":[
        "Vidk\u00e4rr"
    ],
    "name:nno_x_preferred":[
        "Vidk\u00e4rr"
    ],
    "name:swe_x_preferred":[
        "Vidk\u00e4rr"
    ],
    "wof:name":"Viikeri",
    "wof:placetype":"locality"
},
  "geometry": {"coordinates":[21.87703,61.54143000000001],"type":"Point"}
}