{
  "type": "Feature",
  "properties": {
    "gn:admin1_code":"19.0",
    "gn:admin2_code":"194.0",
    "gn:admin3_code":"320.0",
    "gn:asciiname":"Isokylae",
    "gn:country_code":"FI",
    "gn:dem":173,
    "gn:feature_class":"P",
    "gn:feature_code":"PPL",
    "gn:name":"Isokyl\u00e4",
    "gn:population":0,
    "gn:timezone":"Europe/Helsinki",
    "iso:country":"FI",
    "wof:name":"Isokylae",
    "wof:placetype":"locality"
},
  "geometry": {"coordinates":[27.68333,66.63333],"type":"Point"}
}