{
  "type": "Feature",
  "properties": {
    "gn:admin1_code":"18.0",
    "gn:admin2_code":"182.0",
    "gn:admin3_code":"765.0",
    "gn:asciiname":"Sirvioelae",
    "gn:country_code":"FI",
    "gn:dem":151,
    "gn:feature_class":"P",
    "gn:feature_code":"PPL",
    "gn:name":"Sirvi\u00f6l\u00e4",
    "gn:population":0,
    "gn:timezone":"Europe/Helsinki",
    "iso:country":"FI",
    "wof:name":"Sirvioelae",
    "wof:placetype":"locality"
},
  "geometry": {"coordinates":[28.46667,64.16667],"type":"Point"}
}