{
  "type": "Feature",
  "properties": {
    "gn:admin1_code":"18.0",
    "gn:admin2_code":"181.0",
    "gn:admin3_code":"620.0",
    "gn:asciiname":"Marttila",
    "gn:country_code":"FI",
    "gn:dem":232,
    "gn:feature_class":"P",
    "gn:feature_code":"PPL",
    "gn:name":"Marttila",
    "gn:population":0,
    "gn:timezone":"Europe/Helsinki",
    "iso:country":"FI",
    "wof:name":"Marttila",
    "wof:placetype":"locality"
},
  "geometry": {"coordinates":[27.76667,64.84999999999999],"type":"Point"}
}