{
  "type": "Feature",
  "properties": {
    "gn:admin1_code":"2.0",
    "gn:admin2_code":"25.0",
    "gn:admin3_code":"636.0",
    "gn:asciiname":"Paju",
    "gn:country_code":"FI",
    "gn:dem":93,
    "gn:feature_class":"P",
    "gn:feature_code":"PPL",
    "gn:name":"Paju",
    "gn:population":0,
    "gn:timezone":"Europe/Helsinki",
    "iso:country":"FI",
    "name:ara_x_preferred":[
        "\u0628\u0627\u062c\u0648"
    ],
    "name:bul_x_preferred":[
        "\u041f\u0430\u0434\u0436\u0443"
    ],
    "name:ceb_x_preferred":[
        "Paju-si"
    ],
    "name:ces_x_preferred":[
        "Pchad\u017eu"
    ],
    "name:deu_x_preferred":[
        "Paju"
    ],
    "name:epo_x_preferred":[
        "Pa\u011du"
    ],
    "name:est_x_preferred":[
        "Paju"
    ],
    "name:fas_x_preferred":[
        "\u067e\u0627\u062c\u0648"
    ],
    "name:fin_x_preferred":[
        "Paju"
    ],
    "name:fra_x_preferred":[
        "Paju"
    ],
    "name:hak_x_preferred":[
        "Paju S\u1e73"
    ],
    "name:ind_x_preferred":[
        "Paju"
    ],
    "name:ita_x_preferred":[
        "Paju"
    ],
    "name:jpn_x_preferred":[
        "\u5761\u5dde\u5e02"
    ],
    "name:kor_x_preferred":[
        "\ud30c\uc8fc\uc2dc"
    ],
    "name:lfn_x_preferred":[
        "Paju"
    ],
    "name:mon_x_preferred":[
        "\u041f\u0430\u0436\u04af"
    ],
    "name:nld_x_preferred":[
        "Paju"
    ],
    "name:nor_x_preferred":[
        "Paju"
    ],
    "name:pol_x_preferred":[
        "Paju"
    ],
    "name:por_x_preferred":[
        "Paju"
    ],
    "name:rus_x_preferred":[
        "\u041f\u0445\u0430\u0434\u0436\u0443"
    ],
    "name:sco_x_preferred":[
        "Paju"
    ],
    "name:spa_x_preferred":[
        "Paju"
    ],
    "name:swe_x_preferred":[
        "Paju"
    ],
    "name:tgl_x_preferred":[
        "Paju"
    ],
    "name:tha_x_preferred":[
        "\u0e1e\u0e32\u0e08\u0e39"
    ],
    "name:tur_x_preferred":[
        "Paju"
    ],
    "name:ukr_x_preferred":[
        "\u041f\u0445\u0430\u0434\u0436\u0443"
    ],
    "name:urd_x_preferred":[
        "\u067e\u0627\u062c\u0648"
    ],
    "name:vie_x_preferred":[
        "Paju"
    ],
    "name:war_x_preferred":[
        "Paju"
    ],
    "name:zho_x_preferred":[
        "\u5761\u5dde\u5e02"
    ],
    "wof:name":"Paju",
    "wof:placetype":"locality"
},
  "geometry": {"coordinates":[22.68333,60.78333000000001],"type":"Point"}
}