{
  "type": "Feature",
  "properties": {
    "gn:admin1_code":"13.0",
    "gn:admin2_code":"134.0",
    "gn:admin3_code":"182.0",
    "gn:asciiname":"Valkamanperae",
    "gn:country_code":"FI",
    "gn:dem":118,
    "gn:feature_class":"P",
    "gn:feature_code":"PPL",
    "gn:name":"Valkamanper\u00e4",
    "gn:population":0,
    "gn:timezone":"Europe/Helsinki",
    "iso:country":"FI",
    "name:fin_x_preferred":[
        "Valkamanper\u00e4"
    ],
    "wof:name":"Valkamanperae",
    "wof:placetype":"locality"
},
  "geometry": {"coordinates":[24.77985,61.88615],"type":"Point"}
}