{
  "type": "Feature",
  "properties": {
    "gn:admin1_code":"2.0",
    "gn:admin2_code":"25.0",
    "gn:admin3_code":"636.0",
    "gn:asciiname":"Puho",
    "gn:country_code":"FI",
    "gn:dem":75,
    "gn:feature_class":"P",
    "gn:feature_code":"PPL",
    "gn:name":"Puho",
    "gn:population":0,
    "gn:timezone":"Europe/Helsinki",
    "iso:country":"FI",
    "wof:name":"Puho",
    "wof:placetype":"locality"
},
  "geometry": {"coordinates":[22.58569,60.67741],"type":"Point"}
}