{
  "type": "Feature",
  "properties": {
    "gn:admin1_code":"1.0",
    "gn:admin2_code":"11.0",
    "gn:admin3_code":"753.0",
    "gn:asciiname":"Norra Paipis",
    "gn:cc2":"FI",
    "gn:country_code":"FI",
    "gn:dem":58,
    "gn:feature_class":"P",
    "gn:feature_code":"PPL",
    "gn:name":"Norra Paipis",
    "gn:population":0,
    "gn:timezone":"Europe/Helsinki",
    "iso:country":"FI",
    "name:fin_x_preferred":[
        "Pohjois-Paippinen"
    ],
    "name:swe_x_preferred":[
        "Norra Paippis"
    ],
    "name:swe_x_variant":[
        "Norra Paipis"
    ],
    "wof:name":"Norra Paipis",
    "wof:placetype":"locality"
},
  "geometry": {"coordinates":[25.19977,60.47508000000001],"type":"Point"}
}