{
  "type": "Feature",
  "properties": {
    "gn:admin1_code":"13.0",
    "gn:admin2_code":"133.0",
    "gn:admin3_code":"249.0",
    "gn:asciiname":"Riiho",
    "gn:country_code":"FI",
    "gn:dem":113,
    "gn:feature_class":"P",
    "gn:feature_code":"PPL",
    "gn:name":"Riiho",
    "gn:population":0,
    "gn:timezone":"Europe/Helsinki",
    "iso:country":"FI",
    "wof:name":"Riiho",
    "wof:placetype":"locality"
},
  "geometry": {"coordinates":[24.40064,62.20042],"type":"Point"}
}