{
  "type": "Feature",
  "properties": {
    "gn:admin1_code":"6.0",
    "gn:admin2_code":"61.0",
    "gn:admin3_code":"143.0",
    "gn:asciiname":"Karhoinen",
    "gn:country_code":"FI",
    "gn:dem":136,
    "gn:feature_class":"P",
    "gn:feature_code":"PPL",
    "gn:name":"Karhoinen",
    "gn:population":0,
    "gn:timezone":"Europe/Helsinki",
    "iso:country":"FI",
    "wof:name":"Karhoinen",
    "wof:placetype":"locality"
},
  "geometry": {"coordinates":[22.86667000000001,61.76667],"type":"Point"}
}