{
  "type": "Feature",
  "properties": {
    "gn:admin1_code":"1.0",
    "gn:admin2_code":"11.0",
    "gn:admin3_code":"927.0",
    "gn:asciiname":"Pakasela",
    "gn:country_code":"FI",
    "gn:dem":78,
    "gn:feature_class":"P",
    "gn:feature_code":"PPL",
    "gn:name":"Pakasela",
    "gn:population":0,
    "gn:timezone":"Europe/Helsinki",
    "iso:country":"FI",
    "wof:name":"Pakasela",
    "wof:placetype":"locality"
},
  "geometry": {"coordinates":[24.16667,60.45],"type":"Point"}
}