{
  "type": "Feature",
  "properties": {
    "gn:admin1_code":"4.0",
    "gn:admin2_code":"43.0",
    "gn:admin3_code":"609.0",
    "gn:asciiname":"Vaelimaeki",
    "gn:country_code":"FI",
    "gn:dem":12,
    "gn:feature_class":"P",
    "gn:feature_code":"PPL",
    "gn:name":"V\u00e4lim\u00e4ki",
    "gn:population":0,
    "gn:timezone":"Europe/Helsinki",
    "iso:country":"FI",
    "name:fin_x_preferred":[
        "V\u00e4lim\u00e4ki"
    ],
    "wof:name":"Vaelimaeki",
    "wof:placetype":"locality"
},
  "geometry": {"coordinates":[21.73803,61.54221999999999],"type":"Point"}
}