{
  "type": "Feature",
  "properties": {
    "gn:admin1_code":"10.0",
    "gn:admin2_code":"103.0",
    "gn:admin3_code":"740.0",
    "gn:asciiname":"Ala-Saerkilahti",
    "gn:country_code":"FI",
    "gn:dem":103,
    "gn:feature_class":"P",
    "gn:feature_code":"PPL",
    "gn:name":"Ala-S\u00e4rkilahti",
    "gn:population":0,
    "gn:timezone":"Europe/Helsinki",
    "iso:country":"FI",
    "wof:name":"Ala-Saerkilahti",
    "wof:placetype":"locality"
},
  "geometry": {"coordinates":[29.08333,61.55],"type":"Point"}
}