{
  "type": "Feature",
  "properties": {
    "gn:admin1_code":"2.0",
    "gn:admin2_code":"23.0",
    "gn:admin3_code":"853.0",
    "gn:asciiname":"Metsaemaeki",
    "gn:country_code":"FI",
    "gn:dem":11,
    "gn:feature_class":"P",
    "gn:feature_code":"PPL",
    "gn:name":"Mets\u00e4m\u00e4ki",
    "gn:population":0,
    "gn:timezone":"Europe/Helsinki",
    "iso:country":"FI",
    "wof:name":"Metsaemaeki",
    "wof:placetype":"locality"
},
  "geometry": {"coordinates":[22.34575,60.49544],"type":"Point"}
}