{
  "type": "Feature",
  "properties": {
    "gn:admin1_code":"1.0",
    "gn:admin2_code":"11.0",
    "gn:admin3_code":"858.0",
    "gn:asciiname":"Hernemaeki",
    "gn:country_code":"FI",
    "gn:dem":63,
    "gn:feature_class":"P",
    "gn:feature_code":"PPL",
    "gn:name":"Hernem\u00e4ki",
    "gn:population":0,
    "gn:timezone":"Europe/Helsinki",
    "iso:country":"FI",
    "wof:name":"Hernemaeki",
    "wof:placetype":"locality"
},
  "geometry": {"coordinates":[24.95465,60.39095],"type":"Point"}
}