{
  "type": "Feature",
  "properties": {
    "gn:admin1_code":"13.0",
    "gn:admin2_code":"138.0",
    "gn:admin3_code":"265.0",
    "gn:asciiname":"Heinolahti",
    "gn:country_code":"FI",
    "gn:dem":142,
    "gn:feature_class":"P",
    "gn:feature_code":"PPL",
    "gn:name":"Heinolahti",
    "gn:population":0,
    "gn:timezone":"Europe/Helsinki",
    "iso:country":"FI",
    "wof:name":"Heinolahti",
    "wof:placetype":"locality"
},
  "geometry": {"coordinates":[25.03333,63.13333000000001],"type":"Point"}
}