{
  "type": "Feature",
  "properties": {
    "gn:admin1_code":"19.0",
    "gn:admin2_code":"194.0",
    "gn:admin3_code":"742.0",
    "gn:asciiname":"Vaerrioe",
    "gn:country_code":"FI",
    "gn:dem":219,
    "gn:feature_class":"P",
    "gn:feature_code":"PPL",
    "gn:name":"V\u00e4rri\u00f6",
    "gn:population":0,
    "gn:timezone":"Europe/Helsinki",
    "iso:country":"FI",
    "name:eng_x_preferred":[
        "V\u00e4rri\u00f6"
    ],
    "name:rus_x_preferred":[
        "\u0412\u044f\u0440\u0440\u0438\u0435"
    ],
    "name:und_x_variant":[
        "V\u00e4rri\u00f6"
    ],
    "wof:name":"Vaerrioe",
    "wof:placetype":"locality"
},
  "geometry": {"coordinates":[27.99231,67.46535],"type":"Point"}
}