{
  "type": "Feature",
  "properties": {
    "gn:country":"FI",
    "gn:fcode":"PPL",
    "gn:population":0,
    "iso:country":"FI",
    "name:eng_x_preferred":[
        "Rannankyl\u00e4"
    ],
    "name:rus_x_preferred":[
        "\u0420\u0430\u043d\u043d\u0430\u043d\u043a\u044e\u043b\u044f"
    ],
    "qs_pg:aaroncc":"FI",
    "qs_pg:gn_country":"FI",
    "qs_pg:gn_fcode":"PPL",
    "qs_pg:gn_pop":0,
    "qs_pg:name":"Rannankyl\u00e4",
    "qs_pg:name_adm0":"Suomi",
    "qs_pg:name_adm1":"Pohjois-pohjanmaan maakunta",
    "qs_pg:photos":4,
    "qs_pg:photos_1k":1,
    "qs_pg:photos_9k":1,
    "qs_pg:photos_9r":1,
    "qs_pg:photos_all":4,
    "qs_pg:photos_sr":1,
    "qs_pg:pop_sr":0,
    "qs_pg:qs_pg_placetype":"locality",
    "qs_pg:qs_pg_placetype_gp":"Town",
    "qs_pg:woe_adm0":23424812,
    "woe:adm0_id":23424812,
    "woe:name_adm0":"Suomi",
    "woe:name_adm1":"Pohjois-pohjanmaan maakunta",
    "woe:placetype":"Town",
    "wof:name":"Rannankyl\u00e4",
    "wof:placetype":"locality"
},
  "geometry": {"coordinates":[26.06667,63.61667],"type":"Point"}
}