{
  "type": "Feature",
  "properties": {
    "gn:admin1_code":"1.0",
    "gn:admin2_code":"11.0",
    "gn:admin3_code":"755.0",
    "gn:asciiname":"Andby",
    "gn:country_code":"FI",
    "gn:dem":60,
    "gn:feature_class":"P",
    "gn:feature_code":"PPL",
    "gn:name":"Andby",
    "gn:population":0,
    "gn:timezone":"Europe/Helsinki",
    "iso:country":"FI",
    "name:fin_x_preferred":[
        "Annila"
    ],
    "name:swe_x_preferred":[
        "Andby"
    ],
    "wof:name":"Andby",
    "wof:placetype":"locality"
},
  "geometry": {"coordinates":[24.30327,60.22588],"type":"Point"}
}