{
  "type": "Feature",
  "properties": {
    "gn:admin1_code":"12.0",
    "gn:admin2_code":"124.0",
    "gn:admin3_code":"707.0",
    "gn:asciiname":"Seppaelae",
    "gn:country_code":"FI",
    "gn:dem":89,
    "gn:feature_class":"P",
    "gn:feature_code":"PPL",
    "gn:name":"Sepp\u00e4l\u00e4",
    "gn:population":0,
    "gn:timezone":"Europe/Helsinki",
    "iso:country":"FI",
    "wof:name":"Seppaelae",
    "wof:placetype":"locality"
},
  "geometry": {"coordinates":[29.73333,62.21666999999999],"type":"Point"}
}