{
  "type": "Feature",
  "properties": {
    "gn:admin1_code":"9.0",
    "gn:admin2_code":"93.0",
    "gn:admin3_code":"689.0",
    "gn:asciiname":"Kangaskoski",
    "gn:country_code":"FI",
    "gn:dem":50,
    "gn:feature_class":"P",
    "gn:feature_code":"PPL",
    "gn:name":"Kangaskoski",
    "gn:population":0,
    "gn:timezone":"Europe/Helsinki",
    "iso:country":"FI",
    "wof:name":"Kangaskoski",
    "wof:placetype":"locality"
},
  "geometry": {"coordinates":[29.40352,61.41289],"type":"Point"}
}