{
  "type": "Feature",
  "properties": {
    "gn:admin1_code":"10.0",
    "gn:admin2_code":"101.0",
    "gn:admin3_code":"507.0",
    "gn:asciiname":"Kinni",
    "gn:country_code":"FI",
    "gn:dem":114,
    "gn:feature_class":"P",
    "gn:feature_code":"PPL",
    "gn:name":"Kinni",
    "gn:population":0,
    "gn:timezone":"Europe/Helsinki",
    "iso:country":"FI",
    "name:und_x_variant":[
        "Kinnil\u00e4"
    ],
    "wof:name":"Kinni",
    "wof:placetype":"locality"
},
  "geometry": {"coordinates":[26.93106,61.30546999999999],"type":"Point"}
}