{
  "type": "Feature",
  "properties": {
    "gn:admin1_code":"5.0",
    "gn:admin2_code":"51.0",
    "gn:admin3_code":"109.0",
    "gn:asciiname":"Niemikylaet",
    "gn:country_code":"FI",
    "gn:dem":91,
    "gn:feature_class":"P",
    "gn:feature_code":"PPL",
    "gn:name":"Niemikyl\u00e4t",
    "gn:population":0,
    "gn:timezone":"Europe/Helsinki",
    "iso:country":"FI",
    "name:und_x_variant":[
        "Niemikulma",
        "Niemikunta",
        "Niemikyl\u00e4t"
    ],
    "wof:name":"Niemikylaet",
    "wof:placetype":"locality"
},
  "geometry": {"coordinates":[24.40996,61.20829000000001],"type":"Point"}
}