{
  "type": "Feature",
  "properties": {
    "gn:admin1_code":"17.0",
    "gn:admin2_code":"177.0",
    "gn:admin3_code":"746.0",
    "gn:asciiname":"Pirttioja",
    "gn:country_code":"FI",
    "gn:dem":86,
    "gn:feature_class":"P",
    "gn:feature_code":"PPL",
    "gn:name":"Pirttioja",
    "gn:population":0,
    "gn:timezone":"Europe/Helsinki",
    "iso:country":"FI",
    "wof:name":"Pirttioja",
    "wof:placetype":"locality"
},
  "geometry": {"coordinates":[24.63333,63.93333000000001],"type":"Point"}
}