{
  "type": "Feature",
  "properties": {
    "gn:admin1_code":"11.0",
    "gn:admin2_code":"113.0",
    "gn:admin3_code":"857.0",
    "gn:asciiname":"Hauranki",
    "gn:country_code":"FI",
    "gn:dem":145,
    "gn:feature_class":"P",
    "gn:feature_code":"PPL",
    "gn:name":"Hauranki",
    "gn:population":0,
    "gn:timezone":"Europe/Helsinki",
    "iso:country":"FI",
    "wof:name":"Hauranki",
    "wof:placetype":"locality"
},
  "geometry": {"coordinates":[28.3527,62.9147],"type":"Point"}
}