{
  "type": "Feature",
  "properties": {
    "gn:admin1_code":"4.0",
    "gn:admin2_code":"43.0",
    "gn:admin3_code":"484.0",
    "gn:asciiname":"Stupila",
    "gn:country_code":"FI",
    "gn:dem":18,
    "gn:feature_class":"P",
    "gn:feature_code":"PPL",
    "gn:name":"Stupila",
    "gn:population":0,
    "gn:timezone":"Europe/Helsinki",
    "iso:country":"FI",
    "name:swe_x_historical":[
        "Stubbas"
    ],
    "name:swe_x_preferred":[
        "Stubbas"
    ],
    "wof:name":"Stupila",
    "wof:placetype":"locality"
},
  "geometry": {"coordinates":[21.51779,61.85386],"type":"Point"}
}