{
  "type": "Feature",
  "properties": {
    "gn:admin1_code":"6.0",
    "gn:admin2_code":"64.0",
    "gn:admin3_code":"837.0",
    "gn:asciiname":"Messukylae",
    "gn:country_code":"FI",
    "gn:dem":92,
    "gn:feature_class":"P",
    "gn:feature_code":"PPL",
    "gn:name":"Messukyl\u00e4",
    "gn:population":0,
    "gn:timezone":"Europe/Helsinki",
    "iso:country":"FI",
    "name:ces_x_preferred":[
        "Messukyl\u00e4"
    ],
    "name:dan_x_preferred":[
        "Messuby"
    ],
    "name:deu_x_preferred":[
        "Messukyl\u00e4"
    ],
    "name:fin_x_preferred":[
        "Messukyl\u00e4"
    ],
    "name:fra_x_preferred":[
        "Messukyl\u00e4"
    ],
    "name:nor_x_preferred":[
        "Messuby"
    ],
    "name:nor_x_variant":[
        "Messukyl\u00e4"
    ],
    "name:swe_x_preferred":[
        "Messuby"
    ],
    "wof:name":"Messukylae",
    "wof:placetype":"locality"
},
  "geometry": {"coordinates":[23.84222,61.48546999999999],"type":"Point"}
}