{
  "type": "Feature",
  "properties": {
    "gn:admin1_code":"15.0",
    "gn:admin2_code":"152.0",
    "gn:admin3_code":"499.0",
    "gn:asciiname":"Kilen",
    "gn:country_code":"FI",
    "gn:dem":27,
    "gn:feature_class":"P",
    "gn:feature_code":"PPL",
    "gn:name":"Kilen",
    "gn:population":0,
    "gn:timezone":"Europe/Helsinki",
    "iso:country":"FI",
    "name:swe_x_preferred":[
        "Kilen"
    ],
    "wof:name":"Kilen",
    "wof:placetype":"locality"
},
  "geometry": {"coordinates":[22.01792,63.16257],"type":"Point"}
}