{
  "type": "Feature",
  "properties": {
    "gn:admin1_code":"1.0",
    "gn:admin2_code":"14.0",
    "gn:admin3_code":"710.0",
    "gn:asciiname":"Groenvik",
    "gn:country_code":"FI",
    "gn:dem":13,
    "gn:feature_class":"P",
    "gn:feature_code":"PPL",
    "gn:name":"Gr\u00f6nvik",
    "gn:population":0,
    "gn:timezone":"Europe/Helsinki",
    "iso:country":"FI",
    "wof:name":"Groenvik",
    "wof:placetype":"locality"
},
  "geometry": {"coordinates":[22.86667000000001,59.95],"type":"Point"}
}