{
  "type": "Feature",
  "properties": {
    "gn:admin1_code":"17.0",
    "gn:admin2_code":"178.0",
    "gn:admin3_code":"305.0",
    "gn:asciiname":"Harju",
    "gn:country_code":"FI",
    "gn:dem":270,
    "gn:feature_class":"P",
    "gn:feature_code":"PPL",
    "gn:name":"Harju",
    "gn:population":0,
    "gn:timezone":"Europe/Helsinki",
    "iso:country":"FI",
    "name:ceb_x_preferred":[
        "Harju"
    ],
    "name:deu_x_preferred":[
        "Harju"
    ],
    "name:est_x_preferred":[
        "Harju"
    ],
    "name:fin_x_preferred":[
        "Harju"
    ],
    "name:fra_x_preferred":[
        "Harju"
    ],
    "name:rus_x_preferred":[
        "\u0425\u0430\u0440\u044c\u044e"
    ],
    "name:sco_x_preferred":[
        "Harju"
    ],
    "name:swe_x_preferred":[
        "Harju"
    ],
    "name:vol_x_preferred":[
        "Harju"
    ],
    "wof:name":"Harju",
    "wof:placetype":"locality"
},
  "geometry": {"coordinates":[29.81667,65.91667],"type":"Point"}
}