{
  "type": "Feature",
  "properties": {
    "gn:admin1_code":"12.0",
    "gn:admin2_code":"125.0",
    "gn:admin3_code":"911.0",
    "gn:asciiname":"Koppelo",
    "gn:cc2":"FI",
    "gn:country_code":"FI",
    "gn:dem":144,
    "gn:feature_class":"P",
    "gn:feature_code":"PPL",
    "gn:name":"Koppelo",
    "gn:population":0,
    "gn:timezone":"Europe/Helsinki",
    "iso:country":"FI",
    "name:eng_x_preferred":[
        "Koppelo"
    ],
    "name:rus_x_preferred":[
        "\u041a\u043e\u043f\u043f\u0435\u043b\u043e"
    ],
    "name:und_x_variant":[
        "Koppeloj\u00e4rvi"
    ],
    "wof:name":"Koppelo",
    "wof:placetype":"locality"
},
  "geometry": {"coordinates":[28.59873,63.70729],"type":"Point"}
}