{
  "type": "Feature",
  "properties": {
    "gn:admin1_code":"16.0",
    "gn:admin2_code":"162.0",
    "gn:admin3_code":"217.0",
    "gn:asciiname":"Jokisalo",
    "gn:country_code":"FI",
    "gn:dem":54,
    "gn:feature_class":"P",
    "gn:feature_code":"PPL",
    "gn:name":"Jokisalo",
    "gn:population":0,
    "gn:timezone":"Europe/Helsinki",
    "iso:country":"FI",
    "wof:name":"Jokisalo",
    "wof:placetype":"locality"
},
  "geometry": {"coordinates":[23.68606,63.92378000000001],"type":"Point"}
}