{
  "type": "Feature",
  "properties": {
    "gn:admin1_code":"2.0",
    "gn:admin2_code":"21.0",
    "gn:admin3_code":"322.0",
    "gn:asciiname":"Dalen",
    "gn:country_code":"FI",
    "gn:dem":36,
    "gn:feature_class":"P",
    "gn:feature_code":"PPL",
    "gn:name":"Dalen",
    "gn:population":0,
    "gn:timezone":"Europe/Helsinki",
    "iso:country":"FI",
    "name:ceb_x_preferred":[
        "Dalen"
    ],
    "name:cym_x_preferred":[
        "Dalen"
    ],
    "name:fra_x_preferred":[
        "Dalen"
    ],
    "name:fry_x_preferred":[
        "Dalen"
    ],
    "name:ita_x_preferred":[
        "Dalen"
    ],
    "name:nld_x_preferred":[
        "Dalen"
    ],
    "name:pol_x_preferred":[
        "Dalen"
    ],
    "wof:name":"Dalen",
    "wof:placetype":"locality"
},
  "geometry": {"coordinates":[22.48328,60.04133],"type":"Point"}
}