{
  "type": "Feature",
  "properties": {
    "gn:admin1_code":"16.0",
    "gn:admin2_code":"162.0",
    "gn:admin3_code":"217.0",
    "gn:asciiname":"Hanhineva",
    "gn:country_code":"FI",
    "gn:dem":84,
    "gn:feature_class":"P",
    "gn:feature_code":"PPL",
    "gn:name":"Hanhineva",
    "gn:population":0,
    "gn:timezone":"Europe/Helsinki",
    "iso:country":"FI",
    "wof:name":"Hanhineva",
    "wof:placetype":"locality"
},
  "geometry": {"coordinates":[24.18878,63.91123],"type":"Point"}
}