{
  "type": "Feature",
  "properties": {
    "gn:admin1_code":"1.0",
    "gn:admin2_code":"11.0",
    "gn:admin3_code":"858.0",
    "gn:asciiname":"Murto",
    "gn:country_code":"FI",
    "gn:dem":62,
    "gn:feature_class":"P",
    "gn:feature_code":"PPL",
    "gn:name":"Murto",
    "gn:population":0,
    "gn:timezone":"Europe/Helsinki",
    "iso:country":"FI",
    "wof:name":"Murto",
    "wof:placetype":"locality"
},
  "geometry": {"coordinates":[24.89029,60.41065],"type":"Point"}
}