{
  "type": "Feature",
  "properties": {
    "gn:admin1_code":"13.0",
    "gn:admin2_code":"132.0",
    "gn:admin3_code":"435.0",
    "gn:asciiname":"Kesaeniemi",
    "gn:country_code":"FI",
    "gn:dem":137,
    "gn:feature_class":"P",
    "gn:feature_code":"PPL",
    "gn:name":"Kes\u00e4niemi",
    "gn:population":0,
    "gn:timezone":"Europe/Helsinki",
    "iso:country":"FI",
    "wof:name":"Kesaeniemi",
    "wof:placetype":"locality"
},
  "geometry": {"coordinates":[25.7506,61.7785],"type":"Point"}
}