{
  "type": "Feature",
  "properties": {
    "gn:admin1_code":"18.0",
    "gn:admin2_code":"182.0",
    "gn:admin3_code":"578.0",
    "gn:asciiname":"Hiisimaeki",
    "gn:country_code":"FI",
    "gn:dem":199,
    "gn:feature_class":"P",
    "gn:feature_code":"PPL",
    "gn:name":"Hiisim\u00e4ki",
    "gn:population":0,
    "gn:timezone":"Europe/Helsinki",
    "iso:country":"FI",
    "wof:name":"Hiisimaeki",
    "wof:placetype":"locality"
},
  "geometry": {"coordinates":[28.06667,64.43333],"type":"Point"}
}