{
  "type": "Feature",
  "properties": {
    "gn:admin1_code":"2.0",
    "gn:admin2_code":"21.0",
    "gn:admin3_code":"445.0",
    "gn:asciiname":"Sellmo",
    "gn:cc2":"FI",
    "gn:country_code":"FI",
    "gn:dem":7,
    "gn:feature_class":"P",
    "gn:feature_code":"PPL",
    "gn:name":"Sellmo",
    "gn:population":0,
    "gn:timezone":"Europe/Helsinki",
    "iso:country":"FI",
    "name:und_x_variant":[
        "\u00d6sterg\u00e5rd",
        "Sellmo"
    ],
    "wof:name":"Sellmo",
    "wof:placetype":"locality"
},
  "geometry": {"coordinates":[21.84874,60.19923000000001],"type":"Point"}
}