{
  "type": "Feature",
  "properties": {
    "gn:admin1_code":"2.0",
    "gn:admin2_code":"21.0",
    "gn:admin3_code":"322.0",
    "gn:asciiname":"Billboele",
    "gn:country_code":"FI",
    "gn:dem":23,
    "gn:feature_class":"P",
    "gn:feature_code":"PPL",
    "gn:name":"Billb\u00f6le",
    "gn:population":0,
    "gn:timezone":"Europe/Helsinki",
    "iso:country":"FI",
    "wof:name":"Billboele",
    "wof:placetype":"locality"
},
  "geometry": {"coordinates":[22.71337,60.05027],"type":"Point"}
}